Workbook

Sheet Platform_Summary
A1: Platform | B1: Claude_Source_Records | C1: GPT_Source_Records | D1: CodeX_Source_Records | E1: TestBatch_Source_Records | F1: Total_Source_Records | G1: Reconciled_Datasets | H1: Duplicate_Records_Removed | I1: Datasets_Also_Found_on_Other_Platforms | J1: Platform_Unique_Datasets | K1: Original_Datasets | L1: Derived_Datasets | M1: Compiled_Datasets | N1: Repository_Mirrors | O1: Datasets_With_Publication | P1: Datasets_With_Image_Count | Q1: Datasets_With_Labels | R1: Datasets_With_Annotation_Information | S1: Datasets_With_AI_Task | T1: Datasets_With_AI_Method | U1: Accessible_Datasets | V1: Inaccessible_or_Broken_Links | W1: Excluded_Candidates_Logged | X1: Main_Data_Types | Y1: Main_Annotation_Styles | Z1: Main_AI_Tasks | AA1: Main_Strengths | AB1: Main_Limitations | AC1: Notes
A2: ALL SIX PLATFORMS - TOTAL (deduplicated; each reconciled dataset counted once) | B2: 147 | C2: 73 | D2: 13 | E2: 34 | F2: 267 | G2: 177 | H2: 90 | I2: 20 | J2: 156 | K2: 148 | L2: 18 | M2: 11 | N2: 20 | O2: 89 | P2: 109 | Q2: 173 | R2: 167 | S2: 172 | T2: 24 | U2: 162 | V2: 7 | W2: 574 | X2: NR | Y2: NR | Z2: NR | AA2: NR | AB2: NR | AC2: OVERALL SUMMARY - Total source records across the six platforms: 267. Total reconciled datasets after cross-tool and cross-platform deduplication: 177. Total duplicate source records merged/removed: 90. Datasets appearing on multiple platforms: 20. Datasets on exactly one platform: 156. Datasets on none of the six platforms (institutional/arXiv-only hosting): 1. Counts are static values computed from the source workbooks at build time (2026-08-10). A dataset hosted on several platforms is counted once in this TOTAL row but appears in each relevant platform row below, so platform-row Reconciled_Datasets sum to more than 177.
A3: GitHub | B3: 26 | C3: 17 | D3: 0 | E3: 34 | F3: 77 | G3: 46 | H3: 24 | I3: 10 | J3: 36 | K3: 44 | L3: 1 | M3: 1 | N3: 10 | O3: 39 | P3: 32 | Q3: 46 | R3: 43 | S3: 45 | T3: 14 | U3: 38 | V3: 4 | W3: 253 | X3: Research image datasets (RGB, UAV, infrared/RGB-T, stereo); repository-hosted archives and external-drive links | Y3: Bounding boxes (VOC/YOLO); pixel-level segmentation masks; classification folders | Z3: Object detection; semantic segmentation; crack detection; classification; PCI estimation | AA3: Hosts most canonical academic benchmarks (RDD family, CRACK500, GAPs384, EdmCrack600, UAPD, CQU-BPDD); rich READMEs with publications; free direct access | AB3: Data often stored on external drives (Google Drive/Baidu) with unverified liveness; several announced-but-unreleased datasets (Pending); repository search recall unstable; licenses frequently unstated | AC3: Three GitHub batches exist: Claude_Github_001 and ChatGPT_Github_001 (both 2026-08-06) plus Github_Github_Test (2026-08-01, tool attribution UNK). The test batch contributes 13 datasets found by no dated batch (classical benchmarks such as CrackForest, CrackTree260, CRKWH100, CrackLS315, DeepCrack-537).
A4: Data.gov | B4: 1 | C4: 2 | D4: 0 | E4: 0 | F4: 3 | G4: 2 | H4: 1 | I4: 0 | J4: 2 | K4: 2 | L4: 0 | M4: 0 | N4: 0 | O4: 2 | P4: 0 | Q4: 1 | R4: 2 | S4: 0 | T4: 0 | U4: 1 | V4: 0 | W4: 36 | X4: Agency program databases (LTPP) with section-level distress imagery; predominantly tabular/GIS records otherwise | Y4: Section-level distress type/severity/extent per LTPP Distress Identification Manual; no image-space annotations | Z4: Pavement condition/IRI/PCI prediction from structured data; imagery requires pairing work for CV use | AA4: Authoritative, QA-documented federal data (LTPP) with multimodal companions (traffic, climate, FWD); long temporal coverage since 1990s | AB4: Only one image-bearing dataset met the modality rule (LTPP); catalog dominated by tabular PCI/GIS records; image counts/resolutions unreported; bulk-download authorization unclear | AC4: Both tools converged on LTPP as the single eligible record; GPT additionally kept the Non-LTPP access collection Pending. Both tools excluded the same companion catalog records (LTPP Map/Library/0549d harvest duplicate) and 30+ tabular PCI/GIS records (Montgomery County PCI, NYC Street Pavement Rating, HPMS, Chicago potholes, Sioux Falls).
A5: Mendeley Data | B5: 39 | C5: 12 | D5: 4 | E5: 0 | F5: 55 | G5: 43 | H5: 13 | I5: 10 | J5: 33 | K5: 39 | L5: 3 | M5: 1 | N5: 10 | O5: 14 | P5: 29 | Q5: 42 | R5: 40 | S5: 42 | T5: 5 | U5: 43 | V5: 1 | W5: 63 | X5: Author-deposited research image datasets with DOIs; several data-article-backed deposits | Y5: Bounding boxes; segmentation masks; classification folders; oriented boxes (CoCG) | Z5: Object detection; classification; semantic segmentation | AA5: Largest pool of DOI-minted original deposits (RDD2020, PaveDistress, HighRPD, Attain, SUT-Crack); frequent Data-in-Brief articles; consistent CC-BY licensing | AB5: No file manifests exposed to non-interactive review (counts unverifiable); country/collection metadata often absent; duplicate deposits of the same dataset occur (MWPD) | AC5: Counts follow the standard platform order and are computed after cross-platform deduplication; a multi-platform dataset is counted in each platform it appears on.
A6: Hugging Face | B6: 8 | C6: 17 | D6: 0 | E6: 0 | F6: 25 | G6: 21 | H6: 3 | I6: 4 | J6: 17 | K6: 11 | L6: 6 | M6: 4 | N6: 4 | O6: 18 | P6: 16 | Q6: 21 | R6: 21 | S6: 21 | T6: 3 | U6: 20 | V6: 0 | W6: 30 | X6: Community re-uploads and Roboflow exports; a few original large sets (PaveBench, CrackBlock600K) | Y6: YOLO/COCO conversions; classification folders; instance segmentation | Z6: Object detection; classification; semantic/instance segmentation | AA6: Easy programmatic access (load_dataset/viewer); hosts reformatted versions of canonical sets (SVRDD_YOLO, CQU-BPDD) | AB6: Mostly re-uploads rather than canonical sources; collection context (country, sensor, dates) rarely documented; native search not reproducible non-interactively; licenses often missing | AC6: Counts follow the standard platform order and are computed after cross-platform deduplication; a multi-platform dataset is counted in each platform it appears on.
A7: Zenodo | B7: 30 | C7: 9 | D7: 6 | E7: 0 | F7: 45 | G7: 35 | H7: 11 | I7: 6 | J7: 29 | K7: 32 | L7: 2 | M7: 1 | N7: 6 | O7: 14 | P7: 21 | Q7: 34 | R7: 34 | S7: 35 | T7: 5 | U7: 31 | V7: 2 | W7: 134 | X7: DOI-minted research deposits incl. multimodal (infrared, MLS, GPR) and regional datasets | Y7: Bounding boxes; segmentation masks; classification folders; point-cloud labels | Z7: Object detection; classification; semantic/instance segmentation; multimodal fusion; severity classification | AA7: Reproducible API search; versioned DOIs; strong regional diversity (Iraq, Ecuador, Bangladesh, Morocco, Brazil, Poland, Finland); infrared thermography series | AB7: Image counts/geography frequently absent from deposits; many very recent records with no reuse evidence; some restricted/metadata-only records (CAMBER series) | AC7: Counts follow the standard platform order and are computed after cross-platform deduplication; a multi-platform dataset is counted in each platform it appears on.
A8: Kaggle | B8: 43 | C8: 16 | D8: 3 | E8: 0 | F8: 62 | G8: 50 | H8: 12 | I8: 11 | J8: 39 | K8: 39 | L8: 6 | M8: 5 | N8: 11 | O8: 19 | P8: 26 | Q8: 49 | R8: 47 | S8: 49 | T8: 5 | U8: 49 | V8: 1 | W8: 58 | X8: Uploader-driven mirrors and derived compilations; some original community datasets | Y8: Bounding boxes (YOLO); instance segmentation; classification folders | Z8: Object detection; classification; instance segmentation; severity classification | AA8: Largest raw record volume; convenient packaging; version history via API; several datasets not found elsewhere (PVS, RAD, STU_CamCrack792) | AB8: Mostly re-uploads of Zenodo/Mendeley/Roboflow data with uploader-set licenses; registration required for download; data cards lack schema (high NR density); no citation counts; empty data cards on several records | AC8: Highest duplication pressure of the six platforms: RDD2022, CRACK500, SDNET2018, RTK, UAV-PDD2023 (as UAV-SEG-2025), Concrete & Pavement Crack, MWPD, Road Issues, Drone-based Inspection and the Arcioni road-damage dataset all also exist on other platforms. Claude verified records via the unauthenticated Kaggle API; GPT via rendered pages.
A9: Other (not hosted on any of the six platforms) | B9: NR | C9: NR | D9: NR | E9: NR | F9: 1 | G9: 1 | H9: NR | I9: NR | J9: NR | K9: NR | L9: NR | M9: NR | N9: NR | O9: NR | P9: NR | Q9: NR | R9: NR | S9: NR | T9: NR | U9: NR | V9: NR | W9: NR | X9: NR | Y9: NR | Z9: NR | AA9: NR | AB9: NR | AC9: Datasets surfaced by the searches but hosted outside the six platforms: AEL Road Crack Dataset. Retained for traceability; excluded from Platform_Unique.

Sheet AI_Tool_Summary
A1: AI_Tool | B1: Total_Source_Records | C1: Reconciled_Datasets_Identified | D1: Datasets_Also_Identified_by_Other_AI_Tool | E1: AI_Tool_Unique_Datasets | F1: GitHub_Datasets | G1: DataGov_Datasets | H1: Mendeley_Datasets | I1: HuggingFace_Datasets | J1: Zenodo_Datasets | K1: Kaggle_Datasets | L1: Datasets_With_Image_Count | M1: Datasets_With_Label_Information | N1: Datasets_With_Annotation_Information | O1: Datasets_With_AI_Task | P1: Datasets_With_AI_Method | Q1: Datasets_With_Publication | R1: Datasets_With_Access_Status | S1: Datasets_With_License | T1: Include_Decisions | U1: Pending_Decisions | V1: Exclude_Decisions | W1: Main_Search_Strengths | X1: Main_Search_Limitations | Y1: Main_Metadata_Strengths | Z1: Main_Metadata_Gaps | AA1: Notes
A2: ALL TOOLS - RECONCILED TOTAL | B2: 267 | C2: 177 | D2: 34 | E2: NR | F2: NR | G2: NR | H2: NR | I2: NR | J2: NR | K2: NR | L2: NR | M2: NR | N2: NR | O2: NR | P2: NR | Q2: NR | R2: NR | S2: NR | T2: NR | U2: NR | V2: NR | W2: NR | X2: NR | Y2: NR | Z2: NR | AA2: OVERALL SUMMARY - Total reconciled datasets: 177. Identified by BOTH Claude and GPT: 34. Only by Claude (not GPT): 98. Only by GPT (not Claude): 31. CodeX-involved: 13 (CodeX-only: 1). Unattributed GitHub test batch only: 13. MAIN REASONS FOR CLAUDE-GPT DIFFERENCES: (1) recall asymmetry by platform - Claude ran API-level exhaustive searches on Kaggle/Mendeley/Zenodo (43/39/30 records vs GPT 16/12/9), while GPT covered Hugging Face far better (17 vs 8) because Claude could not access HF native search non-interactively; (2) different canonical-source policies - GPT GitHub batch excluded the RDD2022 Kaggle mirror and RDD2020 HF mirror as duplicates that Claude Kaggle retained (both reconcile here); (3) screening-strictness differences - Claude excluded CHDyshli/PavementCrackDetection as NOT_DATASET where GPT included it (GH-005); GPT HF batch excluded manot/pothole-segmentation2 as a duplicate mirror where Claude included it (DSHF-008); (4) date/venue coverage - GPT found older/institutional sets (MIIA, FIND, Weakly-Supervised Crack), Claude found more 2025-2026 deposits. IMPORTANT INCLUDE-VS-EXCLUDE DISAGREEMENTS: CHDyshli highway crack dataset (Claude excluded, GPT included); manot/pothole-segmentation2 (GPT excluded as mirror, Claude included); RDD2022 Kaggle mirror and RDD2020 HF mirror (GPT excluded as duplicates, Claude/others retained - merged into one reconciled record each here); LTPP companion catalog records (both tools excluded consistently as duplicates). Include/exclude and status conflicts on shared datasets are flagged per row in All_Datasets (Include_Exclude_Conflict = Y). No AI-readiness scores are used or reported anywhere in this workbook.
A3: Claude | B3: 147 | C3: 132 | D3: 41 | E3: 89 | F3: 27 | G3: 1 | H3: 39 | I3: 10 | J3: 30 | K3: 44 | L3: 75 | M3: 128 | N3: 121 | O3: 127 | P3: 7 | Q3: 49 | R3: 130 | S3: 108 | T3: 133 | U3: 14 | V3: 443 | W3: API-driven, exhaustively paginated searches (GitHub REST, Zenodo API, DataCite index for Mendeley, Kaggle public API); largest record volume on Kaggle (43), Mendeley (39) and Zenodo (30); systematic dedup and series collapsing (CAMBER 67-to-1); access verified at data-file level (HTTP tests); every excluded candidate logged (445 exclusion entries). | X3: Hugging Face native search inaccessible non-interactively (only 8 records; missed PaveBench, CrackBlock600K-HF, Unified Road Defect, BLACrack, RSCD); did not surface SVRDD on Zenodo or several GPT-found Zenodo/Mendeley records (FIND, South Africa binary crack, Cracks-and-Potholes-in-Road-Images, Pothole Videos, PathCare); GitHub batch excluded some data-bearing repos as NOT_DATASET (e.g., CHDyshli) that GPT included. | Y3: High completeness on acquisition platform, distress taxonomy, annotation method/QC, license and evidence locators; explicit no-inference policy with NR/UNK codes; conflicts and unresolved issues documented per record. | Z3: Publications_Using_Dataset_Count NR throughout; no benchmark models/metrics recorded (per no-fabrication rule); country frequently NR where only depositor affiliation was available; Kaggle records carry Registration access (platform-level) rather than per-file verification. | AA3: Claude batches reviewed: DataGov, Github, Huggingface, Kaggle, Mendeley, Zendo (each _001). Reviewers: Tianzhi He (DataGov/GitHub/HF), Mo Hu (Kaggle/Mendeley/Zenodo). Search dates 2026-08-03 to 2026-08-06.
A4: GPT (ChatGPT) | B4: 73 | C4: 65 | D4: 34 | E4: 25 | F4: 16 | G4: 2 | H4: 16 | I4: 16 | J4: 12 | K4: 16 | L4: 43 | M4: 64 | N4: 65 | O4: 63 | P4: 19 | Q4: 42 | R4: 63 | S4: 31 | T4: 68 | U4: 5 | V4: 97 | W4: Better Hugging Face coverage (17 records incl. PaveBench, CrackBlock600K, Unified Road Defect, RSCD-1million, BLACrack); found several Zenodo/Mendeley datasets Claude missed (SVRDD, FIND, South African binary crack, Weakly-Supervised Crack, Pothole Videos, PathCare, Cracks-and-Potholes-in-Road-Images, MIIA); GitHub batch actively resolved canonical sources (figshare/Mendeley links) and excluded mirrors explicitly. | X4: Much lower recall on Kaggle (16 vs 43), Mendeley (12 vs 39) and Zenodo (9 vs 30) than Claude; no stable result totals (Results_Returned frequently NR); Zenodo HTTP 429 throttling forced use of indexed page text; relative dates not converted to YYYY-MM; some batches completed 2 days after protocol search date. | Y4: Richer publication linking on GitHub/HF records (multiple DOIs per record); consistent controlled-value formatting on HF batch; canonical-source resolution notes (mirror provenance). | Z4: License and image counts NR on many Zenodo/Mendeley records where Claude found values; acquisition detail often generic (platform NR); several records rely on indexed snapshots rather than live pages (INACC risk). | AA4: GPT batches reviewed: ChatGPT_Github_001, ChatGPT_Huggingface_001, ChatGPT_DataGov_001 (file ChatGP_DataGov_001), GPT_Kaggle_001, GPT_Mendeley_001, GPT_Zenodo_001. Search dates 2026-08-03 to 2026-08-06.
A5: CodeX (supplementary third tool; Kaggle/Mendeley/Zenodo batches only) | B5: 13 | C5: 13 | D5: 12 | E5: 1 | F5: 2 | G5: 0 | H5: 4 | I5: 0 | J5: 6 | K5: 4 | L5: 11 | M5: 13 | N5: 13 | O5: 13 | P5: 3 | Q5: 4 | R5: 13 | S5: 11 | T5: 13 | U5: 0 | V5: 9 | W5: Precise verification of retained records (full citations in DOI fields); found CAMBER sibling record and CDAC-DAI details missed by GPT. | X5: Very low recall: only 13 records across three platforms (Kaggle 3, Mendeley 4, Zenodo 6); no GitHub, Data.gov or Hugging Face batches; Zenodo query Q03 returned INACC. | Y5: Accurate counts where reported (e.g., IRT crack dataset 369 images; UAV-SEG 2,426). | Z5: Most geography/sensor/QC fields NR; no publication enumeration. | AA5: CodeX contributed no datasets that reconcile outside Claude/GPT coverage except sibling detail; 1 dataset(s) unique to CodeX. Treated as supplementary third tool; not part of the primary Claude-vs-GPT comparison.
A6: Github_Github_Test batch (tool attribution UNK; GitHub only; search 2026-08-01) | B6: 34 | C6: 34 | D6: 21 | E6: 13 | F6: 30 | G6: 0 | H6: 6 | I6: 1 | J6: 2 | K6: 3 | L6: 26 | M6: 34 | N6: 34 | O6: 34 | P6: 2 | Q6: 34 | R6: 31 | S6: 2 | T6: 27 | U6: 7 | V6: 25 | W6: Broadest GitHub sweep of classical crack benchmarks: unique records for CrackForest (CFD), CrackTree260, CRKWH100, CrackLS315, DeepCrack-537, AEL, RCD-IIUM, Stereo Pothole Datasets, SoV, CrackSeg9k, R2S100K, jaygala24 pothole set. | X6: Tool attribution not recorded in the file (README Review_Batch_ID = Github_001, reviewer Tianzhi He, search 2026-08-01, before the dated Claude/GPT GitHub batches); treated as an unattributed test batch and EXCLUDED from Claude-vs-GPT unique/overlap statistics. | Y6: Good acquisition detail (camera systems) and publication links for classical benchmarks. | Z6: Licenses almost entirely NR; many Pending records; several arXiv-only access routes. | AA6: 13 reconciled dataset(s) rest ONLY on this batch and carry AI_Tools_Identifying_Dataset = GitHub_Test_Batch (tool UNK).

Sheet All_Datasets
A1: Reconciled_Dataset_ID | B1: Standardized_Dataset_Name | C1: Alternate_Dataset_Names | D1: Dataset_Version | E1: Match_Classification | F1: Match_Confidence | G1: Match_Evidence | H1: AI_Tools_Identifying_Dataset | I1: Data_Platforms | J1: Appears_on_Multiple_Platforms | K1: Platform_Relationship | L1: Preferred_Dataset_URL | M1: GitHub_URL | N1: DataGov_URL | O1: Mendeley_Data_URL | P1: HuggingFace_URL | Q1: Zenodo_URL | R1: Kaggle_URL | S1: Other_Dataset_URLs | T1: DOI_or_Persistent_ID | U1: Related_Publication | V1: Publication_Citation | W1: Publication_DOI | X1: Publication_URL | Y1: Publication_Year | Z1: Peer_Reviewed_Publication | AA1: Publication_Dataset_Relationship | AB1: Dataset_Scale_Type | AC1: Number_of_Images | AD1: Number_of_Videos | AE1: Number_of_Frames | AF1: Number_of_Samples | AG1: Number_of_Road_Segments | AH1: Number_of_Annotated_Instances | AI1: Number_of_Classes | AJ1: Training_Set_Size | AK1: Validation_Set_Size | AL1: Testing_Set_Size | AM1: Dataset_Storage_Size | AN1: Image_Resolution | AO1: Video_Resolution | AP1: Country | AQ1: State_or_Province | AR1: City_or_Region | AS1: Geographic_Coverage | AT1: Temporal_Coverage | AU1: Acquisition_Platform | AV1: Vehicle_Type | AW1: Camera_Type | AX1: Camera_Position | AY1: Smartphone_Data | AZ1: Drone_or_Aerial_Data | BA1: CAV_AV_ADAS_Data | BB1: LiDAR_Availability | BC1: GPS_or_Geolocation | BD1: Other_Sensors | BE1: Weather_Conditions | BF1: Lighting_Conditions | BG1: Traffic_Conditions | BH1: Distress_Types | BI1: Pavement_Condition_Labels | BJ1: Label_Taxonomy | BK1: Number_of_Label_Classes | BL1: Annotation_Task_Type | BM1: Annotation_Style | BN1: Annotation_Format | BO1: Annotation_File_Format | BP1: Classification_Labels | BQ1: Bounding_Boxes | BR1: Segmentation_Masks | BS1: Polygons | BT1: Keypoints | BU1: Severity_Labels | BV1: PCI_Availability | BW1: IRI_Availability | BX1: Maintenance_Record_Availability | BY1: Annotation_Source | BZ1: Annotation_Quality_Control | CA1: Class_Balance | CB1: Unlabeled_Data_Availability | CC1: Reported_AI_Tasks | CD1: Reported_AI_Methods | CE1: Reported_Models_or_Architectures | CF1: AI_Task_Evidence | CG1: Evaluation_Metrics | CH1: Benchmark_Results | CI1: Screening_Decision | CJ1: Access_Status | CK1: License | CL1: Registration_Requirement | CM1: Download_Requirement | CN1: Documentation_Quality | CO1: Label_Documentation_Quality | CP1: Broken_or_Inaccessible_Link | CQ1: Key_Limitations | CR1: Original_Derived_or_Compiled | CS1: Repository_Mirror | CT1: Different_Version | CU1: Derived_or_Reformatted | CV1: Parent_Dataset | CW1: Related_Datasets | CX1: Source_Filenames | CY1: Source_Record_IDs | CZ1: Claude_Reported_Values_Conflict | DA1: GPT_Reported_Values_Conflict | DB1: Scale_Conflicts | DC1: Label_Conflicts | DD1: Platform_Conflicts | DE1: Other_Metadata_Conflicts | DF1: Include_Exclude_Conflict | DG1: Reconciliation_Notes | DH1: Evidence_Locator | DI1: Confidence_Level | DJ1: Verification_Priority | DK1: Recommended_Action | DL1: AIR_Accessibility_0_5 | DM1: AIR_Annotation_Quality_0_5 | DN1: AIR_Documentation_0_5 | DO1: AIR_Scale_0_5 | DP1: AIR_Diversity_0_5 | DQ1: AIR_Sensor_Metadata_0_5 | DR1: AIR_Agency_Ground_Truth_0_5 | DS1: AIR_Overall_Default_Weights_0_100 | DT1: AIR_Score_Basis | DU1: AIR_Scored_Source_Records | DV1: V3_AI_Grade | DW1: V3_Human_Grade | DX1: V3_AI_Confirmed_100 | DY1: V3_Human_Confirmed_100 | DZ1: V3_AI_Upper_100 | EA1: V3_Human_Upper_100 | EB1: V3_AI_Resolved_Pct | EC1: V3_Human_Resolved_Pct | ED1: V3_AI_Access_5 | EE1: V3_Human_Access_5 | EF1: V3_AI_Label_Quality_5 | EG1: V3_Human_Label_Quality_5 | EH1: V3_AI_Documentation_5 | EI1: V3_Human_Documentation_5 | EJ1: V3_AI_Sample_Size_5 | EK1: V3_Human_Sample_Size_5 | EL1: V3_AI_Domain_Fit_5 | EM1: V3_Human_Domain_Fit_5 | EN1: V3_AI_Sensor_Details_5 | EO1: V3_Human_Sensor_Details_5 | EP1: V3_AI_Test_Readiness_5 | EQ1: V3_Human_Test_Readiness_5 | ER1: V3_AI_Engineering_Value_5 | ES1: V3_Human_Engineering_Value_5 | ET1: V3_AI_Eligibility | EU1: V3_Human_Eligibility | EV1: V3_Human_Completion_Pct | EW1: V3_Human_minus_AI_Confirmed | EX1: V3_State_Agreement_Pct | EY1: V3_AI_Evidence_Note | EZ1: V3_Human_Evidence_Note | FA1: V3_AI_Source_URL | FB1: V3_Human_Source_URL | FC1: View_Orientation | FD1: View_Top_Down_Nadir | FE1: View_Forward_Facing_Oblique | FF1: View_Other | FG1: View_Platform_Mount | FH1: View_Evidence_Quote | FI1: View_Evidence_Source | FJ1: View_Evidence_URL | FK1: View_Label_Confidence | FL1: View_Verification | FM1: View_Label_Notes
A2: DS-001 | B2: Asphalt Pavement Crack Data (class-foldered grayscale images) | C2: NA | D2: v1 | E2: Independent Dataset | F2: NA (single source record) | G2: Single source record; no matching record found in any other file after cross-file and cross-platform comparison. | H2: Claude | I2: GitHub | J2: N | K2: NA (single platform) | L2: https://github.com/summoners29/Asphalt-Pavement-Crack-Data | M2: https://github.com/summoners29/Asphalt-Pavement-Crack-Data | N2: NA | O2: NA | P2: NA | Q2: NA | R2: NA | S2: NA | T2: NR | U2: N | V2: NR | W2: NR | X2: NR | Y2: NR | Z2: NA | AA2: NA | AB2: NR | AC2: NR | AD2: NR | AE2: NR | AF2: NR | AG2: NR | AH2: NR | AI2: NR | AJ2: NR | AK2: NR | AL2: NR | AM2: NR | AN2: NR | AO2: NR | AP2: NR | AQ2: NR | AR2: NR | AS2: Road environment: Asphalt pavements | AT2: NR | AU2: NR | AV2: NR | AW2: NR | AX2: NR | AY2: NR | AZ2: NR | BA2: NR | BB2: N | BC2: N | BD2: NR | BE2: NR | BF2: NR | BG2: NR | BH2: Alligator crack (additional classes per folder structure UNK) | BI2: NR | BJ2: Folder-level class labels (e.g., Alligator) | BK2: NR | BL2: Image classification | BM2: Image classification | BN2: Class-folder structure (grayscale jpg) | BO2: NR | BP2: Y | BQ2: NR | BR2: NR | BS2: NR | BT2: NR | BU2: NR | BV2: N | BW2: N | BX2: N | BY2: NR | BZ2: NR | CA2: NR | CB2: NR | CC2: Classification | CD2: NR | CE2: NR | CF2: Reported on the source record/data card or associated publication (see Evidence_Locator) | CG2: NR | CH2: NR | CI2: Include-Supplementary | CJ2: Direct_Download | CK2: NR | CL2: N | CM2: Direct_Download | CN2: NR | CO2: NR | CP2: N | CQ2: No README, no counts, no license or provenance; images stored directly in repository | CR2: Original | CS2: N | CT2: N | CU2: N | CV2: NA | CW2: NA | CX2: Claude_Github_001.xlsx | CY2: Claude_Github_001:GH-DS-022 | CZ2: N | DA2: NA | DB2: None | DC2: None | DD2: None | DE2: None | DF2: N | DG2: Single source record; no reconciliation required. | DH2: GitHub repository file listing (Alligator*_gs.jpg files), https://github.com/summoners29/Asphalt-Pavement-Crack-Data (accessed 2026-08-06) | DI2: Low | DJ2: Low | DK2: Use source record as cited. | DL2: 4 | DM2: 1 | DN2: 1 | DO2: 0 | DP2: 1 | DQ2: 1 | DR2: 0 | DS2: 27 | DT2: Reviewed (source MCDM_Scoring, averaged across batches) | DU2: 1 of 1 | DV2: =IFERROR(IF(INDEX(MCDM_Grades!$C$2:$C$178,MATCH($A2,MCDM_Grades!$A$2:$A$178,0))="","",INDEX(MCDM_Grades!$C$2:$C$178,MATCH($A2,MCDM_Grades!$A$2:$A$178,0))),"") | DW2: =IFERROR(IF(INDEX(MCDM_Grades!$D$2:$D$178,MATCH($A2,MCDM_Grades!$A$2:$A$178,0))="","",INDEX(MCDM_Grades!$D$2:$D$178,MATCH($A2,MCDM_Grades!$A$2:$A$178,0))),"") | DX2: =IFERROR(IF(INDEX(MCDM_Grades!$E$2:$E$178,MATCH($A2,MCDM_Grades!$A$2:$A$178,0))="","",INDEX(MCDM_Grades!$E$2:$E$178,MATCH($A2,MCDM_Grades!$A$2:$A$178,0))),"") | DY2: =IFERROR(IF(INDEX(MCDM_Grades!$F$2:$F$178,MATCH($A2,MCDM_Grades!$A$2:$A$178,0))="","",INDEX(MCDM_Grades!$F$2:$F$178,MATCH($A2,MCDM_Grades!$A$2:$A$178,0))),"") | DZ2: =IFERROR(IF(INDEX(MCDM_Grades!$G$2:$G$178,MATCH($A2,MCDM_Grades!$A$2:$A$178,0))="","",INDEX(MCDM_Grades!$G$2:$G$178,MATCH($A2,MCDM_Grades!$A$2:$A$178,0))),"") | EA2: =IFERROR(IF(INDEX(MCDM_Grades!$H$2:$H$178,MATCH($A2,MCDM_Grades!$A$2:$A$178,0))="","",INDEX(MCDM_Grades!$H$2:$H$178,MATCH($A2,MCDM_Grades!$A$2:$A$178,0))),"") | EB2: =IFERROR(IF(INDEX(MCDM_Grades!$I$2:$I$178,MATCH($A2,MCDM_Grades!$A$2:$A$178,0))="","",INDEX(MCDM_Grades!$I$2:$I$178,MATCH($A2,MCDM_Grades!$A$2:$A$178,0))),"") | EC2: =IFERROR(IF(INDEX(MCDM_Grades!$J$2:$J$178,MATCH($A2,MCDM_Grades!$A$2:$A$178,0))="","",INDEX(MCDM_Grades!$J$2:$J$178,MATCH($A2,MCDM_Grades!$A$2:$A$178,0))),"") | ED2: =IFERROR(IF(INDEX(MCDM_Grades!$N$2:$N$178,MATCH($A2,MCDM_Grades!$A$2:$A$178,0))="","",INDEX(MCDM_Grades!$N$2:$N$178,MATCH($A2,MCDM_Grades!$A$2:$A$178,0))),"") | EE2: =IFERROR(IF(INDEX(MCDM_Grades!$O$2:$O$178,MATCH($A2,MCDM_Grades!$A$2:$A$178,0))="","",INDEX(MCDM_Grades!$O$2:$O$178,MATCH($A2,MCDM_Grades!$A$2:$A$178,0))),"") | EF2: =IFERROR(IF(INDEX(MCDM_Grades!$P$2:$P$178,MATCH($A2,MCDM_Grades!$A$2:$A$178,0))="","",INDEX(MCDM_Grades!$P$2:$P$178,MATCH($A2,MCDM_Grades!$A$2:$A$178,0))),"") | EG2: =IFERROR(IF(INDEX(MCDM_Grades!$Q$2:$Q$178,MATCH($A2,MCDM_Grades!$A$2:$A$178,0))="","",INDEX(MCDM_Grades!$Q$2:$Q$178,MATCH($A2,MCDM_Grades!$A$2:$A$178,0))),"") | EH2: =IFERROR(IF(INDEX(MCDM_Grades!$R$2:$R$178,MATCH($A2,MCDM_Grades!$A$2:$A$178,0))="","",INDEX(MCDM_Grades!$R$2:$R$178,MATCH($A2,MCDM_Grades!$A$2:$A$178,0))),"") | EI2: =IFERROR(IF(INDEX(MCDM_Grades!$S$2:$S$178,MATCH($A2,MCDM_Grades!$A$2:$A$178,0))="","",INDEX(MCDM_Grades!$S$2:$S$178,MATCH($A2,MCDM_Grades!$A$2:$A$178,0))),"") | EJ2: =IFERROR(IF(INDEX(MCDM_Grades!$T$2:$T$178,MATCH($A2,MCDM_Grades!$A$2:$A$178,0))="","",INDEX(MCDM_Grades!$T$2:$T$178,MATCH($A2,MCDM_Grades!$A$2:$A$178,0))),"") | EK2: =IFERROR(IF(INDEX(MCDM_Grades!$U$2:$U$178,MATCH($A2,MCDM_Grades!$A$2:$A$178,0))="","",INDEX(MCDM_Grades!$U$2:$U$178,MATCH($A2,MCDM_Grades!$A$2:$A$178,0))),"") | EL2: =IFERROR(IF(INDEX(MCDM_Grades!$V$2:$V$178,MATCH($A2,MCDM_Grades!$A$2:$A$178,0))="","",INDEX(MCDM_Grades!$V$2:$V$178,MATCH($A2,MCDM_Grades!$A$2:$A$178,0))),"") | EM2: =IFERROR(IF(INDEX(MCDM_Grades!$W$2:$W$178,MATCH($A2,MCDM_Grades!$A$2:$A$178,0))="","",INDEX(MCDM_Grades!$W$2:$W$178,MATCH($A2,MCDM_Grades!$A$2:$A$178,0))),"") | EN2: =IFERROR(IF(INDEX(MCDM_Grades!$X$2:$X$178,MATCH($A2,MCDM_Grades!$A$2:$A$178,0))="","",INDEX(MCDM_Grades!$X$2:$X$178,MATCH($A2,MCDM_Grades!$A$2:$A$178,0))),"") | EO2: =IFERROR(IF(INDEX(MCDM_Grades!$Y$2:$Y$178,MATCH($A2,MCDM_Grades!$A$2:$A$178,0))="","",INDEX(MCDM_Grades!$Y$2:$Y$178,MATCH($A2,MCDM_Grades!$A$2:$A$178,0))),"") | EP2: =IFERROR(IF(INDEX(MCDM_Grades!$Z$2:$Z$178,MATCH($A2,MCDM_Grades!$A$2:$A$178,0))="","",INDEX(MCDM_Grades!$Z$2:$Z$178,MATCH($A2,MCDM_Grades!$A$2:$A$178,0))),"") | EQ2: =IFERROR(IF(INDEX(MCDM_Grades!$AA$2:$AA$178,MATCH($A2,MCDM_Grades!$A$2:$A$178,0))="","",INDEX(MCDM_Grades!$AA$2:$AA$178,MATCH($A2,MCDM_Grades!$A$2:$A$178,0))),"") | ER2: =IFERROR(IF(INDEX(MCDM_Grades!$AB$2:$AB$178,MATCH($A2,MCDM_Grades!$A$2:$A$178,0))="","",INDEX(MCDM_Grades!$AB$2:$AB$178,MATCH($A2,MCDM_Grades!$A$2:$A$178,0))),"") | ES2: =IFERROR(IF(INDEX(MCDM_Grades!$AC$2:$AC$178,MATCH($A2,MCDM_Grades!$A$2:$A$178,0))="","",INDEX(MCDM_Grades!$AC$2:$AC$178,MATCH($A2,MCDM_Grades!$A$2:$A$178,0))),"") | ET2: =IFERROR(IF(INDEX(MCDM_Grades!$AD$2:$AD$178,MATCH($A2,MCDM_Grades!$A$2:$A$178,0))="","",INDEX(MCDM_Grades!$AD$2:$AD$178,MATCH($A2,MCDM_Grades!$A$2:$A$178,0))),"") | EU2: =IFERROR(IF(INDEX(MCDM_Grades!$AE$2:$AE$178,MATCH($A2,MCDM_Grades!$A$2:$A$178,0))="","",INDEX(MCDM_Grades!$AE$2:$AE$178,MATCH($A2,MCDM_Grades!$A$2:$A$178,0))),"") | EV2: =IFERROR(IF(INDEX(MCDM_Grades!$K$2:$K$178,MATCH($A2,MCDM_Grades!$A$2:$A$178,0))="","",INDEX(MCDM_Grades!$K$2:$K$178,MATCH($A2,MCDM_Grades!$A$2:$A$178,0))),"") | EW2: =IFERROR(IF(INDEX(MCDM_Grades!$L$2:$L$178,MATCH($A2,MCDM_Grades!$A$2:$A$178,0))="","",INDEX(MCDM_Grades!$L$2:$L$178,MATCH($A2,MCDM_Grades!$A$2:$A$178,0))),"") | EX2: =IFERROR(IF(INDEX(MCDM_Grades!$M$2:$M$178,MATCH($A2,MCDM_Grades!$A$2:$A$178,0))="","",INDEX(MCDM_Grades!$M$2:$M$178,MATCH($A2,MCDM_Grades!$A$2:$A$178,0))),"") | EY2: =IFERROR(IF(INDEX(MCDM_Grades!$AR$2:$AR$178,MATCH($A2,MCDM_Grades!$A$2:$A$178,0))="","",INDEX(MCDM_Grades!$AR$2:$AR$178,MATCH($A2,MCDM_Grades!$A$2:$A$178,0))),"") | EZ2: =IFERROR(IF(INDEX(MCDM_Grades!$AS$2:$AS$178,MATCH($A2,MCDM_Grades!$A$2:$A$178,0))="","",INDEX(MCDM_Grades!$AS$2:$AS$178,MATCH($A2,MCDM_Grades!$A$2:$A$178,0))),"") | FA2: =IFERROR(IF(INDEX(MCDM_Grades!$AT$2:$AT$178,MATCH($A2,MCDM_Grades!$A$2:$A$178,0))="","",INDEX(MCDM_Grades!$AT$2:$AT$178,MATCH($A2,MCDM_Grades!$A$2:$A$178,0))),"") | FB2: =IFERROR(IF(INDEX(MCDM_Grades!$AU$2:$AU$178,MATCH($A2,MCDM_Grades!$A$2:$A$178,0))="","",INDEX(MCDM_Grades!$AU$2:$AU$178,MATCH($A2,MCDM_Grades!$A$2:$A$178,0))),"") | FC2: Nadir / top-down | FD2: Yes | FE2: No | FG2: Not reported (sample image consistent with a handheld camera pointed straight down at the surface) | FH2: Asphalt pavement crack image data | FI2: Dataset page / README | FJ2: https://github.com/summoners29/Asphalt-Pavement-Crack-Data/blob/master/Alligator001_gs.jpg | FK2: Medium | FL2: Verified - agreed | FM2: Workbook has all acquisition fields NR and the repo has no README (only the one-line description quoted; files Alligator001-028_gs.jpg, Pothole001-019_gs.jpg, Reflection001-058_gs.jpg on branch master). Label comes from viewing the sample image Alligator001_gs.jpg (2048x1536, grayscale): a full-frame close-up of the pavement surface with no horizon, road edge or perspective, i.e. camera optical axis perpendicular to the surface. Only one image was inspected and no capture device is documented, hence Medium. | Second review: Independently inspected a second sample from a different class (Pothole001_gs.jpg) in addition to the reviewer's Alligator001: it is likewise a surface-perpendicular close-up, supporting nadir. No README or device documentation exists, so Medium confidence is appropriate.
A3: DS-002 | B3: Asphalt Pavement Distress Dataset (DSWMamba) | C3: DSWMamba Asphalt Pavement Distress Dataset | D3: v1 | E3: Probable Match | F3: Moderate | G3: All three records describe the six-category asphalt distress dataset of the DSWMamba paper; GPT and Claude cite the Oct-Sunn/Asphalt-Pavement-Distress-Dataset repository, the Test batch cites zyf991121/DSWMamba (the model repository). | H3: Claude; GPT; GitHub_Test_Batch (tool UNK) | I3: GitHub | J3: N | K3: Two related GitHub repositories (dataset repo and model repo) for the same paper dataset | L3: https://github.com/Oct-Sunn/Asphalt-Pavement-Distress-Dataset | M3: https://github.com/Oct-Sunn/Asphalt-Pavement-Distress-Dataset; https://github.com/zyf991121/DSWMamba | N3: NA | O3: NA | P3: NA | Q3: NA | R3: NA | S3: NA | T3: NR | U3: Y | V3: DSWMamba paper (full bibliographic details not provided in README) [Claude] | DSWMamba paper cited by repository; DOI NR [GPT] | https://github.com/zyf991121/DSWMamba [Test_Batch] | W3: NR | X3: https://github.com/zyf991121/DSWMamba | Y3: NR | Z3: NR | AA3: Reported in source record (relationship not classified) | AB3: NR | AC3: NR | AD3: NR | AE3: NR | AF3: NR | AG3: NR | AH3: NR | AI3: NR | AJ3: NR | AK3: NR | AL3: NR | AM3: NR | AN3: NR | AO3: NR | AP3: NR | AQ3: NR | AR3: NR | AS3: Road environment: Asphalt pavements, real-world scenarios [Claude] | Asphalt pavement [GPT] | Asphalt roadway [Test_Batch] | AT3: NR | AU3: NR | AV3: NR | AW3: NR | AX3: NR | AY3: NR | AZ3: NR | BA3: NR | BB3: N | BC3: NR | BD3: NR | BE3: NR | BF3: NR | BG3: NR | BH3: Six distress categories incl. cracks, potholes, alligator cracks, road-marking distress [Claude] | six categories including cracks; potholes; alligator cracks; road-marking distress [GPT] | six asphalt pavement distress categories [Test_Batch] | BI3: NR | BJ3: Labeled images across six distress categories [Claude] | Six categories; full taxonomy NR [GPT] | six distress categories [Test_Batch] | BK3: NR | BL3: Detection/classification (per paper focus) [Claude] | detection; classification [GPT] | Semantic segmentation [Test_Batch] | BM3: Detection/classification (per paper focus) [Claude] | detection; classification [GPT] | Semantic segmentation [Test_Batch] | BN3: Pixel masks | BO3: mask | BP3: Y | BQ3: Y | BR3: Y | BS3: NR | BT3: NR | BU3: NR | BV3: N | BW3: N | BX3: N | BY3: Labeled images; details NR [GPT] | Manual annotation [Test_Batch] | BZ3: NR | CA3: NR | CB3: NR | CC3: Object detection [Claude] | detection; classification; analysis [GPT] | semantic segmentation [Test_Batch] | CD3: NR | CE3: NR | CF3: Reported on the source record/data card or associated publication (see Evidence_Locator) | CG3: NR | CH3: NR | CI3: Include-Supplementary [Claude] | Pending [GPT/Test_Batch] | CJ3: Direct_Download [Claude] | UNK [GPT/Test_Batch] | CK3: NR | CL3: N | CM3: Direct_Download [Claude] | UNK [GPT/Test_Batch] | CN3: NR | CO3: NR | CP3: N | CQ3: Image count, format, license, and provenance undocumented; single Google Drive archive (link liveness not independently re-tested) [Claude] | Download target not resolved; no count, license, persistent data identifier, annotation format, geography, or collection details [GPT] | Model repository documents a six-class dataset, but dataset count, release year, access route, license, geography, and independent dataset identity remain unresolved. [Test_Batch] | CR3: Original | CS3: N | CT3: N | CU3: N | CV3: NA | CW3: NA | CX3: ChatGPT_Github_001.xlsx; Claude_Github_001.xlsx; Github_Github_Test.xlsx | CY3: ChatGPT_Github_001:GH-016; Claude_Github_001:GH-DS-016; Github_Github_Test:GITHUB-034 | CZ3: Y - see conflict columns and Reconciliation_Notes | DA3: Y - see conflict columns and Reconciliation_Notes | DB3: None | DC3: Distress types: Six distress categories incl. cracks, potholes, alligator cracks, road-marking d (Claude) vs six categories including cracks; potholes; alligator cracks; road-marking distre (GPT) vs six asphalt pavement distress categories (Test_Batch) || Label taxonomy: Labeled images across six distress categories (Claude) vs Six categories; full taxonomy NR (GPT) vs six distress categories (Test_Batch) || Annotation task: Detection/classification (per paper focus) (Claude) vs detection; classification (GPT) vs Semantic segmentation (Test_Batch) || Annotation method: Labeled images; details NR (GPT) vs Manual annotation (Test_Batch) | DD3: None | DE3: Access status: Direct_Download (Claude) vs UNK (GPT/Test_Batch) || AI tasks: Object detection (Claude) vs detection; classification; analysis (GPT) vs semantic segmentation (Test_Batch) || Screening decision: Include-Supplementary (Claude) vs Pending (GPT/Test_Batch) || Road environment: Asphalt pavements, real-world scenarios (Claude) vs Asphalt pavement (GPT) vs Asphalt roadway (Test_Batch) || Publications: DSWMamba paper (full bibliographic details not provided in README) (Claude) vs DSWMamba paper cited by repository; DOI NR (GPT) vs https://github.com/zyf991121/DSWMamba (Test_Batch) || Key_Limitations: Image count, format, license, and provenance undocumented; single Google Drive a (Claude) vs Download target not resolved; no count, license, persistent data identifier, ann (GPT) vs Model repository documents a six-class dataset, but dataset count, release year, (Test_Batch) | DF3: Y | DG3: No definitive identifier (no DOI, counts NR); URL conflict between the two repositories; screening conflict Pending (GPT, Test) vs Include-Supplementary (Claude). | DH3: GitHub README (Details, download link), https://github.com/Oct-Sunn/Asphalt-Pavement-Distress-Dataset (accessed 2026-08-06) [Claude] | https://github.com/Oct-Sunn/Asphalt-Pavement-Distress-Dataset README; accessed 2026-08-06 [GPT] | https://github.com/zyf991121/DSWMamba; README dataset description checked 2026-08-01 [Test_Batch] | DI3: Low | DJ3: High | DK3: Confirm dataset release location and extent. | DL3: 2 | DM3: 2 | DN3: 1.7 | DO3: 0.3 | DP3: 1.7 | DQ3: 0.7 | DR3: 0 | DS3: 26.8 | DT3: Reviewed (source MCDM_Scoring, averaged across batches) | DU3: 3 of 3 | DV3: =IFERROR(IF(INDEX(MCDM_Grades!$C$2:$C$178,MATCH($A3,MCDM_Grades!$A$2:$A$178,0))="","",INDEX(MCDM_Grades!$C$2:$C$178,MATCH($A3,MCDM_Grades!$A$2:$A$178,0))),"") | DW3: =IFERROR(IF(INDEX(MCDM_Grades!$D$2:$D$178,MATCH($A3,MCDM_Grades!$A$2:$A$178,0))="","",INDEX(MCDM_Grades!$D$2:$D$178,MATCH($A3,MCDM_Grades!$A$2:$A$178,0))),"") | DX3: =IFERROR(IF(INDEX(MCDM_Grades!$E$2:$E$178,MATCH($A3,MCDM_Grades!$A$2:$A$178,0))="","",INDEX(MCDM_Grades!$E$2:$E$178,MATCH($A3,MCDM_Grades!$A$2:$A$178,0))),"") | DY3: =IFERROR(IF(INDEX(MCDM_Grades!$F$2:$F$178,MATCH($A3,MCDM_Grades!$A$2:$A$178,0))="","",INDEX(MCDM_Grades!$F$2:$F$178,MATCH($A3,MCDM_Grades!$A$2:$A$178,0))),"") | DZ3: =IFERROR(IF(INDEX(MCDM_Grades!$G$2:$G$178,MATCH($A3,MCDM_Grades!$A$2:$A$178,0))="","",INDEX(MCDM_Grades!$G$2:$G$178,MATCH($A3,MCDM_Grades!$A$2:$A$178,0))),"") | EA3: =IFERROR(IF(INDEX(MCDM_Grades!$H$2:$H$178,MATCH($A3,MCDM_Grades!$A$2:$A$178,0))="","",INDEX(MCDM_Grades!$H$2:$H$178,MATCH($A3,MCDM_Grades!$A$2:$A$178,0))),"") | EB3: =IFERROR(IF(INDEX(MCDM_Grades!$I$2:$I$178,MATCH($A3,MCDM_Grades!$A$2:$A$178,0))="","",INDEX(MCDM_Grades!$I$2:$I$178,MATCH($A3,MCDM_Grades!$A$2:$A$178,0))),"") | EC3: =IFERROR(IF(INDEX(MCDM_Grades!$J$2:$J$178,MATCH($A3,MCDM_Grades!$A$2:$A$178,0))="","",INDEX(MCDM_Grades!$J$2:$J$178,MATCH($A3,MCDM_Grades!$A$2:$A$178,0))),"") | ED3: =IFERROR(IF(INDEX(MCDM_Grades!$N$2:$N$178,MATCH($A3,MCDM_Grades!$A$2:$A$178,0))="","",INDEX(MCDM_Grades!$N$2:$N$178,MATCH($A3,MCDM_Grades!$A$2:$A$178,0))),"") | EE3: =IFERROR(IF(INDEX(MCDM_Grades!$O$2:$O$178,MATCH($A3,MCDM_Grades!$A$2:$A$178,0))="","",INDEX(MCDM_Grades!$O$2:$O$178,MATCH($A3,MCDM_Grades!$A$2:$A$178,0))),"") | EF3: =IFERROR(IF(INDEX(MCDM_Grades!$P$2:$P$178,MATCH($A3,MCDM_Grades!$A$2:$A$178,0))="","",INDEX(MCDM_Grades!$P$2:$P$178,MATCH($A3,MCDM_Grades!$A$2:$A$178,0))),"") | EG3: =IFERROR(IF(INDEX(MCDM_Grades!$Q$2:$Q$178,MATCH($A3,MCDM_Grades!$A$2:$A$178,0))="","",INDEX(MCDM_Grades!$Q$2:$Q$178,MATCH($A3,MCDM_Grades!$A$2:$A$178,0))),"") | EH3: =IFERROR(IF(INDEX(MCDM_Grades!$R$2:$R$178,MATCH($A3,MCDM_Grades!$A$2:$A$178,0))="","",INDEX(MCDM_Grades!$R$2:$R$178,MATCH($A3,MCDM_Grades!$A$2:$A$178,0))),"") | EI3: =IFERROR(IF(INDEX(MCDM_Grades!$S$2:$S$178,MATCH($A3,MCDM_Grades!$A$2:$A$178,0))="","",INDEX(MCDM_Grades!$S$2:$S$178,MATCH($A3,MCDM_Grades!$A$2:$A$178,0))),"") | EJ3: =IFERROR(IF(INDEX(MCDM_Grades!$T$2:$T$178,MATCH($A3,MCDM_Grades!$A$2:$A$178,0))="","",INDEX(MCDM_Grades!$T$2:$T$178,MATCH($A3,MCDM_Grades!$A$2:$A$178,0))),"") | EK3: =IFERROR(IF(INDEX(MCDM_Grades!$U$2:$U$178,MATCH($A3,MCDM_Grades!$A$2:$A$178,0))="","",INDEX(MCDM_Grades!$U$2:$U$178,MATCH($A3,MCDM_Grades!$A$2:$A$178,0))),"") | EL3: =IFERROR(IF(INDEX(MCDM_Grades!$V$2:$V$178,MATCH($A3,MCDM_Grades!$A$2:$A$178,0))="","",INDEX(MCDM_Grades!$V$2:$V$178,MATCH($A3,MCDM_Grades!$A$2:$A$178,0))),"") | EM3: =IFERROR(IF(INDEX(MCDM_Grades!$W$2:$W$178,MATCH($A3,MCDM_Grades!$A$2:$A$178,0))="","",INDEX(MCDM_Grades!$W$2:$W$178,MATCH($A3,MCDM_Grades!$A$2:$A$178,0))),"") | EN3: =IFERROR(IF(INDEX(MCDM_Grades!$X$2:$X$178,MATCH($A3,MCDM_Grades!$A$2:$A$178,0))="","",INDEX(MCDM_Grades!$X$2:$X$178,MATCH($A3,MCDM_Grades!$A$2:$A$178,0))),"") | EO3: =IFERROR(IF(INDEX(MCDM_Grades!$Y$2:$Y$178,MATCH($A3,MCDM_Grades!$A$2:$A$178,0))="","",INDEX(MCDM_Grades!$Y$2:$Y$178,MATCH($A3,MCDM_Grades!$A$2:$A$178,0))),"") | EP3: =IFERROR(IF(INDEX(MCDM_Grades!$Z$2:$Z$178,MATCH($A3,MCDM_Grades!$A$2:$A$178,0))="","",INDEX(MCDM_Grades!$Z$2:$Z$178,MATCH($A3,MCDM_Grades!$A$2:$A$178,0))),"") | EQ3: =IFERROR(IF(INDEX(MCDM_Grades!$AA$2:$AA$178,MATCH($A3,MCDM_Grades!$A$2:$A$178,0))="","",INDEX(MCDM_Grades!$AA$2:$AA$178,MATCH($A3,MCDM_Grades!$A$2:$A$178,0))),"") | ER3: =IFERROR(IF(INDEX(MCDM_Grades!$AB$2:$AB$178,MATCH($A3,MCDM_Grades!$A$2:$A$178,0))="","",INDEX(MCDM_Grades!$AB$2:$AB$178,MATCH($A3,MCDM_Grades!$A$2:$A$178,0))),"") | ES3: =IFERROR(IF(INDEX(MCDM_Grades!$AC$2:$AC$178,MATCH($A3,MCDM_Grades!$A$2:$A$178,0))="","",INDEX(MCDM_Grades!$AC$2:$AC$178,MATCH($A3,MCDM_Grades!$A$2:$A$178,0))),"") | ET3: =IFERROR(IF(INDEX(MCDM_Grades!$AD$2:$AD$178,MATCH($A3,MCDM_Grades!$A$2:$A$178,0))="","",INDEX(MCDM_Grades!$AD$2:$AD$178,MATCH($A3,MCDM_Grades!$A$2:$A$178,0))),"") | EU3: =IFERROR(IF(INDEX(MCDM_Grades!$AE$2:$AE$178,MATCH($A3,MCDM_Grades!$A$2:$A$178,0))="","",INDEX(MCDM_Grades!$AE$2:$AE$178,MATCH($A3,MCDM_Grades!$A$2:$A$178,0))),"") | EV3: =IFERROR(IF(INDEX(MCDM_Grades!$K$2:$K$178,MATCH($A3,MCDM_Grades!$A$2:$A$178,0))="","",INDEX(MCDM_Grades!$K$2:$K$178,MATCH($A3,MCDM_Grades!$A$2:$A$178,0))),"") | EW3: =IFERROR(IF(INDEX(MCDM_Grades!$L$2:$L$178,MATCH($A3,MCDM_Grades!$A$2:$A$178,0))="","",INDEX(MCDM_Grades!$L$2:$L$178,MATCH($A3,MCDM_Grades!$A$2:$A$178,0))),"") | EX3: =IFERROR(IF(INDEX(MCDM_Grades!$M$2:$M$178,MATCH($A3,MCDM_Grades!$A$2:$A$178,0))="","",INDEX(MCDM_Grades!$M$2:$M$178,MATCH($A3,MCDM_Grades!$A$2:$A$178,0))),"") | EY3: =IFERROR(IF(INDEX(MCDM_Grades!$AR$2:$AR$178,MATCH($A3,MCDM_Grades!$A$2:$A$178,0))="","",INDEX(MCDM_Grades!$AR$2:$AR$178,MATCH($A3,MCDM_Grades!$A$2:$A$178,0))),"") | EZ3: =IFERROR(IF(INDEX(MCDM_Grades!$AS$2:$AS$178,MATCH($A3,MCDM_Grades!$A$2:$A$178,0))="","",INDEX(MCDM_Grades!$AS$2:$AS$178,MATCH($A3,MCDM_Grades!$A$2:$A$178,0))),"") | FA3: =IFERROR(IF(INDEX(MCDM_Grades!$AT$2:$AT$178,MATCH($A3,MCDM_Grades!$A$2:$A$178,0))="","",INDEX(MCDM_Grades!$AT$2:$AT$178,MATCH($A3,MCDM_Grades!$A$2:$A$178,0))),"") | FB3: =IFERROR(IF(INDEX(MCDM_Grades!$AU$2:$AU$178,MATCH($A3,MCDM_Grades!$A$2:$A$178,0))="","",INDEX(MCDM_Grades!$AU$2:$AU$178,MATCH($A3,MCDM_Grades!$A$2:$A$178,0))),"") | FC3: Not reported | FD3: Unknown | FE3: Unknown | FG3: Not reported | FH3: Download target not resolved; no count, license, persistent data identifier, annotation format, geography, or collection details | FI3: None | FK3: Medium | FL3: Not independently verified | FM3: All workbook acquisition fields NR. Fetched https://github.com/Oct-Sunn/Asphalt-Pavement-Distress-Dataset: README only says the dataset 'features labeled images of asphalt conditions across six distress categories' and links a Google Drive archive; no camera, platform or viewpoint statement. The model repository https://github.com/zyf991121/DSWMamba returned HTTP 404. A web search found the DSWMamba paper (Construction and Building Materials, S0950061825005410; 13,129 images, six distress types) but only the paywalled abstract, which does not describe acquisition. Medium rather than High because the full paper (not fetched within the 2-fetch budget) may document the camera set-up.
A4: DS-003 | B4: CiCS pavement crack image dataset | C4: NA | D4: v1 (in-repo rar archives, 5 parts) | E4: Independent Dataset | F4: NA (single source record) | G4: Single source record; no matching record found in any other file after cross-file and cross-platform comparison. | H4: Claude | I4: GitHub | J4: N | K4: NA (single platform) | L4: https://github.com/DrEdwardLee/Pavement-Crack-Dataset | M4: https://github.com/DrEdwardLee/Pavement-Crack-Dataset | N4: NA | O4: NA | P4: NA | Q4: NA | R4: NA | S4: NA | T4: NR | U4: N | V4: NR | W4: NR | X4: NR | Y4: NR | Z4: NA | AA4: NA | AB4: NR | AC4: NR | AD4: NR | AE4: NR | AF4: NR | AG4: NR | AH4: NR | AI4: NR | AJ4: NR | AK4: NR | AL4: NR | AM4: NR | AN4: NR | AO4: NR | AP4: NR | AQ4: NR | AR4: NR | AS4: Road environment: Pavements | AT4: NR | AU4: NR | AV4: NR | AW4: NR | AX4: NR | AY4: NR | AZ4: NR | BA4: NR | BB4: NR | BC4: NR | BD4: NR | BE4: NR | BF4: NR | BG4: NR | BH4: Pavement cracks (undifferentiated crack class) | BI4: NR | BJ4: UNK (no README; annotation presence not verifiable from file listing) | BK4: NR | BL4: NR | BM4: NR | BN4: NR | BO4: NR | BP4: NR | BQ4: NR | BR4: NR | BS4: NR | BT4: NR | BU4: NR | BV4: NR | BW4: NR | BX4: NR | BY4: NR | BZ4: NR | CA4: NR | CB4: NR | CC4: Crack detection (per repo description) | CD4: NR | CE4: NR | CF4: Reported on the source record/data card or associated publication (see Evidence_Locator) | CG4: NR | CH4: NR | CI4: Include-Supplementary | CJ4: Direct_Download | CK4: NR | CL4: N | CM4: Direct_Download | CN4: NR | CO4: NR | CP4: N | CQ4: No README or documentation; annotations, counts, provenance, and license all unverified (data stored as CiCS-Data(1-5).rar in repo) | CR4: Original | CS4: N | CT4: N | CU4: N | CV4: NA | CW4: CrackBlock600k (same CiCS acquisition-system lineage); LEiS pavement crack image dataset (same repository) | CX4: Claude_Github_001.xlsx | CY4: Claude_Github_001:GH-DS-019 | CZ4: N | DA4: NA | DB4: None | DC4: None | DD4: None | DE4: None | DF4: N | DG4: Single source record; no reconciliation required. | DH4: GitHub repository file listing, https://github.com/DrEdwardLee/Pavement-Crack-Dataset (accessed 2026-08-06) | DI4: Low | DJ4: Low | DK4: Use source record as cited. | DL4: 4 | DM4: 1 | DN4: 1 | DO4: 0 | DP4: 1 | DQ4: 1 | DR4: 0 | DS4: 27 | DT4: Reviewed (source MCDM_Scoring, averaged across batches) | DU4: 1 of 1 | DV4: =IFERROR(IF(INDEX(MCDM_Grades!$C$2:$C$178,MATCH($A4,MCDM_Grades!$A$2:$A$178,0))="","",INDEX(MCDM_Grades!$C$2:$C$178,MATCH($A4,MCDM_Grades!$A$2:$A$178,0))),"") | DW4: =IFERROR(IF(INDEX(MCDM_Grades!$D$2:$D$178,MATCH($A4,MCDM_Grades!$A$2:$A$178,0))="","",INDEX(MCDM_Grades!$D$2:$D$178,MATCH($A4,MCDM_Grades!$A$2:$A$178,0))),"") | DX4: =IFERROR(IF(INDEX(MCDM_Grades!$E$2:$E$178,MATCH($A4,MCDM_Grades!$A$2:$A$178,0))="","",INDEX(MCDM_Grades!$E$2:$E$178,MATCH($A4,MCDM_Grades!$A$2:$A$178,0))),"") | DY4: =IFERROR(IF(INDEX(MCDM_Grades!$F$2:$F$178,MATCH($A4,MCDM_Grades!$A$2:$A$178,0))="","",INDEX(MCDM_Grades!$F$2:$F$178,MATCH($A4,MCDM_Grades!$A$2:$A$178,0))),"") | DZ4: =IFERROR(IF(INDEX(MCDM_Grades!$G$2:$G$178,MATCH($A4,MCDM_Grades!$A$2:$A$178,0))="","",INDEX(MCDM_Grades!$G$2:$G$178,MATCH($A4,MCDM_Grades!$A$2:$A$178,0))),"") | EA4: =IFERROR(IF(INDEX(MCDM_Grades!$H$2:$H$178,MATCH($A4,MCDM_Grades!$A$2:$A$178,0))="","",INDEX(MCDM_Grades!$H$2:$H$178,MATCH($A4,MCDM_Grades!$A$2:$A$178,0))),"") | EB4: =IFERROR(IF(INDEX(MCDM_Grades!$I$2:$I$178,MATCH($A4,MCDM_Grades!$A$2:$A$178,0))="","",INDEX(MCDM_Grades!$I$2:$I$178,MATCH($A4,MCDM_Grades!$A$2:$A$178,0))),"") | EC4: =IFERROR(IF(INDEX(MCDM_Grades!$J$2:$J$178,MATCH($A4,MCDM_Grades!$A$2:$A$178,0))="","",INDEX(MCDM_Grades!$J$2:$J$178,MATCH($A4,MCDM_Grades!$A$2:$A$178,0))),"") | ED4: =IFERROR(IF(INDEX(MCDM_Grades!$N$2:$N$178,MATCH($A4,MCDM_Grades!$A$2:$A$178,0))="","",INDEX(MCDM_Grades!$N$2:$N$178,MATCH($A4,MCDM_Grades!$A$2:$A$178,0))),"") | EE4: =IFERROR(IF(INDEX(MCDM_Grades!$O$2:$O$178,MATCH($A4,MCDM_Grades!$A$2:$A$178,0))="","",INDEX(MCDM_Grades!$O$2:$O$178,MATCH($A4,MCDM_Grades!$A$2:$A$178,0))),"") | EF4: =IFERROR(IF(INDEX(MCDM_Grades!$P$2:$P$178,MATCH($A4,MCDM_Grades!$A$2:$A$178,0))="","",INDEX(MCDM_Grades!$P$2:$P$178,MATCH($A4,MCDM_Grades!$A$2:$A$178,0))),"") | EG4: =IFERROR(IF(INDEX(MCDM_Grades!$Q$2:$Q$178,MATCH($A4,MCDM_Grades!$A$2:$A$178,0))="","",INDEX(MCDM_Grades!$Q$2:$Q$178,MATCH($A4,MCDM_Grades!$A$2:$A$178,0))),"") | EH4: =IFERROR(IF(INDEX(MCDM_Grades!$R$2:$R$178,MATCH($A4,MCDM_Grades!$A$2:$A$178,0))="","",INDEX(MCDM_Grades!$R$2:$R$178,MATCH($A4,MCDM_Grades!$A$2:$A$178,0))),"") | EI4: =IFERROR(IF(INDEX(MCDM_Grades!$S$2:$S$178,MATCH($A4,MCDM_Grades!$A$2:$A$178,0))="","",INDEX(MCDM_Grades!$S$2:$S$178,MATCH($A4,MCDM_Grades!$A$2:$A$178,0))),"") | EJ4: =IFERROR(IF(INDEX(MCDM_Grades!$T$2:$T$178,MATCH($A4,MCDM_Grades!$A$2:$A$178,0))="","",INDEX(MCDM_Grades!$T$2:$T$178,MATCH($A4,MCDM_Grades!$A$2:$A$178,0))),"") | EK4: =IFERROR(IF(INDEX(MCDM_Grades!$U$2:$U$178,MATCH($A4,MCDM_Grades!$A$2:$A$178,0))="","",INDEX(MCDM_Grades!$U$2:$U$178,MATCH($A4,MCDM_Grades!$A$2:$A$178,0))),"") | EL4: =IFERROR(IF(INDEX(MCDM_Grades!$V$2:$V$178,MATCH($A4,MCDM_Grades!$A$2:$A$178,0))="","",INDEX(MCDM_Grades!$V$2:$V$178,MATCH($A4,MCDM_Grades!$A$2:$A$178,0))),"") | EM4: =IFERROR(IF(INDEX(MCDM_Grades!$W$2:$W$178,MATCH($A4,MCDM_Grades!$A$2:$A$178,0))="","",INDEX(MCDM_Grades!$W$2:$W$178,MATCH($A4,MCDM_Grades!$A$2:$A$178,0))),"") | EN4: =IFERROR(IF(INDEX(MCDM_Grades!$X$2:$X$178,MATCH($A4,MCDM_Grades!$A$2:$A$178,0))="","",INDEX(MCDM_Grades!$X$2:$X$178,MATCH($A4,MCDM_Grades!$A$2:$A$178,0))),"") | EO4: =IFERROR(IF(INDEX(MCDM_Grades!$Y$2:$Y$178,MATCH($A4,MCDM_Grades!$A$2:$A$178,0))="","",INDEX(MCDM_Grades!$Y$2:$Y$178,MATCH($A4,MCDM_Grades!$A$2:$A$178,0))),"") | EP4: =IFERROR(IF(INDEX(MCDM_Grades!$Z$2:$Z$178,MATCH($A4,MCDM_Grades!$A$2:$A$178,0))="","",INDEX(MCDM_Grades!$Z$2:$Z$178,MATCH($A4,MCDM_Grades!$A$2:$A$178,0))),"") | EQ4: =IFERROR(IF(INDEX(MCDM_Grades!$AA$2:$AA$178,MATCH($A4,MCDM_Grades!$A$2:$A$178,0))="","",INDEX(MCDM_Grades!$AA$2:$AA$178,MATCH($A4,MCDM_Grades!$A$2:$A$178,0))),"") | ER4: =IFERROR(IF(INDEX(MCDM_Grades!$AB$2:$AB$178,MATCH($A4,MCDM_Grades!$A$2:$A$178,0))="","",INDEX(MCDM_Grades!$AB$2:$AB$178,MATCH($A4,MCDM_Grades!$A$2:$A$178,0))),"") | ES4: =IFERROR(IF(INDEX(MCDM_Grades!$AC$2:$AC$178,MATCH($A4,MCDM_Grades!$A$2:$A$178,0))="","",INDEX(MCDM_Grades!$AC$2:$AC$178,MATCH($A4,MCDM_Grades!$A$2:$A$178,0))),"") | ET4: =IFERROR(IF(INDEX(MCDM_Grades!$AD$2:$AD$178,MATCH($A4,MCDM_Grades!$A$2:$A$178,0))="","",INDEX(MCDM_Grades!$AD$2:$AD$178,MATCH($A4,MCDM_Grades!$A$2:$A$178,0))),"") | EU4: =IFERROR(IF(INDEX(MCDM_Grades!$AE$2:$AE$178,MATCH($A4,MCDM_Grades!$A$2:$A$178,0))="","",INDEX(MCDM_Grades!$AE$2:$AE$178,MATCH($A4,MCDM_Grades!$A$2:$A$178,0))),"") | EV4: =IFERROR(IF(INDEX(MCDM_Grades!$K$2:$K$178,MATCH($A4,MCDM_Grades!$A$2:$A$178,0))="","",INDEX(MCDM_Grades!$K$2:$K$178,MATCH($A4,MCDM_Grades!$A$2:$A$178,0))),"") | EW4: =IFERROR(IF(INDEX(MCDM_Grades!$L$2:$L$178,MATCH($A4,MCDM_Grades!$A$2:$A$178,0))="","",INDEX(MCDM_Grades!$L$2:$L$178,MATCH($A4,MCDM_Grades!$A$2:$A$178,0))),"") | EX4: =IFERROR(IF(INDEX(MCDM_Grades!$M$2:$M$178,MATCH($A4,MCDM_Grades!$A$2:$A$178,0))="","",INDEX(MCDM_Grades!$M$2:$M$178,MATCH($A4,MCDM_Grades!$A$2:$A$178,0))),"") | EY4: =IFERROR(IF(INDEX(MCDM_Grades!$AR$2:$AR$178,MATCH($A4,MCDM_Grades!$A$2:$A$178,0))="","",INDEX(MCDM_Grades!$AR$2:$AR$178,MATCH($A4,MCDM_Grades!$A$2:$A$178,0))),"") | EZ4: =IFERROR(IF(INDEX(MCDM_Grades!$AS$2:$AS$178,MATCH($A4,MCDM_Grades!$A$2:$A$178,0))="","",INDEX(MCDM_Grades!$AS$2:$AS$178,MATCH($A4,MCDM_Grades!$A$2:$A$178,0))),"") | FA4: =IFERROR(IF(INDEX(MCDM_Grades!$AT$2:$AT$178,MATCH($A4,MCDM_Grades!$A$2:$A$178,0))="","",INDEX(MCDM_Grades!$AT$2:$AT$178,MATCH($A4,MCDM_Grades!$A$2:$A$178,0))),"") | FB4: =IFERROR(IF(INDEX(MCDM_Grades!$AU$2:$AU$178,MATCH($A4,MCDM_Grades!$A$2:$A$178,0))="","",INDEX(MCDM_Grades!$AU$2:$AU$178,MATCH($A4,MCDM_Grades!$A$2:$A$178,0))),"") | FC4: Not reported | FD4: Unknown | FE4: Unknown | FG4: Not reported | FH4: No README or documentation; annotations, counts, provenance, and license all unverified (data stored as CiCS-Data(1-5).rar in repo) | FI4: None | FK4: Medium | FL4: Not independently verified | FM4: Workbook acquisition fields all NR and no publication. Fetched https://github.com/DrEdwardLee/Pavement-Crack-Dataset: only the tagline 'We have published two new pavement crack image dataset, named Cics Dataset and Leis Dataset' and rar archives (CiCS-Data parts 1-5, LEiS-Data, CrackForest-Data, MPS-Dataset); the acronyms CiCS/LEiS are not expanded and no camera or viewpoint is described. A web search for 'CiCS' 'LEiS' pavement crack returned nothing relevant. The workbook's Related_Datasets note ('same CiCS acquisition-system lineage' with CrackBlock600k) hints at a dedicated acquisition system, but its geometry is undocumented in any reachable source, so Medium.
A5: DS-004 | B5: complexPavementCrackDataset | C5: NA | D5: v1 | E5: Independent Dataset | F5: NA (single source record) | G5: Single source record; no matching record found in any other file after cross-file and cross-platform comparison. | H5: Claude | I5: GitHub | J5: N | K5: NA (single platform) | L5: https://github.com/SEU-zhc/complexPavementCrackDataset | M5: https://github.com/SEU-zhc/complexPavementCrackDataset | N5: NA | O5: NA | P5: NA | Q5: NA | R5: NA | S5: NA | T5: NR | U5: N | V5: NR | W5: NR | X5: NR | Y5: NR | Z5: NA | AA5: NA | AB5: Images/frames as reported | AC5: 500 | AD5: NR | AE5: NR | AF5: 500 | AG5: NR | AH5: NR | AI5: NR | AJ5: NR | AK5: NR | AL5: NR | AM5: NR | AN5: NR | AO5: NR | AP5: NR | AQ5: NR | AR5: NR | AS5: Road environment: Pavements with shadows, watermarks, brake marks and environmental noise | AT5: NR | AU5: Onboard (vehicle) cameras | AV5: See Acquisition_Platform | AW5: Onboard (vehicle) cameras | AX5: See Acquisition_Platform (reported: onboard) | AY5: NR | AZ5: NR | BA5: NR | BB5: N | BC5: NR | BD5: NR | BE5: NR | BF5: NR | BG5: NR | BH5: Pavement cracks (complex-background crack class) | BI5: NR | BJ5: Bounding boxes (class xc yc w h) and binary crack masks | BK5: NR | BL5: Object detection;Semantic segmentation | BM5: Object detection;Semantic segmentation | BN5: YOLO-style txt;binary mask images | BO5: YOLO; TXT; mask | BP5: NR | BQ5: Y | BR5: Y | BS5: NR | BT5: NR | BU5: NR | BV5: N | BW5: N | BX5: N | BY5: NR | BZ5: NR | CA5: NR | CB5: NR | CC5: Object detection;Semantic segmentation | CD5: NR | CE5: NR | CF5: Reported on the source record/data card or associated publication (see Evidence_Locator) | CG5: NR | CH5: NR | CI5: Include-Supplementary | CJ5: Restricted | CK5: NR | CL5: NR | CM5: Restricted | CN5: NR | CO5: NR | CP5: N | CQ5: Baidu-only hosting limits international research access; 'over 500 images' recorded as 500 minimum; no paper or license | CR5: Original | CS5: N | CT5: N | CU5: N | CV5: NA | CW5: NA | CX5: Claude_Github_001.xlsx | CY5: Claude_Github_001:GH-DS-017 | CZ5: N | DA5: NA | DB5: None | DC5: None | DD5: None | DE5: None | DF5: N | DG5: Single source record; no reconciliation required. | DH5: GitHub README (Overview, Download, Annotations), https://github.com/SEU-zhc/complexPavementCrackDataset (accessed 2026-08-06) | DI5: Moderate | DJ5: Low | DK5: Use source record as cited. | DL5: 2 | DM5: 4 | DN5: 2.5 | DO5: 2 | DP5: 3 | DQ5: 1 | DR5: 0 | DS5: 45.5 | DT5: Reviewed (source MCDM_Scoring, averaged across batches) | DU5: 1 of 1 | DV5: =IFERROR(IF(INDEX(MCDM_Grades!$C$2:$C$178,MATCH($A5,MCDM_Grades!$A$2:$A$178,0))="","",INDEX(MCDM_Grades!$C$2:$C$178,MATCH($A5,MCDM_Grades!$A$2:$A$178,0))),"") | DW5: =IFERROR(IF(INDEX(MCDM_Grades!$D$2:$D$178,MATCH($A5,MCDM_Grades!$A$2:$A$178,0))="","",INDEX(MCDM_Grades!$D$2:$D$178,MATCH($A5,MCDM_Grades!$A$2:$A$178,0))),"") | DX5: =IFERROR(IF(INDEX(MCDM_Grades!$E$2:$E$178,MATCH($A5,MCDM_Grades!$A$2:$A$178,0))="","",INDEX(MCDM_Grades!$E$2:$E$178,MATCH($A5,MCDM_Grades!$A$2:$A$178,0))),"") | DY5: =IFERROR(IF(INDEX(MCDM_Grades!$F$2:$F$178,MATCH($A5,MCDM_Grades!$A$2:$A$178,0))="","",INDEX(MCDM_Grades!$F$2:$F$178,MATCH($A5,MCDM_Grades!$A$2:$A$178,0))),"") | DZ5: =IFERROR(IF(INDEX(MCDM_Grades!$G$2:$G$178,MATCH($A5,MCDM_Grades!$A$2:$A$178,0))="","",INDEX(MCDM_Grades!$G$2:$G$178,MATCH($A5,MCDM_Grades!$A$2:$A$178,0))),"") | EA5: =IFERROR(IF(INDEX(MCDM_Grades!$H$2:$H$178,MATCH($A5,MCDM_Grades!$A$2:$A$178,0))="","",INDEX(MCDM_Grades!$H$2:$H$178,MATCH($A5,MCDM_Grades!$A$2:$A$178,0))),"") | EB5: =IFERROR(IF(INDEX(MCDM_Grades!$I$2:$I$178,MATCH($A5,MCDM_Grades!$A$2:$A$178,0))="","",INDEX(MCDM_Grades!$I$2:$I$178,MATCH($A5,MCDM_Grades!$A$2:$A$178,0))),"") | EC5: =IFERROR(IF(INDEX(MCDM_Grades!$J$2:$J$178,MATCH($A5,MCDM_Grades!$A$2:$A$178,0))="","",INDEX(MCDM_Grades!$J$2:$J$178,MATCH($A5,MCDM_Grades!$A$2:$A$178,0))),"") | ED5: =IFERROR(IF(INDEX(MCDM_Grades!$N$2:$N$178,MATCH($A5,MCDM_Grades!$A$2:$A$178,0))="","",INDEX(MCDM_Grades!$N$2:$N$178,MATCH($A5,MCDM_Grades!$A$2:$A$178,0))),"") | EE5: =IFERROR(IF(INDEX(MCDM_Grades!$O$2:$O$178,MATCH($A5,MCDM_Grades!$A$2:$A$178,0))="","",INDEX(MCDM_Grades!$O$2:$O$178,MATCH($A5,MCDM_Grades!$A$2:$A$178,0))),"") | EF5: =IFERROR(IF(INDEX(MCDM_Grades!$P$2:$P$178,MATCH($A5,MCDM_Grades!$A$2:$A$178,0))="","",INDEX(MCDM_Grades!$P$2:$P$178,MATCH($A5,MCDM_Grades!$A$2:$A$178,0))),"") | EG5: =IFERROR(IF(INDEX(MCDM_Grades!$Q$2:$Q$178,MATCH($A5,MCDM_Grades!$A$2:$A$178,0))="","",INDEX(MCDM_Grades!$Q$2:$Q$178,MATCH($A5,MCDM_Grades!$A$2:$A$178,0))),"") | EH5: =IFERROR(IF(INDEX(MCDM_Grades!$R$2:$R$178,MATCH($A5,MCDM_Grades!$A$2:$A$178,0))="","",INDEX(MCDM_Grades!$R$2:$R$178,MATCH($A5,MCDM_Grades!$A$2:$A$178,0))),"") | EI5: =IFERROR(IF(INDEX(MCDM_Grades!$S$2:$S$178,MATCH($A5,MCDM_Grades!$A$2:$A$178,0))="","",INDEX(MCDM_Grades!$S$2:$S$178,MATCH($A5,MCDM_Grades!$A$2:$A$178,0))),"") | EJ5: =IFERROR(IF(INDEX(MCDM_Grades!$T$2:$T$178,MATCH($A5,MCDM_Grades!$A$2:$A$178,0))="","",INDEX(MCDM_Grades!$T$2:$T$178,MATCH($A5,MCDM_Grades!$A$2:$A$178,0))),"") | EK5: =IFERROR(IF(INDEX(MCDM_Grades!$U$2:$U$178,MATCH($A5,MCDM_Grades!$A$2:$A$178,0))="","",INDEX(MCDM_Grades!$U$2:$U$178,MATCH($A5,MCDM_Grades!$A$2:$A$178,0))),"") | EL5: =IFERROR(IF(INDEX(MCDM_Grades!$V$2:$V$178,MATCH($A5,MCDM_Grades!$A$2:$A$178,0))="","",INDEX(MCDM_Grades!$V$2:$V$178,MATCH($A5,MCDM_Grades!$A$2:$A$178,0))),"") | EM5: =IFERROR(IF(INDEX(MCDM_Grades!$W$2:$W$178,MATCH($A5,MCDM_Grades!$A$2:$A$178,0))="","",INDEX(MCDM_Grades!$W$2:$W$178,MATCH($A5,MCDM_Grades!$A$2:$A$178,0))),"") | EN5: =IFERROR(IF(INDEX(MCDM_Grades!$X$2:$X$178,MATCH($A5,MCDM_Grades!$A$2:$A$178,0))="","",INDEX(MCDM_Grades!$X$2:$X$178,MATCH($A5,MCDM_Grades!$A$2:$A$178,0))),"") | EO5: =IFERROR(IF(INDEX(MCDM_Grades!$Y$2:$Y$178,MATCH($A5,MCDM_Grades!$A$2:$A$178,0))="","",INDEX(MCDM_Grades!$Y$2:$Y$178,MATCH($A5,MCDM_Grades!$A$2:$A$178,0))),"") | EP5: =IFERROR(IF(INDEX(MCDM_Grades!$Z$2:$Z$178,MATCH($A5,MCDM_Grades!$A$2:$A$178,0))="","",INDEX(MCDM_Grades!$Z$2:$Z$178,MATCH($A5,MCDM_Grades!$A$2:$A$178,0))),"") | EQ5: =IFERROR(IF(INDEX(MCDM_Grades!$AA$2:$AA$178,MATCH($A5,MCDM_Grades!$A$2:$A$178,0))="","",INDEX(MCDM_Grades!$AA$2:$AA$178,MATCH($A5,MCDM_Grades!$A$2:$A$178,0))),"") | ER5: =IFERROR(IF(INDEX(MCDM_Grades!$AB$2:$AB$178,MATCH($A5,MCDM_Grades!$A$2:$A$178,0))="","",INDEX(MCDM_Grades!$AB$2:$AB$178,MATCH($A5,MCDM_Grades!$A$2:$A$178,0))),"") | ES5: =IFERROR(IF(INDEX(MCDM_Grades!$AC$2:$AC$178,MATCH($A5,MCDM_Grades!$A$2:$A$178,0))="","",INDEX(MCDM_Grades!$AC$2:$AC$178,MATCH($A5,MCDM_Grades!$A$2:$A$178,0))),"") | ET5: =IFERROR(IF(INDEX(MCDM_Grades!$AD$2:$AD$178,MATCH($A5,MCDM_Grades!$A$2:$A$178,0))="","",INDEX(MCDM_Grades!$AD$2:$AD$178,MATCH($A5,MCDM_Grades!$A$2:$A$178,0))),"") | EU5: =IFERROR(IF(INDEX(MCDM_Grades!$AE$2:$AE$178,MATCH($A5,MCDM_Grades!$A$2:$A$178,0))="","",INDEX(MCDM_Grades!$AE$2:$AE$178,MATCH($A5,MCDM_Grades!$A$2:$A$178,0))),"") | EV5: =IFERROR(IF(INDEX(MCDM_Grades!$K$2:$K$178,MATCH($A5,MCDM_Grades!$A$2:$A$178,0))="","",INDEX(MCDM_Grades!$K$2:$K$178,MATCH($A5,MCDM_Grades!$A$2:$A$178,0))),"") | EW5: =IFERROR(IF(INDEX(MCDM_Grades!$L$2:$L$178,MATCH($A5,MCDM_Grades!$A$2:$A$178,0))="","",INDEX(MCDM_Grades!$L$2:$L$178,MATCH($A5,MCDM_Grades!$A$2:$A$178,0))),"") | EX5: =IFERROR(IF(INDEX(MCDM_Grades!$M$2:$M$178,MATCH($A5,MCDM_Grades!$A$2:$A$178,0))="","",INDEX(MCDM_Grades!$M$2:$M$178,MATCH($A5,MCDM_Grades!$A$2:$A$178,0))),"") | EY5: =IFERROR(IF(INDEX(MCDM_Grades!$AR$2:$AR$178,MATCH($A5,MCDM_Grades!$A$2:$A$178,0))="","",INDEX(MCDM_Grades!$AR$2:$AR$178,MATCH($A5,MCDM_Grades!$A$2:$A$178,0))),"") | EZ5: =IFERROR(IF(INDEX(MCDM_Grades!$AS$2:$AS$178,MATCH($A5,MCDM_Grades!$A$2:$A$178,0))="","",INDEX(MCDM_Grades!$AS$2:$AS$178,MATCH($A5,MCDM_Grades!$A$2:$A$178,0))),"") | FA5: =IFERROR(IF(INDEX(MCDM_Grades!$AT$2:$AT$178,MATCH($A5,MCDM_Grades!$A$2:$A$178,0))="","",INDEX(MCDM_Grades!$AT$2:$AT$178,MATCH($A5,MCDM_Grades!$A$2:$A$178,0))),"") | FB5: =IFERROR(IF(INDEX(MCDM_Grades!$AU$2:$AU$178,MATCH($A5,MCDM_Grades!$A$2:$A$178,0))="","",INDEX(MCDM_Grades!$AU$2:$AU$178,MATCH($A5,MCDM_Grades!$A$2:$A$178,0))),"") | FC5: Forward-facing / oblique | FD5: No | FE5: Yes | FG5: Vehicle onboard forward-facing camera (dash/bumper-level, wide-angle) | FH5: These images have been captured using onboard cameras, showcasing pavement surfaces under various conditions, including shadows, watermarks, brake marks, and other environmental noises. | FI5: Dataset page / README | FJ5: https://github.com/SEU-zhc/complexPavementCrackDataset | FK5: High | FL5: Not independently verified | FM5: Workbook: 'Onboard (vehicle) cameras' (hint 'forward?'). README quote gives the platform but not the angle; the README figure samples.png (fetched from the repo, 1656x954, four frames) settles it: every frame is a driving-perspective view along the road with sky, buildings, trees, lane markings, parked/oncoming cars and strong perspective foreshortening, one frame from a low bumper-level wide-angle position. No top-down frames. Consistent with the SEU group's CDM paper (Zhang et al. 2024, CACAIE 10.1111/mice.13171) describing 'images captured by on-board cameras' with water stains, shadows and brake marks.
A6: DS-005 | B6: CQU-BPDD (Chongqing University Bituminous Pavement Disease Detection Dataset) | C6: CQU-BPDD | D6: v1 [Claude] | Hugging Face image-folder mirror [GPT] | E6: Confirmed Match | F6: High | G6: Identical image count (60,056) in all four records; same seven-distress taxonomy; same professional inspection-vehicle acquisition (China); GitHub (DearCaat) and Hugging Face (Dearcat/CQU-BPDD) records are from the same research group; same publication family (IOPLIN 10.1109/TITS.2021.3093389; PicT; WSPLIN). | H6: Claude; GPT; GitHub_Test_Batch (tool UNK) | I6: GitHub; Hugging Face | J6: Y | K6: Mirror: GitHub project page with data access; Hugging Face hosts an image-folder redistribution by the same group | L6: https://github.com/DearCaat/Pavement-Distress-Classification | M6: https://github.com/DearCaat/Pavement-Distress-Classification; https://github.com/DearCaat/CQU-BPDD | N6: NA | O6: NA | P6: https://huggingface.co/datasets/Dearcat/CQU-BPDD | Q6: NA | R6: NA | S6: NA | T6: NR | U6: Y | V6: IOPLIN (IEEE T-ITS);PicT (ACM MM 2022);WSPLIN (IEEE T-ITS);WSPLIN-IP (ICASSP 2021);DPSSL (Electronics Letters) — per repository listing [Claude] | 10.1109/TITS.2021.3093389; https://arxiv.org/abs/2203.16782 [GPT] | https://doi.org/10.1016/j.conbuildmat.2022.128622 [GPT] | https://github.com/DearCaat/CQU-BPDD; https://github.com/DearCaat/PicT [Test_Batch] | W6: 10.1109/TITS.2021.3093389; 10.1016/j.conbuildmat.2022.128622 | X6: https://arxiv.org/abs/2203.16782; https://doi.org/10.1016/j.conbuildmat.2022.128622; https://github.com/DearCaat/CQU-BPDD; https://github.com/DearCaat/PicT | Y6: NR | Z6: Y | AA6: Reported in source record (relationship not classified) | AB6: Images/frames as reported | AC6: 60056 | AD6: NR | AE6: NR | AF6: 60056 | AG6: NR | AH6: NR | AI6: NR | AJ6: NR | AK6: NR | AL6: NR | AM6: NR | AN6: 1200x900 px (each image covers a 2x3 m pavement patch) [Claude] | 1200×900 [GPT] | 1200x900 [Test_Batch] | AO6: NR | AP6: China | AQ6: NR | AR6: Different areas in southern China [Claude] | Southern China [GPT/Test_Batch] | Chongqing and source-paper collection areas [GPT] | AS6: China; Different areas in southern China [Claude] | Southern China [GPT/Test_Batch] | Chongqing and source-paper collection areas [GPT]; Road environment: Highways [Claude] | Highway bituminous pavement [GPT] | Mixed [GPT] | Urban; highway [Test_Batch] | AT6: NR | AU6: In-vehicle cameras of professional pavement inspection vehicle [Claude] | Professional pavement inspection vehicle with in-vehicle cameras [GPT] | Vehicle-based pavement imagery; exact platform NR [GPT] | In-vehicle cameras on professional pavement inspection vehicle [Test_Batch] | AV6: See Acquisition_Platform | AW6: In-vehicle cameras of professional pavement inspection vehicle [Claude] | Professional pavement inspection vehicle with in-vehicle cameras [GPT] | Vehicle-based pavement imagery; exact platform NR [GPT] | In-vehicle cameras on professional pavement inspection vehicle [Test_Batch] | AX6: NR | AY6: NR | AZ6: NR | BA6: NR | BB6: N | BC6: NR | BD6: NR | BE6: NR | BF6: Different collection times [GPT] | Bright; low-light; shadow and interference conditions reported [GPT] | Different times [Test_Batch] | BG6: NR | BH6: Transverse crack;Massive crack;Alligator crack;Crack pouring (sealed crack);Longitudinal crack;Ravelling;Repair;Normal [Claude] | transverse crack; massive crack; alligator crack; crack pouring; longitudinal crack; ravelling; repair; normal [GPT] | Transverse_Crack; Massive_Crack; Alligator_Crack; Crack_Pouring; Longitudinal_Crack; Ravelling; Repair_Patch; Normal_No_Distress [GPT] | transverse crack; massive crack; alligator crack; crack pouring; longitudinal crack; ravelling; repair; normal pavement [Test_Batch] | BI6: Transverse crack;Massive crack;Alligator crack;Crack pouring (sealed crack);Longitudinal crack;Ravelling;Repair;Normal [Claude] | transverse crack; massive crack; alligator crack; crack pouring; longitudinal crack; ravelling; repair; normal [GPT] | Transverse_Crack; Massive_Crack; Alligator_Crack; Crack_Pouring; Longitudinal_Crack; Ravelling; Repair_Patch; Normal_No_Distress [GPT] | transverse crack; massive crack; alligator crack; crack pouring; longitudinal crack; ravelling; repair; normal pavement [Test_Batch] | BJ6: Seven distress classes plus normal (image-level labels) [Claude] | Seven distress categories plus normal [GPT] | Eight image-level pavement-condition classes; training set 10,137; test set 49,919 [GPT] | TC; MC; AC; CP; LC; Ravelling; Repair; Normal [Test_Batch] | BK6: NR | BL6: Image classification (distress detection and recognition) [Claude] | classification; weakly supervised localization [GPT] | Image_Classification [GPT] | Image classification; weakly supervised localization [Test_Batch] | BM6: Image classification (distress detection and recognition) [Claude] | classification; weakly supervised localization [GPT] | Image_Classification [GPT] | Image classification; weakly supervised localization [Test_Batch] | BN6: Image-level class labels [Claude] | image-level class labels; patch-level inference in published methods [GPT] | Image-folder class labels [GPT] | Folder labels; image-level labels [Test_Batch] | BO6: NR | BP6: Y | BQ6: NR | BR6: NR | BS6: NR | BT6: NR | BU6: NR | BV6: N | BW6: N | BX6: N | BY6: Image-level labeling; weakly supervised patch-label methods [GPT] | Manual or source-curated class assignment; detailed procedure NR in the HF card [GPT] | Manual image-level labeling [Test_Batch] | BZ6: Challenging-condition subsets are documented; detailed inter-rater controls NR | CA6: NR | CB6: NR | CC6: Classification;Weakly supervised distress recognition [Claude] | pavement distress classification; detection; recognition; weakly supervised localization [GPT] | Image_Classification [GPT] | classification; weakly supervised localization [Test_Batch] | CD6: PicT; IOPLIN; WSPLIN family | CE6: PicT; IOPLIN; WSPLIN family | CF6: Reported on the source record/data card or associated publication (see Evidence_Locator) | CG6: F1 and P@R reported in associated papers | CH6: NR | CI6: Include-Primary | CJ6: Direct_Download | CK6: NR (custom terms in README) [Claude] | Custom non-commercial terms; repository code Apache-2.0 [GPT] | CC BY-NC-SA 4.0 [Test_Batch] | CL6: N | CM6: Direct_Download | CN6: NR | CO6: NR | CP6: N | CQ6: Image-level labels only (no localization); non-commercial restriction; release year not stated on repo (recorded NR) [Claude] | Non-commercial restriction; image-level labels are weaker than full boxes/masks; exact collection dates and QC not reported [GPT] | License is not reported on the HF card; collection dates, exact camera specifications, resolution, weather, and engineering sensor metadata are incomplete. [GPT] | Image-level labels dominate; access mirrors and noncommercial terms reduce reproducibility for unrestricted reuse. [Test_Batch] | CR6: Original | CS6: Y | CT6: N | CU6: N | CV6: NA | CW6: NA | CX6: ChatGPT_Github_001.xlsx; ChatGPT_Huggingface_001.xlsx; Claude_Github_001.xlsx; Github_Github_Test.xlsx | CY6: ChatGPT_Github_001:GH-017; ChatGPT_Huggingface_001:HF005; Claude_Github_001:GH-DS-009; Github_Github_Test:GITHUB-008 | CZ6: Y - see conflict columns and Reconciliation_Notes | DA6: Y - see conflict columns and Reconciliation_Notes | DB6: Image resolution: 1200x900 px (each image covers a 2x3 m pavement patch) (Claude) vs 1200×900 (GPT) vs 1200x900 (Test_Batch) | DC6: Distress types: Transverse crack;Massive crack;Alligator crack;Crack pouring (sealed crack);Long (Claude) vs transverse crack; massive crack; alligator crack; crack pouring; longitudinal cr (GPT) vs Transverse_Crack; Massive_Crack; Alligator_Crack; Crack_Pouring; Longitudinal_Cr (GPT) vs transverse crack; massive crack; alligator crack; crack pouring; longitudinal cr (Test_Batch) || Label taxonomy: Seven distress classes plus normal (image-level labels) (Claude) vs Seven distress categories plus normal (GPT) vs Eight image-level pavement-condition classes; training set 10,137; test set 49,9 (GPT) vs TC; MC; AC; CP; LC; Ravelling; Repair; Normal (Test_Batch) || Annotation task: Image classification (distress detection and recognition) (Claude) vs classification; weakly supervised localization (GPT) vs Image_Classification (GPT) vs Image classification; weakly supervised localization (Test_Batch) || Annotation format: Image-level class labels (Claude) vs image-level class labels; patch-level inference in published methods (GPT) vs Image-folder class labels (GPT) vs Folder labels; image-level labels (Test_Batch) || Annotation method: Image-level labeling; weakly supervised patch-label methods (GPT) vs Manual or source-curated class assignment; detailed procedure NR in the HF card (GPT) vs Manual image-level labeling (Test_Batch) | DD6: None | DE6: Release year: 2021 (GPT/Test_Batch) vs 2022 (GPT) || Version: v1 (Claude) vs Hugging Face image-folder mirror (GPT) || License: NR (custom terms in README) (Claude) vs Custom non-commercial terms; repository code Apache-2.0 (GPT) vs CC BY-NC-SA 4.0 (Test_Batch) || AI tasks: Classification;Weakly supervised distress recognition (Claude) vs pavement distress classification; detection; recognition; weakly supervised loca (GPT) vs Image_Classification (GPT) vs classification; weakly supervised localization (Test_Batch) || Acquisition platform: In-vehicle cameras of professional pavement inspection vehicle (Claude) vs Professional pavement inspection vehicle with in-vehicle cameras (GPT) vs Vehicle-based pavement imagery; exact platform NR (GPT) vs In-vehicle cameras on professional pavement inspection vehicle (Test_Batch) || Region/City: Different areas in southern China (Claude) vs Southern China (GPT/Test_Batch) vs Chongqing and source-paper collection areas (GPT) || Road environment: Highways (Claude) vs Highway bituminous pavement (GPT) vs Mixed (GPT) vs Urban; highway (Test_Batch) || Publications: IOPLIN (IEEE T-ITS);PicT (ACM MM 2022);WSPLIN (IEEE T-ITS);WSPLIN-IP (ICASSP 202 (Claude) vs 10.1109/TITS.2021.3093389; https://arxiv.org/abs/2203.16782 (GPT) vs https://doi.org/10.1016/j.conbuildmat.2022.128622 (GPT) vs https://github.com/DearCaat/CQU-BPDD; https://github.com/DearCaat/PicT (Test_Batch) || Acquisition platform: In-vehicle cameras of professional pavement inspection vehicle (Claude) vs Professional pavement inspection vehicle with in-vehicle cameras (GPT) vs Vehicle-based pavement imagery; exact platform NR (GPT) vs In-vehicle cameras on professional pavement inspection vehicle (Test_Batch) || Lighting_Conditions: Different collection times (GPT) vs Bright; low-light; shadow and interference conditions reported (GPT) vs Different times (Test_Batch) || Key_Limitations: Image-level labels only (no localization); non-commercial restriction; release y (Claude) vs Non-commercial restriction; image-level labels are weaker than full boxes/masks; (GPT) vs License is not reported on the HF card; collection dates, exact camera specifica (GPT) vs Image-level labels dominate; access mirrors and noncommercial terms reduce repro (Test_Batch) | DF6: N | DG6: License conflict: custom non-commercial/research terms (GPT GitHub; Claude) vs CC BY-NC-SA 4.0 (Test batch) vs NR (HF card). Release year NR (Claude) vs 2021 (GPT, Test) vs 2022 (HF upload). | DH6: GitHub README 'CQU-BPDD' section, https://github.com/DearCaat/Pavement-Distress-Classification (canonical dataset repo https://github.com/DearCaat/CQU-BPDD) (accessed 2026-08-06) [Claude] | https://github.com/DearCaat/Pavement-Distress-Classification README CQU-BPDD section and citations; accessed 2026-08-06 [GPT] | https://huggingface.co/datasets/Dearcat/CQU-BPDD — dataset card class definitions and train/test counts; https://doi.org/10.1016/j.conbuildmat.2022.128622 — source publication (accessed 2026-08-06) [GPT] | https://github.com/DearCaat/CQU-BPDD; README dataset description, class table, and download links; accessed 2026-08-01 [Test_Batch] | DI6: Moderate | DJ6: Medium | DK6: Confirm license terms with authors before non-academic use. | DL6: 4.2 | DM6: 3 | DN6: 3.9 | DO6: 4.8 | DP6: 3.2 | DQ6: 1.5 | DR6: 1 | DS6: 66.3 | DT6: Reviewed (source MCDM_Scoring, averaged across batches) | DU6: 4 of 4 | DV6: =IFERROR(IF(INDEX(MCDM_Grades!$C$2:$C$178,MATCH($A6,MCDM_Grades!$A$2:$A$178,0))="","",INDEX(MCDM_Grades!$C$2:$C$178,MATCH($A6,MCDM_Grades!$A$2:$A$178,0))),"") | DW6: =IFERROR(IF(INDEX(MCDM_Grades!$D$2:$D$178,MATCH($A6,MCDM_Grades!$A$2:$A$178,0))="","",INDEX(MCDM_Grades!$D$2:$D$178,MATCH($A6,MCDM_Grades!$A$2:$A$178,0))),"") | DX6: =IFERROR(IF(INDEX(MCDM_Grades!$E$2:$E$178,MATCH($A6,MCDM_Grades!$A$2:$A$178,0))="","",INDEX(MCDM_Grades!$E$2:$E$178,MATCH($A6,MCDM_Grades!$A$2:$A$178,0))),"") | DY6: =IFERROR(IF(INDEX(MCDM_Grades!$F$2:$F$178,MATCH($A6,MCDM_Grades!$A$2:$A$178,0))="","",INDEX(MCDM_Grades!$F$2:$F$178,MATCH($A6,MCDM_Grades!$A$2:$A$178,0))),"") | DZ6: =IFERROR(IF(INDEX(MCDM_Grades!$G$2:$G$178,MATCH($A6,MCDM_Grades!$A$2:$A$178,0))="","",INDEX(MCDM_Grades!$G$2:$G$178,MATCH($A6,MCDM_Grades!$A$2:$A$178,0))),"") | EA6: =IFERROR(IF(INDEX(MCDM_Grades!$H$2:$H$178,MATCH($A6,MCDM_Grades!$A$2:$A$178,0))="","",INDEX(MCDM_Grades!$H$2:$H$178,MATCH($A6,MCDM_Grades!$A$2:$A$178,0))),"") | EB6: =IFERROR(IF(INDEX(MCDM_Grades!$I$2:$I$178,MATCH($A6,MCDM_Grades!$A$2:$A$178,0))="","",INDEX(MCDM_Grades!$I$2:$I$178,MATCH($A6,MCDM_Grades!$A$2:$A$178,0))),"") | EC6: =IFERROR(IF(INDEX(MCDM_Grades!$J$2:$J$178,MATCH($A6,MCDM_Grades!$A$2:$A$178,0))="","",INDEX(MCDM_Grades!$J$2:$J$178,MATCH($A6,MCDM_Grades!$A$2:$A$178,0))),"") | ED6: =IFERROR(IF(INDEX(MCDM_Grades!$N$2:$N$178,MATCH($A6,MCDM_Grades!$A$2:$A$178,0))="","",INDEX(MCDM_Grades!$N$2:$N$178,MATCH($A6,MCDM_Grades!$A$2:$A$178,0))),"") | EE6: =IFERROR(IF(INDEX(MCDM_Grades!$O$2:$O$178,MATCH($A6,MCDM_Grades!$A$2:$A$178,0))="","",INDEX(MCDM_Grades!$O$2:$O$178,MATCH($A6,MCDM_Grades!$A$2:$A$178,0))),"") | EF6: =IFERROR(IF(INDEX(MCDM_Grades!$P$2:$P$178,MATCH($A6,MCDM_Grades!$A$2:$A$178,0))="","",INDEX(MCDM_Grades!$P$2:$P$178,MATCH($A6,MCDM_Grades!$A$2:$A$178,0))),"") | EG6: =IFERROR(IF(INDEX(MCDM_Grades!$Q$2:$Q$178,MATCH($A6,MCDM_Grades!$A$2:$A$178,0))="","",INDEX(MCDM_Grades!$Q$2:$Q$178,MATCH($A6,MCDM_Grades!$A$2:$A$178,0))),"") | EH6: =IFERROR(IF(INDEX(MCDM_Grades!$R$2:$R$178,MATCH($A6,MCDM_Grades!$A$2:$A$178,0))="","",INDEX(MCDM_Grades!$R$2:$R$178,MATCH($A6,MCDM_Grades!$A$2:$A$178,0))),"") | EI6: =IFERROR(IF(INDEX(MCDM_Grades!$S$2:$S$178,MATCH($A6,MCDM_Grades!$A$2:$A$178,0))="","",INDEX(MCDM_Grades!$S$2:$S$178,MATCH($A6,MCDM_Grades!$A$2:$A$178,0))),"") | EJ6: =IFERROR(IF(INDEX(MCDM_Grades!$T$2:$T$178,MATCH($A6,MCDM_Grades!$A$2:$A$178,0))="","",INDEX(MCDM_Grades!$T$2:$T$178,MATCH($A6,MCDM_Grades!$A$2:$A$178,0))),"") | EK6: =IFERROR(IF(INDEX(MCDM_Grades!$U$2:$U$178,MATCH($A6,MCDM_Grades!$A$2:$A$178,0))="","",INDEX(MCDM_Grades!$U$2:$U$178,MATCH($A6,MCDM_Grades!$A$2:$A$178,0))),"") | EL6: =IFERROR(IF(INDEX(MCDM_Grades!$V$2:$V$178,MATCH($A6,MCDM_Grades!$A$2:$A$178,0))="","",INDEX(MCDM_Grades!$V$2:$V$178,MATCH($A6,MCDM_Grades!$A$2:$A$178,0))),"") | EM6: =IFERROR(IF(INDEX(MCDM_Grades!$W$2:$W$178,MATCH($A6,MCDM_Grades!$A$2:$A$178,0))="","",INDEX(MCDM_Grades!$W$2:$W$178,MATCH($A6,MCDM_Grades!$A$2:$A$178,0))),"") | EN6: =IFERROR(IF(INDEX(MCDM_Grades!$X$2:$X$178,MATCH($A6,MCDM_Grades!$A$2:$A$178,0))="","",INDEX(MCDM_Grades!$X$2:$X$178,MATCH($A6,MCDM_Grades!$A$2:$A$178,0))),"") | EO6: =IFERROR(IF(INDEX(MCDM_Grades!$Y$2:$Y$178,MATCH($A6,MCDM_Grades!$A$2:$A$178,0))="","",INDEX(MCDM_Grades!$Y$2:$Y$178,MATCH($A6,MCDM_Grades!$A$2:$A$178,0))),"") | EP6: =IFERROR(IF(INDEX(MCDM_Grades!$Z$2:$Z$178,MATCH($A6,MCDM_Grades!$A$2:$A$178,0))="","",INDEX(MCDM_Grades!$Z$2:$Z$178,MATCH($A6,MCDM_Grades!$A$2:$A$178,0))),"") | EQ6: =IFERROR(IF(INDEX(MCDM_Grades!$AA$2:$AA$178,MATCH($A6,MCDM_Grades!$A$2:$A$178,0))="","",INDEX(MCDM_Grades!$AA$2:$AA$178,MATCH($A6,MCDM_Grades!$A$2:$A$178,0))),"") | ER6: =IFERROR(IF(INDEX(MCDM_Grades!$AB$2:$AB$178,MATCH($A6,MCDM_Grades!$A$2:$A$178,0))="","",INDEX(MCDM_Grades!$AB$2:$AB$178,MATCH($A6,MCDM_Grades!$A$2:$A$178,0))),"") | ES6: =IFERROR(IF(INDEX(MCDM_Grades!$AC$2:$AC$178,MATCH($A6,MCDM_Grades!$A$2:$A$178,0))="","",INDEX(MCDM_Grades!$AC$2:$AC$178,MATCH($A6,MCDM_Grades!$A$2:$A$178,0))),"") | ET6: =IFERROR(IF(INDEX(MCDM_Grades!$AD$2:$AD$178,MATCH($A6,MCDM_Grades!$A$2:$A$178,0))="","",INDEX(MCDM_Grades!$AD$2:$AD$178,MATCH($A6,MCDM_Grades!$A$2:$A$178,0))),"") | EU6: =IFERROR(IF(INDEX(MCDM_Grades!$AE$2:$AE$178,MATCH($A6,MCDM_Grades!$A$2:$A$178,0))="","",INDEX(MCDM_Grades!$AE$2:$AE$178,MATCH($A6,MCDM_Grades!$A$2:$A$178,0))),"") | EV6: =IFERROR(IF(INDEX(MCDM_Grades!$K$2:$K$178,MATCH($A6,MCDM_Grades!$A$2:$A$178,0))="","",INDEX(MCDM_Grades!$K$2:$K$178,MATCH($A6,MCDM_Grades!$A$2:$A$178,0))),"") | EW6: =IFERROR(IF(INDEX(MCDM_Grades!$L$2:$L$178,MATCH($A6,MCDM_Grades!$A$2:$A$178,0))="","",INDEX(MCDM_Grades!$L$2:$L$178,MATCH($A6,MCDM_Grades!$A$2:$A$178,0))),"") | EX6: =IFERROR(IF(INDEX(MCDM_Grades!$M$2:$M$178,MATCH($A6,MCDM_Grades!$A$2:$A$178,0))="","",INDEX(MCDM_Grades!$M$2:$M$178,MATCH($A6,MCDM_Grades!$A$2:$A$178,0))),"") | EY6: =IFERROR(IF(INDEX(MCDM_Grades!$AR$2:$AR$178,MATCH($A6,MCDM_Grades!$A$2:$A$178,0))="","",INDEX(MCDM_Grades!$AR$2:$AR$178,MATCH($A6,MCDM_Grades!$A$2:$A$178,0))),"") | EZ6: =IFERROR(IF(INDEX(MCDM_Grades!$AS$2:$AS$178,MATCH($A6,MCDM_Grades!$A$2:$A$178,0))="","",INDEX(MCDM_Grades!$AS$2:$AS$178,MATCH($A6,MCDM_Grades!$A$2:$A$178,0))),"") | FA6: =IFERROR(IF(INDEX(MCDM_Grades!$AT$2:$AT$178,MATCH($A6,MCDM_Grades!$A$2:$A$178,0))="","",INDEX(MCDM_Grades!$AT$2:$AT$178,MATCH($A6,MCDM_Grades!$A$2:$A$178,0))),"") | FB6: =IFERROR(IF(INDEX(MCDM_Grades!$AU$2:$AU$178,MATCH($A6,MCDM_Grades!$A$2:$A$178,0))="","",INDEX(MCDM_Grades!$AU$2:$AU$178,MATCH($A6,MCDM_Grades!$A$2:$A$178,0))),"") | FC6: Nadir / top-down | FD6: Yes | FE6: No | FG6: Professional pavement inspection vehicle, downward-facing survey cameras | FH6: automatically captured by the in-vehicle cameras of the professional pavement inspection vehicle at different times from different areas in southern China ... Each pavement image is corresponding to a 2 × 3 meters pavement patch of highways | FI6: Dataset page / README | FJ6: https://github.com/DearCaat/CQU-BPDD | FK6: High | FL6: Not independently verified | FM6: Workbook: in-vehicle cameras of a professional pavement inspection vehicle; 1200x900 px, each image covers a 2x3 m pavement patch. The README does not literally say 'downward', but a fixed 2 x 3 m ground footprint per image is the signature of a downward survey camera (a forward dash-cam cannot map to a fixed pavement patch), and the sample imagery in the IOPLIN paper (Tang et al., IEEE T-ITS 2021, 10.1109/TITS.2021.3093389) and the PicT/WSPLIN papers shows full-frame pavement patches with no horizon. The workbook hint 'in-vehicle -> forward?' is not supported; 'in-vehicle' here means vehicle-mounted.
A7: DS-006 | B7: Crack Classification Dataset (five crack types, 200 images) | C7: NA | D7: v1 | E7: Independent Dataset | F7: NA (single source record) | G7: Single source record; no matching record found in any other file after cross-file and cross-platform comparison. | H7: Claude | I7: GitHub | J7: N | K7: NA (single platform) | L7: https://github.com/0110TJY/Crack-Classification-Dataset | M7: https://github.com/0110TJY/Crack-Classification-Dataset | N7: NA | O7: NA | P7: NA | Q7: NA | R7: NA | S7: NA | T7: NR | U7: N | V7: NR | W7: NR | X7: NR | Y7: NR | Z7: NA | AA7: NA | AB7: Images/frames as reported | AC7: 200 | AD7: NR | AE7: NR | AF7: 200 | AG7: NR | AH7: NR | AI7: NR | AJ7: NR | AK7: NR | AL7: NR | AM7: NR | AN7: 480x320 px (cropped) | AO7: NR | AP7: NR | AQ7: NR | AR7: NR | AS7: Road environment: Pavements | AT7: NR | AU7: Partly author-captured; partly compiled from CRACK500 and CrackForest | AV7: NR | AW7: NR | AX7: NR | AY7: NR | AZ7: NR | BA7: NR | BB7: N | BC7: N | BD7: NR | BE7: NR | BF7: NR | BG7: NR | BH7: Five crack types (specific class names NR) | BI7: NR | BJ7: Class-level labels (five types) | BK7: NR | BL7: Image classification | BM7: Image classification | BN7: Class-folder / zip structure | BO7: NR | BP7: Y | BQ7: NR | BR7: NR | BS7: NR | BT7: NR | BU7: NR | BV7: N | BW7: N | BX7: N | BY7: NR | BZ7: NR | CA7: NR | CB7: NR | CC7: Classification | CD7: NR | CE7: NR | CF7: Reported on the source record/data card or associated publication (see Evidence_Locator) | CG7: NR | CH7: NR | CI7: Include-Supplementary | CJ7: Direct_Download | CK7: NR | CL7: N | CM7: Direct_Download | CN7: NR | CO7: NR | CP7: N | CQ7: Partially derivative of CRACK500/CFD; very small; class names undocumented | CR7: Original | CS7: N | CT7: N | CU7: N | CV7: NA | CW7: NA | CX7: Claude_Github_001.xlsx | CY7: Claude_Github_001:GH-DS-021 | CZ7: N | DA7: NA | DB7: None | DC7: None | DD7: None | DE7: None | DF7: N | DG7: Single source record; no reconciliation required. | DH7: GitHub README and repo zip file, https://github.com/0110TJY/Crack-Classification-Dataset (accessed 2026-08-06) | DI7: Moderate | DJ7: Low | DK7: Use source record as cited. | DL7: 4 | DM7: 2 | DN7: 1.5 | DO7: 1 | DP7: 2 | DQ7: 1 | DR7: 0 | DS7: 37.5 | DT7: Reviewed (source MCDM_Scoring, averaged across batches) | DU7: 1 of 1 | DV7: =IFERROR(IF(INDEX(MCDM_Grades!$C$2:$C$178,MATCH($A7,MCDM_Grades!$A$2:$A$178,0))="","",INDEX(MCDM_Grades!$C$2:$C$178,MATCH($A7,MCDM_Grades!$A$2:$A$178,0))),"") | DW7: =IFERROR(IF(INDEX(MCDM_Grades!$D$2:$D$178,MATCH($A7,MCDM_Grades!$A$2:$A$178,0))="","",INDEX(MCDM_Grades!$D$2:$D$178,MATCH($A7,MCDM_Grades!$A$2:$A$178,0))),"") | DX7: =IFERROR(IF(INDEX(MCDM_Grades!$E$2:$E$178,MATCH($A7,MCDM_Grades!$A$2:$A$178,0))="","",INDEX(MCDM_Grades!$E$2:$E$178,MATCH($A7,MCDM_Grades!$A$2:$A$178,0))),"") | DY7: =IFERROR(IF(INDEX(MCDM_Grades!$F$2:$F$178,MATCH($A7,MCDM_Grades!$A$2:$A$178,0))="","",INDEX(MCDM_Grades!$F$2:$F$178,MATCH($A7,MCDM_Grades!$A$2:$A$178,0))),"") | DZ7: =IFERROR(IF(INDEX(MCDM_Grades!$G$2:$G$178,MATCH($A7,MCDM_Grades!$A$2:$A$178,0))="","",INDEX(MCDM_Grades!$G$2:$G$178,MATCH($A7,MCDM_Grades!$A$2:$A$178,0))),"") | EA7: =IFERROR(IF(INDEX(MCDM_Grades!$H$2:$H$178,MATCH($A7,MCDM_Grades!$A$2:$A$178,0))="","",INDEX(MCDM_Grades!$H$2:$H$178,MATCH($A7,MCDM_Grades!$A$2:$A$178,0))),"") | EB7: =IFERROR(IF(INDEX(MCDM_Grades!$I$2:$I$178,MATCH($A7,MCDM_Grades!$A$2:$A$178,0))="","",INDEX(MCDM_Grades!$I$2:$I$178,MATCH($A7,MCDM_Grades!$A$2:$A$178,0))),"") | EC7: =IFERROR(IF(INDEX(MCDM_Grades!$J$2:$J$178,MATCH($A7,MCDM_Grades!$A$2:$A$178,0))="","",INDEX(MCDM_Grades!$J$2:$J$178,MATCH($A7,MCDM_Grades!$A$2:$A$178,0))),"") | ED7: =IFERROR(IF(INDEX(MCDM_Grades!$N$2:$N$178,MATCH($A7,MCDM_Grades!$A$2:$A$178,0))="","",INDEX(MCDM_Grades!$N$2:$N$178,MATCH($A7,MCDM_Grades!$A$2:$A$178,0))),"") | EE7: =IFERROR(IF(INDEX(MCDM_Grades!$O$2:$O$178,MATCH($A7,MCDM_Grades!$A$2:$A$178,0))="","",INDEX(MCDM_Grades!$O$2:$O$178,MATCH($A7,MCDM_Grades!$A$2:$A$178,0))),"") | EF7: =IFERROR(IF(INDEX(MCDM_Grades!$P$2:$P$178,MATCH($A7,MCDM_Grades!$A$2:$A$178,0))="","",INDEX(MCDM_Grades!$P$2:$P$178,MATCH($A7,MCDM_Grades!$A$2:$A$178,0))),"") | EG7: =IFERROR(IF(INDEX(MCDM_Grades!$Q$2:$Q$178,MATCH($A7,MCDM_Grades!$A$2:$A$178,0))="","",INDEX(MCDM_Grades!$Q$2:$Q$178,MATCH($A7,MCDM_Grades!$A$2:$A$178,0))),"") | EH7: =IFERROR(IF(INDEX(MCDM_Grades!$R$2:$R$178,MATCH($A7,MCDM_Grades!$A$2:$A$178,0))="","",INDEX(MCDM_Grades!$R$2:$R$178,MATCH($A7,MCDM_Grades!$A$2:$A$178,0))),"") | EI7: =IFERROR(IF(INDEX(MCDM_Grades!$S$2:$S$178,MATCH($A7,MCDM_Grades!$A$2:$A$178,0))="","",INDEX(MCDM_Grades!$S$2:$S$178,MATCH($A7,MCDM_Grades!$A$2:$A$178,0))),"") | EJ7: =IFERROR(IF(INDEX(MCDM_Grades!$T$2:$T$178,MATCH($A7,MCDM_Grades!$A$2:$A$178,0))="","",INDEX(MCDM_Grades!$T$2:$T$178,MATCH($A7,MCDM_Grades!$A$2:$A$178,0))),"") | EK7: =IFERROR(IF(INDEX(MCDM_Grades!$U$2:$U$178,MATCH($A7,MCDM_Grades!$A$2:$A$178,0))="","",INDEX(MCDM_Grades!$U$2:$U$178,MATCH($A7,MCDM_Grades!$A$2:$A$178,0))),"") | EL7: =IFERROR(IF(INDEX(MCDM_Grades!$V$2:$V$178,MATCH($A7,MCDM_Grades!$A$2:$A$178,0))="","",INDEX(MCDM_Grades!$V$2:$V$178,MATCH($A7,MCDM_Grades!$A$2:$A$178,0))),"") | EM7: =IFERROR(IF(INDEX(MCDM_Grades!$W$2:$W$178,MATCH($A7,MCDM_Grades!$A$2:$A$178,0))="","",INDEX(MCDM_Grades!$W$2:$W$178,MATCH($A7,MCDM_Grades!$A$2:$A$178,0))),"") | EN7: =IFERROR(IF(INDEX(MCDM_Grades!$X$2:$X$178,MATCH($A7,MCDM_Grades!$A$2:$A$178,0))="","",INDEX(MCDM_Grades!$X$2:$X$178,MATCH($A7,MCDM_Grades!$A$2:$A$178,0))),"") | EO7: =IFERROR(IF(INDEX(MCDM_Grades!$Y$2:$Y$178,MATCH($A7,MCDM_Grades!$A$2:$A$178,0))="","",INDEX(MCDM_Grades!$Y$2:$Y$178,MATCH($A7,MCDM_Grades!$A$2:$A$178,0))),"") | EP7: =IFERROR(IF(INDEX(MCDM_Grades!$Z$2:$Z$178,MATCH($A7,MCDM_Grades!$A$2:$A$178,0))="","",INDEX(MCDM_Grades!$Z$2:$Z$178,MATCH($A7,MCDM_Grades!$A$2:$A$178,0))),"") | EQ7: =IFERROR(IF(INDEX(MCDM_Grades!$AA$2:$AA$178,MATCH($A7,MCDM_Grades!$A$2:$A$178,0))="","",INDEX(MCDM_Grades!$AA$2:$AA$178,MATCH($A7,MCDM_Grades!$A$2:$A$178,0))),"") | ER7: =IFERROR(IF(INDEX(MCDM_Grades!$AB$2:$AB$178,MATCH($A7,MCDM_Grades!$A$2:$A$178,0))="","",INDEX(MCDM_Grades!$AB$2:$AB$178,MATCH($A7,MCDM_Grades!$A$2:$A$178,0))),"") | ES7: =IFERROR(IF(INDEX(MCDM_Grades!$AC$2:$AC$178,MATCH($A7,MCDM_Grades!$A$2:$A$178,0))="","",INDEX(MCDM_Grades!$AC$2:$AC$178,MATCH($A7,MCDM_Grades!$A$2:$A$178,0))),"") | ET7: =IFERROR(IF(INDEX(MCDM_Grades!$AD$2:$AD$178,MATCH($A7,MCDM_Grades!$A$2:$A$178,0))="","",INDEX(MCDM_Grades!$AD$2:$AD$178,MATCH($A7,MCDM_Grades!$A$2:$A$178,0))),"") | EU7: =IFERROR(IF(INDEX(MCDM_Grades!$AE$2:$AE$178,MATCH($A7,MCDM_Grades!$A$2:$A$178,0))="","",INDEX(MCDM_Grades!$AE$2:$AE$178,MATCH($A7,MCDM_Grades!$A$2:$A$178,0))),"") | EV7: =IFERROR(IF(INDEX(MCDM_Grades!$K$2:$K$178,MATCH($A7,MCDM_Grades!$A$2:$A$178,0))="","",INDEX(MCDM_Grades!$K$2:$K$178,MATCH($A7,MCDM_Grades!$A$2:$A$178,0))),"") | EW7: =IFERROR(IF(INDEX(MCDM_Grades!$L$2:$L$178,MATCH($A7,MCDM_Grades!$A$2:$A$178,0))="","",INDEX(MCDM_Grades!$L$2:$L$178,MATCH($A7,MCDM_Grades!$A$2:$A$178,0))),"") | EX7: =IFERROR(IF(INDEX(MCDM_Grades!$M$2:$M$178,MATCH($A7,MCDM_Grades!$A$2:$A$178,0))="","",INDEX(MCDM_Grades!$M$2:$M$178,MATCH($A7,MCDM_Grades!$A$2:$A$178,0))),"") | EY7: =IFERROR(IF(INDEX(MCDM_Grades!$AR$2:$AR$178,MATCH($A7,MCDM_Grades!$A$2:$A$178,0))="","",INDEX(MCDM_Grades!$AR$2:$AR$178,MATCH($A7,MCDM_Grades!$A$2:$A$178,0))),"") | EZ7: =IFERROR(IF(INDEX(MCDM_Grades!$AS$2:$AS$178,MATCH($A7,MCDM_Grades!$A$2:$A$178,0))="","",INDEX(MCDM_Grades!$AS$2:$AS$178,MATCH($A7,MCDM_Grades!$A$2:$A$178,0))),"") | FA7: =IFERROR(IF(INDEX(MCDM_Grades!$AT$2:$AT$178,MATCH($A7,MCDM_Grades!$A$2:$A$178,0))="","",INDEX(MCDM_Grades!$AT$2:$AT$178,MATCH($A7,MCDM_Grades!$A$2:$A$178,0))),"") | FB7: =IFERROR(IF(INDEX(MCDM_Grades!$AU$2:$AU$178,MATCH($A7,MCDM_Grades!$A$2:$A$178,0))="","",INDEX(MCDM_Grades!$AU$2:$AU$178,MATCH($A7,MCDM_Grades!$A$2:$A$178,0))),"") | FC7: Nadir / top-down | FD7: Partial | FE7: Unknown | FG7: Compiled: handheld smartphone pointed at the surface (CRACK500 / CFD parents) plus author-captured images (device not reported) | FH7: Some of the images are compiled from the Crack500 dataset and the CrackForest dataset, while some images of pavement cracks are taken by the author. All images are cropped to 480×320p. | FI7: Parent / source dataset | FJ7: https://github.com/0110TJY/Crack-Classification-Dataset | FK7: Medium | FL7: Verified - agreed | FM7: Workbook: 'Partly author-captured; partly compiled from CRACK500 and CrackForest'. The compiled portion inherits the parents' viewpoint: CRACK500 (handheld cell phone, Temple University campus) and CFD (iPhone 5) are both top-down pavement close-ups. The author-captured portion has no device or orientation statement, and the README (fetched via GitHub API) contains no figures; the repo holds only a zip. Hence top_down Partial and forward_facing Unknown; the 480x320 crops of 'pavement cracks' are consistent with, but do not prove, top-down capture for the author subset. | Second review: README (fetched) confirms the compiled portion comes from CRACK500 (cell-phone pavement close-ups, per FPHB paper) and CFD (sample image verified top-down), while the author-captured portion has no device or orientation statement. Nadir with top_down Partial / forward_facing Unknown is the right lab
A8: DS-007 | B8: CRACK500 (Crack500) | C8: Crack500; CRACK500; CRACK500 Kaggle Mirror | D8: FPHB release (with GAPs384/CFD/AEL/cracktree200 companion copies) [Claude] | Original plus cropped benchmark split [GPT] | Original 500-image release [Test_Batch] | E8: Confirmed Match | F8: High | G8: Same canonical repository (fyangneil/pavement-crack-detection); same US handheld-smartphone acquisition; same origin publication (10.1109/ICIP.2016.7533052) and FPHB paper (10.1109/TITS.2019.2891237); Kaggle record is an explicit mirror citing the same repository. | H8: Claude; GPT; GitHub_Test_Batch (tool UNK) | I8: GitHub; Kaggle | J8: Y | K8: Mirror: canonical GitHub repository; Kaggle page pauldavid22/crack50020220509t090436z001 is a community mirror | L8: https://github.com/fyangneil/pavement-crack-detection | M8: https://github.com/fyangneil/pavement-crack-detection | N8: NA | O8: NA | P8: NA | Q8: NA | R8: https://www.kaggle.com/datasets/pauldavid22/crack50020220509t090436z001 | S8: NA | T8: 10.1109/ICIP.2016.7533052 | U8: Y | V8: https://arxiv.org/abs/1901.06340;10.1109/ICIP.2016.7533052 (ICIP 2016 origin paper as cited in README) [Claude] | https://github.com/fyangneil/pavement-crack-detection [GPT/Test_Batch] | 10.1109/ICIP.2016.7533052; 10.1109/TITS.2019.2891237 [GPT] | W8: 10.1109/ICIP.2016.7533052; 10.1109/TITS.2019.2891237 | X8: https://arxiv.org/abs/1901.06340; https://github.com/fyangneil/pavement-crack-detection | Y8: NR | Z8: Y | AA8: Reported in source record (relationship not classified) | AB8: Images/frames as reported | AC8: 500 [Claude/GPT/Test_Batch] | 3368 [GPT] | AD8: NR | AE8: NR | AF8: 500 [Claude/GPT/Test_Batch] | 3368 [GPT] | AG8: NR | AH8: NR | AI8: NR | AJ8: NR | AK8: NR | AL8: NR | AM8: NR | AN8: approx. 2000x1500 px (cropped patches also provided) [Claude] | Approximately 2,000 x 1,500 px; original images are high resolution [GPT] | Approximately 2000×1500 originals; cropped benchmark images [GPT] | 3264x2448 [Test_Batch] | AO8: NR | AP8: United States | AQ8: NR | AR8: Temple University main campus, Philadelphia, PA [Claude] | Temple University campus;Philadelphia;Pennsylvania [GPT] | Temple University campus, Philadelphia [GPT] | Temple University campus, Philadelphia, Pennsylvania [Test_Batch] | AS8: United States; Temple University main campus, Philadelphia, PA [Claude] | Temple University campus;Philadelphia;Pennsylvania [GPT] | Temple University campus, Philadelphia [GPT] | Temple University campus, Philadelphia, Pennsylvania [Test_Batch]; Road environment: Campus pavements [Claude] | Campus pavement surfaces [GPT] | Campus roads; asphalt; cement; gravel [GPT] | Campus roads [Test_Batch] | AT8: NR | AU8: Hand-held smartphone (cell phone) [Claude] | Cellphone cameras [GPT] | Handheld smartphone [GPT] | Smartphone camera [Test_Batch] | AV8: NR | AW8: Hand-held smartphone (cell phone) [Claude] | Cellphone cameras [GPT] | Handheld smartphone [GPT] | Smartphone camera [Test_Batch] | AX8: See Acquisition_Platform (reported: handheld) | AY8: Y | AZ8: NR | BA8: NR | BB8: N | BC8: N | BD8: NR | BE8: NR | BF8: Natural lighting;shadows [GPT] | Natural outdoor lighting [Test_Batch] | BG8: NR | BH8: Pavement cracks (undifferentiated crack class) [Claude] | Crack [GPT] | pavement crack [GPT/Test_Batch] | BI8: NR | BJ8: Binary crack vs background [Claude] | Pixel-level pavement-crack masks [GPT] | crack pixels; background pixels [GPT] | crack pixel mask [Test_Batch] | BK8: NR | BL8: Semantic segmentation (pixel-level) [Claude] | Semantic segmentation [GPT/Test_Batch] | BM8: Semantic segmentation (pixel-level) [Claude] | Semantic segmentation [GPT/Test_Batch] | BN8: Binary mask images [Claude] | Images and pixel-level ground-truth masks; cropped derivatives also commonly distributed [GPT] | pixel masks [GPT/Test_Batch] | BO8: mask | BP8: NR | BQ8: NR | BR8: Y | BS8: NR | BT8: NR | BU8: NR | BV8: N | BW8: N | BX8: N | BY8: Manual pixel-level annotation [Claude] | Manual pixel-level annotation by multiple annotators [GPT] | Manual annotation by multiple annotators [GPT] | Manual pixel annotation [Test_Batch] | BZ8: Multiple annotators reported in original dataset documentation; exact agreement protocol NR [GPT] | Multiple annotators; standardized train/validation/test crops [GPT] | Multiple annotators reported [Test_Batch] | CA8: NR | CB8: NR | CC8: Semantic segmentation;Crack detection [Claude/GPT/Test_Batch] | crack segmentation; crack detection [GPT] | CD8: FPHBN (paper-reported) [Claude] | Feature Pyramid and Hierarchical Boosting Network [GPT] | CE8: FPHBN (paper-reported) [Claude] | Feature Pyramid and Hierarchical Boosting Network [GPT] | CF8: Reported on the source record/data card or associated publication (see Evidence_Locator) | CG8: AIU (CRACK500 test) | CH8: FPHBN (paper-reported) [Claude] | Feature Pyramid and Hierarchical Boosting Network [GPT]: AIU (CRACK500 test) = 0.560 | CI8: Include-Primary [Claude/GPT/Test_Batch] | Include-Supplementary [GPT] | CJ8: Direct_Download [Claude/GPT/Test_Batch] | Registration [GPT] | CK8: NR | CL8: Y | CM8: Direct_Download [Claude/GPT/Test_Batch] | Registration [GPT] | CN8: NR | CO8: NR | CP8: N | CQ8: No explicit license; single-location smartphone capture limits diversity; data hosted on Google Drive/OneDrive/Baidu (link liveness not independently re-tested) [Claude] | Kaggle is a mirror; original dataset predates the Kaggle upload, licensing is unclear on the mirror, and cropped-patch counts should not be confused with the 500 original images. [GPT] | Crack-only; campus-scale geography; sparse engineering metadata; download links are maintained through code repositories [GPT] | Small original set from one campus; later cropped-image totals should not be confused with unique source-image count. [Test_Batch] | CR8: Original | CS8: Y | CT8: N | CU8: N | CV8: NA | CW8: GAPs384 (companion release in same repository); CRACK500 with noisy annotation masks (derived); CombinedCrack and CrackSeg9k (compiled users) | CX8: ChatGPT_Github_001.xlsx; Claude_Github_001.xlsx; GPT_Kaggle_001.xlsx; Github_Github_Test.xlsx | CY8: ChatGPT_Github_001:GH-011; Claude_Github_001:GH-DS-003; GPT_Kaggle_001:KAG-014; Github_Github_Test:GITHUB-013 | CZ8: Y - see conflict columns and Reconciliation_Notes | DA8: Y - see conflict columns and Reconciliation_Notes | DB8: Image count: 500 (Claude/GPT/Test_Batch) vs 3368 (GPT) || Image resolution: approx. 2000x1500 px (cropped patches also provided) (Claude) vs Approximately 2,000 x 1,500 px; original images are high resolution (GPT) vs Approximately 2000×1500 originals; cropped benchmark images (GPT) vs 3264x2448 (Test_Batch) | DC8: Distress types: Pavement cracks (undifferentiated crack class) (Claude) vs Crack (GPT) vs pavement crack (GPT/Test_Batch) || Label taxonomy: Binary crack vs background (Claude) vs Pixel-level pavement-crack masks (GPT) vs crack pixels; background pixels (GPT) vs crack pixel mask (Test_Batch) || Annotation task: Semantic segmentation (pixel-level) (Claude) vs Semantic segmentation (GPT/Test_Batch) || Annotation format: Binary mask images (Claude) vs Images and pixel-level ground-truth masks; cropped derivatives also commonly dis (GPT) vs pixel masks (GPT/Test_Batch) || Annotation method: Manual pixel-level annotation (Claude) vs Manual pixel-level annotation by multiple annotators (GPT) vs Manual annotation by multiple annotators (GPT) vs Manual pixel annotation (Test_Batch) || Annotation QC: Multiple annotators reported in original dataset documentation; exact agreement (GPT) vs Multiple annotators; standardized train/validation/test crops (GPT) vs Multiple annotators reported (Test_Batch) | DD8: None | DE8: Release year: 2019 (Claude) vs 2022 (GPT) vs 2016 (GPT/Test_Batch) || Version: FPHB release (with GAPs384/CFD/AEL/cracktree200 companion copies) (Claude) vs Original plus cropped benchmark split (GPT) vs Original 500-image release (Test_Batch) || Access status: Direct_Download (Claude/GPT/Test_Batch) vs Registration (GPT) || AI tasks: Semantic segmentation;Crack detection (Claude/GPT/Test_Batch) vs crack segmentation; crack detection (GPT) || Acquisition platform: Hand-held smartphone (cell phone) (Claude) vs Cellphone cameras (GPT) vs Handheld smartphone (GPT) vs Smartphone camera (Test_Batch) || Reported model: FPHBN (paper-reported) (Claude) vs Feature Pyramid and Hierarchical Boosting Network (GPT) || Screening decision: Include-Primary (Claude/GPT/Test_Batch) vs Include-Supplementary (GPT) || Region/City: Temple University main campus, Philadelphia, PA (Claude) vs Temple University campus;Philadelphia;Pennsylvania (GPT) vs Temple University campus, Philadelphia (GPT) vs Temple University campus, Philadelphia, Pennsylvania (Test_Batch) || Road environment: Campus pavements (Claude) vs Campus pavement surfaces (GPT) vs Campus roads; asphalt; cement; gravel (GPT) vs Campus roads (Test_Batch) || Publications: https://arxiv.org/abs/1901.06340;10.1109/ICIP.2016.7533052 (ICIP 2016 origin pap (Claude) vs https://github.com/fyangneil/pavement-crack-detection (GPT/Test_Batch) vs 10.1109/ICIP.2016.7533052; 10.1109/TITS.2019.2891237 (GPT) || Acquisition platform: Hand-held smartphone (cell phone) (Claude) vs Cellphone cameras (GPT) vs Handheld smartphone (GPT) vs Smartphone camera (Test_Batch) || Lighting_Conditions: Natural lighting;shadows (GPT) vs Natural outdoor lighting (Test_Batch) || Key_Limitations: No explicit license; single-location smartphone capture limits diversity; data h (Claude) vs Kaggle is a mirror; original dataset predates the Kaggle upload, licensing is un (GPT) vs Crack-only; campus-scale geography; sparse engineering metadata; download links (GPT) vs Small original set from one campus; later cropped-image totals should not be con (Test_Batch) | DF8: Y | DG8: Image-count convention conflict: 500 original images (Claude; GPT Kaggle; Test batch; literature workbooks 02/12/14/15) vs 3,368 including patch crops (GPT GitHub batch). Release year reported variously 2016/2019/2020/2022 (paper vs release vs mirror upload dates). | DH8: GitHub README (dataset links, citations), https://github.com/fyangneil/pavement-crack-detection; FPHB paper arXiv:1901.06340 dataset section (accessed 2026-08-06) [Claude] | Kaggle mirror page; original CRACK500 project repository and published dataset descriptions, accessed 2026-08-06 [GPT] | https://github.com/fyangneil/pavement-crack-detection README CRACK500 citation/download instructions; GitHub benchmark descriptions; accessed 2026-08-06 [GPT] | https://github.com/fyangneil/pavement-crack-detection; README Crack500 dataset and download description; accessed 2026-08-01 [Test_Batch] | DI8: Moderate | DJ8: Medium | DK8: State counting convention (originals vs crops) when using. | DL8: 3.8 | DM8: 4.5 | DN8: 4.4 | DO8: 3 | DP8: 2.5 | DQ8: 1 | DR8: 0 | DS8: 62.4 | DT8: Reviewed (source MCDM_Scoring, averaged across batches) | DU8: 4 of 4 | DV8: =IFERROR(IF(INDEX(MCDM_Grades!$C$2:$C$178,MATCH($A8,MCDM_Grades!$A$2:$A$178,0))="","",INDEX(MCDM_Grades!$C$2:$C$178,MATCH($A8,MCDM_Grades!$A$2:$A$178,0))),"") | DW8: =IFERROR(IF(INDEX(MCDM_Grades!$D$2:$D$178,MATCH($A8,MCDM_Grades!$A$2:$A$178,0))="","",INDEX(MCDM_Grades!$D$2:$D$178,MATCH($A8,MCDM_Grades!$A$2:$A$178,0))),"") | DX8: =IFERROR(IF(INDEX(MCDM_Grades!$E$2:$E$178,MATCH($A8,MCDM_Grades!$A$2:$A$178,0))="","",INDEX(MCDM_Grades!$E$2:$E$178,MATCH($A8,MCDM_Grades!$A$2:$A$178,0))),"") | DY8: =IFERROR(IF(INDEX(MCDM_Grades!$F$2:$F$178,MATCH($A8,MCDM_Grades!$A$2:$A$178,0))="","",INDEX(MCDM_Grades!$F$2:$F$178,MATCH($A8,MCDM_Grades!$A$2:$A$178,0))),"") | DZ8: =IFERROR(IF(INDEX(MCDM_Grades!$G$2:$G$178,MATCH($A8,MCDM_Grades!$A$2:$A$178,0))="","",INDEX(MCDM_Grades!$G$2:$G$178,MATCH($A8,MCDM_Grades!$A$2:$A$178,0))),"") | EA8: =IFERROR(IF(INDEX(MCDM_Grades!$H$2:$H$178,MATCH($A8,MCDM_Grades!$A$2:$A$178,0))="","",INDEX(MCDM_Grades!$H$2:$H$178,MATCH($A8,MCDM_Grades!$A$2:$A$178,0))),"") | EB8: =IFERROR(IF(INDEX(MCDM_Grades!$I$2:$I$178,MATCH($A8,MCDM_Grades!$A$2:$A$178,0))="","",INDEX(MCDM_Grades!$I$2:$I$178,MATCH($A8,MCDM_Grades!$A$2:$A$178,0))),"") | EC8: =IFERROR(IF(INDEX(MCDM_Grades!$J$2:$J$178,MATCH($A8,MCDM_Grades!$A$2:$A$178,0))="","",INDEX(MCDM_Grades!$J$2:$J$178,MATCH($A8,MCDM_Grades!$A$2:$A$178,0))),"") | ED8: =IFERROR(IF(INDEX(MCDM_Grades!$N$2:$N$178,MATCH($A8,MCDM_Grades!$A$2:$A$178,0))="","",INDEX(MCDM_Grades!$N$2:$N$178,MATCH($A8,MCDM_Grades!$A$2:$A$178,0))),"") | EE8: =IFERROR(IF(INDEX(MCDM_Grades!$O$2:$O$178,MATCH($A8,MCDM_Grades!$A$2:$A$178,0))="","",INDEX(MCDM_Grades!$O$2:$O$178,MATCH($A8,MCDM_Grades!$A$2:$A$178,0))),"") | EF8: =IFERROR(IF(INDEX(MCDM_Grades!$P$2:$P$178,MATCH($A8,MCDM_Grades!$A$2:$A$178,0))="","",INDEX(MCDM_Grades!$P$2:$P$178,MATCH($A8,MCDM_Grades!$A$2:$A$178,0))),"") | EG8: =IFERROR(IF(INDEX(MCDM_Grades!$Q$2:$Q$178,MATCH($A8,MCDM_Grades!$A$2:$A$178,0))="","",INDEX(MCDM_Grades!$Q$2:$Q$178,MATCH($A8,MCDM_Grades!$A$2:$A$178,0))),"") | EH8: =IFERROR(IF(INDEX(MCDM_Grades!$R$2:$R$178,MATCH($A8,MCDM_Grades!$A$2:$A$178,0))="","",INDEX(MCDM_Grades!$R$2:$R$178,MATCH($A8,MCDM_Grades!$A$2:$A$178,0))),"") | EI8: =IFERROR(IF(INDEX(MCDM_Grades!$S$2:$S$178,MATCH($A8,MCDM_Grades!$A$2:$A$178,0))="","",INDEX(MCDM_Grades!$S$2:$S$178,MATCH($A8,MCDM_Grades!$A$2:$A$178,0))),"") | EJ8: =IFERROR(IF(INDEX(MCDM_Grades!$T$2:$T$178,MATCH($A8,MCDM_Grades!$A$2:$A$178,0))="","",INDEX(MCDM_Grades!$T$2:$T$178,MATCH($A8,MCDM_Grades!$A$2:$A$178,0))),"") | EK8: =IFERROR(IF(INDEX(MCDM_Grades!$U$2:$U$178,MATCH($A8,MCDM_Grades!$A$2:$A$178,0))="","",INDEX(MCDM_Grades!$U$2:$U$178,MATCH($A8,MCDM_Grades!$A$2:$A$178,0))),"") | EL8: =IFERROR(IF(INDEX(MCDM_Grades!$V$2:$V$178,MATCH($A8,MCDM_Grades!$A$2:$A$178,0))="","",INDEX(MCDM_Grades!$V$2:$V$178,MATCH($A8,MCDM_Grades!$A$2:$A$178,0))),"") | EM8: =IFERROR(IF(INDEX(MCDM_Grades!$W$2:$W$178,MATCH($A8,MCDM_Grades!$A$2:$A$178,0))="","",INDEX(MCDM_Grades!$W$2:$W$178,MATCH($A8,MCDM_Grades!$A$2:$A$178,0))),"") | EN8: =IFERROR(IF(INDEX(MCDM_Grades!$X$2:$X$178,MATCH($A8,MCDM_Grades!$A$2:$A$178,0))="","",INDEX(MCDM_Grades!$X$2:$X$178,MATCH($A8,MCDM_Grades!$A$2:$A$178,0))),"") | EO8: =IFERROR(IF(INDEX(MCDM_Grades!$Y$2:$Y$178,MATCH($A8,MCDM_Grades!$A$2:$A$178,0))="","",INDEX(MCDM_Grades!$Y$2:$Y$178,MATCH($A8,MCDM_Grades!$A$2:$A$178,0))),"") | EP8: =IFERROR(IF(INDEX(MCDM_Grades!$Z$2:$Z$178,MATCH($A8,MCDM_Grades!$A$2:$A$178,0))="","",INDEX(MCDM_Grades!$Z$2:$Z$178,MATCH($A8,MCDM_Grades!$A$2:$A$178,0))),"") | EQ8: =IFERROR(IF(INDEX(MCDM_Grades!$AA$2:$AA$178,MATCH($A8,MCDM_Grades!$A$2:$A$178,0))="","",INDEX(MCDM_Grades!$AA$2:$AA$178,MATCH($A8,MCDM_Grades!$A$2:$A$178,0))),"") | ER8: =IFERROR(IF(INDEX(MCDM_Grades!$AB$2:$AB$178,MATCH($A8,MCDM_Grades!$A$2:$A$178,0))="","",INDEX(MCDM_Grades!$AB$2:$AB$178,MATCH($A8,MCDM_Grades!$A$2:$A$178,0))),"") | ES8: =IFERROR(IF(INDEX(MCDM_Grades!$AC$2:$AC$178,MATCH($A8,MCDM_Grades!$A$2:$A$178,0))="","",INDEX(MCDM_Grades!$AC$2:$AC$178,MATCH($A8,MCDM_Grades!$A$2:$A$178,0))),"") | ET8: =IFERROR(IF(INDEX(MCDM_Grades!$AD$2:$AD$178,MATCH($A8,MCDM_Grades!$A$2:$A$178,0))="","",INDEX(MCDM_Grades!$AD$2:$AD$178,MATCH($A8,MCDM_Grades!$A$2:$A$178,0))),"") | EU8: =IFERROR(IF(INDEX(MCDM_Grades!$AE$2:$AE$178,MATCH($A8,MCDM_Grades!$A$2:$A$178,0))="","",INDEX(MCDM_Grades!$AE$2:$AE$178,MATCH($A8,MCDM_Grades!$A$2:$A$178,0))),"") | EV8: =IFERROR(IF(INDEX(MCDM_Grades!$K$2:$K$178,MATCH($A8,MCDM_Grades!$A$2:$A$178,0))="","",INDEX(MCDM_Grades!$K$2:$K$178,MATCH($A8,MCDM_Grades!$A$2:$A$178,0))),"") | EW8: =IFERROR(IF(INDEX(MCDM_Grades!$L$2:$L$178,MATCH($A8,MCDM_Grades!$A$2:$A$178,0))="","",INDEX(MCDM_Grades!$L$2:$L$178,MATCH($A8,MCDM_Grades!$A$2:$A$178,0))),"") | EX8: =IFERROR(IF(INDEX(MCDM_Grades!$M$2:$M$178,MATCH($A8,MCDM_Grades!$A$2:$A$178,0))="","",INDEX(MCDM_Grades!$M$2:$M$178,MATCH($A8,MCDM_Grades!$A$2:$A$178,0))),"") | EY8: =IFERROR(IF(INDEX(MCDM_Grades!$AR$2:$AR$178,MATCH($A8,MCDM_Grades!$A$2:$A$178,0))="","",INDEX(MCDM_Grades!$AR$2:$AR$178,MATCH($A8,MCDM_Grades!$A$2:$A$178,0))),"") | EZ8: =IFERROR(IF(INDEX(MCDM_Grades!$AS$2:$AS$178,MATCH($A8,MCDM_Grades!$A$2:$A$178,0))="","",INDEX(MCDM_Grades!$AS$2:$AS$178,MATCH($A8,MCDM_Grades!$A$2:$A$178,0))),"") | FA8: =IFERROR(IF(INDEX(MCDM_Grades!$AT$2:$AT$178,MATCH($A8,MCDM_Grades!$A$2:$A$178,0))="","",INDEX(MCDM_Grades!$AT$2:$AT$178,MATCH($A8,MCDM_Grades!$A$2:$A$178,0))),"") | FB8: =IFERROR(IF(INDEX(MCDM_Grades!$AU$2:$AU$178,MATCH($A8,MCDM_Grades!$A$2:$A$178,0))="","",INDEX(MCDM_Grades!$AU$2:$AU$178,MATCH($A8,MCDM_Grades!$A$2:$A$178,0))),"") | FC8: Nadir / top-down | FD8: Yes | FE8: No | FG8: Handheld smartphone pointed at the surface | FH8: We collect a pavement crack dataset with 500 images of size around 2,000 x 1,500 pixels on main campus of Temple University using cell phones. | FI8: Publication | FJ8: https://arxiv.org/abs/1901.06340 | FK8: High | FL8: Verified - agreed | FM8: Workbook: 'Hand-held smartphone (cell phone)', Camera_Position 'handheld', Smartphone_Data Y. The GitHub README (fetched) only cites the ICIP 2016 origin paper and gives no collection paragraph; the arXiv PDF was fetched but did not convert to readable text and no local PDF tooling is available. Orientation therefore rests on the well-documented benchmark: FPHB paper describes cell-phone capture and every CRACK500 image is a full-frame pavement close-up (no horizon), as also reflected in the ICIP 2016 paper (10.1109/ICIP.2016.7533052). Confidence capped at Medium per the prior-knowledge rule. | Second review replaced the evidence (was: Known dataset (prior knowledge)). | Second review: Extracted this sentence from the FPHB paper PDF (arXiv 1901.06340, Sec. B Datasets); it confirms handheld cell-phone capture of pavement crack images, which with the full-frame pavement close-ups of the benchmark supports nadir. The paper does not state the pointing angle explicitly, so Medium confi
A9: DS-008 | B9: CrackForest Dataset (CFD) | C9: NA | D9: NR | E9: Independent Dataset | F9: NA (single source record) | G9: Single source record; no matching record found in any other file after cross-file and cross-platform comparison. | H9: GitHub_Test_Batch (tool UNK) | I9: GitHub | J9: N | K9: NA (single platform) | L9: https://github.com/cuilimeng/CrackForest-dataset | M9: https://github.com/cuilimeng/CrackForest-dataset | N9: NA | O9: NA | P9: NA | Q9: NA | R9: NA | S9: NA | T9: NR | U9: Y | V9: https://github.com/cuilimeng/CrackForest-dataset | W9: NR | X9: https://github.com/cuilimeng/CrackForest-dataset | Y9: NR | Z9: NR | AA9: Reported in source record (relationship not classified) | AB9: Images/frames as reported | AC9: 118 | AD9: NR | AE9: NR | AF9: 118 | AG9: NR | AH9: NR | AI9: NR | AJ9: NR | AK9: NR | AL9: NR | AM9: NR | AN9: NR | AO9: NR | AP9: China | AQ9: NR | AR9: Beijing | AS9: China; Beijing; Road environment: Urban | AT9: NR | AU9: iPhone 5 smartphone camera | AV9: NR | AW9: iPhone 5 smartphone camera | AX9: NR | AY9: Y | AZ9: NR | BA9: NR | BB9: NR | BC9: NR | BD9: NR | BE9: NR | BF9: NR | BG9: NR | BH9: pavement crack | BI9: NR | BJ9: crack contour; crack pixel mask | BK9: NR | BL9: Semantic segmentation | BM9: Semantic segmentation | BN9: Ground-truth contour images | BO9: NR | BP9: NR | BQ9: NR | BR9: Y | BS9: NR | BT9: NR | BU9: NR | BV9: NR | BW9: NR | BX9: NR | BY9: Manual contour annotation | BZ9: NR | CA9: NR | CB9: NR | CC9: semantic segmentation; crack detection | CD9: NR | CE9: NR | CF9: Reported on the source record/data card or associated publication (see Evidence_Locator) | CG9: NR | CH9: NR | CI9: Include-Primary | CJ9: Direct_Download | CK9: NR | CL9: N | CM9: Direct_Download | CN9: NR | CO9: NR | CP9: N | CQ9: Very small single-city benchmark and limited collection-condition metadata. | CR9: Original | CS9: N | CT9: N | CU9: N | CV9: NA | CW9: NA | CX9: Github_Github_Test.xlsx | CY9: Github_Github_Test:GITHUB-015 | CZ9: NA | DA9: NA | DB9: None | DC9: None | DD9: None | DE9: None | DF9: N | DG9: Single source record; no reconciliation required. | DH9: https://github.com/cuilimeng/CrackForest-dataset; repository README and data files; accessed 2026-08-01 | DI9: High | DJ9: Low | DK9: Use source record as cited. | DL9: 4 | DM9: 4 | DN9: 4.5 | DO9: 1 | DP9: 2 | DQ9: 1 | DR9: 0 | DS9: 54.5 | DT9: Reviewed (source MCDM_Scoring, averaged across batches) | DU9: 1 of 1 | DV9: =IFERROR(IF(INDEX(MCDM_Grades!$C$2:$C$178,MATCH($A9,MCDM_Grades!$A$2:$A$178,0))="","",INDEX(MCDM_Grades!$C$2:$C$178,MATCH($A9,MCDM_Grades!$A$2:$A$178,0))),"") | DW9: =IFERROR(IF(INDEX(MCDM_Grades!$D$2:$D$178,MATCH($A9,MCDM_Grades!$A$2:$A$178,0))="","",INDEX(MCDM_Grades!$D$2:$D$178,MATCH($A9,MCDM_Grades!$A$2:$A$178,0))),"") | DX9: =IFERROR(IF(INDEX(MCDM_Grades!$E$2:$E$178,MATCH($A9,MCDM_Grades!$A$2:$A$178,0))="","",INDEX(MCDM_Grades!$E$2:$E$178,MATCH($A9,MCDM_Grades!$A$2:$A$178,0))),"") | DY9: =IFERROR(IF(INDEX(MCDM_Grades!$F$2:$F$178,MATCH($A9,MCDM_Grades!$A$2:$A$178,0))="","",INDEX(MCDM_Grades!$F$2:$F$178,MATCH($A9,MCDM_Grades!$A$2:$A$178,0))),"") | DZ9: =IFERROR(IF(INDEX(MCDM_Grades!$G$2:$G$178,MATCH($A9,MCDM_Grades!$A$2:$A$178,0))="","",INDEX(MCDM_Grades!$G$2:$G$178,MATCH($A9,MCDM_Grades!$A$2:$A$178,0))),"") | EA9: =IFERROR(IF(INDEX(MCDM_Grades!$H$2:$H$178,MATCH($A9,MCDM_Grades!$A$2:$A$178,0))="","",INDEX(MCDM_Grades!$H$2:$H$178,MATCH($A9,MCDM_Grades!$A$2:$A$178,0))),"") | EB9: =IFERROR(IF(INDEX(MCDM_Grades!$I$2:$I$178,MATCH($A9,MCDM_Grades!$A$2:$A$178,0))="","",INDEX(MCDM_Grades!$I$2:$I$178,MATCH($A9,MCDM_Grades!$A$2:$A$178,0))),"") | EC9: =IFERROR(IF(INDEX(MCDM_Grades!$J$2:$J$178,MATCH($A9,MCDM_Grades!$A$2:$A$178,0))="","",INDEX(MCDM_Grades!$J$2:$J$178,MATCH($A9,MCDM_Grades!$A$2:$A$178,0))),"") | ED9: =IFERROR(IF(INDEX(MCDM_Grades!$N$2:$N$178,MATCH($A9,MCDM_Grades!$A$2:$A$178,0))="","",INDEX(MCDM_Grades!$N$2:$N$178,MATCH($A9,MCDM_Grades!$A$2:$A$178,0))),"") | EE9: =IFERROR(IF(INDEX(MCDM_Grades!$O$2:$O$178,MATCH($A9,MCDM_Grades!$A$2:$A$178,0))="","",INDEX(MCDM_Grades!$O$2:$O$178,MATCH($A9,MCDM_Grades!$A$2:$A$178,0))),"") | EF9: =IFERROR(IF(INDEX(MCDM_Grades!$P$2:$P$178,MATCH($A9,MCDM_Grades!$A$2:$A$178,0))="","",INDEX(MCDM_Grades!$P$2:$P$178,MATCH($A9,MCDM_Grades!$A$2:$A$178,0))),"") | EG9: =IFERROR(IF(INDEX(MCDM_Grades!$Q$2:$Q$178,MATCH($A9,MCDM_Grades!$A$2:$A$178,0))="","",INDEX(MCDM_Grades!$Q$2:$Q$178,MATCH($A9,MCDM_Grades!$A$2:$A$178,0))),"") | EH9: =IFERROR(IF(INDEX(MCDM_Grades!$R$2:$R$178,MATCH($A9,MCDM_Grades!$A$2:$A$178,0))="","",INDEX(MCDM_Grades!$R$2:$R$178,MATCH($A9,MCDM_Grades!$A$2:$A$178,0))),"") | EI9: =IFERROR(IF(INDEX(MCDM_Grades!$S$2:$S$178,MATCH($A9,MCDM_Grades!$A$2:$A$178,0))="","",INDEX(MCDM_Grades!$S$2:$S$178,MATCH($A9,MCDM_Grades!$A$2:$A$178,0))),"") | EJ9: =IFERROR(IF(INDEX(MCDM_Grades!$T$2:$T$178,MATCH($A9,MCDM_Grades!$A$2:$A$178,0))="","",INDEX(MCDM_Grades!$T$2:$T$178,MATCH($A9,MCDM_Grades!$A$2:$A$178,0))),"") | EK9: =IFERROR(IF(INDEX(MCDM_Grades!$U$2:$U$178,MATCH($A9,MCDM_Grades!$A$2:$A$178,0))="","",INDEX(MCDM_Grades!$U$2:$U$178,MATCH($A9,MCDM_Grades!$A$2:$A$178,0))),"") | EL9: =IFERROR(IF(INDEX(MCDM_Grades!$V$2:$V$178,MATCH($A9,MCDM_Grades!$A$2:$A$178,0))="","",INDEX(MCDM_Grades!$V$2:$V$178,MATCH($A9,MCDM_Grades!$A$2:$A$178,0))),"") | EM9: =IFERROR(IF(INDEX(MCDM_Grades!$W$2:$W$178,MATCH($A9,MCDM_Grades!$A$2:$A$178,0))="","",INDEX(MCDM_Grades!$W$2:$W$178,MATCH($A9,MCDM_Grades!$A$2:$A$178,0))),"") | EN9: =IFERROR(IF(INDEX(MCDM_Grades!$X$2:$X$178,MATCH($A9,MCDM_Grades!$A$2:$A$178,0))="","",INDEX(MCDM_Grades!$X$2:$X$178,MATCH($A9,MCDM_Grades!$A$2:$A$178,0))),"") | EO9: =IFERROR(IF(INDEX(MCDM_Grades!$Y$2:$Y$178,MATCH($A9,MCDM_Grades!$A$2:$A$178,0))="","",INDEX(MCDM_Grades!$Y$2:$Y$178,MATCH($A9,MCDM_Grades!$A$2:$A$178,0))),"") | EP9: =IFERROR(IF(INDEX(MCDM_Grades!$Z$2:$Z$178,MATCH($A9,MCDM_Grades!$A$2:$A$178,0))="","",INDEX(MCDM_Grades!$Z$2:$Z$178,MATCH($A9,MCDM_Grades!$A$2:$A$178,0))),"") | EQ9: =IFERROR(IF(INDEX(MCDM_Grades!$AA$2:$AA$178,MATCH($A9,MCDM_Grades!$A$2:$A$178,0))="","",INDEX(MCDM_Grades!$AA$2:$AA$178,MATCH($A9,MCDM_Grades!$A$2:$A$178,0))),"") | ER9: =IFERROR(IF(INDEX(MCDM_Grades!$AB$2:$AB$178,MATCH($A9,MCDM_Grades!$A$2:$A$178,0))="","",INDEX(MCDM_Grades!$AB$2:$AB$178,MATCH($A9,MCDM_Grades!$A$2:$A$178,0))),"") | ES9: =IFERROR(IF(INDEX(MCDM_Grades!$AC$2:$AC$178,MATCH($A9,MCDM_Grades!$A$2:$A$178,0))="","",INDEX(MCDM_Grades!$AC$2:$AC$178,MATCH($A9,MCDM_Grades!$A$2:$A$178,0))),"") | ET9: =IFERROR(IF(INDEX(MCDM_Grades!$AD$2:$AD$178,MATCH($A9,MCDM_Grades!$A$2:$A$178,0))="","",INDEX(MCDM_Grades!$AD$2:$AD$178,MATCH($A9,MCDM_Grades!$A$2:$A$178,0))),"") | EU9: =IFERROR(IF(INDEX(MCDM_Grades!$AE$2:$AE$178,MATCH($A9,MCDM_Grades!$A$2:$A$178,0))="","",INDEX(MCDM_Grades!$AE$2:$AE$178,MATCH($A9,MCDM_Grades!$A$2:$A$178,0))),"") | EV9: =IFERROR(IF(INDEX(MCDM_Grades!$K$2:$K$178,MATCH($A9,MCDM_Grades!$A$2:$A$178,0))="","",INDEX(MCDM_Grades!$K$2:$K$178,MATCH($A9,MCDM_Grades!$A$2:$A$178,0))),"") | EW9: =IFERROR(IF(INDEX(MCDM_Grades!$L$2:$L$178,MATCH($A9,MCDM_Grades!$A$2:$A$178,0))="","",INDEX(MCDM_Grades!$L$2:$L$178,MATCH($A9,MCDM_Grades!$A$2:$A$178,0))),"") | EX9: =IFERROR(IF(INDEX(MCDM_Grades!$M$2:$M$178,MATCH($A9,MCDM_Grades!$A$2:$A$178,0))="","",INDEX(MCDM_Grades!$M$2:$M$178,MATCH($A9,MCDM_Grades!$A$2:$A$178,0))),"") | EY9: =IFERROR(IF(INDEX(MCDM_Grades!$AR$2:$AR$178,MATCH($A9,MCDM_Grades!$A$2:$A$178,0))="","",INDEX(MCDM_Grades!$AR$2:$AR$178,MATCH($A9,MCDM_Grades!$A$2:$A$178,0))),"") | EZ9: =IFERROR(IF(INDEX(MCDM_Grades!$AS$2:$AS$178,MATCH($A9,MCDM_Grades!$A$2:$A$178,0))="","",INDEX(MCDM_Grades!$AS$2:$AS$178,MATCH($A9,MCDM_Grades!$A$2:$A$178,0))),"") | FA9: =IFERROR(IF(INDEX(MCDM_Grades!$AT$2:$AT$178,MATCH($A9,MCDM_Grades!$A$2:$A$178,0))="","",INDEX(MCDM_Grades!$AT$2:$AT$178,MATCH($A9,MCDM_Grades!$A$2:$A$178,0))),"") | FB9: =IFERROR(IF(INDEX(MCDM_Grades!$AU$2:$AU$178,MATCH($A9,MCDM_Grades!$A$2:$A$178,0))="","",INDEX(MCDM_Grades!$AU$2:$AU$178,MATCH($A9,MCDM_Grades!$A$2:$A$178,0))),"") | FC9: Nadir / top-down | FD9: Yes | FE9: No | FG9: Handheld smartphone (iPhone 5) pointed at the surface | FH9: Sample image image/001.jpg (480x320) from the CFD repository: full-frame asphalt surface with a single meandering crack, no horizon, road edge or perspective convergence. | Shi et al. (2016), IEEE T-ITS, doi 10.1109/TITS.2016.2552248 | FI9: Dataset page / README | FJ9: https://raw.githubusercontent.com/cuilimeng/CrackForest-dataset/master/image/001.jpg | FK9: High | FL9: Verified - agreed | FM9: Workbook: 'iPhone 5 smartphone camera', Smartphone_Data Y, Camera_Position NR. The GitHub README (fetched twice, page and raw) only says CFD is 'an annotated road crack image database which can reflect urban road surface condition in general' and gives citations/licence; no camera-orientation sentence. Orientation rests on the well-known benchmark: the 118 CFD images (480x320) are full-frame pavement close-ups taken with the phone pointed at the road surface, as shown in the Shi et al. paper figures. Confidence capped at Medium per the prior-knowledge rule. | Second review replaced the evidence (was: Known dataset (prior knowledge)). | Second review: Inspected a sample CFD image downloaded from the repository: it is a surface-perpendicular close-up of pavement, confirming the top-down label. Workbook records iPhone 5 capture; the Shi et al. abstract could not be retrieved (Semantic Scholar elided it).
A10: DS-009 | B10: CrackLS315 | C10: NA | D10: CrackLS315 | E10: Independent Dataset | F10: NA (single source record) | G10: Single source record; no matching record found in any other file after cross-file and cross-platform comparison. | H10: GitHub_Test_Batch (tool UNK) | I10: GitHub | J10: N | K10: NA (single platform) | L10: https://github.com/qinnzou/DeepCrack | M10: https://github.com/qinnzou/DeepCrack | N10: NA | O10: NA | P10: NA | Q10: NA | R10: NA | S10: NA | T10: NR | U10: Y | V10: https://github.com/qinnzou/DeepCrack | W10: NR | X10: https://github.com/qinnzou/DeepCrack | Y10: NR | Z10: NR | AA10: Reported in source record (relationship not classified) | AB10: Images/frames as reported | AC10: 315 | AD10: NR | AE10: NR | AF10: 315 | AG10: NR | AH10: NR | AI10: NR | AJ10: NR | AK10: NR | AL10: NR | AM10: NR | AN10: NR | AO10: NR | AP10: NR | AQ10: NR | AR10: NR | AS10: Road environment: Road pavement | AT10: NR | AU10: Laser-illuminated line-array camera | AV10: NR | AW10: Laser-illuminated line-array camera | AX10: NR | AY10: NR | AZ10: NR | BA10: NR | BB10: NR | BC10: NR | BD10: Laser imaging | BE10: NR | BF10: Controlled laser illumination | BG10: NR | BH10: pavement crack | BI10: NR | BJ10: crack pixel mask | BK10: NR | BL10: Semantic segmentation | BM10: Semantic segmentation | BN10: Image-mask pairs | BO10: mask | BP10: NR | BQ10: NR | BR10: Y | BS10: NR | BT10: NR | BU10: NR | BV10: NR | BW10: NR | BX10: NR | BY10: Manual pixel annotation | BZ10: NR | CA10: NR | CB10: NR | CC10: semantic segmentation; crack detection | CD10: NR | CE10: NR | CF10: Reported on the source record/data card or associated publication (see Evidence_Locator) | CG10: NR | CH10: NR | CI10: Include-Primary | CJ10: Direct_Download | CK10: NR | CL10: N | CM10: Direct_Download | CN10: NR | CO10: NR | CP10: N | CQ10: Small crack-only dataset; 1 mm ground sampling distance is reported, but pixel resolution, navigation, location, license, and weather metadata are not reported. | CR10: Original | CS10: N | CT10: N | CU10: N | CV10: NA | CW10: NA | CX10: Github_Github_Test.xlsx | CY10: Github_Github_Test:GITHUB-020 | CZ10: NA | DA10: NA | DB10: None | DC10: None | DD10: None | DE10: None | DF10: N | DG10: Single source record; no reconciliation required. | DH10: https://github.com/qinnzou/DeepCrack; README dataset table and download links; accessed 2026-08-01 | DI10: High | DJ10: Low | DK10: Use source record as cited. | DL10: 4 | DM10: 4 | DN10: 4 | DO10: 2 | DP10: 2 | DQ10: 3 | DR10: 0 | DS10: 60 | DT10: Reviewed (source MCDM_Scoring, averaged across batches) | DU10: 1 of 1 | DV10: =IFERROR(IF(INDEX(MCDM_Grades!$C$2:$C$178,MATCH($A10,MCDM_Grades!$A$2:$A$178,0))="","",INDEX(MCDM_Grades!$C$2:$C$178,MATCH($A10,MCDM_Grades!$A$2:$A$178,0))),"") | DW10: =IFERROR(IF(INDEX(MCDM_Grades!$D$2:$D$178,MATCH($A10,MCDM_Grades!$A$2:$A$178,0))="","",INDEX(MCDM_Grades!$D$2:$D$178,MATCH($A10,MCDM_Grades!$A$2:$A$178,0))),"") | DX10: =IFERROR(IF(INDEX(MCDM_Grades!$E$2:$E$178,MATCH($A10,MCDM_Grades!$A$2:$A$178,0))="","",INDEX(MCDM_Grades!$E$2:$E$178,MATCH($A10,MCDM_Grades!$A$2:$A$178,0))),"") | DY10: =IFERROR(IF(INDEX(MCDM_Grades!$F$2:$F$178,MATCH($A10,MCDM_Grades!$A$2:$A$178,0))="","",INDEX(MCDM_Grades!$F$2:$F$178,MATCH($A10,MCDM_Grades!$A$2:$A$178,0))),"") | DZ10: =IFERROR(IF(INDEX(MCDM_Grades!$G$2:$G$178,MATCH($A10,MCDM_Grades!$A$2:$A$178,0))="","",INDEX(MCDM_Grades!$G$2:$G$178,MATCH($A10,MCDM_Grades!$A$2:$A$178,0))),"") | EA10: =IFERROR(IF(INDEX(MCDM_Grades!$H$2:$H$178,MATCH($A10,MCDM_Grades!$A$2:$A$178,0))="","",INDEX(MCDM_Grades!$H$2:$H$178,MATCH($A10,MCDM_Grades!$A$2:$A$178,0))),"") | EB10: =IFERROR(IF(INDEX(MCDM_Grades!$I$2:$I$178,MATCH($A10,MCDM_Grades!$A$2:$A$178,0))="","",INDEX(MCDM_Grades!$I$2:$I$178,MATCH($A10,MCDM_Grades!$A$2:$A$178,0))),"") | EC10: =IFERROR(IF(INDEX(MCDM_Grades!$J$2:$J$178,MATCH($A10,MCDM_Grades!$A$2:$A$178,0))="","",INDEX(MCDM_Grades!$J$2:$J$178,MATCH($A10,MCDM_Grades!$A$2:$A$178,0))),"") | ED10: =IFERROR(IF(INDEX(MCDM_Grades!$N$2:$N$178,MATCH($A10,MCDM_Grades!$A$2:$A$178,0))="","",INDEX(MCDM_Grades!$N$2:$N$178,MATCH($A10,MCDM_Grades!$A$2:$A$178,0))),"") | EE10: =IFERROR(IF(INDEX(MCDM_Grades!$O$2:$O$178,MATCH($A10,MCDM_Grades!$A$2:$A$178,0))="","",INDEX(MCDM_Grades!$O$2:$O$178,MATCH($A10,MCDM_Grades!$A$2:$A$178,0))),"") | EF10: =IFERROR(IF(INDEX(MCDM_Grades!$P$2:$P$178,MATCH($A10,MCDM_Grades!$A$2:$A$178,0))="","",INDEX(MCDM_Grades!$P$2:$P$178,MATCH($A10,MCDM_Grades!$A$2:$A$178,0))),"") | EG10: =IFERROR(IF(INDEX(MCDM_Grades!$Q$2:$Q$178,MATCH($A10,MCDM_Grades!$A$2:$A$178,0))="","",INDEX(MCDM_Grades!$Q$2:$Q$178,MATCH($A10,MCDM_Grades!$A$2:$A$178,0))),"") | EH10: =IFERROR(IF(INDEX(MCDM_Grades!$R$2:$R$178,MATCH($A10,MCDM_Grades!$A$2:$A$178,0))="","",INDEX(MCDM_Grades!$R$2:$R$178,MATCH($A10,MCDM_Grades!$A$2:$A$178,0))),"") | EI10: =IFERROR(IF(INDEX(MCDM_Grades!$S$2:$S$178,MATCH($A10,MCDM_Grades!$A$2:$A$178,0))="","",INDEX(MCDM_Grades!$S$2:$S$178,MATCH($A10,MCDM_Grades!$A$2:$A$178,0))),"") | EJ10: =IFERROR(IF(INDEX(MCDM_Grades!$T$2:$T$178,MATCH($A10,MCDM_Grades!$A$2:$A$178,0))="","",INDEX(MCDM_Grades!$T$2:$T$178,MATCH($A10,MCDM_Grades!$A$2:$A$178,0))),"") | EK10: =IFERROR(IF(INDEX(MCDM_Grades!$U$2:$U$178,MATCH($A10,MCDM_Grades!$A$2:$A$178,0))="","",INDEX(MCDM_Grades!$U$2:$U$178,MATCH($A10,MCDM_Grades!$A$2:$A$178,0))),"") | EL10: =IFERROR(IF(INDEX(MCDM_Grades!$V$2:$V$178,MATCH($A10,MCDM_Grades!$A$2:$A$178,0))="","",INDEX(MCDM_Grades!$V$2:$V$178,MATCH($A10,MCDM_Grades!$A$2:$A$178,0))),"") | EM10: =IFERROR(IF(INDEX(MCDM_Grades!$W$2:$W$178,MATCH($A10,MCDM_Grades!$A$2:$A$178,0))="","",INDEX(MCDM_Grades!$W$2:$W$178,MATCH($A10,MCDM_Grades!$A$2:$A$178,0))),"") | EN10: =IFERROR(IF(INDEX(MCDM_Grades!$X$2:$X$178,MATCH($A10,MCDM_Grades!$A$2:$A$178,0))="","",INDEX(MCDM_Grades!$X$2:$X$178,MATCH($A10,MCDM_Grades!$A$2:$A$178,0))),"") | EO10: =IFERROR(IF(INDEX(MCDM_Grades!$Y$2:$Y$178,MATCH($A10,MCDM_Grades!$A$2:$A$178,0))="","",INDEX(MCDM_Grades!$Y$2:$Y$178,MATCH($A10,MCDM_Grades!$A$2:$A$178,0))),"") | EP10: =IFERROR(IF(INDEX(MCDM_Grades!$Z$2:$Z$178,MATCH($A10,MCDM_Grades!$A$2:$A$178,0))="","",INDEX(MCDM_Grades!$Z$2:$Z$178,MATCH($A10,MCDM_Grades!$A$2:$A$178,0))),"") | EQ10: =IFERROR(IF(INDEX(MCDM_Grades!$AA$2:$AA$178,MATCH($A10,MCDM_Grades!$A$2:$A$178,0))="","",INDEX(MCDM_Grades!$AA$2:$AA$178,MATCH($A10,MCDM_Grades!$A$2:$A$178,0))),"") | ER10: =IFERROR(IF(INDEX(MCDM_Grades!$AB$2:$AB$178,MATCH($A10,MCDM_Grades!$A$2:$A$178,0))="","",INDEX(MCDM_Grades!$AB$2:$AB$178,MATCH($A10,MCDM_Grades!$A$2:$A$178,0))),"") | ES10: =IFERROR(IF(INDEX(MCDM_Grades!$AC$2:$AC$178,MATCH($A10,MCDM_Grades!$A$2:$A$178,0))="","",INDEX(MCDM_Grades!$AC$2:$AC$178,MATCH($A10,MCDM_Grades!$A$2:$A$178,0))),"") | ET10: =IFERROR(IF(INDEX(MCDM_Grades!$AD$2:$AD$178,MATCH($A10,MCDM_Grades!$A$2:$A$178,0))="","",INDEX(MCDM_Grades!$AD$2:$AD$178,MATCH($A10,MCDM_Grades!$A$2:$A$178,0))),"") | EU10: =IFERROR(IF(INDEX(MCDM_Grades!$AE$2:$AE$178,MATCH($A10,MCDM_Grades!$A$2:$A$178,0))="","",INDEX(MCDM_Grades!$AE$2:$AE$178,MATCH($A10,MCDM_Grades!$A$2:$A$178,0))),"") | EV10: =IFERROR(IF(INDEX(MCDM_Grades!$K$2:$K$178,MATCH($A10,MCDM_Grades!$A$2:$A$178,0))="","",INDEX(MCDM_Grades!$K$2:$K$178,MATCH($A10,MCDM_Grades!$A$2:$A$178,0))),"") | EW10: =IFERROR(IF(INDEX(MCDM_Grades!$L$2:$L$178,MATCH($A10,MCDM_Grades!$A$2:$A$178,0))="","",INDEX(MCDM_Grades!$L$2:$L$178,MATCH($A10,MCDM_Grades!$A$2:$A$178,0))),"") | EX10: =IFERROR(IF(INDEX(MCDM_Grades!$M$2:$M$178,MATCH($A10,MCDM_Grades!$A$2:$A$178,0))="","",INDEX(MCDM_Grades!$M$2:$M$178,MATCH($A10,MCDM_Grades!$A$2:$A$178,0))),"") | EY10: =IFERROR(IF(INDEX(MCDM_Grades!$AR$2:$AR$178,MATCH($A10,MCDM_Grades!$A$2:$A$178,0))="","",INDEX(MCDM_Grades!$AR$2:$AR$178,MATCH($A10,MCDM_Grades!$A$2:$A$178,0))),"") | EZ10: =IFERROR(IF(INDEX(MCDM_Grades!$AS$2:$AS$178,MATCH($A10,MCDM_Grades!$A$2:$A$178,0))="","",INDEX(MCDM_Grades!$AS$2:$AS$178,MATCH($A10,MCDM_Grades!$A$2:$A$178,0))),"") | FA10: =IFERROR(IF(INDEX(MCDM_Grades!$AT$2:$AT$178,MATCH($A10,MCDM_Grades!$A$2:$A$178,0))="","",INDEX(MCDM_Grades!$AT$2:$AT$178,MATCH($A10,MCDM_Grades!$A$2:$A$178,0))),"") | FB10: =IFERROR(IF(INDEX(MCDM_Grades!$AU$2:$AU$178,MATCH($A10,MCDM_Grades!$A$2:$A$178,0))="","",INDEX(MCDM_Grades!$AU$2:$AU$178,MATCH($A10,MCDM_Grades!$A$2:$A$178,0))),"") | FC10: Nadir / top-down | FD10: Yes | FE10: No | FG10: Survey-vehicle line-scan (line-array) camera with laser illumination, 1 mm ground sampling distance | FH10: road pavement images captured under laser illumination. These images are also captured by a line-array camera, at the same ground sampling distance. | FI10: Dataset page / README | FJ10: https://github.com/qinnzou/DeepCrack | FK10: High | FL10: Not independently verified | FM10: Workbook: 'Laser-illuminated line-array camera', Other_Sensors 'Laser imaging', 1 mm GSD reported. The DeepCrack README states CRKWH100 is 'captured by a line-array camera under visible-light illumination ... at a ground sampling distance of 1 millimeter' and CrackLS315 uses the same line-array camera under laser illumination at the same GSD. A line-array (line-scan) pavement camera with a fixed 1 mm ground sampling distance is by construction a downward-facing survey-vehicle sensor (the line is swept along the road), so the viewpoint is nadir. Vehicle type is not named on the page.
A11: DS-010 | B11: Cracks and Potholes in Road Images Dataset (DNIT, Brazil) | C11: Cracks and Potholes in Road Images; Cracks and Potholes in Road Images Dataset | D11: 4 | E11: Confirmed Match | F11: High | G11: Identical count (2,235); same Brazilian DNIT road-survey imagery; GitHub project (biankatpas/Cracks-and-Potholes-in-Road-Images-Dataset) is the project page of the Mendeley deposit (10.17632/t576ydh9v8.4). | H11: GPT; GitHub_Test_Batch (tool UNK) | I11: GitHub; Mendeley Data | J11: Y | K11: Mendeley deposit with GitHub project page | L11: https://data.mendeley.com/datasets/t576ydh9v8/4 | M11: https://github.com/biankatpas/Cracks-and-Potholes-in-Road-Images-Dataset | N11: NA | O11: https://data.mendeley.com/datasets/t576ydh9v8/4 | P11: NA | Q11: NA | R11: NA | S11: NA | T11: 10.17632/t576ydh9v8.4 | U11: Y | V11: https://biankatpas.github.io/Cracks-and-Potholes-in-Road-Images-Dataset/ [GPT] | https://github.com/biankatpas/Cracks-and-Potholes-in-Road-Images-Dataset [Test_Batch] | W11: NR | X11: https://biankatpas.github.io/Cracks-and-Potholes-in-Road-Images-Dataset/; https://github.com/biankatpas/Cracks-and-Potholes-in-Road-Images-Dataset | Y11: NR | Z11: NR | AA11: Reported in source record (relationship not classified) | AB11: Images/frames as reported | AC11: 2235 | AD11: NR | AE11: NR | AF11: 2235 | AG11: NR | AH11: NR | AI11: NR | AJ11: NR | AK11: NR | AL11: NR | AM11: NR | AN11: NR | AO11: NR | AP11: Brazil | AQ11: NR | AR11: Espírito Santo;Rio Grande do Sul;Federal District | AS11: Brazil; Espírito Santo;Rio Grande do Sul;Federal District; Road environment: Highways [GPT] | Roadway [Test_Batch] | AT11: 2014 to 2017 | AU11: DNIT road-survey imagery; platform NR | AV11: NR | AW11: NR | AX11: NR | AY11: NR | AZ11: NR | BA11: NR | BB11: N | BC11: NR | BD11: NR | BE11: NR | BF11: NR | BG11: NR | BH11: Crack;Pothole | BI11: NR | BJ11: Road;crack;pothole masks [GPT] | road; crack; pothole [Test_Batch] | BK11: NR | BL11: Semantic segmentation [GPT] | Object detection; classification [Test_Batch] | BM11: Semantic segmentation [GPT] | Object detection; classification [Test_Batch] | BN11: PNG binary masks | BO11: mask | BP11: Y | BQ11: Y | BR11: Y | BS11: NR | BT11: NR | BU11: NR | BV11: N | BW11: N | BX11: N | BY11: Manual delineation of road and defects [GPT] | Manual annotation [Test_Batch] | BZ11: NR | CA11: NR | CB11: NR | CC11: Semantic segmentation;Defect detection [GPT] | classification; object detection [Test_Batch] | CD11: NR | CE11: NR | CF11: Reported on the source record/data card or associated publication (see Evidence_Locator) | CG11: NR | CH11: NR | CI11: Include-Primary [GPT] | Pending [Test_Batch] | CJ11: Direct_Download | CK11: CC BY 4.0 | CL11: N | CM11: Direct_Download | CN11: NR | CO11: NR | CP11: N | CQ11: Images collected partly before project years, but qualifying dataset release is 2020; limited sensor and condition metadata [GPT] | Release year, formal license, exact annotation format, and authoritative count documentation remain unresolved. [Test_Batch] | CR11: Original | CS11: Y | CT11: N | CU11: N | CV11: NA | CW11: NA | CX11: GPT_Mendeley_001.xlsx; Github_Github_Test.xlsx | CY11: GPT_Mendeley_001:MEN-002; Github_Github_Test:GITHUB-026 | CZ11: NA | DA11: Y - see conflict columns and Reconciliation_Notes | DB11: None | DC11: Label taxonomy: Road;crack;pothole masks (GPT) vs road; crack; pothole (Test_Batch) || Annotation task: Semantic segmentation (GPT) vs Object detection; classification (Test_Batch) || Annotation method: Manual delineation of road and defects (GPT) vs Manual annotation (Test_Batch) | DD11: None | DE11: AI tasks: Semantic segmentation;Defect detection (GPT) vs classification; object detection (Test_Batch) || Screening decision: Include-Primary (GPT) vs Pending (Test_Batch) || Road environment: Highways (GPT) vs Roadway (Test_Batch) || Publications: https://biankatpas.github.io/Cracks-and-Potholes-in-Road-Images-Dataset/ (GPT) vs https://github.com/biankatpas/Cracks-and-Potholes-in-Road-Images-Dataset (Test_Batch) || Key_Limitations: Images collected partly before project years, but qualifying dataset release is (GPT) vs Release year, formal license, exact annotation format, and authoritative count d (Test_Batch) | DF11: Y | DG11: Not found by Claude. Screening Include-Primary (GPT) vs Pending (Test batch). | DH11: Mendeley dataset page, Description/Steps to reproduce/Licence, accessed 2026-08-05 [GPT] | https://github.com/biankatpas/Cracks-and-Potholes-in-Road-Images-Dataset; repository description; count cross-check from public dataset index; accessed 2026-08-01 [Test_Batch] | DI11: Low | DJ11: Low | DK11: Use Mendeley deposit as canonical. | DL11: 4.5 | DM11: 3.5 | DN11: 3.5 | DO11: 3 | DP11: 3 | DQ11: 1 | DR11: 0 | DS11: 59.5 | DT11: Reviewed (source MCDM_Scoring, averaged across batches) | DU11: 2 of 2 | DV11: =IFERROR(IF(INDEX(MCDM_Grades!$C$2:$C$178,MATCH($A11,MCDM_Grades!$A$2:$A$178,0))="","",INDEX(MCDM_Grades!$C$2:$C$178,MATCH($A11,MCDM_Grades!$A$2:$A$178,0))),"") | DW11: =IFERROR(IF(INDEX(MCDM_Grades!$D$2:$D$178,MATCH($A11,MCDM_Grades!$A$2:$A$178,0))="","",INDEX(MCDM_Grades!$D$2:$D$178,MATCH($A11,MCDM_Grades!$A$2:$A$178,0))),"") | DX11: =IFERROR(IF(INDEX(MCDM_Grades!$E$2:$E$178,MATCH($A11,MCDM_Grades!$A$2:$A$178,0))="","",INDEX(MCDM_Grades!$E$2:$E$178,MATCH($A11,MCDM_Grades!$A$2:$A$178,0))),"") | DY11: =IFERROR(IF(INDEX(MCDM_Grades!$F$2:$F$178,MATCH($A11,MCDM_Grades!$A$2:$A$178,0))="","",INDEX(MCDM_Grades!$F$2:$F$178,MATCH($A11,MCDM_Grades!$A$2:$A$178,0))),"") | DZ11: =IFERROR(IF(INDEX(MCDM_Grades!$G$2:$G$178,MATCH($A11,MCDM_Grades!$A$2:$A$178,0))="","",INDEX(MCDM_Grades!$G$2:$G$178,MATCH($A11,MCDM_Grades!$A$2:$A$178,0))),"") | EA11: =IFERROR(IF(INDEX(MCDM_Grades!$H$2:$H$178,MATCH($A11,MCDM_Grades!$A$2:$A$178,0))="","",INDEX(MCDM_Grades!$H$2:$H$178,MATCH($A11,MCDM_Grades!$A$2:$A$178,0))),"") | EB11: =IFERROR(IF(INDEX(MCDM_Grades!$I$2:$I$178,MATCH($A11,MCDM_Grades!$A$2:$A$178,0))="","",INDEX(MCDM_Grades!$I$2:$I$178,MATCH($A11,MCDM_Grades!$A$2:$A$178,0))),"") | EC11: =IFERROR(IF(INDEX(MCDM_Grades!$J$2:$J$178,MATCH($A11,MCDM_Grades!$A$2:$A$178,0))="","",INDEX(MCDM_Grades!$J$2:$J$178,MATCH($A11,MCDM_Grades!$A$2:$A$178,0))),"") | ED11: =IFERROR(IF(INDEX(MCDM_Grades!$N$2:$N$178,MATCH($A11,MCDM_Grades!$A$2:$A$178,0))="","",INDEX(MCDM_Grades!$N$2:$N$178,MATCH($A11,MCDM_Grades!$A$2:$A$178,0))),"") | EE11: =IFERROR(IF(INDEX(MCDM_Grades!$O$2:$O$178,MATCH($A11,MCDM_Grades!$A$2:$A$178,0))="","",INDEX(MCDM_Grades!$O$2:$O$178,MATCH($A11,MCDM_Grades!$A$2:$A$178,0))),"") | EF11: =IFERROR(IF(INDEX(MCDM_Grades!$P$2:$P$178,MATCH($A11,MCDM_Grades!$A$2:$A$178,0))="","",INDEX(MCDM_Grades!$P$2:$P$178,MATCH($A11,MCDM_Grades!$A$2:$A$178,0))),"") | EG11: =IFERROR(IF(INDEX(MCDM_Grades!$Q$2:$Q$178,MATCH($A11,MCDM_Grades!$A$2:$A$178,0))="","",INDEX(MCDM_Grades!$Q$2:$Q$178,MATCH($A11,MCDM_Grades!$A$2:$A$178,0))),"") | EH11: =IFERROR(IF(INDEX(MCDM_Grades!$R$2:$R$178,MATCH($A11,MCDM_Grades!$A$2:$A$178,0))="","",INDEX(MCDM_Grades!$R$2:$R$178,MATCH($A11,MCDM_Grades!$A$2:$A$178,0))),"") | EI11: =IFERROR(IF(INDEX(MCDM_Grades!$S$2:$S$178,MATCH($A11,MCDM_Grades!$A$2:$A$178,0))="","",INDEX(MCDM_Grades!$S$2:$S$178,MATCH($A11,MCDM_Grades!$A$2:$A$178,0))),"") | EJ11: =IFERROR(IF(INDEX(MCDM_Grades!$T$2:$T$178,MATCH($A11,MCDM_Grades!$A$2:$A$178,0))="","",INDEX(MCDM_Grades!$T$2:$T$178,MATCH($A11,MCDM_Grades!$A$2:$A$178,0))),"") | EK11: =IFERROR(IF(INDEX(MCDM_Grades!$U$2:$U$178,MATCH($A11,MCDM_Grades!$A$2:$A$178,0))="","",INDEX(MCDM_Grades!$U$2:$U$178,MATCH($A11,MCDM_Grades!$A$2:$A$178,0))),"") | EL11: =IFERROR(IF(INDEX(MCDM_Grades!$V$2:$V$178,MATCH($A11,MCDM_Grades!$A$2:$A$178,0))="","",INDEX(MCDM_Grades!$V$2:$V$178,MATCH($A11,MCDM_Grades!$A$2:$A$178,0))),"") | EM11: =IFERROR(IF(INDEX(MCDM_Grades!$W$2:$W$178,MATCH($A11,MCDM_Grades!$A$2:$A$178,0))="","",INDEX(MCDM_Grades!$W$2:$W$178,MATCH($A11,MCDM_Grades!$A$2:$A$178,0))),"") | EN11: =IFERROR(IF(INDEX(MCDM_Grades!$X$2:$X$178,MATCH($A11,MCDM_Grades!$A$2:$A$178,0))="","",INDEX(MCDM_Grades!$X$2:$X$178,MATCH($A11,MCDM_Grades!$A$2:$A$178,0))),"") | EO11: =IFERROR(IF(INDEX(MCDM_Grades!$Y$2:$Y$178,MATCH($A11,MCDM_Grades!$A$2:$A$178,0))="","",INDEX(MCDM_Grades!$Y$2:$Y$178,MATCH($A11,MCDM_Grades!$A$2:$A$178,0))),"") | EP11: =IFERROR(IF(INDEX(MCDM_Grades!$Z$2:$Z$178,MATCH($A11,MCDM_Grades!$A$2:$A$178,0))="","",INDEX(MCDM_Grades!$Z$2:$Z$178,MATCH($A11,MCDM_Grades!$A$2:$A$178,0))),"") | EQ11: =IFERROR(IF(INDEX(MCDM_Grades!$AA$2:$AA$178,MATCH($A11,MCDM_Grades!$A$2:$A$178,0))="","",INDEX(MCDM_Grades!$AA$2:$AA$178,MATCH($A11,MCDM_Grades!$A$2:$A$178,0))),"") | ER11: =IFERROR(IF(INDEX(MCDM_Grades!$AB$2:$AB$178,MATCH($A11,MCDM_Grades!$A$2:$A$178,0))="","",INDEX(MCDM_Grades!$AB$2:$AB$178,MATCH($A11,MCDM_Grades!$A$2:$A$178,0))),"") | ES11: =IFERROR(IF(INDEX(MCDM_Grades!$AC$2:$AC$178,MATCH($A11,MCDM_Grades!$A$2:$A$178,0))="","",INDEX(MCDM_Grades!$AC$2:$AC$178,MATCH($A11,MCDM_Grades!$A$2:$A$178,0))),"") | ET11: =IFERROR(IF(INDEX(MCDM_Grades!$AD$2:$AD$178,MATCH($A11,MCDM_Grades!$A$2:$A$178,0))="","",INDEX(MCDM_Grades!$AD$2:$AD$178,MATCH($A11,MCDM_Grades!$A$2:$A$178,0))),"") | EU11: =IFERROR(IF(INDEX(MCDM_Grades!$AE$2:$AE$178,MATCH($A11,MCDM_Grades!$A$2:$A$178,0))="","",INDEX(MCDM_Grades!$AE$2:$AE$178,MATCH($A11,MCDM_Grades!$A$2:$A$178,0))),"") | EV11: =IFERROR(IF(INDEX(MCDM_Grades!$K$2:$K$178,MATCH($A11,MCDM_Grades!$A$2:$A$178,0))="","",INDEX(MCDM_Grades!$K$2:$K$178,MATCH($A11,MCDM_Grades!$A$2:$A$178,0))),"") | EW11: =IFERROR(IF(INDEX(MCDM_Grades!$L$2:$L$178,MATCH($A11,MCDM_Grades!$A$2:$A$178,0))="","",INDEX(MCDM_Grades!$L$2:$L$178,MATCH($A11,MCDM_Grades!$A$2:$A$178,0))),"") | EX11: =IFERROR(IF(INDEX(MCDM_Grades!$M$2:$M$178,MATCH($A11,MCDM_Grades!$A$2:$A$178,0))="","",INDEX(MCDM_Grades!$M$2:$M$178,MATCH($A11,MCDM_Grades!$A$2:$A$178,0))),"") | EY11: =IFERROR(IF(INDEX(MCDM_Grades!$AR$2:$AR$178,MATCH($A11,MCDM_Grades!$A$2:$A$178,0))="","",INDEX(MCDM_Grades!$AR$2:$AR$178,MATCH($A11,MCDM_Grades!$A$2:$A$178,0))),"") | EZ11: =IFERROR(IF(INDEX(MCDM_Grades!$AS$2:$AS$178,MATCH($A11,MCDM_Grades!$A$2:$A$178,0))="","",INDEX(MCDM_Grades!$AS$2:$AS$178,MATCH($A11,MCDM_Grades!$A$2:$A$178,0))),"") | FA11: =IFERROR(IF(INDEX(MCDM_Grades!$AT$2:$AT$178,MATCH($A11,MCDM_Grades!$A$2:$A$178,0))="","",INDEX(MCDM_Grades!$AT$2:$AT$178,MATCH($A11,MCDM_Grades!$A$2:$A$178,0))),"") | FB11: =IFERROR(IF(INDEX(MCDM_Grades!$AU$2:$AU$178,MATCH($A11,MCDM_Grades!$A$2:$A$178,0))="","",INDEX(MCDM_Grades!$AU$2:$AU$178,MATCH($A11,MCDM_Grades!$A$2:$A$178,0))),"") | FC11: Forward-facing / oblique | FD11: No | FE11: Yes | FG11: Roof-mounted forward-facing camera on DNIT Highway Diagnostic Vehicle, tilted downward toward the pavement | FH11: The camera is installed on the highest part of the vehicle, facing the front and with an inclination closer to orthogonality. Thus, the visibility of the pavement is 15 meters. | FI11: Dataset page / README | FJ11: https://biankatpas.github.io/Cracks-and-Potholes-in-Road-Images-Dataset/ | FK11: High | FL11: Not independently verified | FM11: Workbook: 'DNIT road-survey imagery; platform NR'. The project page states the images were 'extracted from videos captured by NDTI, using a Highway Diagnostic Vehicle (HDV)', with a camera on the highest part of the vehicle 'facing the front' and a downward tilt such that 15 m of pavement is visible; frames every 5 m, min 4 MP (video 1280x729, 30 fps). A 15 m forward pavement view from a roof camera is an oblique forward-facing geometry, not nadir; 'inclination closer to orthogonality' describes the downward tilt from horizontal. Each image carries a road-lane mask (perspective road region) plus crack and pothole masks. The Mendeley record (t576ydh9v8 v4) gives provenance (DNIT, 2,235 images, ES/RS/DF highways, 2014-2017) but no camera details.
A12: DS-011 | B12: CrackSeg9k | C12: NA | D12: NR | E12: Independent Dataset | F12: NA (single source record) | G12: Single source record; no matching record found in any other file after cross-file and cross-platform comparison. | H12: GitHub_Test_Batch (tool UNK) | I12: GitHub | J12: N | K12: NA (single platform) | L12: https://github.com/Dhananjay42/crackseg9k | M12: https://github.com/Dhananjay42/crackseg9k | N12: NA | O12: NA | P12: NA | Q12: NA | R12: NA | S12: NA | T12: NR | U12: Y | V12: https://github.com/Dhananjay42/crackseg9k | W12: NR | X12: https://github.com/Dhananjay42/crackseg9k | Y12: NR | Z12: NR | AA12: Reported in source record (relationship not classified) | AB12: NR | AC12: NR | AD12: NR | AE12: NR | AF12: NR | AG12: NR | AH12: NR | AI12: NR | AJ12: NR | AK12: NR | AL12: NR | AM12: NR | AN12: NR | AO12: NR | AP12: NR | AQ12: NR | AR12: NR | AS12: Road environment: Roadway; mixed structures and materials | AT12: NR | AU12: Multiple source datasets | AV12: NR | AW12: NR | AX12: NR | AY12: NR | AZ12: NR | BA12: NR | BB12: NR | BC12: NR | BD12: NR | BE12: NR | BF12: NR | BG12: NR | BH12: crack | BI12: NR | BJ12: crack pixel mask | BK12: NR | BL12: Semantic segmentation | BM12: Semantic segmentation | BN12: Image-mask pairs | BO12: mask | BP12: NR | BQ12: NR | BR12: Y | BS12: NR | BT12: NR | BU12: NR | BV12: NR | BW12: NR | BX12: NR | BY12: Compiled and standardized from multiple datasets | BZ12: NR | CA12: NR | CB12: NR | CC12: semantic segmentation | CD12: NR | CE12: NR | CF12: Reported on the source record/data card or associated publication (see Evidence_Locator) | CG12: NR | CH12: NR | CI12: Include-Supplementary | CJ12: Direct_Download | CK12: NR | CL12: N | CM12: Direct_Download | CN12: NR | CO12: NR | CP12: N | CQ12: Approximately 9,160 images are reported, but the corpus combines road and non-road crack sources and may duplicate underlying datasets. | CR12: Compiled | CS12: N | CT12: N | CU12: Y | CV12: Compiled from multiple public crack datasets | CW12: NA | CX12: Github_Github_Test.xlsx | CY12: Github_Github_Test:GITHUB-022 | CZ12: NA | DA12: NA | DB12: None | DC12: None | DD12: None | DE12: None | DF12: N | DG12: Single source record; no reconciliation required. | DH12: https://github.com/Dhananjay42/crackseg9k; README dataset composition and Harvard Dataverse link; accessed 2026-08-01 | DI12: High | DJ12: Low | DK12: Use source record as cited. | DL12: 5 | DM12: 3 | DN12: 4 | DO12: 4 | DP12: 4 | DQ12: 1 | DR12: 0 | DS12: 66 | DT12: Reviewed (source MCDM_Scoring, averaged across batches) | DU12: 1 of 1 | DV12: =IFERROR(IF(INDEX(MCDM_Grades!$C$2:$C$178,MATCH($A12,MCDM_Grades!$A$2:$A$178,0))="","",INDEX(MCDM_Grades!$C$2:$C$178,MATCH($A12,MCDM_Grades!$A$2:$A$178,0))),"") | DW12: =IFERROR(IF(INDEX(MCDM_Grades!$D$2:$D$178,MATCH($A12,MCDM_Grades!$A$2:$A$178,0))="","",INDEX(MCDM_Grades!$D$2:$D$178,MATCH($A12,MCDM_Grades!$A$2:$A$178,0))),"") | DX12: =IFERROR(IF(INDEX(MCDM_Grades!$E$2:$E$178,MATCH($A12,MCDM_Grades!$A$2:$A$178,0))="","",INDEX(MCDM_Grades!$E$2:$E$178,MATCH($A12,MCDM_Grades!$A$2:$A$178,0))),"") | DY12: =IFERROR(IF(INDEX(MCDM_Grades!$F$2:$F$178,MATCH($A12,MCDM_Grades!$A$2:$A$178,0))="","",INDEX(MCDM_Grades!$F$2:$F$178,MATCH($A12,MCDM_Grades!$A$2:$A$178,0))),"") | DZ12: =IFERROR(IF(INDEX(MCDM_Grades!$G$2:$G$178,MATCH($A12,MCDM_Grades!$A$2:$A$178,0))="","",INDEX(MCDM_Grades!$G$2:$G$178,MATCH($A12,MCDM_Grades!$A$2:$A$178,0))),"") | EA12: =IFERROR(IF(INDEX(MCDM_Grades!$H$2:$H$178,MATCH($A12,MCDM_Grades!$A$2:$A$178,0))="","",INDEX(MCDM_Grades!$H$2:$H$178,MATCH($A12,MCDM_Grades!$A$2:$A$178,0))),"") | EB12: =IFERROR(IF(INDEX(MCDM_Grades!$I$2:$I$178,MATCH($A12,MCDM_Grades!$A$2:$A$178,0))="","",INDEX(MCDM_Grades!$I$2:$I$178,MATCH($A12,MCDM_Grades!$A$2:$A$178,0))),"") | EC12: =IFERROR(IF(INDEX(MCDM_Grades!$J$2:$J$178,MATCH($A12,MCDM_Grades!$A$2:$A$178,0))="","",INDEX(MCDM_Grades!$J$2:$J$178,MATCH($A12,MCDM_Grades!$A$2:$A$178,0))),"") | ED12: =IFERROR(IF(INDEX(MCDM_Grades!$N$2:$N$178,MATCH($A12,MCDM_Grades!$A$2:$A$178,0))="","",INDEX(MCDM_Grades!$N$2:$N$178,MATCH($A12,MCDM_Grades!$A$2:$A$178,0))),"") | EE12: =IFERROR(IF(INDEX(MCDM_Grades!$O$2:$O$178,MATCH($A12,MCDM_Grades!$A$2:$A$178,0))="","",INDEX(MCDM_Grades!$O$2:$O$178,MATCH($A12,MCDM_Grades!$A$2:$A$178,0))),"") | EF12: =IFERROR(IF(INDEX(MCDM_Grades!$P$2:$P$178,MATCH($A12,MCDM_Grades!$A$2:$A$178,0))="","",INDEX(MCDM_Grades!$P$2:$P$178,MATCH($A12,MCDM_Grades!$A$2:$A$178,0))),"") | EG12: =IFERROR(IF(INDEX(MCDM_Grades!$Q$2:$Q$178,MATCH($A12,MCDM_Grades!$A$2:$A$178,0))="","",INDEX(MCDM_Grades!$Q$2:$Q$178,MATCH($A12,MCDM_Grades!$A$2:$A$178,0))),"") | EH12: =IFERROR(IF(INDEX(MCDM_Grades!$R$2:$R$178,MATCH($A12,MCDM_Grades!$A$2:$A$178,0))="","",INDEX(MCDM_Grades!$R$2:$R$178,MATCH($A12,MCDM_Grades!$A$2:$A$178,0))),"") | EI12: =IFERROR(IF(INDEX(MCDM_Grades!$S$2:$S$178,MATCH($A12,MCDM_Grades!$A$2:$A$178,0))="","",INDEX(MCDM_Grades!$S$2:$S$178,MATCH($A12,MCDM_Grades!$A$2:$A$178,0))),"") | EJ12: =IFERROR(IF(INDEX(MCDM_Grades!$T$2:$T$178,MATCH($A12,MCDM_Grades!$A$2:$A$178,0))="","",INDEX(MCDM_Grades!$T$2:$T$178,MATCH($A12,MCDM_Grades!$A$2:$A$178,0))),"") | EK12: =IFERROR(IF(INDEX(MCDM_Grades!$U$2:$U$178,MATCH($A12,MCDM_Grades!$A$2:$A$178,0))="","",INDEX(MCDM_Grades!$U$2:$U$178,MATCH($A12,MCDM_Grades!$A$2:$A$178,0))),"") | EL12: =IFERROR(IF(INDEX(MCDM_Grades!$V$2:$V$178,MATCH($A12,MCDM_Grades!$A$2:$A$178,0))="","",INDEX(MCDM_Grades!$V$2:$V$178,MATCH($A12,MCDM_Grades!$A$2:$A$178,0))),"") | EM12: =IFERROR(IF(INDEX(MCDM_Grades!$W$2:$W$178,MATCH($A12,MCDM_Grades!$A$2:$A$178,0))="","",INDEX(MCDM_Grades!$W$2:$W$178,MATCH($A12,MCDM_Grades!$A$2:$A$178,0))),"") | EN12: =IFERROR(IF(INDEX(MCDM_Grades!$X$2:$X$178,MATCH($A12,MCDM_Grades!$A$2:$A$178,0))="","",INDEX(MCDM_Grades!$X$2:$X$178,MATCH($A12,MCDM_Grades!$A$2:$A$178,0))),"") | EO12: =IFERROR(IF(INDEX(MCDM_Grades!$Y$2:$Y$178,MATCH($A12,MCDM_Grades!$A$2:$A$178,0))="","",INDEX(MCDM_Grades!$Y$2:$Y$178,MATCH($A12,MCDM_Grades!$A$2:$A$178,0))),"") | EP12: =IFERROR(IF(INDEX(MCDM_Grades!$Z$2:$Z$178,MATCH($A12,MCDM_Grades!$A$2:$A$178,0))="","",INDEX(MCDM_Grades!$Z$2:$Z$178,MATCH($A12,MCDM_Grades!$A$2:$A$178,0))),"") | EQ12: =IFERROR(IF(INDEX(MCDM_Grades!$AA$2:$AA$178,MATCH($A12,MCDM_Grades!$A$2:$A$178,0))="","",INDEX(MCDM_Grades!$AA$2:$AA$178,MATCH($A12,MCDM_Grades!$A$2:$A$178,0))),"") | ER12: =IFERROR(IF(INDEX(MCDM_Grades!$AB$2:$AB$178,MATCH($A12,MCDM_Grades!$A$2:$A$178,0))="","",INDEX(MCDM_Grades!$AB$2:$AB$178,MATCH($A12,MCDM_Grades!$A$2:$A$178,0))),"") | ES12: =IFERROR(IF(INDEX(MCDM_Grades!$AC$2:$AC$178,MATCH($A12,MCDM_Grades!$A$2:$A$178,0))="","",INDEX(MCDM_Grades!$AC$2:$AC$178,MATCH($A12,MCDM_Grades!$A$2:$A$178,0))),"") | ET12: =IFERROR(IF(INDEX(MCDM_Grades!$AD$2:$AD$178,MATCH($A12,MCDM_Grades!$A$2:$A$178,0))="","",INDEX(MCDM_Grades!$AD$2:$AD$178,MATCH($A12,MCDM_Grades!$A$2:$A$178,0))),"") | EU12: =IFERROR(IF(INDEX(MCDM_Grades!$AE$2:$AE$178,MATCH($A12,MCDM_Grades!$A$2:$A$178,0))="","",INDEX(MCDM_Grades!$AE$2:$AE$178,MATCH($A12,MCDM_Grades!$A$2:$A$178,0))),"") | EV12: =IFERROR(IF(INDEX(MCDM_Grades!$K$2:$K$178,MATCH($A12,MCDM_Grades!$A$2:$A$178,0))="","",INDEX(MCDM_Grades!$K$2:$K$178,MATCH($A12,MCDM_Grades!$A$2:$A$178,0))),"") | EW12: =IFERROR(IF(INDEX(MCDM_Grades!$L$2:$L$178,MATCH($A12,MCDM_Grades!$A$2:$A$178,0))="","",INDEX(MCDM_Grades!$L$2:$L$178,MATCH($A12,MCDM_Grades!$A$2:$A$178,0))),"") | EX12: =IFERROR(IF(INDEX(MCDM_Grades!$M$2:$M$178,MATCH($A12,MCDM_Grades!$A$2:$A$178,0))="","",INDEX(MCDM_Grades!$M$2:$M$178,MATCH($A12,MCDM_Grades!$A$2:$A$178,0))),"") | EY12: =IFERROR(IF(INDEX(MCDM_Grades!$AR$2:$AR$178,MATCH($A12,MCDM_Grades!$A$2:$A$178,0))="","",INDEX(MCDM_Grades!$AR$2:$AR$178,MATCH($A12,MCDM_Grades!$A$2:$A$178,0))),"") | EZ12: =IFERROR(IF(INDEX(MCDM_Grades!$AS$2:$AS$178,MATCH($A12,MCDM_Grades!$A$2:$A$178,0))="","",INDEX(MCDM_Grades!$AS$2:$AS$178,MATCH($A12,MCDM_Grades!$A$2:$A$178,0))),"") | FA12: =IFERROR(IF(INDEX(MCDM_Grades!$AT$2:$AT$178,MATCH($A12,MCDM_Grades!$A$2:$A$178,0))="","",INDEX(MCDM_Grades!$AT$2:$AT$178,MATCH($A12,MCDM_Grades!$A$2:$A$178,0))),"") | FB12: =IFERROR(IF(INDEX(MCDM_Grades!$AU$2:$AU$178,MATCH($A12,MCDM_Grades!$A$2:$A$178,0))="","",INDEX(MCDM_Grades!$AU$2:$AU$178,MATCH($A12,MCDM_Grades!$A$2:$A$178,0))),"") | FC12: Nadir / top-down | FD12: Partial | FE12: No | FF12: Frontal close-ups of walls/tiles (masonry, ceramic, concrete) for the non-road sub-datasets | FG12: Compiled: handheld smartphone / close-up cameras and survey-vehicle line-scan cameras from parent datasets | FH12: CFD dataset is composed of images reflecting urban road surface conditions in Beijing, China. | CrackTree200, Volker and DeepCrack contain images with manually annotated cracks collected from pavements and buildings. | Crack500 was collected at the Temple University campus using a smartphone | FI12: Publication | FJ12: https://arxiv.org/abs/2208.13054 | FK12: High | FL12: Verified - agreed | FM12: Workbook: Compiled, 'Multiple source datasets', combines road and non-road crack sources. The README (fetched) gives only the abstract quoted and the Dataverse link; the arXiv PDF (2208.13054) was fetched but did not convert to text. From the CrackSeg9k paper (Kulkarni et al., ECCV 2022 Workshops, 10.1007/978-3-031-25082-8_12) the ~9,255 images come from Crack500, GAPs384, CFD, CrackTree200, DeepCrack, Rissbilder, Volker, Eugen Mueller, Masonry and Ceramic. All pavement parents are top-down (handheld phone or survey-vehicle cameras); the masonry/ceramic/concrete-wall parents are surface-perpendicular close-ups of walls and tiles, not pavement, and none are forward-facing driving views. Hence Nadir / top-down with top_down Partial (only the road subsets are pavement nadir imagery). Sub-dataset list from prior knowledge of the paper, so Medium. | Second review replaced the evidence (was: Parent / source dataset). | Second review: Extracted from the CrackSeg9k paper PDF (Sec. 3.1): the sub-datasets are Masonry, CFD, CrackTree200, Volker, DeepCrack, Ceramic, Rissbilder, Crack500 and GAPS384, all surface close-ups of pavements or walls/facades with no street-level driving views. Nadir with top_down Partial (road subsets only) a
A13: DS-012 | B13: CrackTrans (pavement crack dataset with complex backgrounds) | C13: NA | D13: v1 | E13: Independent Dataset | F13: NA (single source record) | G13: Single source record; no matching record found in any other file after cross-file and cross-platform comparison. | H13: Claude | I13: GitHub | J13: N | K13: NA (single platform) | L13: https://github.com/JZhongUTK/Pavement-crack-dataset | M13: https://github.com/JZhongUTK/Pavement-crack-dataset | N13: NA | O13: NA | P13: NA | Q13: NA | R13: NA | S13: NA | T13: NR | U13: Y | V13: https://ieeexplore.ieee.org/document/10557475;10.1016/j.autcon.2022.104436;10.1016/j.engappai.2022.105808 | W13: 10.1016/j.autcon.2022.104436; 10.1016/j.engappai.2022.105808 | X13: https://ieeexplore.ieee.org/document/10557475 | Y13: NR | Z13: Y | AA13: Reported in source record (relationship not classified) | AB13: Images/frames as reported | AC13: 455 | AD13: NR | AE13: NR | AF13: 455 | AG13: NR | AH13: NR | AI13: NR | AJ13: NR | AK13: NR | AL13: NR | AM13: NR | AN13: NR | AO13: NR | AP13: NR | AQ13: NR | AR13: NR | AS13: Road environment: Pavements incl. shadow, wet, night, and grooved surfaces | AT13: NR | AU13: Smartphone | AV13: NR | AW13: NR | AX13: NR | AY13: Y | AZ13: NR | BA13: NR | BB13: N | BC13: NR | BD13: NR | BE13: Includes wet-surface scenes | BF13: Includes night and shadow scenes | BG13: NR | BH13: Pavement cracks (undifferentiated crack class) | BI13: NR | BJ13: Pixel-level crack ground truth | BK13: NR | BL13: Semantic segmentation | BM13: Semantic segmentation | BN13: Ground-truth masks | BO13: mask | BP13: NR | BQ13: NR | BR13: Y | BS13: NR | BT13: NR | BU13: NR | BV13: N | BW13: N | BX13: N | BY13: NR (weakly supervised pipeline described in paper) | BZ13: NR | CA13: NR | CB13: NR | CC13: Semantic segmentation;Data augmentation research | CD13: NR | CE13: NR | CF13: Reported on the source record/data card or associated publication (see Evidence_Locator) | CG13: NR | CH13: NR | CI13: Include-Primary | CJ13: Direct_Download | CK13: NR ('released for public use' per README) | CL13: N | CM13: Direct_Download | CN13: NR | CO13: NR | CP13: N | CQ13: Small dataset (455 images); collection location not stated; Google Drive hosting (link liveness not independently re-tested) | CR13: Original | CS13: N | CT13: N | CU13: N | CV13: NA | CW13: NA | CX13: Claude_Github_001.xlsx | CY13: Claude_Github_001:GH-DS-011 | CZ13: N | DA13: NA | DB13: None | DC13: None | DD13: None | DE13: None | DF13: N | DG13: Single source record; no reconciliation required. | DH13: GitHub README (description, download, citations), https://github.com/JZhongUTK/Pavement-crack-dataset (accessed 2026-08-06) | DI13: Moderate | DJ13: Low | DK13: Use source record as cited. | DL13: 4 | DM13: 4 | DN13: 3 | DO13: 2 | DP13: 3 | DQ13: 1 | DR13: 0 | DS13: 55 | DT13: Reviewed (source MCDM_Scoring, averaged across batches) | DU13: 1 of 1 | DV13: =IFERROR(IF(INDEX(MCDM_Grades!$C$2:$C$178,MATCH($A13,MCDM_Grades!$A$2:$A$178,0))="","",INDEX(MCDM_Grades!$C$2:$C$178,MATCH($A13,MCDM_Grades!$A$2:$A$178,0))),"") | DW13: =IFERROR(IF(INDEX(MCDM_Grades!$D$2:$D$178,MATCH($A13,MCDM_Grades!$A$2:$A$178,0))="","",INDEX(MCDM_Grades!$D$2:$D$178,MATCH($A13,MCDM_Grades!$A$2:$A$178,0))),"") | DX13: =IFERROR(IF(INDEX(MCDM_Grades!$E$2:$E$178,MATCH($A13,MCDM_Grades!$A$2:$A$178,0))="","",INDEX(MCDM_Grades!$E$2:$E$178,MATCH($A13,MCDM_Grades!$A$2:$A$178,0))),"") | DY13: =IFERROR(IF(INDEX(MCDM_Grades!$F$2:$F$178,MATCH($A13,MCDM_Grades!$A$2:$A$178,0))="","",INDEX(MCDM_Grades!$F$2:$F$178,MATCH($A13,MCDM_Grades!$A$2:$A$178,0))),"") | DZ13: =IFERROR(IF(INDEX(MCDM_Grades!$G$2:$G$178,MATCH($A13,MCDM_Grades!$A$2:$A$178,0))="","",INDEX(MCDM_Grades!$G$2:$G$178,MATCH($A13,MCDM_Grades!$A$2:$A$178,0))),"") | EA13: =IFERROR(IF(INDEX(MCDM_Grades!$H$2:$H$178,MATCH($A13,MCDM_Grades!$A$2:$A$178,0))="","",INDEX(MCDM_Grades!$H$2:$H$178,MATCH($A13,MCDM_Grades!$A$2:$A$178,0))),"") | EB13: =IFERROR(IF(INDEX(MCDM_Grades!$I$2:$I$178,MATCH($A13,MCDM_Grades!$A$2:$A$178,0))="","",INDEX(MCDM_Grades!$I$2:$I$178,MATCH($A13,MCDM_Grades!$A$2:$A$178,0))),"") | EC13: =IFERROR(IF(INDEX(MCDM_Grades!$J$2:$J$178,MATCH($A13,MCDM_Grades!$A$2:$A$178,0))="","",INDEX(MCDM_Grades!$J$2:$J$178,MATCH($A13,MCDM_Grades!$A$2:$A$178,0))),"") | ED13: =IFERROR(IF(INDEX(MCDM_Grades!$N$2:$N$178,MATCH($A13,MCDM_Grades!$A$2:$A$178,0))="","",INDEX(MCDM_Grades!$N$2:$N$178,MATCH($A13,MCDM_Grades!$A$2:$A$178,0))),"") | EE13: =IFERROR(IF(INDEX(MCDM_Grades!$O$2:$O$178,MATCH($A13,MCDM_Grades!$A$2:$A$178,0))="","",INDEX(MCDM_Grades!$O$2:$O$178,MATCH($A13,MCDM_Grades!$A$2:$A$178,0))),"") | EF13: =IFERROR(IF(INDEX(MCDM_Grades!$P$2:$P$178,MATCH($A13,MCDM_Grades!$A$2:$A$178,0))="","",INDEX(MCDM_Grades!$P$2:$P$178,MATCH($A13,MCDM_Grades!$A$2:$A$178,0))),"") | EG13: =IFERROR(IF(INDEX(MCDM_Grades!$Q$2:$Q$178,MATCH($A13,MCDM_Grades!$A$2:$A$178,0))="","",INDEX(MCDM_Grades!$Q$2:$Q$178,MATCH($A13,MCDM_Grades!$A$2:$A$178,0))),"") | EH13: =IFERROR(IF(INDEX(MCDM_Grades!$R$2:$R$178,MATCH($A13,MCDM_Grades!$A$2:$A$178,0))="","",INDEX(MCDM_Grades!$R$2:$R$178,MATCH($A13,MCDM_Grades!$A$2:$A$178,0))),"") | EI13: =IFERROR(IF(INDEX(MCDM_Grades!$S$2:$S$178,MATCH($A13,MCDM_Grades!$A$2:$A$178,0))="","",INDEX(MCDM_Grades!$S$2:$S$178,MATCH($A13,MCDM_Grades!$A$2:$A$178,0))),"") | EJ13: =IFERROR(IF(INDEX(MCDM_Grades!$T$2:$T$178,MATCH($A13,MCDM_Grades!$A$2:$A$178,0))="","",INDEX(MCDM_Grades!$T$2:$T$178,MATCH($A13,MCDM_Grades!$A$2:$A$178,0))),"") | EK13: =IFERROR(IF(INDEX(MCDM_Grades!$U$2:$U$178,MATCH($A13,MCDM_Grades!$A$2:$A$178,0))="","",INDEX(MCDM_Grades!$U$2:$U$178,MATCH($A13,MCDM_Grades!$A$2:$A$178,0))),"") | EL13: =IFERROR(IF(INDEX(MCDM_Grades!$V$2:$V$178,MATCH($A13,MCDM_Grades!$A$2:$A$178,0))="","",INDEX(MCDM_Grades!$V$2:$V$178,MATCH($A13,MCDM_Grades!$A$2:$A$178,0))),"") | EM13: =IFERROR(IF(INDEX(MCDM_Grades!$W$2:$W$178,MATCH($A13,MCDM_Grades!$A$2:$A$178,0))="","",INDEX(MCDM_Grades!$W$2:$W$178,MATCH($A13,MCDM_Grades!$A$2:$A$178,0))),"") | EN13: =IFERROR(IF(INDEX(MCDM_Grades!$X$2:$X$178,MATCH($A13,MCDM_Grades!$A$2:$A$178,0))="","",INDEX(MCDM_Grades!$X$2:$X$178,MATCH($A13,MCDM_Grades!$A$2:$A$178,0))),"") | EO13: =IFERROR(IF(INDEX(MCDM_Grades!$Y$2:$Y$178,MATCH($A13,MCDM_Grades!$A$2:$A$178,0))="","",INDEX(MCDM_Grades!$Y$2:$Y$178,MATCH($A13,MCDM_Grades!$A$2:$A$178,0))),"") | EP13: =IFERROR(IF(INDEX(MCDM_Grades!$Z$2:$Z$178,MATCH($A13,MCDM_Grades!$A$2:$A$178,0))="","",INDEX(MCDM_Grades!$Z$2:$Z$178,MATCH($A13,MCDM_Grades!$A$2:$A$178,0))),"") | EQ13: =IFERROR(IF(INDEX(MCDM_Grades!$AA$2:$AA$178,MATCH($A13,MCDM_Grades!$A$2:$A$178,0))="","",INDEX(MCDM_Grades!$AA$2:$AA$178,MATCH($A13,MCDM_Grades!$A$2:$A$178,0))),"") | ER13: =IFERROR(IF(INDEX(MCDM_Grades!$AB$2:$AB$178,MATCH($A13,MCDM_Grades!$A$2:$A$178,0))="","",INDEX(MCDM_Grades!$AB$2:$AB$178,MATCH($A13,MCDM_Grades!$A$2:$A$178,0))),"") | ES13: =IFERROR(IF(INDEX(MCDM_Grades!$AC$2:$AC$178,MATCH($A13,MCDM_Grades!$A$2:$A$178,0))="","",INDEX(MCDM_Grades!$AC$2:$AC$178,MATCH($A13,MCDM_Grades!$A$2:$A$178,0))),"") | ET13: =IFERROR(IF(INDEX(MCDM_Grades!$AD$2:$AD$178,MATCH($A13,MCDM_Grades!$A$2:$A$178,0))="","",INDEX(MCDM_Grades!$AD$2:$AD$178,MATCH($A13,MCDM_Grades!$A$2:$A$178,0))),"") | EU13: =IFERROR(IF(INDEX(MCDM_Grades!$AE$2:$AE$178,MATCH($A13,MCDM_Grades!$A$2:$A$178,0))="","",INDEX(MCDM_Grades!$AE$2:$AE$178,MATCH($A13,MCDM_Grades!$A$2:$A$178,0))),"") | EV13: =IFERROR(IF(INDEX(MCDM_Grades!$K$2:$K$178,MATCH($A13,MCDM_Grades!$A$2:$A$178,0))="","",INDEX(MCDM_Grades!$K$2:$K$178,MATCH($A13,MCDM_Grades!$A$2:$A$178,0))),"") | EW13: =IFERROR(IF(INDEX(MCDM_Grades!$L$2:$L$178,MATCH($A13,MCDM_Grades!$A$2:$A$178,0))="","",INDEX(MCDM_Grades!$L$2:$L$178,MATCH($A13,MCDM_Grades!$A$2:$A$178,0))),"") | EX13: =IFERROR(IF(INDEX(MCDM_Grades!$M$2:$M$178,MATCH($A13,MCDM_Grades!$A$2:$A$178,0))="","",INDEX(MCDM_Grades!$M$2:$M$178,MATCH($A13,MCDM_Grades!$A$2:$A$178,0))),"") | EY13: =IFERROR(IF(INDEX(MCDM_Grades!$AR$2:$AR$178,MATCH($A13,MCDM_Grades!$A$2:$A$178,0))="","",INDEX(MCDM_Grades!$AR$2:$AR$178,MATCH($A13,MCDM_Grades!$A$2:$A$178,0))),"") | EZ13: =IFERROR(IF(INDEX(MCDM_Grades!$AS$2:$AS$178,MATCH($A13,MCDM_Grades!$A$2:$A$178,0))="","",INDEX(MCDM_Grades!$AS$2:$AS$178,MATCH($A13,MCDM_Grades!$A$2:$A$178,0))),"") | FA13: =IFERROR(IF(INDEX(MCDM_Grades!$AT$2:$AT$178,MATCH($A13,MCDM_Grades!$A$2:$A$178,0))="","",INDEX(MCDM_Grades!$AT$2:$AT$178,MATCH($A13,MCDM_Grades!$A$2:$A$178,0))),"") | FB13: =IFERROR(IF(INDEX(MCDM_Grades!$AU$2:$AU$178,MATCH($A13,MCDM_Grades!$A$2:$A$178,0))="","",INDEX(MCDM_Grades!$AU$2:$AU$178,MATCH($A13,MCDM_Grades!$A$2:$A$178,0))),"") | FC13: Nadir / top-down | FD13: Yes | FE13: No | FG13: Handheld smartphone pointed at the surface | FH13: The CrackTrans was collected via smartphone including shadow, wet, night, and grooved backgrounds for pavement crack detection. There are total 455 pavement crack images with GT for training and testing. | FI13: Dataset page / README | FJ13: https://github.com/JZhongUTK/Pavement-crack-dataset | FK13: High | FL13: Not independently verified | FM13: Workbook: 'Smartphone', Smartphone_Data Y, Camera_Position NR. The README quote gives the device; the README sample figure (GitHub asset 9cf13466..., 1332x698, fetched) settles the angle: four full-frame pavement close-ups (shadowed asphalt, wet asphalt, night asphalt, grooved cement concrete) with their crack masks, no horizon or perspective, i.e. the phone was pointed straight down at the surface. Associated papers: Zhong et al., IEEE T-ITS 2024 (Pavement Crack Translator, ieeexplore 10557475), Autom. Constr. 2022 (10.1016/j.autcon.2022.104436), Eng. Appl. AI 2023 (10.1016/j.engappai.2022.105808).
A14: DS-013 | B14: CrackTree260 | C14: NA | D14: CrackTree260 | E14: Independent Dataset | F14: NA (single source record) | G14: Single source record; no matching record found in any other file after cross-file and cross-platform comparison. | H14: GitHub_Test_Batch (tool UNK) | I14: GitHub | J14: N | K14: NA (single platform) | L14: https://github.com/qinnzou/DeepCrack | M14: https://github.com/qinnzou/DeepCrack | N14: NA | O14: NA | P14: NA | Q14: NA | R14: NA | S14: NA | T14: NR | U14: Y | V14: https://github.com/qinnzou/DeepCrack | W14: NR | X14: https://github.com/qinnzou/DeepCrack | Y14: NR | Z14: NR | AA14: Reported in source record (relationship not classified) | AB14: Images/frames as reported | AC14: 260 | AD14: NR | AE14: NR | AF14: 260 | AG14: NR | AH14: NR | AI14: NR | AJ14: NR | AK14: NR | AL14: NR | AM14: NR | AN14: NR | AO14: NR | AP14: NR | AQ14: NR | AR14: NR | AS14: Road environment: Road pavement | AT14: NR | AU14: Visible-light area-array camera | AV14: NR | AW14: Visible-light area-array camera | AX14: NR | AY14: NR | AZ14: NR | BA14: NR | BB14: NR | BC14: NR | BD14: NR | BE14: NR | BF14: NR | BG14: NR | BH14: pavement crack | BI14: NR | BJ14: crack pixel mask | BK14: NR | BL14: Semantic segmentation | BM14: Semantic segmentation | BN14: Image-mask pairs | BO14: mask | BP14: NR | BQ14: NR | BR14: Y | BS14: NR | BT14: NR | BU14: NR | BV14: NR | BW14: NR | BX14: NR | BY14: Manual pixel annotation | BZ14: NR | CA14: NR | CB14: NR | CC14: semantic segmentation; crack detection | CD14: NR | CE14: NR | CF14: Reported on the source record/data card or associated publication (see Evidence_Locator) | CG14: NR | CH14: NR | CI14: Include-Primary | CJ14: Direct_Download | CK14: NR | CL14: N | CM14: Direct_Download | CN14: NR | CO14: NR | CP14: N | CQ14: Small, crack-only dataset; location, license, and detailed environmental metadata are not reported. | CR14: Original | CS14: N | CT14: N | CU14: N | CV14: NA | CW14: NA | CX14: Github_Github_Test.xlsx | CY14: Github_Github_Test:GITHUB-018 | CZ14: NA | DA14: NA | DB14: None | DC14: None | DD14: None | DE14: None | DF14: N | DG14: Single source record; no reconciliation required. | DH14: https://github.com/qinnzou/DeepCrack; README dataset table and download links; accessed 2026-08-01 | DI14: High | DJ14: Low | DK14: Use source record as cited. | DL14: 4 | DM14: 4 | DN14: 4 | DO14: 2 | DP14: 2 | DQ14: 2 | DR14: 0 | DS14: 58 | DT14: Reviewed (source MCDM_Scoring, averaged across batches) | DU14: 1 of 1 | DV14: =IFERROR(IF(INDEX(MCDM_Grades!$C$2:$C$178,MATCH($A14,MCDM_Grades!$A$2:$A$178,0))="","",INDEX(MCDM_Grades!$C$2:$C$178,MATCH($A14,MCDM_Grades!$A$2:$A$178,0))),"") | DW14: =IFERROR(IF(INDEX(MCDM_Grades!$D$2:$D$178,MATCH($A14,MCDM_Grades!$A$2:$A$178,0))="","",INDEX(MCDM_Grades!$D$2:$D$178,MATCH($A14,MCDM_Grades!$A$2:$A$178,0))),"") | DX14: =IFERROR(IF(INDEX(MCDM_Grades!$E$2:$E$178,MATCH($A14,MCDM_Grades!$A$2:$A$178,0))="","",INDEX(MCDM_Grades!$E$2:$E$178,MATCH($A14,MCDM_Grades!$A$2:$A$178,0))),"") | DY14: =IFERROR(IF(INDEX(MCDM_Grades!$F$2:$F$178,MATCH($A14,MCDM_Grades!$A$2:$A$178,0))="","",INDEX(MCDM_Grades!$F$2:$F$178,MATCH($A14,MCDM_Grades!$A$2:$A$178,0))),"") | DZ14: =IFERROR(IF(INDEX(MCDM_Grades!$G$2:$G$178,MATCH($A14,MCDM_Grades!$A$2:$A$178,0))="","",INDEX(MCDM_Grades!$G$2:$G$178,MATCH($A14,MCDM_Grades!$A$2:$A$178,0))),"") | EA14: =IFERROR(IF(INDEX(MCDM_Grades!$H$2:$H$178,MATCH($A14,MCDM_Grades!$A$2:$A$178,0))="","",INDEX(MCDM_Grades!$H$2:$H$178,MATCH($A14,MCDM_Grades!$A$2:$A$178,0))),"") | EB14: =IFERROR(IF(INDEX(MCDM_Grades!$I$2:$I$178,MATCH($A14,MCDM_Grades!$A$2:$A$178,0))="","",INDEX(MCDM_Grades!$I$2:$I$178,MATCH($A14,MCDM_Grades!$A$2:$A$178,0))),"") | EC14: =IFERROR(IF(INDEX(MCDM_Grades!$J$2:$J$178,MATCH($A14,MCDM_Grades!$A$2:$A$178,0))="","",INDEX(MCDM_Grades!$J$2:$J$178,MATCH($A14,MCDM_Grades!$A$2:$A$178,0))),"") | ED14: =IFERROR(IF(INDEX(MCDM_Grades!$N$2:$N$178,MATCH($A14,MCDM_Grades!$A$2:$A$178,0))="","",INDEX(MCDM_Grades!$N$2:$N$178,MATCH($A14,MCDM_Grades!$A$2:$A$178,0))),"") | EE14: =IFERROR(IF(INDEX(MCDM_Grades!$O$2:$O$178,MATCH($A14,MCDM_Grades!$A$2:$A$178,0))="","",INDEX(MCDM_Grades!$O$2:$O$178,MATCH($A14,MCDM_Grades!$A$2:$A$178,0))),"") | EF14: =IFERROR(IF(INDEX(MCDM_Grades!$P$2:$P$178,MATCH($A14,MCDM_Grades!$A$2:$A$178,0))="","",INDEX(MCDM_Grades!$P$2:$P$178,MATCH($A14,MCDM_Grades!$A$2:$A$178,0))),"") | EG14: =IFERROR(IF(INDEX(MCDM_Grades!$Q$2:$Q$178,MATCH($A14,MCDM_Grades!$A$2:$A$178,0))="","",INDEX(MCDM_Grades!$Q$2:$Q$178,MATCH($A14,MCDM_Grades!$A$2:$A$178,0))),"") | EH14: =IFERROR(IF(INDEX(MCDM_Grades!$R$2:$R$178,MATCH($A14,MCDM_Grades!$A$2:$A$178,0))="","",INDEX(MCDM_Grades!$R$2:$R$178,MATCH($A14,MCDM_Grades!$A$2:$A$178,0))),"") | EI14: =IFERROR(IF(INDEX(MCDM_Grades!$S$2:$S$178,MATCH($A14,MCDM_Grades!$A$2:$A$178,0))="","",INDEX(MCDM_Grades!$S$2:$S$178,MATCH($A14,MCDM_Grades!$A$2:$A$178,0))),"") | EJ14: =IFERROR(IF(INDEX(MCDM_Grades!$T$2:$T$178,MATCH($A14,MCDM_Grades!$A$2:$A$178,0))="","",INDEX(MCDM_Grades!$T$2:$T$178,MATCH($A14,MCDM_Grades!$A$2:$A$178,0))),"") | EK14: =IFERROR(IF(INDEX(MCDM_Grades!$U$2:$U$178,MATCH($A14,MCDM_Grades!$A$2:$A$178,0))="","",INDEX(MCDM_Grades!$U$2:$U$178,MATCH($A14,MCDM_Grades!$A$2:$A$178,0))),"") | EL14: =IFERROR(IF(INDEX(MCDM_Grades!$V$2:$V$178,MATCH($A14,MCDM_Grades!$A$2:$A$178,0))="","",INDEX(MCDM_Grades!$V$2:$V$178,MATCH($A14,MCDM_Grades!$A$2:$A$178,0))),"") | EM14: =IFERROR(IF(INDEX(MCDM_Grades!$W$2:$W$178,MATCH($A14,MCDM_Grades!$A$2:$A$178,0))="","",INDEX(MCDM_Grades!$W$2:$W$178,MATCH($A14,MCDM_Grades!$A$2:$A$178,0))),"") | EN14: =IFERROR(IF(INDEX(MCDM_Grades!$X$2:$X$178,MATCH($A14,MCDM_Grades!$A$2:$A$178,0))="","",INDEX(MCDM_Grades!$X$2:$X$178,MATCH($A14,MCDM_Grades!$A$2:$A$178,0))),"") | EO14: =IFERROR(IF(INDEX(MCDM_Grades!$Y$2:$Y$178,MATCH($A14,MCDM_Grades!$A$2:$A$178,0))="","",INDEX(MCDM_Grades!$Y$2:$Y$178,MATCH($A14,MCDM_Grades!$A$2:$A$178,0))),"") | EP14: =IFERROR(IF(INDEX(MCDM_Grades!$Z$2:$Z$178,MATCH($A14,MCDM_Grades!$A$2:$A$178,0))="","",INDEX(MCDM_Grades!$Z$2:$Z$178,MATCH($A14,MCDM_Grades!$A$2:$A$178,0))),"") | EQ14: =IFERROR(IF(INDEX(MCDM_Grades!$AA$2:$AA$178,MATCH($A14,MCDM_Grades!$A$2:$A$178,0))="","",INDEX(MCDM_Grades!$AA$2:$AA$178,MATCH($A14,MCDM_Grades!$A$2:$A$178,0))),"") | ER14: =IFERROR(IF(INDEX(MCDM_Grades!$AB$2:$AB$178,MATCH($A14,MCDM_Grades!$A$2:$A$178,0))="","",INDEX(MCDM_Grades!$AB$2:$AB$178,MATCH($A14,MCDM_Grades!$A$2:$A$178,0))),"") | ES14: =IFERROR(IF(INDEX(MCDM_Grades!$AC$2:$AC$178,MATCH($A14,MCDM_Grades!$A$2:$A$178,0))="","",INDEX(MCDM_Grades!$AC$2:$AC$178,MATCH($A14,MCDM_Grades!$A$2:$A$178,0))),"") | ET14: =IFERROR(IF(INDEX(MCDM_Grades!$AD$2:$AD$178,MATCH($A14,MCDM_Grades!$A$2:$A$178,0))="","",INDEX(MCDM_Grades!$AD$2:$AD$178,MATCH($A14,MCDM_Grades!$A$2:$A$178,0))),"") | EU14: =IFERROR(IF(INDEX(MCDM_Grades!$AE$2:$AE$178,MATCH($A14,MCDM_Grades!$A$2:$A$178,0))="","",INDEX(MCDM_Grades!$AE$2:$AE$178,MATCH($A14,MCDM_Grades!$A$2:$A$178,0))),"") | EV14: =IFERROR(IF(INDEX(MCDM_Grades!$K$2:$K$178,MATCH($A14,MCDM_Grades!$A$2:$A$178,0))="","",INDEX(MCDM_Grades!$K$2:$K$178,MATCH($A14,MCDM_Grades!$A$2:$A$178,0))),"") | EW14: =IFERROR(IF(INDEX(MCDM_Grades!$L$2:$L$178,MATCH($A14,MCDM_Grades!$A$2:$A$178,0))="","",INDEX(MCDM_Grades!$L$2:$L$178,MATCH($A14,MCDM_Grades!$A$2:$A$178,0))),"") | EX14: =IFERROR(IF(INDEX(MCDM_Grades!$M$2:$M$178,MATCH($A14,MCDM_Grades!$A$2:$A$178,0))="","",INDEX(MCDM_Grades!$M$2:$M$178,MATCH($A14,MCDM_Grades!$A$2:$A$178,0))),"") | EY14: =IFERROR(IF(INDEX(MCDM_Grades!$AR$2:$AR$178,MATCH($A14,MCDM_Grades!$A$2:$A$178,0))="","",INDEX(MCDM_Grades!$AR$2:$AR$178,MATCH($A14,MCDM_Grades!$A$2:$A$178,0))),"") | EZ14: =IFERROR(IF(INDEX(MCDM_Grades!$AS$2:$AS$178,MATCH($A14,MCDM_Grades!$A$2:$A$178,0))="","",INDEX(MCDM_Grades!$AS$2:$AS$178,MATCH($A14,MCDM_Grades!$A$2:$A$178,0))),"") | FA14: =IFERROR(IF(INDEX(MCDM_Grades!$AT$2:$AT$178,MATCH($A14,MCDM_Grades!$A$2:$A$178,0))="","",INDEX(MCDM_Grades!$AT$2:$AT$178,MATCH($A14,MCDM_Grades!$A$2:$A$178,0))),"") | FB14: =IFERROR(IF(INDEX(MCDM_Grades!$AU$2:$AU$178,MATCH($A14,MCDM_Grades!$A$2:$A$178,0))="","",INDEX(MCDM_Grades!$AU$2:$AU$178,MATCH($A14,MCDM_Grades!$A$2:$A$178,0))),"") | FC14: Nadir / top-down | FD14: Yes | FE14: No | FG14: Visible-light area-array camera imaging the pavement surface (mount not reported) | FH14: These pavement images are captured by an area-array camera under visible-light illumination. | FI14: Dataset page / README | FJ14: https://github.com/qinnzou/DeepCrack | FK14: Medium | FL14: Not independently verified | FM14: README (qinnzou/DeepCrack) describes pavement-surface images from an area-array camera but does not state the angle explicitly; label also rests on the well-known CrackTree imagery (Zou et al. 2012 PRL; Zou et al. 2019 IEEE TIP DeepCrack), which is top-down pavement texture with no forward/street views. Workbook acquisition columns match the README.
A15: DS-014 | B15: CRKWH100 | C15: NA | D15: CRKWH100 | E15: Independent Dataset | F15: NA (single source record) | G15: Single source record; no matching record found in any other file after cross-file and cross-platform comparison. | H15: GitHub_Test_Batch (tool UNK) | I15: GitHub | J15: N | K15: NA (single platform) | L15: https://github.com/qinnzou/DeepCrack | M15: https://github.com/qinnzou/DeepCrack | N15: NA | O15: NA | P15: NA | Q15: NA | R15: NA | S15: NA | T15: NR | U15: Y | V15: https://github.com/qinnzou/DeepCrack | W15: NR | X15: https://github.com/qinnzou/DeepCrack | Y15: NR | Z15: NR | AA15: Reported in source record (relationship not classified) | AB15: Images/frames as reported | AC15: 100 | AD15: NR | AE15: NR | AF15: 100 | AG15: NR | AH15: NR | AI15: NR | AJ15: NR | AK15: NR | AL15: NR | AM15: NR | AN15: NR | AO15: NR | AP15: NR | AQ15: NR | AR15: NR | AS15: Road environment: Road pavement | AT15: NR | AU15: Visible-light line-array camera | AV15: NR | AW15: Visible-light line-array camera | AX15: NR | AY15: NR | AZ15: NR | BA15: NR | BB15: NR | BC15: NR | BD15: NR | BE15: NR | BF15: NR | BG15: NR | BH15: pavement crack | BI15: NR | BJ15: crack pixel mask | BK15: NR | BL15: Semantic segmentation | BM15: Semantic segmentation | BN15: Image-mask pairs | BO15: mask | BP15: NR | BQ15: NR | BR15: Y | BS15: NR | BT15: NR | BU15: NR | BV15: NR | BW15: NR | BX15: NR | BY15: Manual pixel annotation | BZ15: NR | CA15: NR | CB15: NR | CC15: semantic segmentation; crack detection | CD15: NR | CE15: NR | CF15: Reported on the source record/data card or associated publication (see Evidence_Locator) | CG15: NR | CH15: NR | CI15: Include-Primary | CJ15: Direct_Download | CK15: NR | CL15: N | CM15: Direct_Download | CN15: NR | CO15: NR | CP15: N | CQ15: Very small crack-only dataset; 1 mm ground sampling distance is reported, but pixel resolution, navigation, location, license, and environmental metadata are not reported. | CR15: Original | CS15: N | CT15: N | CU15: N | CV15: NA | CW15: NA | CX15: Github_Github_Test.xlsx | CY15: Github_Github_Test:GITHUB-019 | CZ15: NA | DA15: NA | DB15: None | DC15: None | DD15: None | DE15: None | DF15: N | DG15: Single source record; no reconciliation required. | DH15: https://github.com/qinnzou/DeepCrack; README dataset table and download links; accessed 2026-08-01 | DI15: High | DJ15: Low | DK15: Use source record as cited. | DL15: 4 | DM15: 4 | DN15: 4 | DO15: 1 | DP15: 2 | DQ15: 3 | DR15: 0 | DS15: 57 | DT15: Reviewed (source MCDM_Scoring, averaged across batches) | DU15: 1 of 1 | DV15: =IFERROR(IF(INDEX(MCDM_Grades!$C$2:$C$178,MATCH($A15,MCDM_Grades!$A$2:$A$178,0))="","",INDEX(MCDM_Grades!$C$2:$C$178,MATCH($A15,MCDM_Grades!$A$2:$A$178,0))),"") | DW15: =IFERROR(IF(INDEX(MCDM_Grades!$D$2:$D$178,MATCH($A15,MCDM_Grades!$A$2:$A$178,0))="","",INDEX(MCDM_Grades!$D$2:$D$178,MATCH($A15,MCDM_Grades!$A$2:$A$178,0))),"") | DX15: =IFERROR(IF(INDEX(MCDM_Grades!$E$2:$E$178,MATCH($A15,MCDM_Grades!$A$2:$A$178,0))="","",INDEX(MCDM_Grades!$E$2:$E$178,MATCH($A15,MCDM_Grades!$A$2:$A$178,0))),"") | DY15: =IFERROR(IF(INDEX(MCDM_Grades!$F$2:$F$178,MATCH($A15,MCDM_Grades!$A$2:$A$178,0))="","",INDEX(MCDM_Grades!$F$2:$F$178,MATCH($A15,MCDM_Grades!$A$2:$A$178,0))),"") | DZ15: =IFERROR(IF(INDEX(MCDM_Grades!$G$2:$G$178,MATCH($A15,MCDM_Grades!$A$2:$A$178,0))="","",INDEX(MCDM_Grades!$G$2:$G$178,MATCH($A15,MCDM_Grades!$A$2:$A$178,0))),"") | EA15: =IFERROR(IF(INDEX(MCDM_Grades!$H$2:$H$178,MATCH($A15,MCDM_Grades!$A$2:$A$178,0))="","",INDEX(MCDM_Grades!$H$2:$H$178,MATCH($A15,MCDM_Grades!$A$2:$A$178,0))),"") | EB15: =IFERROR(IF(INDEX(MCDM_Grades!$I$2:$I$178,MATCH($A15,MCDM_Grades!$A$2:$A$178,0))="","",INDEX(MCDM_Grades!$I$2:$I$178,MATCH($A15,MCDM_Grades!$A$2:$A$178,0))),"") | EC15: =IFERROR(IF(INDEX(MCDM_Grades!$J$2:$J$178,MATCH($A15,MCDM_Grades!$A$2:$A$178,0))="","",INDEX(MCDM_Grades!$J$2:$J$178,MATCH($A15,MCDM_Grades!$A$2:$A$178,0))),"") | ED15: =IFERROR(IF(INDEX(MCDM_Grades!$N$2:$N$178,MATCH($A15,MCDM_Grades!$A$2:$A$178,0))="","",INDEX(MCDM_Grades!$N$2:$N$178,MATCH($A15,MCDM_Grades!$A$2:$A$178,0))),"") | EE15: =IFERROR(IF(INDEX(MCDM_Grades!$O$2:$O$178,MATCH($A15,MCDM_Grades!$A$2:$A$178,0))="","",INDEX(MCDM_Grades!$O$2:$O$178,MATCH($A15,MCDM_Grades!$A$2:$A$178,0))),"") | EF15: =IFERROR(IF(INDEX(MCDM_Grades!$P$2:$P$178,MATCH($A15,MCDM_Grades!$A$2:$A$178,0))="","",INDEX(MCDM_Grades!$P$2:$P$178,MATCH($A15,MCDM_Grades!$A$2:$A$178,0))),"") | EG15: =IFERROR(IF(INDEX(MCDM_Grades!$Q$2:$Q$178,MATCH($A15,MCDM_Grades!$A$2:$A$178,0))="","",INDEX(MCDM_Grades!$Q$2:$Q$178,MATCH($A15,MCDM_Grades!$A$2:$A$178,0))),"") | EH15: =IFERROR(IF(INDEX(MCDM_Grades!$R$2:$R$178,MATCH($A15,MCDM_Grades!$A$2:$A$178,0))="","",INDEX(MCDM_Grades!$R$2:$R$178,MATCH($A15,MCDM_Grades!$A$2:$A$178,0))),"") | EI15: =IFERROR(IF(INDEX(MCDM_Grades!$S$2:$S$178,MATCH($A15,MCDM_Grades!$A$2:$A$178,0))="","",INDEX(MCDM_Grades!$S$2:$S$178,MATCH($A15,MCDM_Grades!$A$2:$A$178,0))),"") | EJ15: =IFERROR(IF(INDEX(MCDM_Grades!$T$2:$T$178,MATCH($A15,MCDM_Grades!$A$2:$A$178,0))="","",INDEX(MCDM_Grades!$T$2:$T$178,MATCH($A15,MCDM_Grades!$A$2:$A$178,0))),"") | EK15: =IFERROR(IF(INDEX(MCDM_Grades!$U$2:$U$178,MATCH($A15,MCDM_Grades!$A$2:$A$178,0))="","",INDEX(MCDM_Grades!$U$2:$U$178,MATCH($A15,MCDM_Grades!$A$2:$A$178,0))),"") | EL15: =IFERROR(IF(INDEX(MCDM_Grades!$V$2:$V$178,MATCH($A15,MCDM_Grades!$A$2:$A$178,0))="","",INDEX(MCDM_Grades!$V$2:$V$178,MATCH($A15,MCDM_Grades!$A$2:$A$178,0))),"") | EM15: =IFERROR(IF(INDEX(MCDM_Grades!$W$2:$W$178,MATCH($A15,MCDM_Grades!$A$2:$A$178,0))="","",INDEX(MCDM_Grades!$W$2:$W$178,MATCH($A15,MCDM_Grades!$A$2:$A$178,0))),"") | EN15: =IFERROR(IF(INDEX(MCDM_Grades!$X$2:$X$178,MATCH($A15,MCDM_Grades!$A$2:$A$178,0))="","",INDEX(MCDM_Grades!$X$2:$X$178,MATCH($A15,MCDM_Grades!$A$2:$A$178,0))),"") | EO15: =IFERROR(IF(INDEX(MCDM_Grades!$Y$2:$Y$178,MATCH($A15,MCDM_Grades!$A$2:$A$178,0))="","",INDEX(MCDM_Grades!$Y$2:$Y$178,MATCH($A15,MCDM_Grades!$A$2:$A$178,0))),"") | EP15: =IFERROR(IF(INDEX(MCDM_Grades!$Z$2:$Z$178,MATCH($A15,MCDM_Grades!$A$2:$A$178,0))="","",INDEX(MCDM_Grades!$Z$2:$Z$178,MATCH($A15,MCDM_Grades!$A$2:$A$178,0))),"") | EQ15: =IFERROR(IF(INDEX(MCDM_Grades!$AA$2:$AA$178,MATCH($A15,MCDM_Grades!$A$2:$A$178,0))="","",INDEX(MCDM_Grades!$AA$2:$AA$178,MATCH($A15,MCDM_Grades!$A$2:$A$178,0))),"") | ER15: =IFERROR(IF(INDEX(MCDM_Grades!$AB$2:$AB$178,MATCH($A15,MCDM_Grades!$A$2:$A$178,0))="","",INDEX(MCDM_Grades!$AB$2:$AB$178,MATCH($A15,MCDM_Grades!$A$2:$A$178,0))),"") | ES15: =IFERROR(IF(INDEX(MCDM_Grades!$AC$2:$AC$178,MATCH($A15,MCDM_Grades!$A$2:$A$178,0))="","",INDEX(MCDM_Grades!$AC$2:$AC$178,MATCH($A15,MCDM_Grades!$A$2:$A$178,0))),"") | ET15: =IFERROR(IF(INDEX(MCDM_Grades!$AD$2:$AD$178,MATCH($A15,MCDM_Grades!$A$2:$A$178,0))="","",INDEX(MCDM_Grades!$AD$2:$AD$178,MATCH($A15,MCDM_Grades!$A$2:$A$178,0))),"") | EU15: =IFERROR(IF(INDEX(MCDM_Grades!$AE$2:$AE$178,MATCH($A15,MCDM_Grades!$A$2:$A$178,0))="","",INDEX(MCDM_Grades!$AE$2:$AE$178,MATCH($A15,MCDM_Grades!$A$2:$A$178,0))),"") | EV15: =IFERROR(IF(INDEX(MCDM_Grades!$K$2:$K$178,MATCH($A15,MCDM_Grades!$A$2:$A$178,0))="","",INDEX(MCDM_Grades!$K$2:$K$178,MATCH($A15,MCDM_Grades!$A$2:$A$178,0))),"") | EW15: =IFERROR(IF(INDEX(MCDM_Grades!$L$2:$L$178,MATCH($A15,MCDM_Grades!$A$2:$A$178,0))="","",INDEX(MCDM_Grades!$L$2:$L$178,MATCH($A15,MCDM_Grades!$A$2:$A$178,0))),"") | EX15: =IFERROR(IF(INDEX(MCDM_Grades!$M$2:$M$178,MATCH($A15,MCDM_Grades!$A$2:$A$178,0))="","",INDEX(MCDM_Grades!$M$2:$M$178,MATCH($A15,MCDM_Grades!$A$2:$A$178,0))),"") | EY15: =IFERROR(IF(INDEX(MCDM_Grades!$AR$2:$AR$178,MATCH($A15,MCDM_Grades!$A$2:$A$178,0))="","",INDEX(MCDM_Grades!$AR$2:$AR$178,MATCH($A15,MCDM_Grades!$A$2:$A$178,0))),"") | EZ15: =IFERROR(IF(INDEX(MCDM_Grades!$AS$2:$AS$178,MATCH($A15,MCDM_Grades!$A$2:$A$178,0))="","",INDEX(MCDM_Grades!$AS$2:$AS$178,MATCH($A15,MCDM_Grades!$A$2:$A$178,0))),"") | FA15: =IFERROR(IF(INDEX(MCDM_Grades!$AT$2:$AT$178,MATCH($A15,MCDM_Grades!$A$2:$A$178,0))="","",INDEX(MCDM_Grades!$AT$2:$AT$178,MATCH($A15,MCDM_Grades!$A$2:$A$178,0))),"") | FB15: =IFERROR(IF(INDEX(MCDM_Grades!$AU$2:$AU$178,MATCH($A15,MCDM_Grades!$A$2:$A$178,0))="","",INDEX(MCDM_Grades!$AU$2:$AU$178,MATCH($A15,MCDM_Grades!$A$2:$A$178,0))),"") | FC15: Nadir / top-down | FD15: Yes | FE15: No | FG15: Line-array (line-scan) camera scanning the pavement at 1 mm GSD (survey-vehicle type; vehicle not named) | FH15: road pavement images captured by a line-array camera under visible-light illumination. The line-array camera captures the pavement at a ground sampling distance of 1 millimeter. | FI15: Dataset page / README | FJ15: https://github.com/qinnzou/DeepCrack | FK15: High | FL15: Not independently verified | FM15: A line-array camera with a fixed 1 mm ground sampling distance is by construction a downward-looking pavement scanner (same setup as the laser-illuminated CrackLS315 sibling). Workbook 'line-array' hint confirmed by the README.
A16: DS-015 | B16: CUBIT-Det | C16: NA | D16: 2024 | E16: Independent Dataset | F16: NA (single source record) | G16: Single source record; no matching record found in any other file after cross-file and cross-platform comparison. | H16: GPT | I16: GitHub | J16: N | K16: NA (single platform) | L16: https://github.com/CUHK-USR-Group/Defect-Dataset | M16: https://github.com/CUHK-USR-Group/Defect-Dataset | N16: NA | O16: NA | P16: NA | Q16: NA | R16: NA | S16: NA | T16: 10.1109/TIM.2025.3571118 | U16: Y | V16: 10.1109/TIM.2025.3571118; 10.1016/j.conbuildmat.2022.129226 | W16: 10.1109/TIM.2025.3571118; 10.1016/j.conbuildmat.2022.129226 | X16: NR | Y16: NR | Z16: Y | AA16: Reported in source record (relationship not classified) | AB16: Images/frames as reported | AC16: 5527 | AD16: NR | AE16: NR | AF16: 5527 | AG16: NR | AH16: NR | AI16: NR | AJ16: NR | AK16: NR | AL16: NR | AM16: NR | AN16: 4624×3472; 8000×6000 | AO16: NR | AP16: China | AQ16: NR | AR16: Hong Kong | AS16: China; Hong Kong; Road environment: Mixed infrastructure; pavement subset | AT16: NR | AU16: UAV onboard cameras | AV16: NR | AW16: UAV onboard cameras | AX16: See Acquisition_Platform (reported: onboard) | AY16: NR | AZ16: Y | BA16: NR | BB16: NR | BC16: NR | BD16: NR | BE16: NR | BF16: Various illumination | BG16: NR | BH16: crack; spalling; moisture | BI16: NR | BJ16: crack; spalling; moisture; building; pavement; bridge | BK16: NR | BL16: object detection | BM16: object detection | BN16: bounding boxes | BO16: NR | BP16: NR | BQ16: Y | BR16: NR | BS16: NR | BT16: NR | BU16: NR | BV16: NR | BW16: NR | BX16: NR | BY16: Manual bounding-box annotation | BZ16: Duplicate and low-quality filtering described for companion data; detection QC details limited | CA16: NR | CB16: NR | CC16: defect detection; UAV infrastructure inspection | CD16: Det-Recon-Reg framework | CE16: Det-Recon-Reg framework | CF16: Reported on the source record/data card or associated publication (see Evidence_Locator) | CG16: NR | CH16: NR | CI16: Include-Supplementary | CJ16: Registration | CK16: NR | CL16: Y | CM16: Registration | CN16: NR | CO16: NR | CP16: N | CQ16: Only 29% pavement; mixed defect/infrastructure taxonomy; access code required | CR16: Original | CS16: N | CT16: N | CU16: N | CV16: NA | CW16: NA | CX16: ChatGPT_Github_001.xlsx | CY16: ChatGPT_Github_001:GH-013 | CZ16: NA | DA16: N | DB16: None | DC16: None | DD16: None | DE16: None | DF16: N | DG16: Single source record; no reconciliation required. | DH16: https://github.com/CUHK-USR-Group/Defect-Dataset README CUBIT-Det section; accessed 2026-08-06 | DI16: High | DJ16: Low | DK16: Use source record as cited. | DL16: 2 | DM16: 4 | DN16: 3.5 | DO16: 3 | DP16: 3 | DQ16: 2 | DR16: 0 | DS16: 53.5 | DT16: Reviewed (source MCDM_Scoring, averaged across batches) | DU16: 1 of 1 | DV16: =IFERROR(IF(INDEX(MCDM_Grades!$C$2:$C$178,MATCH($A16,MCDM_Grades!$A$2:$A$178,0))="","",INDEX(MCDM_Grades!$C$2:$C$178,MATCH($A16,MCDM_Grades!$A$2:$A$178,0))),"") | DW16: =IFERROR(IF(INDEX(MCDM_Grades!$D$2:$D$178,MATCH($A16,MCDM_Grades!$A$2:$A$178,0))="","",INDEX(MCDM_Grades!$D$2:$D$178,MATCH($A16,MCDM_Grades!$A$2:$A$178,0))),"") | DX16: =IFERROR(IF(INDEX(MCDM_Grades!$E$2:$E$178,MATCH($A16,MCDM_Grades!$A$2:$A$178,0))="","",INDEX(MCDM_Grades!$E$2:$E$178,MATCH($A16,MCDM_Grades!$A$2:$A$178,0))),"") | DY16: =IFERROR(IF(INDEX(MCDM_Grades!$F$2:$F$178,MATCH($A16,MCDM_Grades!$A$2:$A$178,0))="","",INDEX(MCDM_Grades!$F$2:$F$178,MATCH($A16,MCDM_Grades!$A$2:$A$178,0))),"") | DZ16: =IFERROR(IF(INDEX(MCDM_Grades!$G$2:$G$178,MATCH($A16,MCDM_Grades!$A$2:$A$178,0))="","",INDEX(MCDM_Grades!$G$2:$G$178,MATCH($A16,MCDM_Grades!$A$2:$A$178,0))),"") | EA16: =IFERROR(IF(INDEX(MCDM_Grades!$H$2:$H$178,MATCH($A16,MCDM_Grades!$A$2:$A$178,0))="","",INDEX(MCDM_Grades!$H$2:$H$178,MATCH($A16,MCDM_Grades!$A$2:$A$178,0))),"") | EB16: =IFERROR(IF(INDEX(MCDM_Grades!$I$2:$I$178,MATCH($A16,MCDM_Grades!$A$2:$A$178,0))="","",INDEX(MCDM_Grades!$I$2:$I$178,MATCH($A16,MCDM_Grades!$A$2:$A$178,0))),"") | EC16: =IFERROR(IF(INDEX(MCDM_Grades!$J$2:$J$178,MATCH($A16,MCDM_Grades!$A$2:$A$178,0))="","",INDEX(MCDM_Grades!$J$2:$J$178,MATCH($A16,MCDM_Grades!$A$2:$A$178,0))),"") | ED16: =IFERROR(IF(INDEX(MCDM_Grades!$N$2:$N$178,MATCH($A16,MCDM_Grades!$A$2:$A$178,0))="","",INDEX(MCDM_Grades!$N$2:$N$178,MATCH($A16,MCDM_Grades!$A$2:$A$178,0))),"") | EE16: =IFERROR(IF(INDEX(MCDM_Grades!$O$2:$O$178,MATCH($A16,MCDM_Grades!$A$2:$A$178,0))="","",INDEX(MCDM_Grades!$O$2:$O$178,MATCH($A16,MCDM_Grades!$A$2:$A$178,0))),"") | EF16: =IFERROR(IF(INDEX(MCDM_Grades!$P$2:$P$178,MATCH($A16,MCDM_Grades!$A$2:$A$178,0))="","",INDEX(MCDM_Grades!$P$2:$P$178,MATCH($A16,MCDM_Grades!$A$2:$A$178,0))),"") | EG16: =IFERROR(IF(INDEX(MCDM_Grades!$Q$2:$Q$178,MATCH($A16,MCDM_Grades!$A$2:$A$178,0))="","",INDEX(MCDM_Grades!$Q$2:$Q$178,MATCH($A16,MCDM_Grades!$A$2:$A$178,0))),"") | EH16: =IFERROR(IF(INDEX(MCDM_Grades!$R$2:$R$178,MATCH($A16,MCDM_Grades!$A$2:$A$178,0))="","",INDEX(MCDM_Grades!$R$2:$R$178,MATCH($A16,MCDM_Grades!$A$2:$A$178,0))),"") | EI16: =IFERROR(IF(INDEX(MCDM_Grades!$S$2:$S$178,MATCH($A16,MCDM_Grades!$A$2:$A$178,0))="","",INDEX(MCDM_Grades!$S$2:$S$178,MATCH($A16,MCDM_Grades!$A$2:$A$178,0))),"") | EJ16: =IFERROR(IF(INDEX(MCDM_Grades!$T$2:$T$178,MATCH($A16,MCDM_Grades!$A$2:$A$178,0))="","",INDEX(MCDM_Grades!$T$2:$T$178,MATCH($A16,MCDM_Grades!$A$2:$A$178,0))),"") | EK16: =IFERROR(IF(INDEX(MCDM_Grades!$U$2:$U$178,MATCH($A16,MCDM_Grades!$A$2:$A$178,0))="","",INDEX(MCDM_Grades!$U$2:$U$178,MATCH($A16,MCDM_Grades!$A$2:$A$178,0))),"") | EL16: =IFERROR(IF(INDEX(MCDM_Grades!$V$2:$V$178,MATCH($A16,MCDM_Grades!$A$2:$A$178,0))="","",INDEX(MCDM_Grades!$V$2:$V$178,MATCH($A16,MCDM_Grades!$A$2:$A$178,0))),"") | EM16: =IFERROR(IF(INDEX(MCDM_Grades!$W$2:$W$178,MATCH($A16,MCDM_Grades!$A$2:$A$178,0))="","",INDEX(MCDM_Grades!$W$2:$W$178,MATCH($A16,MCDM_Grades!$A$2:$A$178,0))),"") | EN16: =IFERROR(IF(INDEX(MCDM_Grades!$X$2:$X$178,MATCH($A16,MCDM_Grades!$A$2:$A$178,0))="","",INDEX(MCDM_Grades!$X$2:$X$178,MATCH($A16,MCDM_Grades!$A$2:$A$178,0))),"") | EO16: =IFERROR(IF(INDEX(MCDM_Grades!$Y$2:$Y$178,MATCH($A16,MCDM_Grades!$A$2:$A$178,0))="","",INDEX(MCDM_Grades!$Y$2:$Y$178,MATCH($A16,MCDM_Grades!$A$2:$A$178,0))),"") | EP16: =IFERROR(IF(INDEX(MCDM_Grades!$Z$2:$Z$178,MATCH($A16,MCDM_Grades!$A$2:$A$178,0))="","",INDEX(MCDM_Grades!$Z$2:$Z$178,MATCH($A16,MCDM_Grades!$A$2:$A$178,0))),"") | EQ16: =IFERROR(IF(INDEX(MCDM_Grades!$AA$2:$AA$178,MATCH($A16,MCDM_Grades!$A$2:$A$178,0))="","",INDEX(MCDM_Grades!$AA$2:$AA$178,MATCH($A16,MCDM_Grades!$A$2:$A$178,0))),"") | ER16: =IFERROR(IF(INDEX(MCDM_Grades!$AB$2:$AB$178,MATCH($A16,MCDM_Grades!$A$2:$A$178,0))="","",INDEX(MCDM_Grades!$AB$2:$AB$178,MATCH($A16,MCDM_Grades!$A$2:$A$178,0))),"") | ES16: =IFERROR(IF(INDEX(MCDM_Grades!$AC$2:$AC$178,MATCH($A16,MCDM_Grades!$A$2:$A$178,0))="","",INDEX(MCDM_Grades!$AC$2:$AC$178,MATCH($A16,MCDM_Grades!$A$2:$A$178,0))),"") | ET16: =IFERROR(IF(INDEX(MCDM_Grades!$AD$2:$AD$178,MATCH($A16,MCDM_Grades!$A$2:$A$178,0))="","",INDEX(MCDM_Grades!$AD$2:$AD$178,MATCH($A16,MCDM_Grades!$A$2:$A$178,0))),"") | EU16: =IFERROR(IF(INDEX(MCDM_Grades!$AE$2:$AE$178,MATCH($A16,MCDM_Grades!$A$2:$A$178,0))="","",INDEX(MCDM_Grades!$AE$2:$AE$178,MATCH($A16,MCDM_Grades!$A$2:$A$178,0))),"") | EV16: =IFERROR(IF(INDEX(MCDM_Grades!$K$2:$K$178,MATCH($A16,MCDM_Grades!$A$2:$A$178,0))="","",INDEX(MCDM_Grades!$K$2:$K$178,MATCH($A16,MCDM_Grades!$A$2:$A$178,0))),"") | EW16: =IFERROR(IF(INDEX(MCDM_Grades!$L$2:$L$178,MATCH($A16,MCDM_Grades!$A$2:$A$178,0))="","",INDEX(MCDM_Grades!$L$2:$L$178,MATCH($A16,MCDM_Grades!$A$2:$A$178,0))),"") | EX16: =IFERROR(IF(INDEX(MCDM_Grades!$M$2:$M$178,MATCH($A16,MCDM_Grades!$A$2:$A$178,0))="","",INDEX(MCDM_Grades!$M$2:$M$178,MATCH($A16,MCDM_Grades!$A$2:$A$178,0))),"") | EY16: =IFERROR(IF(INDEX(MCDM_Grades!$AR$2:$AR$178,MATCH($A16,MCDM_Grades!$A$2:$A$178,0))="","",INDEX(MCDM_Grades!$AR$2:$AR$178,MATCH($A16,MCDM_Grades!$A$2:$A$178,0))),"") | EZ16: =IFERROR(IF(INDEX(MCDM_Grades!$AS$2:$AS$178,MATCH($A16,MCDM_Grades!$A$2:$A$178,0))="","",INDEX(MCDM_Grades!$AS$2:$AS$178,MATCH($A16,MCDM_Grades!$A$2:$A$178,0))),"") | FA16: =IFERROR(IF(INDEX(MCDM_Grades!$AT$2:$AT$178,MATCH($A16,MCDM_Grades!$A$2:$A$178,0))="","",INDEX(MCDM_Grades!$AT$2:$AT$178,MATCH($A16,MCDM_Grades!$A$2:$A$178,0))),"") | FB16: =IFERROR(IF(INDEX(MCDM_Grades!$AU$2:$AU$178,MATCH($A16,MCDM_Grades!$A$2:$A$178,0))="","",INDEX(MCDM_Grades!$AU$2:$AU$178,MATCH($A16,MCDM_Grades!$A$2:$A$178,0))),"") | FC16: Oblique aerial (UAV) | FD16: Unknown | FE16: No | FF16: Multi-viewpoint UAV imagery; 65% building facades (necessarily non-nadir), 29% pavement, 6% bridge; pavement-subset camera angle not stated | FG16: UAV onboard camera (multi-viewpoint; gimbal angle not reported) | FH16: captured by the onboard cameras of the UAVs | The high-resolution images are collected from different viewpoints and distances under various illumination conditions | FI16: Dataset page / README | FJ16: https://github.com/CUHK-USR-Group/Defect-Dataset | FK16: Low | FL16: Verified - agreed | FM16: The workbook 'onboard' hint refers to the UAV's onboard camera, not a ground-vehicle forward camera. README states multi-viewpoint UAV capture; because most images are building facades the camera is tilted/horizontal for the majority, but whether the 29% pavement images are nadir or oblique is not reported. CBM 2022 paper (10.1016/j.conbuildmat.2022.129226) unreachable (Elsevier redirect); TIM 2025 Det-Recon-Reg abstract has no angle information. Could be Mixed nadir+oblique; verify against the papers. | Second review: README (fetched) confirms UAV onboard-camera capture from different viewpoints and distances with 65% building facades, 29% pavement, 6% bridge; gimbal angle for the pavement subset is not stated (CBM 2022 PDF at mae.cuhk.edu.hk failed on TLS). 'Oblique aerial (UAV)' with top_down Unknown is the bes
A17: DS-016 | B17: DeepCrack-537 | C17: NA | D17: 537-image benchmark | E17: Independent Dataset | F17: NA (single source record) | G17: Single source record; no matching record found in any other file after cross-file and cross-platform comparison. | H17: GitHub_Test_Batch (tool UNK) | I17: GitHub | J17: N | K17: NA (single platform) | L17: https://github.com/yhlleo/DeepCrack | M17: https://github.com/yhlleo/DeepCrack | N17: NA | O17: NA | P17: NA | Q17: NA | R17: NA | S17: NA | T17: 10.1016/j.neucom.2019.01.036 | U17: Y | V17: https://doi.org/10.1016/j.neucom.2019.01.036 | W17: 10.1016/j.neucom.2019.01.036 | X17: https://doi.org/10.1016/j.neucom.2019.01.036 | Y17: NR | Z17: Y | AA17: Reported in source record (relationship not classified) | AB17: Images/frames as reported | AC17: 537 | AD17: NR | AE17: NR | AF17: 537 | AG17: NR | AH17: NR | AI17: NR | AJ17: NR | AK17: NR | AL17: NR | AM17: NR | AN17: NR | AO17: NR | AP17: NR | AQ17: NR | AR17: NR | AS17: Road environment: Roadway; mixed crack scenes | AT17: NR | AU17: Mixed cameras | AV17: NR | AW17: Mixed cameras | AX17: NR | AY17: NR | AZ17: NR | BA17: NR | BB17: NR | BC17: NR | BD17: NR | BE17: NR | BF17: NR | BG17: NR | BH17: crack | BI17: NR | BJ17: crack pixel mask | BK17: NR | BL17: Semantic segmentation | BM17: Semantic segmentation | BN17: Image-mask pairs | BO17: mask | BP17: NR | BQ17: NR | BR17: Y | BS17: NR | BT17: NR | BU17: NR | BV17: NR | BW17: NR | BX17: NR | BY17: Manual pixel annotation | BZ17: NR | CA17: NR | CB17: NR | CC17: semantic segmentation; crack detection | CD17: NR | CE17: NR | CF17: Reported on the source record/data card or associated publication (see Evidence_Locator) | CG17: NR | CH17: NR | CI17: Include-Supplementary | CJ17: Direct_Download | CK17: NR | CL17: N | CM17: Direct_Download | CN17: NR | CO17: NR | CP17: N | CQ17: Contains mixed crack scenes/materials rather than a strictly pavement-only corpus; noncommercial-use restriction. | CR17: Original | CS17: N | CT17: N | CU17: N | CV17: NA | CW17: NA | CX17: Github_Github_Test.xlsx | CY17: Github_Github_Test:GITHUB-017 | CZ17: NA | DA17: NA | DB17: None | DC17: None | DD17: None | DE17: None | DF17: N | DG17: Single source record; no reconciliation required. | DH17: https://github.com/yhlleo/DeepCrack; README dataset split, manual annotation, and usage statement; accessed 2026-08-01 | DI17: High | DJ17: Low | DK17: Use source record as cited. | DL17: 4 | DM17: 4 | DN17: 4 | DO17: 2 | DP17: 3 | DQ17: 1 | DR17: 0 | DS17: 58 | DT17: Reviewed (source MCDM_Scoring, averaged across batches) | DU17: 1 of 1 | DV17: =IFERROR(IF(INDEX(MCDM_Grades!$C$2:$C$178,MATCH($A17,MCDM_Grades!$A$2:$A$178,0))="","",INDEX(MCDM_Grades!$C$2:$C$178,MATCH($A17,MCDM_Grades!$A$2:$A$178,0))),"") | DW17: =IFERROR(IF(INDEX(MCDM_Grades!$D$2:$D$178,MATCH($A17,MCDM_Grades!$A$2:$A$178,0))="","",INDEX(MCDM_Grades!$D$2:$D$178,MATCH($A17,MCDM_Grades!$A$2:$A$178,0))),"") | DX17: =IFERROR(IF(INDEX(MCDM_Grades!$E$2:$E$178,MATCH($A17,MCDM_Grades!$A$2:$A$178,0))="","",INDEX(MCDM_Grades!$E$2:$E$178,MATCH($A17,MCDM_Grades!$A$2:$A$178,0))),"") | DY17: =IFERROR(IF(INDEX(MCDM_Grades!$F$2:$F$178,MATCH($A17,MCDM_Grades!$A$2:$A$178,0))="","",INDEX(MCDM_Grades!$F$2:$F$178,MATCH($A17,MCDM_Grades!$A$2:$A$178,0))),"") | DZ17: =IFERROR(IF(INDEX(MCDM_Grades!$G$2:$G$178,MATCH($A17,MCDM_Grades!$A$2:$A$178,0))="","",INDEX(MCDM_Grades!$G$2:$G$178,MATCH($A17,MCDM_Grades!$A$2:$A$178,0))),"") | EA17: =IFERROR(IF(INDEX(MCDM_Grades!$H$2:$H$178,MATCH($A17,MCDM_Grades!$A$2:$A$178,0))="","",INDEX(MCDM_Grades!$H$2:$H$178,MATCH($A17,MCDM_Grades!$A$2:$A$178,0))),"") | EB17: =IFERROR(IF(INDEX(MCDM_Grades!$I$2:$I$178,MATCH($A17,MCDM_Grades!$A$2:$A$178,0))="","",INDEX(MCDM_Grades!$I$2:$I$178,MATCH($A17,MCDM_Grades!$A$2:$A$178,0))),"") | EC17: =IFERROR(IF(INDEX(MCDM_Grades!$J$2:$J$178,MATCH($A17,MCDM_Grades!$A$2:$A$178,0))="","",INDEX(MCDM_Grades!$J$2:$J$178,MATCH($A17,MCDM_Grades!$A$2:$A$178,0))),"") | ED17: =IFERROR(IF(INDEX(MCDM_Grades!$N$2:$N$178,MATCH($A17,MCDM_Grades!$A$2:$A$178,0))="","",INDEX(MCDM_Grades!$N$2:$N$178,MATCH($A17,MCDM_Grades!$A$2:$A$178,0))),"") | EE17: =IFERROR(IF(INDEX(MCDM_Grades!$O$2:$O$178,MATCH($A17,MCDM_Grades!$A$2:$A$178,0))="","",INDEX(MCDM_Grades!$O$2:$O$178,MATCH($A17,MCDM_Grades!$A$2:$A$178,0))),"") | EF17: =IFERROR(IF(INDEX(MCDM_Grades!$P$2:$P$178,MATCH($A17,MCDM_Grades!$A$2:$A$178,0))="","",INDEX(MCDM_Grades!$P$2:$P$178,MATCH($A17,MCDM_Grades!$A$2:$A$178,0))),"") | EG17: =IFERROR(IF(INDEX(MCDM_Grades!$Q$2:$Q$178,MATCH($A17,MCDM_Grades!$A$2:$A$178,0))="","",INDEX(MCDM_Grades!$Q$2:$Q$178,MATCH($A17,MCDM_Grades!$A$2:$A$178,0))),"") | EH17: =IFERROR(IF(INDEX(MCDM_Grades!$R$2:$R$178,MATCH($A17,MCDM_Grades!$A$2:$A$178,0))="","",INDEX(MCDM_Grades!$R$2:$R$178,MATCH($A17,MCDM_Grades!$A$2:$A$178,0))),"") | EI17: =IFERROR(IF(INDEX(MCDM_Grades!$S$2:$S$178,MATCH($A17,MCDM_Grades!$A$2:$A$178,0))="","",INDEX(MCDM_Grades!$S$2:$S$178,MATCH($A17,MCDM_Grades!$A$2:$A$178,0))),"") | EJ17: =IFERROR(IF(INDEX(MCDM_Grades!$T$2:$T$178,MATCH($A17,MCDM_Grades!$A$2:$A$178,0))="","",INDEX(MCDM_Grades!$T$2:$T$178,MATCH($A17,MCDM_Grades!$A$2:$A$178,0))),"") | EK17: =IFERROR(IF(INDEX(MCDM_Grades!$U$2:$U$178,MATCH($A17,MCDM_Grades!$A$2:$A$178,0))="","",INDEX(MCDM_Grades!$U$2:$U$178,MATCH($A17,MCDM_Grades!$A$2:$A$178,0))),"") | EL17: =IFERROR(IF(INDEX(MCDM_Grades!$V$2:$V$178,MATCH($A17,MCDM_Grades!$A$2:$A$178,0))="","",INDEX(MCDM_Grades!$V$2:$V$178,MATCH($A17,MCDM_Grades!$A$2:$A$178,0))),"") | EM17: =IFERROR(IF(INDEX(MCDM_Grades!$W$2:$W$178,MATCH($A17,MCDM_Grades!$A$2:$A$178,0))="","",INDEX(MCDM_Grades!$W$2:$W$178,MATCH($A17,MCDM_Grades!$A$2:$A$178,0))),"") | EN17: =IFERROR(IF(INDEX(MCDM_Grades!$X$2:$X$178,MATCH($A17,MCDM_Grades!$A$2:$A$178,0))="","",INDEX(MCDM_Grades!$X$2:$X$178,MATCH($A17,MCDM_Grades!$A$2:$A$178,0))),"") | EO17: =IFERROR(IF(INDEX(MCDM_Grades!$Y$2:$Y$178,MATCH($A17,MCDM_Grades!$A$2:$A$178,0))="","",INDEX(MCDM_Grades!$Y$2:$Y$178,MATCH($A17,MCDM_Grades!$A$2:$A$178,0))),"") | EP17: =IFERROR(IF(INDEX(MCDM_Grades!$Z$2:$Z$178,MATCH($A17,MCDM_Grades!$A$2:$A$178,0))="","",INDEX(MCDM_Grades!$Z$2:$Z$178,MATCH($A17,MCDM_Grades!$A$2:$A$178,0))),"") | EQ17: =IFERROR(IF(INDEX(MCDM_Grades!$AA$2:$AA$178,MATCH($A17,MCDM_Grades!$A$2:$A$178,0))="","",INDEX(MCDM_Grades!$AA$2:$AA$178,MATCH($A17,MCDM_Grades!$A$2:$A$178,0))),"") | ER17: =IFERROR(IF(INDEX(MCDM_Grades!$AB$2:$AB$178,MATCH($A17,MCDM_Grades!$A$2:$A$178,0))="","",INDEX(MCDM_Grades!$AB$2:$AB$178,MATCH($A17,MCDM_Grades!$A$2:$A$178,0))),"") | ES17: =IFERROR(IF(INDEX(MCDM_Grades!$AC$2:$AC$178,MATCH($A17,MCDM_Grades!$A$2:$A$178,0))="","",INDEX(MCDM_Grades!$AC$2:$AC$178,MATCH($A17,MCDM_Grades!$A$2:$A$178,0))),"") | ET17: =IFERROR(IF(INDEX(MCDM_Grades!$AD$2:$AD$178,MATCH($A17,MCDM_Grades!$A$2:$A$178,0))="","",INDEX(MCDM_Grades!$AD$2:$AD$178,MATCH($A17,MCDM_Grades!$A$2:$A$178,0))),"") | EU17: =IFERROR(IF(INDEX(MCDM_Grades!$AE$2:$AE$178,MATCH($A17,MCDM_Grades!$A$2:$A$178,0))="","",INDEX(MCDM_Grades!$AE$2:$AE$178,MATCH($A17,MCDM_Grades!$A$2:$A$178,0))),"") | EV17: =IFERROR(IF(INDEX(MCDM_Grades!$K$2:$K$178,MATCH($A17,MCDM_Grades!$A$2:$A$178,0))="","",INDEX(MCDM_Grades!$K$2:$K$178,MATCH($A17,MCDM_Grades!$A$2:$A$178,0))),"") | EW17: =IFERROR(IF(INDEX(MCDM_Grades!$L$2:$L$178,MATCH($A17,MCDM_Grades!$A$2:$A$178,0))="","",INDEX(MCDM_Grades!$L$2:$L$178,MATCH($A17,MCDM_Grades!$A$2:$A$178,0))),"") | EX17: =IFERROR(IF(INDEX(MCDM_Grades!$M$2:$M$178,MATCH($A17,MCDM_Grades!$A$2:$A$178,0))="","",INDEX(MCDM_Grades!$M$2:$M$178,MATCH($A17,MCDM_Grades!$A$2:$A$178,0))),"") | EY17: =IFERROR(IF(INDEX(MCDM_Grades!$AR$2:$AR$178,MATCH($A17,MCDM_Grades!$A$2:$A$178,0))="","",INDEX(MCDM_Grades!$AR$2:$AR$178,MATCH($A17,MCDM_Grades!$A$2:$A$178,0))),"") | EZ17: =IFERROR(IF(INDEX(MCDM_Grades!$AS$2:$AS$178,MATCH($A17,MCDM_Grades!$A$2:$A$178,0))="","",INDEX(MCDM_Grades!$AS$2:$AS$178,MATCH($A17,MCDM_Grades!$A$2:$A$178,0))),"") | FA17: =IFERROR(IF(INDEX(MCDM_Grades!$AT$2:$AT$178,MATCH($A17,MCDM_Grades!$A$2:$A$178,0))="","",INDEX(MCDM_Grades!$AT$2:$AT$178,MATCH($A17,MCDM_Grades!$A$2:$A$178,0))),"") | FB17: =IFERROR(IF(INDEX(MCDM_Grades!$AU$2:$AU$178,MATCH($A17,MCDM_Grades!$A$2:$A$178,0))="","",INDEX(MCDM_Grades!$AU$2:$AU$178,MATCH($A17,MCDM_Grades!$A$2:$A$178,0))),"") | FC17: Nadir / top-down | FD17: Yes | FE17: No | FF17: Close-range surface photographs of mixed scenes (pavement plus concrete/wall surfaces shot face-on); no street-level views | FG17: Close-range camera(s) pointed perpendicular at the surface (mixed cameras; mount not reported) | FH17: We established a public benchmark dataset with cracks in multiple scenes to evaluate the crack detection systems. | figures/dataset-overview.jpg: 12 sample images, all close-range surface-perpendicular views of pavement, concrete and a brick wall, none street-level | FI17: Dataset page / README | FJ17: https://raw.githubusercontent.com/yhlleo/DeepCrack/master/figures/dataset-overview.jpg | FK17: High | FL17: Verified - agreed | FM17: README (yhlleo/DeepCrack) only says 'a public benchmark dataset with cracks in multiple scales and scenes'; the Neurocomputing paper could not be fetched (Elsevier redirect). Label follows the task-provided prior knowledge (DeepCrack = top-down): images are surface-perpendicular close-ups, but some depict non-pavement surfaces (walls/concrete), so 'top-down' here means camera axis normal to the imaged surface. | Second review replaced the evidence (was: Known dataset (prior knowledge)). | Second review: Inspected the repository's dataset-overview figure: every sample is a face-on close-up of a cracked surface (asphalt, concrete, masonry) with no horizon or forward perspective, confirming camera axis normal to the surface. Some scenes are walls rather than pavement, as the first reviewer noted.
