Workbook

Sheet Top10_Review
A2: Ten datasets for manual review
A3: Review order covers contrasting data types and verification issues. It is a purposive shortlist, not a ranking by documentation score.
A5: Priority | B5: Dataset ID | C5: Dataset | D5: Representation | E5: Lower /100 | F5: Upper /100 | G5: Resolved share | H5: Dataset link | I5: Paper / evidence | J5: Why selected | K5: First manual action | L5: Release / scope | M5: Known limitation | N5: Review status | O5: Review inputs | P5: Check evidence
A6: 1 | B6: DS-084 | C6: SDNET2018 — pavement subset | D6: Binary image classification | E6: =INDEX(MCDM_Grades!$E$6:$E$238,MATCH(B6,MCDM_Grades!$A$6:$A$238,0)) -> 88.888889 | F6: =INDEX(MCDM_Grades!$F$6:$F$238,MATCH(B6,MCDM_Grades!$A$6:$A$238,0)) -> 100 | G6: =INDEX(MCDM_Grades!$G$6:$G$238,MATCH(B6,MCDM_Grades!$A$6:$A$238,0)) -> 0.88888889 | H6: =HYPERLINK("https://digitalcommons.usu.edu/all_datasets/48/","Dataset") -> Dataset | I6: =HYPERLINK("https://doi.org/10.1016/j.dib.2018.11.015","Evidence") -> Evidence | J6: Compact class-folder example; checks whether pavement crops are distinguished from walls/decks and original captures. | K6: Open USU Methodology and ReadMe; identify pavement C/U folders; then inspect one cracked and one uncracked crop. | L6: USU SDNET2018 deposit, 2018; pavement subset within full release | M6: Whole-deposit count is not pavement-only count; related crops are not independent images. No payload inspection. | N6: =INDEX(Manual_Review!$AH$6:$AH$238,MATCH(B6,Manual_Review!$A$6:$A$238,0)) -> Not started | O6: =HYPERLINK("#'Manual_Review'!A"&(MATCH("DS-084",Manual_Review!$A$6:$A$238,0)+5),"Enter review") -> Enter review | P6: =HYPERLINK("#'MCDM_Checks'!A"&(MATCH("DS-084",MCDM_Checks!$B$6:$B$3733,0)+5),"Check evidence") -> Check evidence
A7: 2 | B7: DS-007 | C7: CRACK500 | D7: Crack segmentation | E7: =INDEX(MCDM_Grades!$E$6:$E$238,MATCH(B7,MCDM_Grades!$A$6:$A$238,0)) -> 77.777778 | F7: =INDEX(MCDM_Grades!$F$6:$F$238,MATCH(B7,MCDM_Grades!$A$6:$A$238,0)) -> 100 | G7: =INDEX(MCDM_Grades!$G$6:$G$238,MATCH(B7,MCDM_Grades!$A$6:$A$238,0)) -> 0.77777778 | H7: =HYPERLINK("https://github.com/fyangneil/pavement-crack-detection","Dataset") -> Dataset | I7: =HYPERLINK("https://arxiv.org/abs/1901.06340","Evidence") -> Evidence | J7: Small original corpus with clear original-image/crop distinction; useful calibration for sampling and ancestry. | K7: Read paper IV-B1; verify 500 original images versus 3,368 retained crops and map one image to its binary mask. | L7: FPHBN documented CRACK500 split, 2019 paper / author repository | M7: Repository bundles other datasets. Do not count companion corpora as CRACK500. Data terms and label QA remain unresolved. | N7: =INDEX(Manual_Review!$AH$6:$AH$238,MATCH(B7,Manual_Review!$A$6:$A$238,0)) -> Not started | O7: =HYPERLINK("#'Manual_Review'!A"&(MATCH("DS-007",Manual_Review!$A$6:$A$238,0)+5),"Enter review") -> Enter review | P7: =HYPERLINK("#'MCDM_Checks'!A"&(MATCH("DS-007",MCDM_Checks!$B$6:$B$3733,0)+5),"Check evidence") -> Check evidence
A8: 3 | B8: DS-035 | C8: RDD2022 | D8: Multicountry distress detection | E8: =INDEX(MCDM_Grades!$E$6:$E$238,MATCH(B8,MCDM_Grades!$A$6:$A$238,0)) -> 94.444444 | F8: =INDEX(MCDM_Grades!$F$6:$F$238,MATCH(B8,MCDM_Grades!$A$6:$A$238,0)) -> 100 | G8: =INDEX(MCDM_Grades!$G$6:$G$238,MATCH(B8,MCDM_Grades!$A$6:$A$238,0)) -> 0.94444444 | H8: =HYPERLINK("https://figshare.com/articles/dataset/RDD2022_-_The_multi-national_Road_Damage_Dataset_released_through_CRDDC_2022/21431547/1","Dataset") -> Dataset | I8: =HYPERLINK("https://arxiv.org/abs/2209.08538","Evidence") -> Evidence | J8: Well-documented detection exemplar with country subsets, label map and download manifest. | K8: Open label_map.pbtxt and directory structure; inspect one public training XML; note test annotations are withheld. | L8: Figshare version 1, DOI 10.6084/m9.figshare.21431547.v1 | M8: Contains earlier RDD lineage. Country folders do not prove route-independent splits; third-party rights require separate reuse check. | N8: =INDEX(Manual_Review!$AH$6:$AH$238,MATCH(B8,Manual_Review!$A$6:$A$238,0)) -> Not started | O8: =HYPERLINK("#'Manual_Review'!A"&(MATCH("DS-035",Manual_Review!$A$6:$A$238,0)+5),"Enter review") -> Enter review | P8: =HYPERLINK("#'MCDM_Checks'!A"&(MATCH("DS-035",MCDM_Checks!$B$6:$B$3733,0)+5),"Check evidence") -> Check evidence
A9: 4 | B9: DS-096 | C9: PaveBench / PaveVQA | D9: Multitask perception and vision-language | E9: =INDEX(MCDM_Grades!$E$6:$E$238,MATCH(B9,MCDM_Grades!$A$6:$A$238,0)) -> 100 | F9: =INDEX(MCDM_Grades!$F$6:$F$238,MATCH(B9,MCDM_Grades!$A$6:$A$238,0)) -> 100 | G9: =INDEX(MCDM_Grades!$G$6:$G$238,MATCH(B9,MCDM_Grades!$A$6:$A$238,0)) -> 1 | H9: =HYPERLINK("https://huggingface.co/datasets/MML-Group/PaveBench","Dataset") -> Dataset | I9: =HYPERLINK("https://arxiv.org/abs/2604.02804","Evidence") -> Evidence | J9: Meeting-critical example; public task tree makes differences among classification, detection, masks and VQA easy to check. | K9: Compare six classification categories with merged detection/segmentation classes; inspect label_map.txt and one QA record. | L9: Hugging Face MML-Group/PaveBench, current card snapshot 2026-10-11 | M9: Documentation-only pass does not validate mask accuracy, physical metrology, benchmark independence or maintenance outcomes. | N9: =INDEX(Manual_Review!$AH$6:$AH$238,MATCH(B9,Manual_Review!$A$6:$A$238,0)) -> Not started | O9: =HYPERLINK("#'Manual_Review'!A"&(MATCH("DS-096",Manual_Review!$A$6:$A$238,0)+5),"Enter review") -> Enter review | P9: =HYPERLINK("#'MCDM_Checks'!A"&(MATCH("DS-096",MCDM_Checks!$B$6:$B$3733,0)+5),"Check evidence") -> Check evidence
A10: 5 | B10: DS-011 | C10: CrackSeg9k | D10: Compiled derivative and lineage audit | E10: =INDEX(MCDM_Grades!$E$6:$E$238,MATCH(B10,MCDM_Grades!$A$6:$A$238,0)) -> 58.333333 | F10: =INDEX(MCDM_Grades!$F$6:$F$238,MATCH(B10,MCDM_Grades!$A$6:$A$238,0)) -> 100 | G10: =INDEX(MCDM_Grades!$G$6:$G$238,MATCH(B10,MCDM_Grades!$A$6:$A$238,0)) -> 0.58333333 | H10: =HYPERLINK("https://dataverse.harvard.edu/dataset.xhtml?persistentId=doi:10.7910/DVN/EGIEBY&version=4.0","Dataset") -> Dataset | I10: =HYPERLINK("https://arxiv.org/abs/2208.13054","Evidence") -> Evidence | J10: Deliberate derivative exemplar exposes parent overlap, annotation transformations and changed release counts. | K10: Open author README V4 instructions; reconcile approximately 9,160 current images with 9,255 in the paper; inspect parent prefixes. | L10: Author-recommended Dataverse V4, June 2024; release content requires reconciliation | M10: Shares parents with SDNET2018 and CRACK500 in this shortlist. Not an independent external test. V4 payload not inspected. | N10: =INDEX(Manual_Review!$AH$6:$AH$238,MATCH(B10,Manual_Review!$A$6:$A$238,0)) -> Not started | O10: =HYPERLINK("#'Manual_Review'!A"&(MATCH("DS-011",Manual_Review!$A$6:$A$238,0)+5),"Enter review") -> Enter review | P10: =HYPERLINK("#'MCDM_Checks'!A"&(MATCH("DS-011",MCDM_Checks!$B$6:$B$3733,0)+5),"Check evidence") -> Check evidence
A11: 6 | B11: DS-135 | C11: UAV-PDD2023 | D11: UAV distress detection | E11: =INDEX(MCDM_Grades!$E$6:$E$238,MATCH(B11,MCDM_Grades!$A$6:$A$238,0)) -> 100 | F11: =INDEX(MCDM_Grades!$F$6:$F$238,MATCH(B11,MCDM_Grades!$A$6:$A$238,0)) -> 100 | G11: =INDEX(MCDM_Grades!$G$6:$G$238,MATCH(B11,MCDM_Grades!$A$6:$A$238,0)) -> 1 | H11: =HYPERLINK("https://zenodo.org/records/8429208","Dataset") -> Dataset | I11: =HYPERLINK("https://doi.org/10.1016/j.dib.2023.109692","Evidence") -> Evidence | J11: Stable DOI and compact data paper provide an accessible UAV example with concrete label-overlay verification. | K11: Open paper Figures 2–3 and XML example; verify six class codes, 2,440 images and one image-label overlay. | L11: Zenodo v4, 2023-10-11; DOI 10.5281/zenodo.8429208 | M11: Images include crops and augmentation. Random splits do not establish original-frame independence; route groups remain unverified. | N11: =INDEX(Manual_Review!$AH$6:$AH$238,MATCH(B11,Manual_Review!$A$6:$A$238,0)) -> Not started | O11: =HYPERLINK("#'Manual_Review'!A"&(MATCH("DS-135",Manual_Review!$A$6:$A$238,0)+5),"Enter review") -> Enter review | P11: =HYPERLINK("#'MCDM_Checks'!A"&(MATCH("DS-135",MCDM_Checks!$B$6:$B$3733,0)+5),"Check evidence") -> Check evidence
A12: 7 | B12: DS-157 | C12: Pothole-600 | D12: RGB and transformed-disparity segmentation | E12: =INDEX(MCDM_Grades!$E$6:$E$238,MATCH(B12,MCDM_Grades!$A$6:$A$238,0)) -> 55.555556 | F12: =INDEX(MCDM_Grades!$F$6:$F$238,MATCH(B12,MCDM_Grades!$A$6:$A$238,0)) -> 100 | G12: =INDEX(MCDM_Grades!$G$6:$G$238,MATCH(B12,MCDM_Grades!$A$6:$A$238,0)) -> 0.55555556 | H12: =HYPERLINK("https://sites.google.com/view/pothole-600/dataset","Dataset") -> Dataset | I12: =HYPERLINK("https://arxiv.org/abs/2008.06840","Evidence") -> Evidence | J12: Manageable multimodal exemplar with 600 paired items and a clear source site; useful contrast between imagery and metrology. | K12: Follow official Dataset page to Drive/Kaggle; match one RGB image, transformed disparity and mask; confirm data terms. | L12: Author Pothole-600 release accompanying ECCV Workshops 2020 | M12: Distinguish from separate 2019 Stereo Pothole Datasets. Transformation is not calibrated pothole depth; license/QA/location remain unresolved. | N12: =INDEX(Manual_Review!$AH$6:$AH$238,MATCH(B12,Manual_Review!$A$6:$A$238,0)) -> Not started | O12: =HYPERLINK("#'Manual_Review'!A"&(MATCH("DS-157",Manual_Review!$A$6:$A$238,0)+5),"Enter review") -> Enter review | P12: =HYPERLINK("#'MCDM_Checks'!A"&(MATCH("DS-157",MCDM_Checks!$B$6:$B$3733,0)+5),"Check evidence") -> Check evidence
A13: 8 | B13: DS-160 | C13: PVS — Passive Vehicular Sensors | D13: Inertial sensors and roughness categories | E13: =INDEX(MCDM_Grades!$E$6:$E$238,MATCH(B13,MCDM_Grades!$A$6:$A$238,0)) -> 75 | F13: =INDEX(MCDM_Grades!$F$6:$F$238,MATCH(B13,MCDM_Grades!$A$6:$A$238,0)) -> 100 | G13: =INDEX(MCDM_Grades!$G$6:$G$238,MATCH(B13,MCDM_Grades!$A$6:$A$238,0)) -> 0.75 | H13: =HYPERLINK("https://github.com/jefmenegazzo/Intelligent-Vehicle-Perception-Based-on-Inertial-Sensing-and-Artificial-Intelligence","Dataset") -> Dataset | I13: =HYPERLINK("https://doi.org/10.1109/SBESC51047.2020.9277846","Evidence") -> Evidence | J13: Nine-run example makes non-image units, sensor rates and category-versus-measured-IRI distinction practical to review. | K13: Read sensor and run tables; check one dataset_labels.csv with its GPS record and environmental-video timestamp. | L13: Nine-run PVS family; author README snapshot 2026-10-11 | M13: Three vehicle/driver pairs are confounded. Roughness classes are not measured IRI. Missing codes, label QA and terms scope need confirmation. | N13: =INDEX(Manual_Review!$AH$6:$AH$238,MATCH(B13,Manual_Review!$A$6:$A$238,0)) -> Not started | O13: =HYPERLINK("#'Manual_Review'!A"&(MATCH("DS-160",Manual_Review!$A$6:$A$238,0)+5),"Enter review") -> Enter review | P13: =HYPERLINK("#'MCDM_Checks'!A"&(MATCH("DS-160",MCDM_Checks!$B$6:$B$3733,0)+5),"Check evidence") -> Check evidence
A14: 9 | B14: DS-047 | C14: LTPP — Long-Term Pavement Performance | D14: Engineering measurements and longitudinal sections | E14: =INDEX(MCDM_Grades!$E$6:$E$238,MATCH(B14,MCDM_Grades!$A$6:$A$238,0)) -> 83.333333 | F14: =INDEX(MCDM_Grades!$F$6:$F$238,MATCH(B14,MCDM_Grades!$A$6:$A$238,0)) -> 100 | G14: =INDEX(MCDM_Grades!$G$6:$G$238,MATCH(B14,MCDM_Grades!$A$6:$A$238,0)) -> 0.83333333 | H14: =HYPERLINK("https://infopave.fhwa.dot.gov/Data/StandardDataRelease","Dataset") -> Dataset | I14: =HYPERLINK("https://infopave.fhwa.dot.gov/InfoPave_Repository/files/FHWA-HRT-21-038.pdf","Evidence") -> Evidence | J14: Essential engineering contrast; manual pilot can focus on one section and measurement table rather than the entire database. | K14: Confirm SDR selection, open LTPPDD and MON_DIS_AC_REV definitions, then inspect one section/date with null-versus-zero handling. | L14: SDR39 context retained from v4; current portal identifies SDR40 as latest; selection pending | M14: Release-specific counts/distributions and schema continuity remain pending; 2021 guide is context, not proof of SDR39/40 completeness. | N14: =INDEX(Manual_Review!$AH$6:$AH$238,MATCH(B14,Manual_Review!$A$6:$A$238,0)) -> Not started | O14: =HYPERLINK("#'Manual_Review'!A"&(MATCH("DS-047",Manual_Review!$A$6:$A$238,0)+5),"Enter review") -> Enter review | P14: =HYPERLINK("#'MCDM_Checks'!A"&(MATCH("DS-047",MCDM_Checks!$B$6:$B$3733,0)+5),"Check evidence") -> Check evidence
A15: 10 | B15: DS-183 | C15: Zenseact Open Dataset — Frames | D15: AV fleet road wetness and snow classification | E15: =INDEX(MCDM_Grades!$E$6:$E$238,MATCH(B15,MCDM_Grades!$A$6:$A$238,0)) -> 88.888889 | F15: =INDEX(MCDM_Grades!$F$6:$F$238,MATCH(B15,MCDM_Grades!$A$6:$A$238,0)) -> 100 | G15: =INDEX(MCDM_Grades!$G$6:$G$238,MATCH(B15,MCDM_Grades!$A$6:$A$238,0)) -> 0.88888889 | H15: =HYPERLINK("https://zod.zenseact.com/frames/","Dataset") -> Dataset | I15: =HYPERLINK("https://arxiv.org/abs/2305.02008","Evidence") -> Evidence | J15: New AV-inventory exemplar with public samples, concise surface-label definitions and an SDK mini-download option. | K15: Open Annotations → Road surface and Frames samples; verify wetness/snow labels in one Frame; check access route before retrieval. | L15: ZOD Frames public documentation snapshot 2026-10-11; distinguish Sequences/Drives | M15: Surface labels apply to Frames; do not infer labels on every video frame or autonomous engagement. Not crack/PCI ground truth. | N15: =INDEX(Manual_Review!$AH$6:$AH$238,MATCH(B15,Manual_Review!$A$6:$A$238,0)) -> Not started | O15: =HYPERLINK("#'Manual_Review'!A"&(MATCH("DS-183",Manual_Review!$A$6:$A$238,0)+5),"Enter review") -> Enter review | P15: =HYPERLINK("#'MCDM_Checks'!A"&(MATCH("DS-183",MCDM_Checks!$B$6:$B$3733,0)+5),"Check evidence") -> Check evidence

Sheet All_Datasets
A2: Merged dataset inventory
A3: 233 retained records from 248 source rows. Blue rows are the ten purposive manual-review priorities. Scores are provisional documentation bounds.
A5: Dataset ID | B5: Dataset / release | C5: Review priority | D5: Profile | E5: Lower /100 | F5: Upper /100 | G5: Resolved share | H5: Dataset link | I5: Evidence / paper | J5: Assessed release | K5: Task / target scope | L5: Media | M5: Capture context | N5: Labels / targets | O5: Annotation format | P5: Stated terms | Q5: Access route | R5: Reported size and unit | S5: Geography | T5: Publisher | U5: Limitations | V5: Source IDs | W5: Merge decision | X5: Related-release flags | Y5: Conflicts / release issues | Z5: Evidence basis | AA5: Manual review | AB5: Check evidence | AC5: Platforms | AD5: Primary URL | AE5: Evidence URL | AF5: Source lineage
A6: DS-001 | B6: Asphalt Pavement Crack Data (class-foldered grayscale images) | D6: Labeled-16 | E6: =INDEX(MCDM_Grades!$E$6:$E$238,MATCH(A6,MCDM_Grades!$A$6:$A$238,0)) -> 11.111111 | F6: =INDEX(MCDM_Grades!$F$6:$F$238,MATCH(A6,MCDM_Grades!$A$6:$A$238,0)) -> 100 | G6: =INDEX(MCDM_Grades!$G$6:$G$238,MATCH(A6,MCDM_Grades!$A$6:$A$238,0)) -> 0.11111111 | H6: =HYPERLINK("https://github.com/summoners29/Asphalt-Pavement-Crack-Data","Dataset") -> Dataset | I6: =HYPERLINK("https://github.com/summoners29/Asphalt-Pavement-Crack-Data","Evidence / paper") -> Evidence / paper | J6: v1 | K6: Classification | L6: NR | M6: NR | N6: Folder-level class labels (e.g., Alligator) | O6: Class-folder structure (grayscale jpg) | P6: NR | Q6: Direct_Download | R6: NR | S6: Road environment: Asphalt pavements | U6: No README, no counts, no license or provenance; images stored directly in repository | V6: DS-001 | W6: Retained existing record | Z6: v3 evidence snapshot | AA6: =HYPERLINK("#'Manual_Review'!A"&(MATCH("DS-001",Manual_Review!$A$6:$A$238,0)+5),"Enter review") -> Enter review | AB6: =HYPERLINK("#'MCDM_Checks'!A"&(MATCH("DS-001",MCDM_Checks!$B$6:$B$3733,0)+5),"Check evidence") -> Check evidence | AC6: GitHub | AD6: https://github.com/summoners29/Asphalt-Pavement-Crack-Data | AE6: https://github.com/summoners29/Asphalt-Pavement-Crack-Data | AF6: Compared_All_Platforms_TH_v3.0.xlsx!All_Datasets row 2 (DS-001)
A7: DS-002 | B7: Asphalt Pavement Distress Dataset (DSWMamba) | D7: Labeled-16 | E7: =INDEX(MCDM_Grades!$E$6:$E$238,MATCH(A7,MCDM_Grades!$A$6:$A$238,0)) -> 11.111111 | F7: =INDEX(MCDM_Grades!$F$6:$F$238,MATCH(A7,MCDM_Grades!$A$6:$A$238,0)) -> 100 | G7: =INDEX(MCDM_Grades!$G$6:$G$238,MATCH(A7,MCDM_Grades!$A$6:$A$238,0)) -> 0.11111111 | H7: =HYPERLINK("https://github.com/Oct-Sunn/Asphalt-Pavement-Distress-Dataset","Dataset") -> Dataset | I7: =HYPERLINK("https://github.com/Oct-Sunn/Asphalt-Pavement-Distress-Dataset","Evidence / paper") -> Evidence / paper | J7: v1 | K7: Object detection [Claude] | detection; classification; analysis [GPT] | semantic segmentation [Test_Batch] | L7: NR | M7: NR | N7: Labeled images across six distress categories [Claude] | Six categories; full taxonomy NR [GPT] | six distress categories [Test_Batch] | O7: Pixel masks | P7: NR | Q7: Direct_Download [Claude] | UNK [GPT/Test_Batch] | R7: NR | S7: Road environment: Asphalt pavements, real-world scenarios [Claude] | Asphalt pavement [GPT] | Asphalt roadway [Test_Batch] | U7: Image count, format, license, and provenance undocumented; single Google Drive archive (link liveness not independently re-tested) [Claude] | Download target not resolved; no count, license, persistent data identifier, annotation format, geography, or collection details [GPT] | Model repository documents a six-class dataset, but dataset count, release year, access route, license, geography, and independent dataset identity remain unresolved. [Test_Batch] | V7: DS-002 | W7: Retained existing record | Z7: v3 evidence snapshot | AA7: =HYPERLINK("#'Manual_Review'!A"&(MATCH("DS-002",Manual_Review!$A$6:$A$238,0)+5),"Enter review") -> Enter review | AB7: =HYPERLINK("#'MCDM_Checks'!A"&(MATCH("DS-002",MCDM_Checks!$B$6:$B$3733,0)+5),"Check evidence") -> Check evidence | AC7: GitHub | AD7: https://github.com/Oct-Sunn/Asphalt-Pavement-Distress-Dataset | AE7: https://github.com/Oct-Sunn/Asphalt-Pavement-Distress-Dataset | AF7: Compared_All_Platforms_TH_v3.0.xlsx!All_Datasets row 3 (DS-002)
A8: DS-003 | B8: CiCS pavement crack image dataset | D8: Labeled-16 | E8: =INDEX(MCDM_Grades!$E$6:$E$238,MATCH(A8,MCDM_Grades!$A$6:$A$238,0)) -> 11.111111 | F8: =INDEX(MCDM_Grades!$F$6:$F$238,MATCH(A8,MCDM_Grades!$A$6:$A$238,0)) -> 100 | G8: =INDEX(MCDM_Grades!$G$6:$G$238,MATCH(A8,MCDM_Grades!$A$6:$A$238,0)) -> 0.11111111 | H8: =HYPERLINK("https://github.com/DrEdwardLee/Pavement-Crack-Dataset","Dataset") -> Dataset | I8: =HYPERLINK("https://github.com/DrEdwardLee/Pavement-Crack-Dataset","Evidence / paper") -> Evidence / paper | J8: v1 (in-repo rar archives, 5 parts) | K8: Crack detection (per repo description) | L8: NR | M8: NR | N8: UNK (no README; annotation presence not verifiable from file listing) | O8: NR | P8: NR | Q8: Direct_Download | R8: NR | S8: Road environment: Pavements | U8: No README or documentation; annotations, counts, provenance, and license all unverified (data stored as CiCS-Data(1-5).rar in repo) | V8: DS-003 | W8: Retained existing record | X8: Same acquisition lineage; different archives/releases (DS-003, DS-025, DS-090) | Z8: v3 evidence snapshot | AA8: =HYPERLINK("#'Manual_Review'!A"&(MATCH("DS-003",Manual_Review!$A$6:$A$238,0)+5),"Enter review") -> Enter review | AB8: =HYPERLINK("#'MCDM_Checks'!A"&(MATCH("DS-003",MCDM_Checks!$B$6:$B$3733,0)+5),"Check evidence") -> Check evidence | AC8: GitHub | AD8: https://github.com/DrEdwardLee/Pavement-Crack-Dataset | AE8: https://github.com/DrEdwardLee/Pavement-Crack-Dataset | AF8: Compared_All_Platforms_TH_v3.0.xlsx!All_Datasets row 4 (DS-003)
A9: DS-004 | B9: complexPavementCrackDataset | D9: Labeled-16 | E9: =INDEX(MCDM_Grades!$E$6:$E$238,MATCH(A9,MCDM_Grades!$A$6:$A$238,0)) -> 36.111111 | F9: =INDEX(MCDM_Grades!$F$6:$F$238,MATCH(A9,MCDM_Grades!$A$6:$A$238,0)) -> 100 | G9: =INDEX(MCDM_Grades!$G$6:$G$238,MATCH(A9,MCDM_Grades!$A$6:$A$238,0)) -> 0.36111111 | H9: =HYPERLINK("https://github.com/SEU-zhc/complexPavementCrackDataset","Dataset") -> Dataset | I9: =HYPERLINK("https://github.com/SEU-zhc/complexPavementCrackDataset","Evidence / paper") -> Evidence / paper | J9: v1 | K9: Object detection;Semantic segmentation | L9: Images/frames as reported | M9: Onboard (vehicle) cameras | N9: Bounding boxes (class xc yc w h) and binary crack masks | O9: YOLO-style txt;binary mask images | P9: NR | Q9: Restricted | R9: 500 | S9: Road environment: Pavements with shadows, watermarks, brake marks and environmental noise | U9: Baidu-only hosting limits international research access; 'over 500 images' recorded as 500 minimum; no paper or license | V9: DS-004 | W9: Retained existing record | Z9: v3 evidence snapshot | AA9: =HYPERLINK("#'Manual_Review'!A"&(MATCH("DS-004",Manual_Review!$A$6:$A$238,0)+5),"Enter review") -> Enter review | AB9: =HYPERLINK("#'MCDM_Checks'!A"&(MATCH("DS-004",MCDM_Checks!$B$6:$B$3733,0)+5),"Check evidence") -> Check evidence | AC9: GitHub | AD9: https://github.com/SEU-zhc/complexPavementCrackDataset | AE9: https://github.com/SEU-zhc/complexPavementCrackDataset | AF9: Compared_All_Platforms_TH_v3.0.xlsx!All_Datasets row 5 (DS-004)
A10: DS-005 | B10: CQU-BPDD — Chongqing University Bituminous Pavement Disease Detection Dataset | D10: Labeled-16 | E10: =INDEX(MCDM_Grades!$E$6:$E$238,MATCH(A10,MCDM_Grades!$A$6:$A$238,0)) -> 61.111111 | F10: =INDEX(MCDM_Grades!$F$6:$F$238,MATCH(A10,MCDM_Grades!$A$6:$A$238,0)) -> 100 | G10: =INDEX(MCDM_Grades!$G$6:$G$238,MATCH(A10,MCDM_Grades!$A$6:$A$238,0)) -> 0.61111111 | H10: =HYPERLINK("https://huggingface.co/datasets/Dearcat/CQU-BPDD","Dataset") -> Dataset | I10: =HYPERLINK("https://github.com/DearCaat/Pavement-Distress-Classification","Evidence / paper") -> Evidence / paper | J10: 2020–2021; CQU-BPDD — Bituminous Pavement Distress | K10: Distress / roughness | L10: Images / patches | M10: Human-driven survey | N10: Transverse, longitudinal, massive and alligator crack; crack pouring; raveling; repair; normal. | O10: Image/patch classification | P10: CC BY-NC 4.0 (current author HF release) | Q10: Public links | R10: 60,056 images in current dataset card; paper abstract says 60,059 | S10: Southern China highways | T10: Chongqing University / Wenhao Tang, Sheng Huang and collaborators | U10: Count discrepancy retained. Strong distress classification data but specialized top-down survey imagery, not conventional AV forward footage. | V10: DS-005; D023 | W10: Same dataset, authorized host | Y10: Legacy license alternatives are superseded for the chosen HF release by current CC BY-NC 4.0 card; original repository also limits use to noncommercial. | Z10: AV inventory evidence snapshot | AA10: =HYPERLINK("#'Manual_Review'!A"&(MATCH("DS-005",Manual_Review!$A$6:$A$238,0)+5),"Enter review") -> Enter review | AB10: =HYPERLINK("#'MCDM_Checks'!A"&(MATCH("DS-005",MCDM_Checks!$B$6:$B$3733,0)+5),"Check evidence") -> Check evidence | AC10: Hugging Face; GitHub | AD10: https://huggingface.co/datasets/Dearcat/CQU-BPDD | AE10: https://github.com/DearCaat/Pavement-Distress-Classification | AF10: Compared_All_Platforms_TH_v3.0.xlsx!All_Datasets row 6 (DS-005); AV_Pavement_Dataset_Inventory.xlsx!Datasets row 29 (D023)
A11: DS-006 | B11: Crack Classification Dataset (five crack types, 200 images) | D11: Labeled-16 | E11: =INDEX(MCDM_Grades!$E$6:$E$238,MATCH(A11,MCDM_Grades!$A$6:$A$238,0)) -> 50 | F11: =INDEX(MCDM_Grades!$F$6:$F$238,MATCH(A11,MCDM_Grades!$A$6:$A$238,0)) -> 100 | G11: =INDEX(MCDM_Grades!$G$6:$G$238,MATCH(A11,MCDM_Grades!$A$6:$A$238,0)) -> 0.5 | H11: =HYPERLINK("https://github.com/0110TJY/Crack-Classification-Dataset","Dataset") -> Dataset | I11: =HYPERLINK("https://github.com/0110TJY/Crack-Classification-Dataset","Evidence / paper") -> Evidence / paper | J11: v1 | K11: Classification | L11: Images/frames as reported | M11: Partly author-captured; partly compiled from CRACK500 and CrackForest | N11: Class-level labels (five types) | O11: Class-folder / zip structure | P11: NR | Q11: Direct_Download | R11: 200 | S11: Road environment: Pavements | U11: Partially derivative of CRACK500/CFD; very small; class names undocumented | V11: DS-006 | W11: Retained existing record | Z11: v3 evidence snapshot | AA11: =HYPERLINK("#'Manual_Review'!A"&(MATCH("DS-006",Manual_Review!$A$6:$A$238,0)+5),"Enter review") -> Enter review | AB11: =HYPERLINK("#'MCDM_Checks'!A"&(MATCH("DS-006",MCDM_Checks!$B$6:$B$3733,0)+5),"Check evidence") -> Check evidence | AC11: GitHub | AD11: https://github.com/0110TJY/Crack-Classification-Dataset | AE11: https://github.com/0110TJY/Crack-Classification-Dataset | AF11: Compared_All_Platforms_TH_v3.0.xlsx!All_Datasets row 7 (DS-006)
A12: DS-007 | B12: CRACK500 (Crack500) | C12: 2 | D12: Labeled-16 | E12: =INDEX(MCDM_Grades!$E$6:$E$238,MATCH(A12,MCDM_Grades!$A$6:$A$238,0)) -> 77.777778 | F12: =INDEX(MCDM_Grades!$F$6:$F$238,MATCH(A12,MCDM_Grades!$A$6:$A$238,0)) -> 100 | G12: =INDEX(MCDM_Grades!$G$6:$G$238,MATCH(A12,MCDM_Grades!$A$6:$A$238,0)) -> 0.77777778 | H12: =HYPERLINK("https://github.com/fyangneil/pavement-crack-detection","Dataset") -> Dataset | I12: =HYPERLINK("https://arxiv.org/abs/1901.06340","Evidence / paper") -> Evidence / paper | J12: FPHBN documented CRACK500 split, 2019 paper / author repository | K12: Semantic segmentation;Crack detection [Claude/GPT/Test_Batch] | crack segmentation; crack detection [GPT] | L12: Images/frames as reported | M12: Hand-held smartphone (cell phone) [Claude] | Cellphone cameras [GPT] | Handheld smartphone [GPT] | Smartphone camera [Test_Batch] | N12: Binary crack vs background [Claude] | Pixel-level pavement-crack masks [GPT] | crack pixels; background pixels [GPT] | crack pixel mask [Test_Batch] | O12: Binary mask images [Claude] | Images and pixel-level ground-truth masks; cropped derivatives also commonly distributed [GPT] | pixel masks [GPT/Test_Batch] | P12: NR | Q12: Direct_Download [Claude/GPT/Test_Batch] | Registration [GPT] | R12: 500 [Claude/GPT/Test_Batch] | 3368 [GPT] | S12: United States; Temple University main campus, Philadelphia, PA [Claude] | Temple University campus;Philadelphia;Pennsylvania [GPT] | Temple University campus, Philadelphia [GPT] | Temple University campus, Philadelphia, Pennsylvania [Test_Batch]; Road environment: Campus pavements [Claude] | Campus pavement surfaces [GPT] | Campus roads; asphalt; cement; gravel [GPT] | Campus roads [Test_Batch] | U12: No explicit license; single-location smartphone capture limits diversity; data hosted on Google Drive/OneDrive/Baidu (link liveness not independently re-tested) [Claude] | Kaggle is a mirror; original dataset predates the Kaggle upload, licensing is unclear on the mirror, and cropped-patch counts should not be confused with the 500 original images. [GPT] | Crack-only; campus-scale geography; sparse engineering metadata; download links are maintained through code repositories [GPT] | Small original set from one campus; later cropped-image totals should not be confused with unique source-image count. [Test_Batch] | V12: DS-007 | W12: Retained existing record | X12: Shared host; distinct data (DS-007, DS-018); Parent and noisy-mask derivative (DS-007, DS-062); Compiled crack ancestry (DS-007, DS-008, DS-011, DS-016, DS-142) | Y12: Repository bundles other datasets. Do not count companion corpora as CRACK500. Data terms and label QA remain unresolved. | Z12: Primary documentation checked | AA12: =HYPERLINK("#'Manual_Review'!A"&(MATCH("DS-007",Manual_Review!$A$6:$A$238,0)+5),"Enter review") -> Enter review | AB12: =HYPERLINK("#'MCDM_Checks'!A"&(MATCH("DS-007",MCDM_Checks!$B$6:$B$3733,0)+5),"Check evidence") -> Check evidence | AC12: GitHub; Kaggle | AD12: https://github.com/fyangneil/pavement-crack-detection | AE12: https://arxiv.org/abs/1901.06340 | AF12: Compared_All_Platforms_TH_v3.0.xlsx!All_Datasets row 8 (DS-007)
A13: DS-008 | B13: CrackForest Dataset (CFD) | D13: Labeled-16 | E13: =INDEX(MCDM_Grades!$E$6:$E$238,MATCH(A13,MCDM_Grades!$A$6:$A$238,0)) -> 69.444444 | F13: =INDEX(MCDM_Grades!$F$6:$F$238,MATCH(A13,MCDM_Grades!$A$6:$A$238,0)) -> 100 | G13: =INDEX(MCDM_Grades!$G$6:$G$238,MATCH(A13,MCDM_Grades!$A$6:$A$238,0)) -> 0.69444444 | H13: =HYPERLINK("https://github.com/cuilimeng/CrackForest-dataset","Dataset") -> Dataset | I13: =HYPERLINK("https://github.com/cuilimeng/CrackForest-dataset","Evidence / paper") -> Evidence / paper | J13: NR | K13: semantic segmentation; crack detection | L13: Images/frames as reported | M13: iPhone 5 smartphone camera | N13: crack contour; crack pixel mask | O13: Ground-truth contour images | P13: NR | Q13: Direct_Download | R13: 118 | S13: China; Beijing; Road environment: Urban | U13: Very small single-city benchmark and limited collection-condition metadata. | V13: DS-008 | W13: Retained existing record | X13: Compiled crack ancestry (DS-007, DS-008, DS-011, DS-016, DS-142) | Z13: v3 evidence snapshot | AA13: =HYPERLINK("#'Manual_Review'!A"&(MATCH("DS-008",Manual_Review!$A$6:$A$238,0)+5),"Enter review") -> Enter review | AB13: =HYPERLINK("#'MCDM_Checks'!A"&(MATCH("DS-008",MCDM_Checks!$B$6:$B$3733,0)+5),"Check evidence") -> Check evidence | AC13: GitHub | AD13: https://github.com/cuilimeng/CrackForest-dataset | AE13: https://github.com/cuilimeng/CrackForest-dataset | AF13: Compared_All_Platforms_TH_v3.0.xlsx!All_Datasets row 9 (DS-008)
A14: DS-009 | B14: CrackLS315 | D14: Labeled-16 | E14: =INDEX(MCDM_Grades!$E$6:$E$238,MATCH(A14,MCDM_Grades!$A$6:$A$238,0)) -> 41.666667 | F14: =INDEX(MCDM_Grades!$F$6:$F$238,MATCH(A14,MCDM_Grades!$A$6:$A$238,0)) -> 100 | G14: =INDEX(MCDM_Grades!$G$6:$G$238,MATCH(A14,MCDM_Grades!$A$6:$A$238,0)) -> 0.41666667 | H14: =HYPERLINK("https://github.com/qinnzou/DeepCrack","Dataset") -> Dataset | I14: =HYPERLINK("https://github.com/qinnzou/DeepCrack","Evidence / paper") -> Evidence / paper | J14: CrackLS315 | K14: semantic segmentation; crack detection | L14: Images/frames as reported | M14: Laser-illuminated line-array camera | N14: crack pixel mask | O14: Image-mask pairs | P14: NR | Q14: Direct_Download | R14: 315 | S14: Road environment: Road pavement | U14: Small crack-only dataset; 1 mm ground sampling distance is reported, but pixel resolution, navigation, location, license, and weather metadata are not reported. | V14: DS-009 | W14: Retained existing record | X14: Shared host; distinct data (DS-009, DS-013, DS-014) | Z14: v3 evidence snapshot | AA14: =HYPERLINK("#'Manual_Review'!A"&(MATCH("DS-009",Manual_Review!$A$6:$A$238,0)+5),"Enter review") -> Enter review | AB14: =HYPERLINK("#'MCDM_Checks'!A"&(MATCH("DS-009",MCDM_Checks!$B$6:$B$3733,0)+5),"Check evidence") -> Check evidence | AC14: GitHub | AD14: https://github.com/qinnzou/DeepCrack | AE14: https://github.com/qinnzou/DeepCrack | AF14: Compared_All_Platforms_TH_v3.0.xlsx!All_Datasets row 10 (DS-009)
A15: DS-010 | B15: Cracks and Potholes in Road Images Dataset (DNIT, Brazil) | D15: Labeled-16 | E15: =INDEX(MCDM_Grades!$E$6:$E$238,MATCH(A15,MCDM_Grades!$A$6:$A$238,0)) -> 58.333333 | F15: =INDEX(MCDM_Grades!$F$6:$F$238,MATCH(A15,MCDM_Grades!$A$6:$A$238,0)) -> 100 | G15: =INDEX(MCDM_Grades!$G$6:$G$238,MATCH(A15,MCDM_Grades!$A$6:$A$238,0)) -> 0.58333333 | H15: =HYPERLINK("https://data.mendeley.com/datasets/t576ydh9v8/4","Dataset") -> Dataset | I15: =HYPERLINK("https://data.mendeley.com/datasets/t576ydh9v8/4","Evidence / paper") -> Evidence / paper | J15: 4 | K15: Semantic segmentation;Defect detection [GPT] | classification; object detection [Test_Batch] | L15: Images/frames as reported | M15: DNIT road-survey imagery; platform NR | N15: Road;crack;pothole masks [GPT] | road; crack; pothole [Test_Batch] | O15: PNG binary masks | P15: CC BY 4.0 | Q15: Direct_Download | R15: 2235 | S15: Brazil; Espírito Santo;Rio Grande do Sul;Federal District; Road environment: Highways [GPT] | Roadway [Test_Batch] | U15: Images collected partly before project years, but qualifying dataset release is 2020; limited sensor and condition metadata [GPT] | Release year, formal license, exact annotation format, and authoritative count documentation remain unresolved. [Test_Batch] | V15: DS-010 | W15: Retained existing record | Z15: v3 evidence snapshot | AA15: =HYPERLINK("#'Manual_Review'!A"&(MATCH("DS-010",Manual_Review!$A$6:$A$238,0)+5),"Enter review") -> Enter review | AB15: =HYPERLINK("#'MCDM_Checks'!A"&(MATCH("DS-010",MCDM_Checks!$B$6:$B$3733,0)+5),"Check evidence") -> Check evidence | AC15: Mendeley Data; GitHub | AD15: https://data.mendeley.com/datasets/t576ydh9v8/4 | AE15: https://data.mendeley.com/datasets/t576ydh9v8/4 | AF15: Compared_All_Platforms_TH_v3.0.xlsx!All_Datasets row 11 (DS-010)
A16: DS-011 | B16: CrackSeg9k | C16: 5 | D16: Labeled-16 | E16: =INDEX(MCDM_Grades!$E$6:$E$238,MATCH(A16,MCDM_Grades!$A$6:$A$238,0)) -> 58.333333 | F16: =INDEX(MCDM_Grades!$F$6:$F$238,MATCH(A16,MCDM_Grades!$A$6:$A$238,0)) -> 100 | G16: =INDEX(MCDM_Grades!$G$6:$G$238,MATCH(A16,MCDM_Grades!$A$6:$A$238,0)) -> 0.58333333 | H16: =HYPERLINK("https://dataverse.harvard.edu/dataset.xhtml?persistentId=doi:10.7910/DVN/EGIEBY&version=4.0","Dataset") -> Dataset | I16: =HYPERLINK("https://arxiv.org/abs/2208.13054","Evidence / paper") -> Evidence / paper | J16: Author-recommended Dataverse V4, June 2024; release content requires reconciliation | K16: semantic segmentation | L16: NR | M16: Multiple source datasets | N16: crack pixel mask | O16: Image-mask pairs | P16: NR | Q16: Direct_Download | R16: NR | S16: Road environment: Roadway; mixed structures and materials | U16: Approximately 9,160 images are reported, but the corpus combines road and non-road crack sources and may duplicate underlying datasets. | V16: DS-011 | W16: Retained existing record | X16: Compiled crack ancestry (DS-007, DS-008, DS-011, DS-016, DS-142) | Y16: Shares parents with SDNET2018 and CRACK500 in this shortlist. Not an independent external test. V4 payload not inspected. | Z16: Primary documentation checked | AA16: =HYPERLINK("#'Manual_Review'!A"&(MATCH("DS-011",Manual_Review!$A$6:$A$238,0)+5),"Enter review") -> Enter review | AB16: =HYPERLINK("#'MCDM_Checks'!A"&(MATCH("DS-011",MCDM_Checks!$B$6:$B$3733,0)+5),"Check evidence") -> Check evidence | AC16: Other official / repository; GitHub | AD16: https://dataverse.harvard.edu/dataset.xhtml?persistentId=doi:10.7910/DVN/EGIEBY&version=4.0 | AE16: https://arxiv.org/abs/2208.13054 | AF16: Compared_All_Platforms_TH_v3.0.xlsx!All_Datasets row 12 (DS-011)
A17: DS-012 | B17: CrackTrans (pavement crack dataset with complex backgrounds) | D17: Labeled-16 | E17: =INDEX(MCDM_Grades!$E$6:$E$238,MATCH(A17,MCDM_Grades!$A$6:$A$238,0)) -> 44.444444 | F17: =INDEX(MCDM_Grades!$F$6:$F$238,MATCH(A17,MCDM_Grades!$A$6:$A$238,0)) -> 100 | G17: =INDEX(MCDM_Grades!$G$6:$G$238,MATCH(A17,MCDM_Grades!$A$6:$A$238,0)) -> 0.44444444 | H17: =HYPERLINK("https://github.com/JZhongUTK/Pavement-crack-dataset","Dataset") -> Dataset | I17: =HYPERLINK("https://github.com/JZhongUTK/Pavement-crack-dataset","Evidence / paper") -> Evidence / paper | J17: v1 | K17: Semantic segmentation;Data augmentation research | L17: Images/frames as reported | M17: Smartphone | N17: Pixel-level crack ground truth | O17: Ground-truth masks | P17: NR ('released for public use' per README) | Q17: Direct_Download | R17: 455 | S17: Road environment: Pavements incl. shadow, wet, night, and grooved surfaces | U17: Small dataset (455 images); collection location not stated; Google Drive hosting (link liveness not independently re-tested) | V17: DS-012 | W17: Retained existing record | Z17: v3 evidence snapshot | AA17: =HYPERLINK("#'Manual_Review'!A"&(MATCH("DS-012",Manual_Review!$A$6:$A$238,0)+5),"Enter review") -> Enter review | AB17: =HYPERLINK("#'MCDM_Checks'!A"&(MATCH("DS-012",MCDM_Checks!$B$6:$B$3733,0)+5),"Check evidence") -> Check evidence | AC17: GitHub | AD17: https://github.com/JZhongUTK/Pavement-crack-dataset | AE17: https://github.com/JZhongUTK/Pavement-crack-dataset | AF17: Compared_All_Platforms_TH_v3.0.xlsx!All_Datasets row 13 (DS-012)
A18: DS-013 | B18: CrackTree260 | D18: Labeled-16 | E18: =INDEX(MCDM_Grades!$E$6:$E$238,MATCH(A18,MCDM_Grades!$A$6:$A$238,0)) -> 61.111111 | F18: =INDEX(MCDM_Grades!$F$6:$F$238,MATCH(A18,MCDM_Grades!$A$6:$A$238,0)) -> 100 | G18: =INDEX(MCDM_Grades!$G$6:$G$238,MATCH(A18,MCDM_Grades!$A$6:$A$238,0)) -> 0.61111111 | H18: =HYPERLINK("https://github.com/qinnzou/DeepCrack","Dataset") -> Dataset | I18: =HYPERLINK("https://github.com/qinnzou/DeepCrack","Evidence / paper") -> Evidence / paper | J18: CrackTree260 | K18: semantic segmentation; crack detection | L18: Images/frames as reported | M18: Visible-light area-array camera | N18: crack pixel mask | O18: Image-mask pairs | P18: NR | Q18: Direct_Download | R18: 260 | S18: Road environment: Road pavement | U18: Small, crack-only dataset; location, license, and detailed environmental metadata are not reported. | V18: DS-013 | W18: Retained existing record | X18: Shared host; distinct data (DS-009, DS-013, DS-014) | Z18: v3 evidence snapshot | AA18: =HYPERLINK("#'Manual_Review'!A"&(MATCH("DS-013",Manual_Review!$A$6:$A$238,0)+5),"Enter review") -> Enter review | AB18: =HYPERLINK("#'MCDM_Checks'!A"&(MATCH("DS-013",MCDM_Checks!$B$6:$B$3733,0)+5),"Check evidence") -> Check evidence | AC18: GitHub | AD18: https://github.com/qinnzou/DeepCrack | AE18: https://github.com/qinnzou/DeepCrack | AF18: Compared_All_Platforms_TH_v3.0.xlsx!All_Datasets row 14 (DS-013)
A19: DS-014 | B19: CRKWH100 | D19: Labeled-16 | E19: =INDEX(MCDM_Grades!$E$6:$E$238,MATCH(A19,MCDM_Grades!$A$6:$A$238,0)) -> 50 | F19: =INDEX(MCDM_Grades!$F$6:$F$238,MATCH(A19,MCDM_Grades!$A$6:$A$238,0)) -> 100 | G19: =INDEX(MCDM_Grades!$G$6:$G$238,MATCH(A19,MCDM_Grades!$A$6:$A$238,0)) -> 0.5 | H19: =HYPERLINK("https://github.com/qinnzou/DeepCrack","Dataset") -> Dataset | I19: =HYPERLINK("https://github.com/qinnzou/DeepCrack","Evidence / paper") -> Evidence / paper | J19: CRKWH100 | K19: semantic segmentation; crack detection | L19: Images/frames as reported | M19: Visible-light line-array camera | N19: crack pixel mask | O19: Image-mask pairs | P19: NR | Q19: Direct_Download | R19: 100 | S19: Road environment: Road pavement | U19: Very small crack-only dataset; 1 mm ground sampling distance is reported, but pixel resolution, navigation, location, license, and environmental metadata are not reported. | V19: DS-014 | W19: Retained existing record | X19: Shared host; distinct data (DS-009, DS-013, DS-014) | Z19: v3 evidence snapshot | AA19: =HYPERLINK("#'Manual_Review'!A"&(MATCH("DS-014",Manual_Review!$A$6:$A$238,0)+5),"Enter review") -> Enter review | AB19: =HYPERLINK("#'MCDM_Checks'!A"&(MATCH("DS-014",MCDM_Checks!$B$6:$B$3733,0)+5),"Check evidence") -> Check evidence | AC19: GitHub | AD19: https://github.com/qinnzou/DeepCrack | AE19: https://github.com/qinnzou/DeepCrack | AF19: Compared_All_Platforms_TH_v3.0.xlsx!All_Datasets row 15 (DS-014)
A20: DS-015 | B20: CUBIT-Det | D20: Labeled-16 | E20: =INDEX(MCDM_Grades!$E$6:$E$238,MATCH(A20,MCDM_Grades!$A$6:$A$238,0)) -> 77.777778 | F20: =INDEX(MCDM_Grades!$F$6:$F$238,MATCH(A20,MCDM_Grades!$A$6:$A$238,0)) -> 100 | G20: =INDEX(MCDM_Grades!$G$6:$G$238,MATCH(A20,MCDM_Grades!$A$6:$A$238,0)) -> 0.77777778 | H20: =HYPERLINK("https://github.com/CUHK-USR-Group/Defect-Dataset","Dataset") -> Dataset | I20: =HYPERLINK("https://github.com/CUHK-USR-Group/Defect-Dataset","Evidence / paper") -> Evidence / paper | J20: 2024 | K20: defect detection; UAV infrastructure inspection | L20: Images/frames as reported | M20: UAV onboard cameras | N20: crack; spalling; moisture; building; pavement; bridge | O20: bounding boxes | P20: NR | Q20: Registration | R20: 5527 | S20: China; Hong Kong; Road environment: Mixed infrastructure; pavement subset | U20: Only 29% pavement; mixed defect/infrastructure taxonomy; access code required | V20: DS-015 | W20: Retained existing record | Z20: v3 evidence snapshot | AA20: =HYPERLINK("#'Manual_Review'!A"&(MATCH("DS-015",Manual_Review!$A$6:$A$238,0)+5),"Enter review") -> Enter review | AB20: =HYPERLINK("#'MCDM_Checks'!A"&(MATCH("DS-015",MCDM_Checks!$B$6:$B$3733,0)+5),"Check evidence") -> Check evidence | AC20: GitHub | AD20: https://github.com/CUHK-USR-Group/Defect-Dataset | AE20: https://github.com/CUHK-USR-Group/Defect-Dataset | AF20: Compared_All_Platforms_TH_v3.0.xlsx!All_Datasets row 16 (DS-015)
A21: DS-016 | B21: DeepCrack-537 | D21: Labeled-16 | E21: =INDEX(MCDM_Grades!$E$6:$E$238,MATCH(A21,MCDM_Grades!$A$6:$A$238,0)) -> 61.111111 | F21: =INDEX(MCDM_Grades!$F$6:$F$238,MATCH(A21,MCDM_Grades!$A$6:$A$238,0)) -> 100 | G21: =INDEX(MCDM_Grades!$G$6:$G$238,MATCH(A21,MCDM_Grades!$A$6:$A$238,0)) -> 0.61111111 | H21: =HYPERLINK("https://github.com/yhlleo/DeepCrack","Dataset") -> Dataset | I21: =HYPERLINK("https://github.com/yhlleo/DeepCrack","Evidence / paper") -> Evidence / paper | J21: 537-image benchmark | K21: semantic segmentation; crack detection | L21: Images/frames as reported | M21: Mixed cameras | N21: crack pixel mask | O21: Image-mask pairs | P21: NR | Q21: Direct_Download | R21: 537 | S21: Road environment: Roadway; mixed crack scenes | U21: Contains mixed crack scenes/materials rather than a strictly pavement-only corpus; noncommercial-use restriction. | V21: DS-016 | W21: Retained existing record | X21: Compiled crack ancestry (DS-007, DS-008, DS-011, DS-016, DS-142) | Z21: v3 evidence snapshot | AA21: =HYPERLINK("#'Manual_Review'!A"&(MATCH("DS-016",Manual_Review!$A$6:$A$238,0)+5),"Enter review") -> Enter review | AB21: =HYPERLINK("#'MCDM_Checks'!A"&(MATCH("DS-016",MCDM_Checks!$B$6:$B$3733,0)+5),"Check evidence") -> Check evidence | AC21: GitHub | AD21: https://github.com/yhlleo/DeepCrack | AE21: https://github.com/yhlleo/DeepCrack | AF21: Compared_All_Platforms_TH_v3.0.xlsx!All_Datasets row 17 (DS-016)
A22: DS-017 | B22: EdmCrack600 | D22: Labeled-16 | E22: =INDEX(MCDM_Grades!$E$6:$E$238,MATCH(A22,MCDM_Grades!$A$6:$A$238,0)) -> 44.444444 | F22: =INDEX(MCDM_Grades!$F$6:$F$238,MATCH(A22,MCDM_Grades!$A$6:$A$238,0)) -> 100 | G22: =INDEX(MCDM_Grades!$G$6:$G$238,MATCH(A22,MCDM_Grades!$A$6:$A$238,0)) -> 0.44444444 | H22: =HYPERLINK("https://github.com/mqp2259/EdmCrack600","Dataset") -> Dataset | I22: =HYPERLINK("https://github.com/mqp2259/EdmCrack600","Evidence / paper") -> Evidence / paper | J22: 2020; EdmCrack600 | K22: Distress / roughness | L22: Images / patches | M22: Other / mixed capture | N22: Crack/background. | O22: Pixel-level masks | P22: Academic use; commercial use prohibited by authors. | Q22: Public links | R22: 600 images | S22: Edmonton, Canada | T22: Qipei Mei, Mustafa Gül and collaborators | U22: Useful supplemental crack segmentation set; also partly reused by Pothole Mix. Do not interpret as verified AV footage. | V22: DS-017; D024 | W22: Same release | Z22: AV inventory evidence snapshot | AA22: =HYPERLINK("#'Manual_Review'!A"&(MATCH("DS-017",Manual_Review!$A$6:$A$238,0)+5),"Enter review") -> Enter review | AB22: =HYPERLINK("#'MCDM_Checks'!A"&(MATCH("DS-017",MCDM_Checks!$B$6:$B$3733,0)+5),"Check evidence") -> Check evidence | AC22: GitHub | AD22: https://github.com/mqp2259/EdmCrack600 | AE22: https://github.com/mqp2259/EdmCrack600 | AF22: Compared_All_Platforms_TH_v3.0.xlsx!All_Datasets row 18 (DS-017); AV_Pavement_Dataset_Inventory.xlsx!Datasets row 30 (D024)
A23: DS-018 | B23: GAPs384 | D23: Labeled-16 | E23: =INDEX(MCDM_Grades!$E$6:$E$238,MATCH(A23,MCDM_Grades!$A$6:$A$238,0)) -> 75 | F23: =INDEX(MCDM_Grades!$F$6:$F$238,MATCH(A23,MCDM_Grades!$A$6:$A$238,0)) -> 100 | G23: =INDEX(MCDM_Grades!$G$6:$G$238,MATCH(A23,MCDM_Grades!$A$6:$A$238,0)) -> 0.75 | H23: =HYPERLINK("https://github.com/fyangneil/pavement-crack-detection","Dataset") -> Dataset | I23: =HYPERLINK("https://github.com/fyangneil/pavement-crack-detection","Evidence / paper") -> Evidence / paper | J23: 384-image pixel-annotated subset [GPT] | GAPs384 [Test_Batch] | K23: crack segmentation [GPT] | semantic segmentation; crack detection [Test_Batch] | L23: Images/frames as reported | M23: Professional pavement inspection imagery derived from GAPs [GPT] | Road inspection camera [Test_Batch] | N23: crack pixels; background pixels [GPT] | crack pixel mask [Test_Batch] | O23: pixel masks | P23: NR | Q23: Direct_Download | R23: 384 | S23: Germany; Road environment: Asphalt pavement [GPT] | Roadway [Test_Batch] | U23: Small crack-only subset; limited geographic and collection metadata [GPT] | Small crack-only benchmark; license, detailed weather, and vehicle metadata are not clearly documented. [Test_Batch] | V23: DS-018 | W23: Retained existing record | X23: Shared host; distinct data (DS-007, DS-018); GAPs family; distinct releases (DS-018, DS-193, DS-194) | Z23: v3 evidence snapshot | AA23: =HYPERLINK("#'Manual_Review'!A"&(MATCH("DS-018",Manual_Review!$A$6:$A$238,0)+5),"Enter review") -> Enter review | AB23: =HYPERLINK("#'MCDM_Checks'!A"&(MATCH("DS-018",MCDM_Checks!$B$6:$B$3733,0)+5),"Check evidence") -> Check evidence | AC23: GitHub | AD23: https://github.com/fyangneil/pavement-crack-detection | AE23: https://github.com/fyangneil/pavement-crack-detection | AF23: Compared_All_Platforms_TH_v3.0.xlsx!All_Datasets row 19 (DS-018)
A24: DS-019 | B24: GeoPave-DroneSet (UAV pavement distress dataset, DronePave-DfineX) | D24: Labeled-16 | E24: =INDEX(MCDM_Grades!$E$6:$E$238,MATCH(A24,MCDM_Grades!$A$6:$A$238,0)) -> 16.666667 | F24: =INDEX(MCDM_Grades!$F$6:$F$238,MATCH(A24,MCDM_Grades!$A$6:$A$238,0)) -> 94.444444 | G24: =INDEX(MCDM_Grades!$G$6:$G$238,MATCH(A24,MCDM_Grades!$A$6:$A$238,0)) -> 0.22222222 | H24: =HYPERLINK("https://github.com/chenxiang-web/DronePave-DfineX","Dataset") -> Dataset | I24: =HYPERLINK("https://github.com/chenxiang-web/DronePave-DfineX","Evidence / paper") -> Evidence / paper | J24: Partial preview (full release pending paper acceptance) | K24: Object detection | L24: NR | M24: UAV (full-resolution imagery) | N24: Annotated atop full-resolution images (details NR) | O24: NR | P24: NR | Q24: Metadata_Only | R24: NR | S24: Road environment: Pavements with complex backgrounds (UAV inspection) | U24: Complete dataset to be released only after paper acceptance; only sample images available; re-check for release | V24: DS-019 | W24: Retained existing record | Z24: v3 evidence snapshot | AA24: =HYPERLINK("#'Manual_Review'!A"&(MATCH("DS-019",Manual_Review!$A$6:$A$238,0)+5),"Enter review") -> Enter review | AB24: =HYPERLINK("#'MCDM_Checks'!A"&(MATCH("DS-019",MCDM_Checks!$B$6:$B$3733,0)+5),"Check evidence") -> Check evidence | AC24: GitHub | AD24: https://github.com/chenxiang-web/DronePave-DfineX | AE24: https://github.com/chenxiang-web/DronePave-DfineX | AF24: Compared_All_Platforms_TH_v3.0.xlsx!All_Datasets row 20 (DS-019)
A25: DS-020 | B25: Highway Crack and Sealed-Crack Dataset (CHDyshli) | D25: Labeled-16 | E25: =INDEX(MCDM_Grades!$E$6:$E$238,MATCH(A25,MCDM_Grades!$A$6:$A$238,0)) -> 52.777778 | F25: =INDEX(MCDM_Grades!$F$6:$F$238,MATCH(A25,MCDM_Grades!$A$6:$A$238,0)) -> 100 | G25: =INDEX(MCDM_Grades!$G$6:$G$238,MATCH(A25,MCDM_Grades!$A$6:$A$238,0)) -> 0.52777778 | H25: =HYPERLINK("https://github.com/CHDyshli/PavementCrackDetection","Dataset") -> Dataset | I25: =HYPERLINK("https://github.com/CHDyshli/PavementCrackDetection","Evidence / paper") -> Evidence / paper | J25: NR | K25: object detection | L25: Images/frames as reported | M25: Highway condition monitoring vehicle [GPT] | Highway pavement-condition monitoring vehicle [Test_Batch] | N25: crack; sealed crack | O25: NR | P25: NR | Q25: Direct_Download | R25: 10400 | S25: China; Road environment: Highway asphalt pavement [GPT] | Highway [Test_Batch] | U25: Only two target classes; license, geography, resolution, and collection dates not reported in README [GPT] | Release year, geography, image resolution, license, and annotation format are unresolved despite strong reported scale. [Test_Batch] | V25: DS-020 | W25: Retained existing record | Z25: v3 evidence snapshot | AA25: =HYPERLINK("#'Manual_Review'!A"&(MATCH("DS-020",Manual_Review!$A$6:$A$238,0)+5),"Enter review") -> Enter review | AB25: =HYPERLINK("#'MCDM_Checks'!A"&(MATCH("DS-020",MCDM_Checks!$B$6:$B$3733,0)+5),"Check evidence") -> Check evidence | AC25: GitHub | AD25: https://github.com/CHDyshli/PavementCrackDetection | AE25: https://github.com/CHDyshli/PavementCrackDetection | AF25: Compared_All_Platforms_TH_v3.0.xlsx!All_Datasets row 21 (DS-020)
A26: DS-021 | B26: IRRDD (Iran Road Damage Dataset) | D26: Labeled-16 | E26: =INDEX(MCDM_Grades!$E$6:$E$238,MATCH(A26,MCDM_Grades!$A$6:$A$238,0)) -> 47.222222 | F26: =INDEX(MCDM_Grades!$F$6:$F$238,MATCH(A26,MCDM_Grades!$A$6:$A$238,0)) -> 100 | G26: =INDEX(MCDM_Grades!$G$6:$G$238,MATCH(A26,MCDM_Grades!$A$6:$A$238,0)) -> 0.47222222 | H26: =HYPERLINK("https://github.com/IranRoadDamageDataset/IRRDD","Dataset") -> Dataset | I26: =HYPERLINK("https://github.com/IranRoadDamageDataset/IRRDD","Evidence / paper") -> Evidence / paper | J26: 2022 release | K26: Object detection | L26: Images/frames as reported | M26: NR | N26: RDD-style four-class taxonomy (D00/D10/D20/D40) | O26: YOLO txt | P26: NR | Q26: Direct_Download | R26: 25000 | S26: Iran; Road environment: Public roads | U26: No associated peer-reviewed data paper identified; collection platform and QC undocumented; 6-part Google Drive hosting (link liveness not independently re-tested) | V26: DS-021 | W26: Retained existing record | Z26: v3 evidence snapshot | AA26: =HYPERLINK("#'Manual_Review'!A"&(MATCH("DS-021",Manual_Review!$A$6:$A$238,0)+5),"Enter review") -> Enter review | AB26: =HYPERLINK("#'MCDM_Checks'!A"&(MATCH("DS-021",MCDM_Checks!$B$6:$B$3733,0)+5),"Check evidence") -> Check evidence | AC26: GitHub | AD26: https://github.com/IranRoadDamageDataset/IRRDD | AE26: https://github.com/IranRoadDamageDataset/IRRDD | AF26: Compared_All_Platforms_TH_v3.0.xlsx!All_Datasets row 22 (DS-021)
A27: DS-022 | B27: IRT Asphalt Pavement Crack Segmentation Dataset (RGB + Infrared + Fusion) | D27: Labeled-16 | E27: =INDEX(MCDM_Grades!$E$6:$E$238,MATCH(A27,MCDM_Grades!$A$6:$A$238,0)) -> 75 | F27: =INDEX(MCDM_Grades!$F$6:$F$238,MATCH(A27,MCDM_Grades!$A$6:$A$238,0)) -> 100 | G27: =INDEX(MCDM_Grades!$G$6:$G$238,MATCH(A27,MCDM_Grades!$A$6:$A$238,0)) -> 0.75 | H27: =HYPERLINK("https://github.com/lfangyu09/IR-Crack-detection","Dataset") -> Dataset | I27: =HYPERLINK("https://github.com/lfangyu09/IR-Crack-detection","Evidence / paper") -> Evidence / paper | J27: Zenodo record 11624965 [Claude] | v1 [CodeX] | K27: Semantic segmentation;RGB-T multimodal fusion [Claude] | Semantic_Segmentation;Multimodal_Fusion [Claude] | Semantic segmentation [CodeX] | multimodal semantic segmentation; crack detection [Test_Batch] | L27: Images/frames as reported | M27: Infrared thermography camera (visible + infrared + IR-Fusion imagery) [Claude] | Vehicle_Mounted_Camera [Claude] | Visible camera; Infrared thermography [CodeX] | Aligned visible and infrared camera system [Test_Batch] | N27: Manually annotated crack ground truth (Photoshop) [Claude] | Binary ground-truth images (crack vs background) paired with visible, infrared and 50 percent fusion imagery [Claude] | Binary ground truth masks [CodeX] | crack pixel mask [Test_Batch] | O27: Ground-truth mask images [Claude] | Binary_Image_Mask [Claude] | ZIP; Binary images [CodeX] | Aligned RGB; thermal infrared; pixel masks [Test_Batch] | P27: NR (Zenodo record license not re-verified in this batch) [Claude] | CC-BY-4.0 [Claude] | Creative Commons Attribution 4.0 International [CodeX] | Q27: Direct_Download [Claude/CodeX] | UNK [Test_Batch] | R27: 448 [Claude] | 369 [CodeX] | S27: United States; Road environment: Asphalt pavements; clean and rough, light and dark backgrounds; three periods in one day [Claude] | Asphalt pavement [CodeX] | Roadway [Test_Batch] | U27: 448 image sets (small); acquisition location not stated; Release_Year taken from associated T-ITS paper year (Zenodo deposit 2024, not separately versioned here) [Claude] | Image count, resolution and collection geography not reported in the Zenodo record; single distress class (crack); performance figures live in the journal article rather than the data record [Claude] | Image count, resolution, site, and explicit QA process are not reported on the Zenodo record. [CodeX] | Dataset identity, data-access route, count, license, and collection geography require resolution beyond the model repository. [Test_Batch] | V27: DS-022 | W27: Retained existing record | X27: Related infrared dataset releases (DS-022, DS-023, DS-113, DS-114) | Z27: v3 evidence snapshot | AA27: =HYPERLINK("#'Manual_Review'!A"&(MATCH("DS-022",Manual_Review!$A$6:$A$238,0)+5),"Enter review") -> Enter review | AB27: =HYPERLINK("#'MCDM_Checks'!A"&(MATCH("DS-022",MCDM_Checks!$B$6:$B$3733,0)+5),"Check evidence") -> Check evidence | AC27: GitHub; Zenodo | AD27: https://github.com/lfangyu09/IR-Crack-detection | AE27: https://github.com/lfangyu09/IR-Crack-detection | AF27: Compared_All_Platforms_TH_v3.0.xlsx!All_Datasets row 23 (DS-022)
A28: DS-023 | B28: IRT Multiple-Type Pavement Distress Detection Dataset (Infrared Thermography) | D28: Labeled-16 | E28: =INDEX(MCDM_Grades!$E$6:$E$238,MATCH(A28,MCDM_Grades!$A$6:$A$238,0)) -> 36.111111 | F28: =INDEX(MCDM_Grades!$F$6:$F$238,MATCH(A28,MCDM_Grades!$A$6:$A$238,0)) -> 100 | G28: =INDEX(MCDM_Grades!$G$6:$G$238,MATCH(A28,MCDM_Grades!$A$6:$A$238,0)) -> 0.36111111 | H28: =HYPERLINK("https://github.com/lfangyu09/IR-Crack-detection","Dataset") -> Dataset | I28: =HYPERLINK("https://github.com/lfangyu09/IR-Crack-detection","Evidence / paper") -> Evidence / paper | J28: Zenodo record 11638443 | K28: Object detection;Multimodal (RGB + thermal) learning [Claude] | Object_Detection;Multimodal_Fusion [Claude] | L28: NR | M28: Infrared thermography camera (visible + infrared imagery) [Claude] | Vehicle_Mounted_Camera [Claude] | N28: Multi-type distress detection labels [Claude] | PASCAL VOC object classes across visible, infrared and three visible/infrared fusion levels (25/50/75 percent IRT) [Claude] | O28: PASCAL_VOC_XML | P28: NR (Zenodo record license not re-verified in this batch) [Claude] | CC-BY-4.0 [Claude] | Q28: Direct_Download | R28: NR | S28: United States; Road environment: Asphalt concrete pavement | U28: Image count, class list, and format not stated in README (NR); niche thermographic modality [Claude] | Image count, resolution and collection geography not reported in the Zenodo record; class list not enumerated on the landing page; performance figures live in the journal article rather than the data record [Claude] | V28: DS-023 | W28: Retained existing record | X28: Related infrared dataset releases (DS-022, DS-023, DS-113, DS-114) | Z28: v3 evidence snapshot | AA28: =HYPERLINK("#'Manual_Review'!A"&(MATCH("DS-023",Manual_Review!$A$6:$A$238,0)+5),"Enter review") -> Enter review | AB28: =HYPERLINK("#'MCDM_Checks'!A"&(MATCH("DS-023",MCDM_Checks!$B$6:$B$3733,0)+5),"Check evidence") -> Check evidence | AC28: GitHub; Zenodo | AD28: https://github.com/lfangyu09/IR-Crack-detection | AE28: https://github.com/lfangyu09/IR-Crack-detection | AF28: Compared_All_Platforms_TH_v3.0.xlsx!All_Datasets row 24 (DS-023)
A29: DS-024 | B29: Kansas City LCMS Pavement Distress Dataset (Image2PCI) | D29: Labeled-16 | E29: =INDEX(MCDM_Grades!$E$6:$E$238,MATCH(A29,MCDM_Grades!$A$6:$A$238,0)) -> 38.888889 | F29: =INDEX(MCDM_Grades!$F$6:$F$238,MATCH(A29,MCDM_Grades!$A$6:$A$238,0)) -> 100 | G29: =INDEX(MCDM_Grades!$G$6:$G$238,MATCH(A29,MCDM_Grades!$A$6:$A$238,0)) -> 0.38888889 | H29: =HYPERLINK("https://github.com/neemajakisa/Pavement-Distress-Dataset","Dataset") -> Dataset | I29: =HYPERLINK("https://github.com/neemajakisa/Pavement-Distress-Dataset","Evidence / paper") -> Evidence / paper | J29: v1 | K29: Segmentation;PCI estimation model training/benchmarking [Claude] | instance segmentation; distress classification; severity estimation; PCI prediction [GPT] | instance segmentation; PCI estimation [Test_Batch] | L29: NR | M29: Laser Crack Measurement System (LCMS) survey vehicle [Claude] | Laser Crack Measurement System inspection vehicle [GPT] | LCMS pavement survey vehicle [Test_Batch] | N29: Polygon annotations combining crack type and severity (PCI-aligned) [Claude] | distress type; severity [GPT] | distress type; distress severity [Test_Batch] | O29: JSON annotation files [Claude] | JSON polygon annotations [GPT/Test_Batch] | P29: NR | Q29: Direct_Download | R29: NR | S29: United States; Kansas City, Missouri; Road environment: Public roads (top-down pavement surface views) [Claude] | Urban roadway [GPT] | Urban [Test_Batch] | U29: Image count not reported in README (NR); LCMS imagery differs from CAV camera viewpoint; Google Drive folder hosting (link liveness not independently re-tested) [Claude] | Image count, image resolution, license, and collection dates not reported on the repository landing page [GPT] | Image count, formal license, collection dates, and explicit PCI ground-truth fields are not reported in the README. [Test_Batch] | V29: DS-024 | W29: Retained existing record | Z29: v3 evidence snapshot | AA29: =HYPERLINK("#'Manual_Review'!A"&(MATCH("DS-024",Manual_Review!$A$6:$A$238,0)+5),"Enter review") -> Enter review | AB29: =HYPERLINK("#'MCDM_Checks'!A"&(MATCH("DS-024",MCDM_Checks!$B$6:$B$3733,0)+5),"Check evidence") -> Check evidence | AC29: GitHub | AD29: https://github.com/neemajakisa/Pavement-Distress-Dataset | AE29: https://github.com/neemajakisa/Pavement-Distress-Dataset | AF29: Compared_All_Platforms_TH_v3.0.xlsx!All_Datasets row 25 (DS-024)
A30: DS-025 | B30: LEiS pavement crack image dataset | D30: Labeled-16 | E30: =INDEX(MCDM_Grades!$E$6:$E$238,MATCH(A30,MCDM_Grades!$A$6:$A$238,0)) -> 11.111111 | F30: =INDEX(MCDM_Grades!$F$6:$F$238,MATCH(A30,MCDM_Grades!$A$6:$A$238,0)) -> 100 | G30: =INDEX(MCDM_Grades!$G$6:$G$238,MATCH(A30,MCDM_Grades!$A$6:$A$238,0)) -> 0.11111111 | H30: =HYPERLINK("https://github.com/DrEdwardLee/Pavement-Crack-Dataset","Dataset") -> Dataset | I30: =HYPERLINK("https://github.com/DrEdwardLee/Pavement-Crack-Dataset","Evidence / paper") -> Evidence / paper | J30: v1 (in-repo rar archive) | K30: Crack detection (per repo description) | L30: NR | M30: NR | N30: UNK (no README; annotation presence not verifiable from file listing) | O30: NR | P30: NR | Q30: Direct_Download | R30: NR | S30: Road environment: Pavements | U30: No README or documentation; annotations, counts, provenance, and license all unverified (data stored as LEiS-Data.rar in repo) | V30: DS-025 | W30: Retained existing record | X30: Same acquisition lineage; different archives/releases (DS-003, DS-025, DS-090) | Z30: v3 evidence snapshot | AA30: =HYPERLINK("#'Manual_Review'!A"&(MATCH("DS-025",Manual_Review!$A$6:$A$238,0)+5),"Enter review") -> Enter review | AB30: =HYPERLINK("#'MCDM_Checks'!A"&(MATCH("DS-025",MCDM_Checks!$B$6:$B$3733,0)+5),"Check evidence") -> Check evidence | AC30: GitHub | AD30: https://github.com/DrEdwardLee/Pavement-Crack-Dataset | AE30: https://github.com/DrEdwardLee/Pavement-Crack-Dataset | AF30: Compared_All_Platforms_TH_v3.0.xlsx!All_Datasets row 26 (DS-025)
A31: DS-026 | B31: MTPDSD (Multi-Type Pavement Distress Segmentation Dataset) | D31: Labeled-16 | E31: =INDEX(MCDM_Grades!$E$6:$E$238,MATCH(A31,MCDM_Grades!$A$6:$A$238,0)) -> 25 | F31: =INDEX(MCDM_Grades!$F$6:$F$238,MATCH(A31,MCDM_Grades!$A$6:$A$238,0)) -> 94.444444 | G31: =INDEX(MCDM_Grades!$G$6:$G$238,MATCH(A31,MCDM_Grades!$A$6:$A$238,0)) -> 0.30555556 | H31: =HYPERLINK("https://github.com/FwDeng/MTPDSD","Dataset") -> Dataset | I31: =HYPERLINK("https://github.com/FwDeng/MTPDSD","Evidence / paper") -> Evidence / paper | J31: Announced (not yet released) | K31: Instance segmentation | L31: Images/frames as reported | M31: Vehicle-mounted system: dashboard wide-angle camera + rear-view high-resolution camera | N31: Instance segmentation masks; 3,596 labeled instances across 7 categories | O31: NR | P31: NR | Q31: Metadata_Only | R31: 2600 | S31: Road environment: Pavements (vehicle-mounted collection) | U31: Data not yet released ('will be made available soon'); re-check for release before final synthesis | V31: DS-026 | W31: Retained existing record | Z31: v3 evidence snapshot | AA31: =HYPERLINK("#'Manual_Review'!A"&(MATCH("DS-026",Manual_Review!$A$6:$A$238,0)+5),"Enter review") -> Enter review | AB31: =HYPERLINK("#'MCDM_Checks'!A"&(MATCH("DS-026",MCDM_Checks!$B$6:$B$3733,0)+5),"Check evidence") -> Check evidence | AC31: GitHub | AD31: https://github.com/FwDeng/MTPDSD | AE31: https://github.com/FwDeng/MTPDSD | AF31: Compared_All_Platforms_TH_v3.0.xlsx!All_Datasets row 27 (DS-026)
A32: DS-027 | B32: NightInspect (low-light pavement crack dataset) | D32: Labeled-16 | E32: =INDEX(MCDM_Grades!$E$6:$E$238,MATCH(A32,MCDM_Grades!$A$6:$A$238,0)) -> 11.111111 | F32: =INDEX(MCDM_Grades!$F$6:$F$238,MATCH(A32,MCDM_Grades!$A$6:$A$238,0)) -> 100 | G32: =INDEX(MCDM_Grades!$G$6:$G$238,MATCH(A32,MCDM_Grades!$A$6:$A$238,0)) -> 0.11111111 | H32: =HYPERLINK("https://github.com/FXBIOVELSY/NightInspect-dataset","Dataset") -> Dataset | I32: =HYPERLINK("https://github.com/FXBIOVELSY/NightInspect-dataset","Evidence / paper") -> Evidence / paper | J32: v1 | K32: Crack detection;Low-light image enhancement | L32: NR | M32: NR | N32: NR | O32: NR | P32: NR | Q32: Restricted | R32: NR | S32: Road environment: Nighttime pavements (low-light) | U32: Counts, labels, and license undocumented; Quark drive hosting limits accessibility; paper status unresolved | V32: DS-027 | W32: Retained existing record | Z32: v3 evidence snapshot | AA32: =HYPERLINK("#'Manual_Review'!A"&(MATCH("DS-027",Manual_Review!$A$6:$A$238,0)+5),"Enter review") -> Enter review | AB32: =HYPERLINK("#'MCDM_Checks'!A"&(MATCH("DS-027",MCDM_Checks!$B$6:$B$3733,0)+5),"Check evidence") -> Check evidence | AC32: GitHub | AD32: https://github.com/FXBIOVELSY/NightInspect-dataset | AE32: https://github.com/FXBIOVELSY/NightInspect-dataset | AF32: Compared_All_Platforms_TH_v3.0.xlsx!All_Datasets row 28 (DS-027)
A33: DS-028 | B33: Pavementscapes | D33: Labeled-16 | E33: =INDEX(MCDM_Grades!$E$6:$E$238,MATCH(A33,MCDM_Grades!$A$6:$A$238,0)) -> 25 | F33: =INDEX(MCDM_Grades!$F$6:$F$238,MATCH(A33,MCDM_Grades!$A$6:$A$238,0)) -> 100 | G33: =INDEX(MCDM_Grades!$G$6:$G$238,MATCH(A33,MCDM_Grades!$A$6:$A$238,0)) -> 0.25 | H33: =HYPERLINK("https://github.com/tongzheng1992/Pavementscapes","Dataset") -> Dataset | I33: =HYPERLINK("https://github.com/tongzheng1992/Pavementscapes","Evidence / paper") -> Evidence / paper | J33: NR | K33: semantic segmentation; instance segmentation | L33: Images/frames as reported | M33: Road inspection imagery | N33: 15 pavement classes; six damage classes | O33: Pixel-level labels | P33: NR | Q33: UNK | R33: 4000 | S33: Road environment: Roadway | U33: A usable public data-access route and license were not verified from GitHub; dataset remains pending despite detailed paper metadata. | V33: DS-028 | W33: Retained existing record | Z33: v3 evidence snapshot | AA33: =HYPERLINK("#'Manual_Review'!A"&(MATCH("DS-028",Manual_Review!$A$6:$A$238,0)+5),"Enter review") -> Enter review | AB33: =HYPERLINK("#'MCDM_Checks'!A"&(MATCH("DS-028",MCDM_Checks!$B$6:$B$3733,0)+5),"Check evidence") -> Check evidence | AC33: GitHub; Other official / repository | AD33: https://github.com/tongzheng1992/Pavementscapes | AE33: https://github.com/tongzheng1992/Pavementscapes | AF33: Compared_All_Platforms_TH_v3.0.xlsx!All_Datasets row 29 (DS-028)
A34: DS-029 | B34: PaveSeg Dataset | D34: Labeled-16 | E34: =INDEX(MCDM_Grades!$E$6:$E$238,MATCH(A34,MCDM_Grades!$A$6:$A$238,0)) -> 61.111111 | F34: =INDEX(MCDM_Grades!$F$6:$F$238,MATCH(A34,MCDM_Grades!$A$6:$A$238,0)) -> 94.444444 | G34: =INDEX(MCDM_Grades!$G$6:$G$238,MATCH(A34,MCDM_Grades!$A$6:$A$238,0)) -> 0.66666667 | H34: =HYPERLINK("https://github.com/FuturePave/PaveSeg-Dataset","Dataset") -> Dataset | I34: =HYPERLINK("https://github.com/FuturePave/PaveSeg-Dataset","Evidence / paper") -> Evidence / paper | J34: 2025 publication context; repository date not verified; PaveSeg | K34: Distress / roughness | L34: Images / patches | M34: Other / mixed capture | N34: Crack, pothole, sealed crack, patch, alligator crack, utility cover, expansion joint; undamaged background. | O34: Expert grayscale pixel masks (seven foreground classes) | P34: Noncommercial full-data access; preview license not clearly specified. | Q34: Partial public release | R34: 2,400 described; 100 images/masks publicly previewed | S34: Not specified in accessed repository. | T34: FuturePave | U34: Do not describe all 2,400 as freely downloadable. Public preview is useful; full availability needs confirmation. | V34: DS-029; D029 | W34: Same dataset | Z34: AV inventory evidence snapshot | AA34: =HYPERLINK("#'Manual_Review'!A"&(MATCH("DS-029",Manual_Review!$A$6:$A$238,0)+5),"Enter review") -> Enter review | AB34: =HYPERLINK("#'MCDM_Checks'!A"&(MATCH("DS-029",MCDM_Checks!$B$6:$B$3733,0)+5),"Check evidence") -> Check evidence | AC34: GitHub | AD34: https://github.com/FuturePave/PaveSeg-Dataset | AE34: https://github.com/FuturePave/PaveSeg-Dataset | AF34: Compared_All_Platforms_TH_v3.0.xlsx!All_Datasets row 30 (DS-029); AV_Pavement_Dataset_Inventory.xlsx!Datasets row 35 (D029)
A35: DS-030 | B35: PID (Pavement Image Dataset) | D35: Labeled-16 | E35: =INDEX(MCDM_Grades!$E$6:$E$238,MATCH(A35,MCDM_Grades!$A$6:$A$238,0)) -> 50 | F35: =INDEX(MCDM_Grades!$F$6:$F$238,MATCH(A35,MCDM_Grades!$A$6:$A$238,0)) -> 100 | G35: =INDEX(MCDM_Grades!$G$6:$G$238,MATCH(A35,MCDM_Grades!$A$6:$A$238,0)) -> 0.5 | H35: =HYPERLINK("https://github.com/Nan2020/PID-Pavement-Image-Dataset","Dataset") -> Dataset | I35: =HYPERLINK("https://github.com/Nan2020/PID-Pavement-Image-Dataset","Evidence / paper") -> Evidence / paper | J35: Original paired-view release | K35: object detection; classification; distress density estimation [GPT] | object detection; classification [Test_Batch] | L35: Images/frames as reported | M35: Google Street View API [GPT] | Google Street View imagery; top-down pavement imagery [Test_Batch] | N35: Nine pavement distress categories [GPT] | nine manually annotated pavement categories [Test_Batch] | O35: bounding boxes; paired wide-view and top-down images | P35: NR | Q35: Direct_Download [GPT] | Metadata_Only [Test_Batch] | R35: 7237 | S35: United States; 22 pavement sections; Road environment: Interstate and U.S. highways [GPT] | Roadway [Test_Batch] | U35: Google Street View dependence; U.S.-only coverage; top-down images are paired but only wide views are bounding-box annotated [GPT] | Public data route and reuse rights for source imagery were not verified; GitHub evidence is secondary. [Test_Batch] | V35: DS-030 | W35: Retained existing record | Z35: v3 evidence snapshot | AA35: =HYPERLINK("#'Manual_Review'!A"&(MATCH("DS-030",Manual_Review!$A$6:$A$238,0)+5),"Enter review") -> Enter review | AB35: =HYPERLINK("#'MCDM_Checks'!A"&(MATCH("DS-030",MCDM_Checks!$B$6:$B$3733,0)+5),"Check evidence") -> Check evidence | AC35: GitHub; Other official / repository | AD35: https://github.com/Nan2020/PID-Pavement-Image-Dataset | AE35: https://github.com/Nan2020/PID-Pavement-Image-Dataset | AF35: Compared_All_Platforms_TH_v3.0.xlsx!All_Datasets row 31 (DS-030)
A36: DS-031 | B36: Pothole Detection Dataset (1,243 images) | D36: Labeled-16 | E36: =INDEX(MCDM_Grades!$E$6:$E$238,MATCH(A36,MCDM_Grades!$A$6:$A$238,0)) -> 41.666667 | F36: =INDEX(MCDM_Grades!$F$6:$F$238,MATCH(A36,MCDM_Grades!$A$6:$A$238,0)) -> 100 | G36: =INDEX(MCDM_Grades!$G$6:$G$238,MATCH(A36,MCDM_Grades!$A$6:$A$238,0)) -> 0.41666667 | H36: =HYPERLINK("https://github.com/jaygala24/pothole-detection","Dataset") -> Dataset | I36: =HYPERLINK("https://github.com/jaygala24/pothole-detection","Evidence / paper") -> Evidence / paper | J36: NR | K36: object detection | L36: Images/frames as reported | M36: Web-collected road images | N36: pothole bounding box | O36: YOLO TXT | P36: NR | Q36: Direct_Download | R36: 1243 | S36: Road environment: Roadway | U36: Web-sourced images have weak provenance, unknown collection conditions, unresolved release year, and no formal dataset license. | V36: DS-031 | W36: Retained existing record | Z36: v3 evidence snapshot | AA36: =HYPERLINK("#'Manual_Review'!A"&(MATCH("DS-031",Manual_Review!$A$6:$A$238,0)+5),"Enter review") -> Enter review | AB36: =HYPERLINK("#'MCDM_Checks'!A"&(MATCH("DS-031",MCDM_Checks!$B$6:$B$3733,0)+5),"Check evidence") -> Check evidence | AC36: GitHub | AD36: https://github.com/jaygala24/pothole-detection | AE36: https://github.com/jaygala24/pothole-detection | AF36: Compared_All_Platforms_TH_v3.0.xlsx!All_Datasets row 32 (DS-031)
A37: DS-032 | B37: R2S100K Road-Region Segmentation Dataset | D37: Labeled-16 | E37: =INDEX(MCDM_Grades!$E$6:$E$238,MATCH(A37,MCDM_Grades!$A$6:$A$238,0)) -> 58.333333 | F37: =INDEX(MCDM_Grades!$F$6:$F$238,MATCH(A37,MCDM_Grades!$A$6:$A$238,0)) -> 100 | G37: =INDEX(MCDM_Grades!$G$6:$G$238,MATCH(A37,MCDM_Grades!$A$6:$A$238,0)) -> 0.58333333 | H37: =HYPERLINK("https://github.com/moatifbutt/r2s100k","Dataset") -> Dataset | I37: =HYPERLINK("https://github.com/moatifbutt/r2s100k","Evidence / paper") -> Evidence / paper | J37: 2023 preprint; 2025 journal; R2S100K — Road-Region Segmentation | K37: Distress / roughness | L37: Images / patches | M37: Human-driven survey | N37: 14 road-region classes including distress, wet surface, puddle, gravel, boggy, earthen, concrete patches and speed breakers. | O37: Pixel-level semantic segmentation for 14,000 images | P37: Not specified in accessed repository; request terms with access. | Q37: Request access | R37: 100,000 images total; 14,000 labeled, 86,000 unlabeled described; over 1,000 km | S37: Geography not verified from accessed project/repository. | T37: Muhammad Atif Butt and collaborators | U37: High-value combined distress/surface-state benchmark, but not an unrestricted instant download. Access to all 100k is not confirmed. | V37: DS-032; D008 | W37: Same dataset | Z37: AV inventory evidence snapshot | AA37: =HYPERLINK("#'Manual_Review'!A"&(MATCH("DS-032",Manual_Review!$A$6:$A$238,0)+5),"Enter review") -> Enter review | AB37: =HYPERLINK("#'MCDM_Checks'!A"&(MATCH("DS-032",MCDM_Checks!$B$6:$B$3733,0)+5),"Check evidence") -> Check evidence | AC37: GitHub | AD37: https://github.com/moatifbutt/r2s100k | AE37: https://github.com/moatifbutt/r2s100k | AF37: Compared_All_Platforms_TH_v3.0.xlsx!All_Datasets row 33 (DS-032); AV_Pavement_Dataset_Inventory.xlsx!Datasets row 14 (D008)
A38: DS-033 | B38: RCD-IIUM Road Crack Detection Dataset | D38: Labeled-16 | E38: =INDEX(MCDM_Grades!$E$6:$E$238,MATCH(A38,MCDM_Grades!$A$6:$A$238,0)) -> 55.555556 | F38: =INDEX(MCDM_Grades!$F$6:$F$238,MATCH(A38,MCDM_Grades!$A$6:$A$238,0)) -> 100 | G38: =INDEX(MCDM_Grades!$G$6:$G$238,MATCH(A38,MCDM_Grades!$A$6:$A$238,0)) -> 0.55555556 | H38: =HYPERLINK("https://github.com/ArselanAshraf/RCD-IIUM-Road-Crack-Detection-Dataset-","Dataset") -> Dataset | I38: =HYPERLINK("https://github.com/ArselanAshraf/RCD-IIUM-Road-Crack-Detection-Dataset-","Evidence / paper") -> Evidence / paper | J38: NR | K38: instance segmentation; object detection | L38: NR | M38: Digital camera | N38: crack instance | O38: Roboflow segmentation TXT | P38: NR | Q38: Direct_Download | R38: NR | S38: Malaysia; Selangor; Kuala Lumpur; Road environment: Urban | U38: Image count, exact resolution, license, and acquisition conditions are not reported in the repository summary. | V38: DS-033 | W38: Retained existing record | Z38: v3 evidence snapshot | AA38: =HYPERLINK("#'Manual_Review'!A"&(MATCH("DS-033",Manual_Review!$A$6:$A$238,0)+5),"Enter review") -> Enter review | AB38: =HYPERLINK("#'MCDM_Checks'!A"&(MATCH("DS-033",MCDM_Checks!$B$6:$B$3733,0)+5),"Check evidence") -> Check evidence | AC38: GitHub | AD38: https://github.com/ArselanAshraf/RCD-IIUM-Road-Crack-Detection-Dataset- | AE38: https://github.com/ArselanAshraf/RCD-IIUM-Road-Crack-Detection-Dataset- | AF38: Compared_All_Platforms_TH_v3.0.xlsx!All_Datasets row 34 (DS-033)
A39: DS-034 | B39: RDD2020: Road Damage Dataset 2020 | D39: Labeled-16 | E39: =INDEX(MCDM_Grades!$E$6:$E$238,MATCH(A39,MCDM_Grades!$A$6:$A$238,0)) -> 69.444444 | F39: =INDEX(MCDM_Grades!$F$6:$F$238,MATCH(A39,MCDM_Grades!$A$6:$A$238,0)) -> 100 | G39: =INDEX(MCDM_Grades!$G$6:$G$238,MATCH(A39,MCDM_Grades!$A$6:$A$238,0)) -> 0.69444444 | H39: =HYPERLINK("https://data.mendeley.com/datasets/5ty2wb6gvg/1","Dataset") -> Dataset | I39: =HYPERLINK("https://data.mendeley.com/datasets/5ty2wb6gvg/1","Evidence / paper") -> Evidence / paper | J39: RDD2020 (Mendeley v1) [Claude] | 2 [Claude/GPT] | RDD2020 / canonical public version [GPT] | V1 [GPT/Test_Batch] | K39: Object detection;Classification [Claude/Test_Batch] | Detection; Classification [Claude] | Object_Detection [GPT] | Object detection;Classification;Benchmarking [GPT] | object detection; classification; transfer learning; cross-country generalization [GPT] | L39: Images/frames as reported | M39: Vehicle-mounted smartphone [Claude/GPT] | Smartphone or vehicle-mounted camera; country-specific collection protocols [GPT] | Smartphone-based vehicle collection [GPT] | Smartphone mounted on vehicle [Test_Batch] | N39: Japanese road-damage code taxonomy D00/D10/D20/D40 [Claude] | 4 damage classes; more than 31000 annotated damage instances [Claude] | D00 longitudinal crack; D10 transverse crack; D20 alligator crack; D40 pothole; more than 31,000 instances [GPT] | D00 longitudinal crack;D10 transverse crack;D20 alligator crack;D40 pothole [GPT] | D00; D10; D20; D40 [GPT/Test_Batch] | O39: PASCAL VOC XML [Claude/GPT/Test_Batch] | Pascal VOC XML; image files [GPT] | Bounding-box annotations;format NR on landing page [GPT] | P39: CC BY-SA 4.0 (images, per repository README) [Claude] | CC BY-NC 3.0 [Claude/GPT] | CC BY 4.0 [GPT] | Q39: Direct_Download | R39: 26336 [Claude/GPT] | 26620 [Test_Batch] | S39: Japan;India;Czech Republic [Claude/Test_Batch] | India; Japan; Czech Republic [Claude/GPT]; Multiple municipalities (Japan);Gurugram region (India);Czech municipalities — per data article [Claude] | Multiple cities/regions in the three participating countries [GPT] | Multiple cities and road networks [GPT]; Road environment: Urban and rural public roads [Claude] | Urban road; Rural road; Highway [Claude] | Mixed [GPT] | Urban;interurban;multi-country roads [GPT] | Urban; rural; interurban [GPT] | Urban; highway [Test_Batch] | U39: Superseded by RDD2022 for multi-country coverage; image count not re-verified from primary source in this batch (recorded NR); no sensor metadata [Claude] | CC BY-NC 3.0 blocks commercial deployment and some agency use; annotation format, image resolution and collection dates not stated on the canonical record; superseded in practice by RDD2022, which is not hosted on Mendeley Data [Claude] | Country-specific imaging protocols and image resolutions vary; collection dates and engineering-condition indicators are incompletely documented. [GPT] | No PCI/IRI or maintenance records; non-commercial license; collection dates and sensor metadata not reported on landing page [GPT] | Four-class taxonomy; heterogeneous country image specifications; limited engineering sensor metadata [GPT] | Limited sensor metadata and no reported PCI, IRI, or maintenance linkage. [Test_Batch] | V39: DS-034 | W39: Retained existing record | X39: Successive RDD releases (DS-037, DS-038, DS-034, DS-035) | Z39: v3 evidence snapshot | AA39: =HYPERLINK("#'Manual_Review'!A"&(MATCH("DS-034",Manual_Review!$A$6:$A$238,0)+5),"Enter review") -> Enter review | AB39: =HYPERLINK("#'MCDM_Checks'!A"&(MATCH("DS-034",MCDM_Checks!$B$6:$B$3733,0)+5),"Check evidence") -> Check evidence | AC39: Mendeley Data; GitHub | AD39: https://data.mendeley.com/datasets/5ty2wb6gvg/1 | AE39: https://data.mendeley.com/datasets/5ty2wb6gvg/1 | AF39: Compared_All_Platforms_TH_v3.0.xlsx!All_Datasets row 35 (DS-034)
A40: DS-035 | B40: RDD2022: Multi-National Road Damage Dataset (CRDDC 2022) | C40: 3 | D40: Labeled-16 | E40: =INDEX(MCDM_Grades!$E$6:$E$238,MATCH(A40,MCDM_Grades!$A$6:$A$238,0)) -> 94.444444 | F40: =INDEX(MCDM_Grades!$F$6:$F$238,MATCH(A40,MCDM_Grades!$A$6:$A$238,0)) -> 100 | G40: =INDEX(MCDM_Grades!$G$6:$G$238,MATCH(A40,MCDM_Grades!$A$6:$A$238,0)) -> 0.94444444 | H40: =HYPERLINK("https://figshare.com/articles/dataset/RDD2022_-_The_multi-national_Road_Damage_Dataset_released_through_CRDDC_2022/21431547/1","Dataset") -> Dataset | I40: =HYPERLINK("https://arxiv.org/abs/2209.08538","Evidence / paper") -> Evidence / paper | J40: Figshare version 1, DOI 10.6084/m9.figshare.21431547.v1 | K40: Distress / roughness | L40: Images / patches | M40: Human-driven survey | N40: Longitudinal crack D00, transverse crack D10, alligator crack D20, pothole D40. | O40: PASCAL VOC XML bounding boxes for train; test imagery only | P40: Author repository states images CC BY-SA 4.0; verify release-specific repository terms. | Q40: Public links | R40: 47,420 images from six countries | S40: Japan, India, Czech Republic, Norway, United States, China | T40: Sekimoto Lab / Deeksha Arya, Hiroya Maeda and collaborators | U40: Strong defect-detection baseline. RDD2020/2019/2018 downloads remain on same official page; overlapping family releases grouped to avoid inflated counts. | V40: DS-035; D019 | W40: Same release | X40: Successive RDD releases (DS-037, DS-038, DS-034, DS-035); Derived/compiled RDD family (DS-035, DS-072, DS-095, DS-099, DS-132, DS-162, DS-104, DS-105) | Y40: Contains earlier RDD lineage. Country folders do not prove route-independent splits; third-party rights require separate reuse check. | Z40: Primary documentation checked | AA40: =HYPERLINK("#'Manual_Review'!A"&(MATCH("DS-035",Manual_Review!$A$6:$A$238,0)+5),"Enter review") -> Enter review | AB40: =HYPERLINK("#'MCDM_Checks'!A"&(MATCH("DS-035",MCDM_Checks!$B$6:$B$3733,0)+5),"Check evidence") -> Check evidence | AC40: Other official / repository; GitHub; Kaggle | AD40: https://figshare.com/articles/dataset/RDD2022_-_The_multi-national_Road_Damage_Dataset_released_through_CRDDC_2022/21431547/1 | AE40: https://arxiv.org/abs/2209.08538 | AF40: Compared_All_Platforms_TH_v3.0.xlsx!All_Datasets row 36 (DS-035); AV_Pavement_Dataset_Inventory.xlsx!Datasets row 25 (D019)
A41: DS-036 | B41: RDDC2024-ID (Crowdsourced Road Damage Detection Dataset - Indonesia) | D41: Labeled-16 | E41: =INDEX(MCDM_Grades!$E$6:$E$238,MATCH(A41,MCDM_Grades!$A$6:$A$238,0)) -> 50 | F41: =INDEX(MCDM_Grades!$F$6:$F$238,MATCH(A41,MCDM_Grades!$A$6:$A$238,0)) -> 100 | G41: =INDEX(MCDM_Grades!$G$6:$G$238,MATCH(A41,MCDM_Grades!$A$6:$A$238,0)) -> 0.5 | H41: =HYPERLINK("https://github.com/endurancechallengeindonesia/RDDC2024-ID","Dataset") -> Dataset | I41: =HYPERLINK("https://github.com/endurancechallengeindonesia/RDDC2024-ID","Evidence / paper") -> Evidence / paper | J41: v1 (2024) | K41: Object detection | L41: Images/frames as reported | M41: NR (crowdsourced imagery) | N41: Five classes (0-4) incl. 'Other' | O41: YOLO txt | P41: NR | Q41: Direct_Download | R41: 9000 | S41: Indonesia; Various locations throughout Indonesia; Road environment: Public roads (nationwide crowdsourced) | U41: Image count stated as 'over 9,000' (recorded as 9000 minimum); no license or data paper; single Google Drive archive (link liveness not independently re-tested) | V41: DS-036 | W41: Retained existing record | Z41: v3 evidence snapshot | AA41: =HYPERLINK("#'Manual_Review'!A"&(MATCH("DS-036",Manual_Review!$A$6:$A$238,0)+5),"Enter review") -> Enter review | AB41: =HYPERLINK("#'MCDM_Checks'!A"&(MATCH("DS-036",MCDM_Checks!$B$6:$B$3733,0)+5),"Check evidence") -> Check evidence | AC41: GitHub | AD41: https://github.com/endurancechallengeindonesia/RDDC2024-ID | AE41: https://github.com/endurancechallengeindonesia/RDDC2024-ID | AF41: Compared_All_Platforms_TH_v3.0.xlsx!All_Datasets row 37 (DS-036)
A42: DS-037 | B42: Road Damage Dataset 2018 (RDD2018) | D42: Labeled-16 | E42: =INDEX(MCDM_Grades!$E$6:$E$238,MATCH(A42,MCDM_Grades!$A$6:$A$238,0)) -> 75 | F42: =INDEX(MCDM_Grades!$F$6:$F$238,MATCH(A42,MCDM_Grades!$A$6:$A$238,0)) -> 100 | G42: =INDEX(MCDM_Grades!$G$6:$G$238,MATCH(A42,MCDM_Grades!$A$6:$A$238,0)) -> 0.75 | H42: =HYPERLINK("https://github.com/sekilab/RoadDamageDetector","Dataset") -> Dataset | I42: =HYPERLINK("https://github.com/sekilab/RoadDamageDetector","Evidence / paper") -> Evidence / paper | J42: v1 [GPT] | 2018 [Test_Batch] | K42: object detection; classification; mobile inference [GPT] | object detection; classification [Test_Batch] | L42: Images/frames as reported | M42: Smartphone mounted on car [GPT] | Smartphone mounted on vehicle [Test_Batch] | N42: Eight road-damage types [GPT] | D00; D01; D10; D11; D20; D40; D43; D44 [Test_Batch] | O42: Pascal VOC XML | P42: CC BY-SA 4.0 (images); MIT (repository code) [GPT] | CC BY-SA 4.0 [Test_Batch] | Q42: Direct_Download | R42: 9053 | S42: Japan; Adachi; Chiba; Muroran; Ichihara; Sumida; Nagakute; Numazu; Road environment: Urban; municipal roads [GPT] | Urban; highway [Test_Batch] | U42: Single-country municipal coverage; no documented GPS/IMU/PCI/IRI package [GPT] | Single-country original release; no reported engineering condition indices or rich vehicle-sensor metadata. [Test_Batch] | V42: DS-037 | W42: Retained existing record | X42: Successive RDD releases (DS-037, DS-038, DS-034, DS-035) | Z42: v3 evidence snapshot | AA42: =HYPERLINK("#'Manual_Review'!A"&(MATCH("DS-037",Manual_Review!$A$6:$A$238,0)+5),"Enter review") -> Enter review | AB42: =HYPERLINK("#'MCDM_Checks'!A"&(MATCH("DS-037",MCDM_Checks!$B$6:$B$3733,0)+5),"Check evidence") -> Check evidence | AC42: GitHub | AD42: https://github.com/sekilab/RoadDamageDetector | AE42: https://github.com/sekilab/RoadDamageDetector | AF42: Compared_All_Platforms_TH_v3.0.xlsx!All_Datasets row 38 (DS-037)
A43: DS-038 | B43: Road Damage Dataset 2019 (RDD2019) | D43: Labeled-16 | E43: =INDEX(MCDM_Grades!$E$6:$E$238,MATCH(A43,MCDM_Grades!$A$6:$A$238,0)) -> 44.444444 | F43: =INDEX(MCDM_Grades!$F$6:$F$238,MATCH(A43,MCDM_Grades!$A$6:$A$238,0)) -> 100 | G43: =INDEX(MCDM_Grades!$G$6:$G$238,MATCH(A43,MCDM_Grades!$A$6:$A$238,0)) -> 0.44444444 | H43: =HYPERLINK("https://github.com/sekilab/RoadDamageDetector","Dataset") -> Dataset | I43: =HYPERLINK("https://github.com/sekilab/RoadDamageDetector","Evidence / paper") -> Evidence / paper | J43: 2019 | K43: object detection; data augmentation [GPT] | object detection; classification [Test_Batch] | L43: NR | M43: Vehicle-mounted smartphone; synthetic augmentation pipeline [GPT] | Smartphone mounted on vehicle [Test_Batch] | N43: Pascal VOC-compatible road damage labels [GPT] | D00; D10; D20; D40 [Test_Batch] | O43: Pascal VOC XML | P43: NR | Q43: Direct_Download | R43: NR | S43: Japan; Road environment: Municipal roads [GPT] | Urban; highway [Test_Batch] | U43: Synthetic-augmented version; exact real/synthetic composition and license not resolved [GPT] | Version-specific image count, license, and detailed collection conditions were not located in the official README. [Test_Batch] | V43: DS-038 | W43: Retained existing record | X43: Successive RDD releases (DS-037, DS-038, DS-034, DS-035) | Z43: v3 evidence snapshot | AA43: =HYPERLINK("#'Manual_Review'!A"&(MATCH("DS-038",Manual_Review!$A$6:$A$238,0)+5),"Enter review") -> Enter review | AB43: =HYPERLINK("#'MCDM_Checks'!A"&(MATCH("DS-038",MCDM_Checks!$B$6:$B$3733,0)+5),"Check evidence") -> Check evidence | AC43: GitHub | AD43: https://github.com/sekilab/RoadDamageDetector | AE43: https://github.com/sekilab/RoadDamageDetector | AF43: Compared_All_Platforms_TH_v3.0.xlsx!All_Datasets row 39 (DS-038)
A44: DS-039 | B44: RoadRutting Dataset (sekilab) | D44: Labeled-16 | E44: =INDEX(MCDM_Grades!$E$6:$E$238,MATCH(A44,MCDM_Grades!$A$6:$A$238,0)) -> 36.111111 | F44: =INDEX(MCDM_Grades!$F$6:$F$238,MATCH(A44,MCDM_Grades!$A$6:$A$238,0)) -> 100 | G44: =INDEX(MCDM_Grades!$G$6:$G$238,MATCH(A44,MCDM_Grades!$A$6:$A$238,0)) -> 0.36111111 | H44: =HYPERLINK("https://data.mendeley.com/datasets/v8mbnvx8pv/1","Dataset") -> Dataset | I44: =HYPERLINK("https://data.mendeley.com/datasets/v8mbnvx8pv/1","Evidence / paper") -> Evidence / paper | J44: 1 | K44: Detection; Segmentation [Claude] | object detection; segmentation [Test_Batch] | L44: Images/frames as reported | M44: NR | N44: Object-level and pixel-level annotations for road rutting [Claude] | rutting object; rutting pixel mask [Test_Batch] | O44: Bounding boxes; pixel masks | P44: CC BY 4.0 | Q44: Direct_Download | R44: 949 | S44: Road environment: Roadway | U44: Country, acquisition platform, resolution and collection dates are all unreported; single distress type; 949 images; annotation formats not enumerated on the record [Claude] | Small, single-distress dataset; collection location, resolution, license, and sensor metadata are not documented. [Test_Batch] | V44: DS-039 | W44: Retained existing record | Z44: v3 evidence snapshot | AA44: =HYPERLINK("#'Manual_Review'!A"&(MATCH("DS-039",Manual_Review!$A$6:$A$238,0)+5),"Enter review") -> Enter review | AB44: =HYPERLINK("#'MCDM_Checks'!A"&(MATCH("DS-039",MCDM_Checks!$B$6:$B$3733,0)+5),"Check evidence") -> Check evidence | AC44: Mendeley Data | AD44: https://data.mendeley.com/datasets/v8mbnvx8pv/1 | AE44: https://data.mendeley.com/datasets/v8mbnvx8pv/1 | AF44: Compared_All_Platforms_TH_v3.0.xlsx!All_Datasets row 40 (DS-039)
A45: DS-040 | B45: RTK — Road Traversing Knowledge (701-image segmentation release) | D45: Labeled-16 | E45: =INDEX(MCDM_Grades!$E$6:$E$238,MATCH(A45,MCDM_Grades!$A$6:$A$238,0)) -> 77.777778 | F45: =INDEX(MCDM_Grades!$F$6:$F$238,MATCH(A45,MCDM_Grades!$A$6:$A$238,0)) -> 100 | G45: =INDEX(MCDM_Grades!$G$6:$G$238,MATCH(A45,MCDM_Grades!$A$6:$A$238,0)) -> 0.77777778 | H45: =HYPERLINK("https://data.mendeley.com/datasets/hssswvmjwf/1","Dataset") -> Dataset | I45: =HYPERLINK("https://data.mendeley.com/datasets/hssswvmjwf/1","Evidence / paper") -> Evidence / paper | J45: 2020 paper; 2023 repository release; RTK — Road Traversing Knowledge (segmentation) | K45: Distress / roughness | L45: Images / patches | M45: Driving research | N45: 12 semantic classes including road materials, potholes, cracks, puddles, patches and road markings/fixtures. | O45: Dense pixel-level segmentation | P45: CC BY 4.0 for this Mendeley release. | Q45: Public links | R45: 701 images (352×288): 561 train / 140 validation | S45: Santa Catarina, Brazil | T45: Thiago Rateke, Aldo von Wangenheim, Rafael Toledo / UFSC | U45: This row is the 701-image segmentation release, not the larger RTK material/quality classification collection. Daylight and good weather only. | V45: DS-040; D006 | W45: Same release | X45: Subset and parent sequence release (DS-040, DS-181); Stereo pothole / compiled ancestry (DS-043, DS-157, DS-079, DS-040) | Z45: AV inventory evidence snapshot | AA45: =HYPERLINK("#'Manual_Review'!A"&(MATCH("DS-040",Manual_Review!$A$6:$A$238,0)+5),"Enter review") -> Enter review | AB45: =HYPERLINK("#'MCDM_Checks'!A"&(MATCH("DS-040",MCDM_Checks!$B$6:$B$3733,0)+5),"Check evidence") -> Check evidence | AC45: Mendeley Data; GitHub; Kaggle | AD45: https://data.mendeley.com/datasets/hssswvmjwf/1 | AE45: https://data.mendeley.com/datasets/hssswvmjwf/1 | AF45: Compared_All_Platforms_TH_v3.0.xlsx!All_Datasets row 41 (DS-040); AV_Pavement_Dataset_Inventory.xlsx!Datasets row 12 (D006)
A46: DS-041 | B46: SEU Asphalt Pavement Crack Dataset (transverse/longitudinal/net cracks) | D46: Labeled-16 | E46: =INDEX(MCDM_Grades!$E$6:$E$238,MATCH(A46,MCDM_Grades!$A$6:$A$238,0)) -> 11.111111 | F46: =INDEX(MCDM_Grades!$F$6:$F$238,MATCH(A46,MCDM_Grades!$A$6:$A$238,0)) -> 94.444444 | G46: =INDEX(MCDM_Grades!$G$6:$G$238,MATCH(A46,MCDM_Grades!$A$6:$A$238,0)) -> 0.16666667 | H46: =HYPERLINK("https://github.com/SEUxia/Asphalt-pavement-crack-dataset","Dataset") -> Dataset | I46: =HYPERLINK("https://github.com/SEUxia/Asphalt-pavement-crack-dataset","Evidence / paper") -> Evidence / paper | J46: Announced (not yet released) | K46: NR | L46: NR | M46: NR | N46: NR | O46: NR | P46: NR | Q46: Metadata_Only | R46: NR | S46: Road environment: Asphalt pavements | U46: Images to be made public 'upon receipt of the article'; dataset-versus-paper status unresolved | V46: DS-041 | W46: Retained existing record | Z46: v3 evidence snapshot | AA46: =HYPERLINK("#'Manual_Review'!A"&(MATCH("DS-041",Manual_Review!$A$6:$A$238,0)+5),"Enter review") -> Enter review | AB46: =HYPERLINK("#'MCDM_Checks'!A"&(MATCH("DS-041",MCDM_Checks!$B$6:$B$3733,0)+5),"Check evidence") -> Check evidence | AC46: GitHub | AD46: https://github.com/SEUxia/Asphalt-pavement-crack-dataset | AE46: https://github.com/SEUxia/Asphalt-pavement-crack-dataset | AF46: Compared_All_Platforms_TH_v3.0.xlsx!All_Datasets row 42 (DS-041)
A47: DS-042 | B47: SoV Pothole Dataset | D47: Labeled-16 | E47: =INDEX(MCDM_Grades!$E$6:$E$238,MATCH(A47,MCDM_Grades!$A$6:$A$238,0)) -> 58.333333 | F47: =INDEX(MCDM_Grades!$F$6:$F$238,MATCH(A47,MCDM_Grades!$A$6:$A$238,0)) -> 100 | G47: =INDEX(MCDM_Grades!$G$6:$G$238,MATCH(A47,MCDM_Grades!$A$6:$A$238,0)) -> 0.58333333 | H47: =HYPERLINK("https://github.com/achireistefan/Pothole-Detection","Dataset") -> Dataset | I47: =HYPERLINK("https://github.com/achireistefan/Pothole-Detection","Evidence / paper") -> Evidence / paper | J47: NR | K47: object detection; depth-assisted pothole detection | L47: Images/frames as reported | M47: Person-mounted ZED 2 stereo camera | N47: pothole; drain | O47: Left RGB; right RGB; depth; annotations | P47: NR | Q47: Direct_Download | R47: 447 | S47: Road environment: Roadway | U47: Small, person-mounted capture rather than vehicle-mounted CAV collection; location and license are not clearly reported. | V47: DS-042 | W47: Retained existing record | Z47: v3 evidence snapshot | AA47: =HYPERLINK("#'Manual_Review'!A"&(MATCH("DS-042",Manual_Review!$A$6:$A$238,0)+5),"Enter review") -> Enter review | AB47: =HYPERLINK("#'MCDM_Checks'!A"&(MATCH("DS-042",MCDM_Checks!$B$6:$B$3733,0)+5),"Check evidence") -> Check evidence | AC47: GitHub | AD47: https://github.com/achireistefan/Pothole-Detection | AE47: https://github.com/achireistefan/Pothole-Detection | AF47: Compared_All_Platforms_TH_v3.0.xlsx!All_Datasets row 43 (DS-042)
A48: DS-043 | B48: Stereo Pothole Datasets | D48: Labeled-16 | E48: =INDEX(MCDM_Grades!$E$6:$E$238,MATCH(A48,MCDM_Grades!$A$6:$A$238,0)) -> 58.333333 | F48: =INDEX(MCDM_Grades!$F$6:$F$238,MATCH(A48,MCDM_Grades!$A$6:$A$238,0)) -> 100 | G48: =INDEX(MCDM_Grades!$G$6:$G$238,MATCH(A48,MCDM_Grades!$A$6:$A$238,0)) -> 0.58333333 | H48: =HYPERLINK("https://github.com/ruirangerfan/stereo_pothole_datasets","Dataset") -> Dataset | I48: =HYPERLINK("https://github.com/ruirangerfan/stereo_pothole_datasets","Evidence / paper") -> Evidence / paper | J48: NR | K48: semantic segmentation; pothole detection; 3D reconstruction | L48: NR | M48: Stereo camera system | N48: pothole pixel mask | O48: RGB images; disparity maps; pixel labels; point clouds | P48: NR | Q48: Direct_Download | R48: NR | S48: Road environment: Roadway | U48: Repository does not clearly report image count, resolution, location, license, or collection conditions. | V48: DS-043 | W48: Retained existing record | X48: Stereo pothole / compiled ancestry (DS-043, DS-157, DS-079, DS-040) | Z48: v3 evidence snapshot | AA48: =HYPERLINK("#'Manual_Review'!A"&(MATCH("DS-043",Manual_Review!$A$6:$A$238,0)+5),"Enter review") -> Enter review | AB48: =HYPERLINK("#'MCDM_Checks'!A"&(MATCH("DS-043",MCDM_Checks!$B$6:$B$3733,0)+5),"Check evidence") -> Check evidence | AC48: GitHub | AD48: https://github.com/ruirangerfan/stereo_pothole_datasets | AE48: https://github.com/ruirangerfan/stereo_pothole_datasets | AF48: Compared_All_Platforms_TH_v3.0.xlsx!All_Datasets row 44 (DS-043)
A49: DS-044 | B49: SUT-Crack (Sharif University of Technology Crack Dataset) | D49: Labeled-16 | E49: =INDEX(MCDM_Grades!$E$6:$E$238,MATCH(A49,MCDM_Grades!$A$6:$A$238,0)) -> 44.444444 | F49: =INDEX(MCDM_Grades!$F$6:$F$238,MATCH(A49,MCDM_Grades!$A$6:$A$238,0)) -> 100 | G49: =INDEX(MCDM_Grades!$G$6:$G$238,MATCH(A49,MCDM_Grades!$A$6:$A$238,0)) -> 0.44444444 | H49: =HYPERLINK("https://data.mendeley.com/datasets/gsbmknrhkv/6","Dataset") -> Dataset | I49: =HYPERLINK("https://data.mendeley.com/datasets/gsbmknrhkv/6","Evidence / paper") -> Evidence / paper | J49: Mendeley Data v6 [Claude] | 6 [Claude/CodeX] | K49: Classification;Object detection;Semantic segmentation [Claude] | Classification; Detection; Segmentation [Claude/CodeX] | classification; object detection [Test_Batch] | L49: Images/frames as reported | M49: Fixed-height camera (672 mm above pavement surface) [Claude] | Camera at a fixed height of 672 mm above the pavement surface [Claude] | Fixed-height camera, 672 mm above pavement surface [CodeX] | Fixed-height road camera [Test_Batch] | N49: Crack ground truth for segmentation/detection; with-crack vs without-crack for classification crops [Claude] | Annotations supporting classification, object detection and segmentation; per-image geotags with latitude and longitude [Claude] | crack; non-crack; localization labels [Test_Batch] | O49: Image crops; full-size images; geotag metadata | P49: NR (Mendeley record license not re-verified in this batch) [Claude] | CC BY 4.0 [Claude/CodeX] | Q49: Direct_Download | R49: 130 (segmentation/detection) + 25,563 (classification) per 15_SUT_Crack.xlsx; source records: 130 / NR | S49: Iran [Claude] | NR (depositor affiliation: Sharif University of Technology) [Claude]; Tehran (Sharif University of Technology); Road environment: Asphalt pavements incl. oil stains, shadows, varied lighting [Claude] | Urban road [Claude] | Roadway [Test_Batch] | U49: Small base-image count (130); fixed-height acquisition differs from vehicle-mounted CAV viewpoint [Claude] | Image count and resolution are not stated on the canonical record; country of collection is not stated and was not confirmed from an authoritative source; annotation file formats not enumerated; six versions exist with no changelog, so version-to-version differences are opaque [Claude] | Image count, label taxonomy, annotation format, country, and collection dates NR on landing page [CodeX] | Only 130 unique source images; release date, geography, license, and exact localization annotation schema are unresolved. [Test_Batch] | V49: DS-044 | W49: Retained existing record | Z49: v3 evidence snapshot | AA49: =HYPERLINK("#'Manual_Review'!A"&(MATCH("DS-044",Manual_Review!$A$6:$A$238,0)+5),"Enter review") -> Enter review | AB49: =HYPERLINK("#'MCDM_Checks'!A"&(MATCH("DS-044",MCDM_Checks!$B$6:$B$3733,0)+5),"Check evidence") -> Check evidence | AC49: Mendeley Data; GitHub | AD49: https://data.mendeley.com/datasets/gsbmknrhkv/6 | AE49: https://data.mendeley.com/datasets/gsbmknrhkv/6 | AF49: Compared_All_Platforms_TH_v3.0.xlsx!All_Datasets row 45 (DS-044)
A50: DS-045 | B50: UAPD (UAV Asphalt Pavement Distress Dataset) | D50: Labeled-16 | E50: =INDEX(MCDM_Grades!$E$6:$E$238,MATCH(A50,MCDM_Grades!$A$6:$A$238,0)) -> 52.777778 | F50: =INDEX(MCDM_Grades!$F$6:$F$238,MATCH(A50,MCDM_Grades!$A$6:$A$238,0)) -> 100 | G50: =INDEX(MCDM_Grades!$G$6:$G$238,MATCH(A50,MCDM_Grades!$A$6:$A$238,0)) -> 0.52777778 | H50: =HYPERLINK("https://github.com/tantantetetao/UAPD-Pavement-Distress-Dataset","Dataset") -> Dataset | I50: =HYPERLINK("https://github.com/tantantetetao/UAPD-Pavement-Distress-Dataset","Evidence / paper") -> Evidence / paper | J50: v1 (public release 2022) | K50: Object detection;Semantic segmentation (companion work) [Claude] | object detection; segmentation [Test_Batch] | L50: Images/frames as reported | M50: UAV with high-resolution camera [Claude] | UAV high-resolution camera [Test_Batch] | N50: Six distress categories [Claude] | transverse crack; longitudinal crack; oblique crack; alligator crack; pothole; repair [Test_Batch] | O50: NR | P50: NR | Q50: Direct_Download | R50: 3151 | S50: China; Road environment: Asphalt pavements (UAV survey) [Claude] | Roadway [Test_Batch] | U50: Annotation format and geographic coverage not stated in README; Google Drive hosting (link liveness not independently re-tested) [Claude] | Single acquisition mode and geography; formal data license and synchronized navigation metadata are not reported. [Test_Batch] | V50: DS-045 | W50: Retained existing record | Z50: v3 evidence snapshot | AA50: =HYPERLINK("#'Manual_Review'!A"&(MATCH("DS-045",Manual_Review!$A$6:$A$238,0)+5),"Enter review") -> Enter review | AB50: =HYPERLINK("#'MCDM_Checks'!A"&(MATCH("DS-045",MCDM_Checks!$B$6:$B$3733,0)+5),"Check evidence") -> Check evidence | AC50: GitHub | AD50: https://github.com/tantantetetao/UAPD-Pavement-Distress-Dataset | AE50: https://github.com/tantantetetao/UAPD-Pavement-Distress-Dataset | AF50: Compared_All_Platforms_TH_v3.0.xlsx!All_Datasets row 46 (DS-045)
A51: DS-046 | B51: UAV-CrackX (UAV pavement crack segmentation, x4/x8/x16 magnifications) | D51: Labeled-16 | E51: =INDEX(MCDM_Grades!$E$6:$E$238,MATCH(A51,MCDM_Grades!$A$6:$A$238,0)) -> 52.777778 | F51: =INDEX(MCDM_Grades!$F$6:$F$238,MATCH(A51,MCDM_Grades!$A$6:$A$238,0)) -> 100 | G51: =INDEX(MCDM_Grades!$G$6:$G$238,MATCH(A51,MCDM_Grades!$A$6:$A$238,0)) -> 0.52777778 | H51: =HYPERLINK("https://github.com/SHAN-JH/UAV-CrackX-Datasets","Dataset") -> Dataset | I51: =HYPERLINK("https://github.com/SHAN-JH/UAV-CrackX-Datasets","Evidence / paper") -> Evidence / paper | J51: 1,500-image release (1,200 annotated) | K51: Semantic segmentation;Cross-resolution domain adaptation | L51: Images/frames as reported | M51: UAV (50 m altitude, x4/x8/x16 magnification levels) | N51: Grayscale masks (0 = pavement, 1 = crack); 1,200 annotated images (400 per magnification) | O51: Grayscale mask images | P51: NR | Q51: UNK | R51: 1500 | S51: NR (Chang'an University group); Road environment: Pavements surveyed by UAV at 50 m altitude | U51: No public download route found in repository (no data files or hosting links); benchmark submission portal only (vlp.chd.edu.cn) — access route unresolved; contact author | V51: DS-046 | W51: Retained existing record | Z51: v3 evidence snapshot | AA51: =HYPERLINK("#'Manual_Review'!A"&(MATCH("DS-046",Manual_Review!$A$6:$A$238,0)+5),"Enter review") -> Enter review | AB51: =HYPERLINK("#'MCDM_Checks'!A"&(MATCH("DS-046",MCDM_Checks!$B$6:$B$3733,0)+5),"Check evidence") -> Check evidence | AC51: GitHub | AD51: https://github.com/SHAN-JH/UAV-CrackX-Datasets | AE51: https://github.com/SHAN-JH/UAV-CrackX-Datasets | AF51: Compared_All_Platforms_TH_v3.0.xlsx!All_Datasets row 47 (DS-046)
A52: DS-047 | B52: Long-Term Pavement Performance (LTPP) | C52: 9 | D52: Labeled-16 | E52: =INDEX(MCDM_Grades!$E$6:$E$238,MATCH(A52,MCDM_Grades!$A$6:$A$238,0)) -> 83.333333 | F52: =INDEX(MCDM_Grades!$F$6:$F$238,MATCH(A52,MCDM_Grades!$A$6:$A$238,0)) -> 100 | G52: =INDEX(MCDM_Grades!$G$6:$G$238,MATCH(A52,MCDM_Grades!$A$6:$A$238,0)) -> 0.83333333 | H52: =HYPERLINK("https://infopave.fhwa.dot.gov/Data/StandardDataRelease","Dataset") -> Dataset | I52: =HYPERLINK("https://infopave.fhwa.dot.gov/InfoPave_Repository/files/FHWA-HRT-21-038.pdf","Evidence / paper") -> Evidence / paper | J52: SDR39 context retained from v4; current portal identifies SDR40 as latest; selection pending | K52: NR | L52: NR | M52: Survey vehicle (photographic/film distress surveys); manual field surveys [Claude] | Photographic survey;manual survey;survey vehicle;field instrumentation [GPT] | N52: LTPP Distress Identification Manual (FHWA-RD-03-031): distress type, severity, and extent [Claude] | Distress type;severity;quantity;extent [GPT] | O52: Relational database tables; distress map and distress image files (PDF) per section survey [Claude] | Relational tables;distress maps;photographs;videos [GPT] | P52: NR | Q52: UNK [Claude] | Direct_Download [GPT] | R52: NR | S52: United States; Canada; 2,500+ in-service test sections across U.S. states and Canadian provinces [Claude] | Multiple U.S. states and Canadian provinces [GPT]; Road environment: In-service highways; asphalt-surfaced and concrete-surfaced test sections [Claude] | In-service highway test sections [GPT] | U52: Imagery not packaged as a CV-ready corpus (distress maps/images distributed per section via viewer and Ancillary Data download); image count and resolution not reported; older surveys are film-derived; labels are section-level engineering measures, not pixel/bounding-box annotations; bulk-download authorization requirements unverified; collection ongoing since 1990 (start month not reported); catalog license field points to 'unknown-license' [Claude] | Exact image count, exact active section count, image resolution, per-image label linkage, and named license are not reported in the Data.gov record. FHWA sources conflict on whether collection began in 1989 or 1990, so the exact collection month is UNK. Photographic and manual survey methods require method-aware use. [GPT] | V52: DS-047 | W52: Retained existing record | Y52: Release-specific counts/distributions and schema continuity remain pending; 2021 guide is context, not proof of SDR39/40 completeness. | Z52: Primary documentation checked | AA52: =HYPERLINK("#'Manual_Review'!A"&(MATCH("DS-047",Manual_Review!$A$6:$A$238,0)+5),"Enter review") -> Enter review | AB52: =HYPERLINK("#'MCDM_Checks'!A"&(MATCH("DS-047",MCDM_Checks!$B$6:$B$3733,0)+5),"Check evidence") -> Check evidence | AC52: Other official / repository; Data.gov | AD52: https://infopave.fhwa.dot.gov/Data/StandardDataRelease | AE52: https://infopave.fhwa.dot.gov/InfoPave_Repository/files/FHWA-HRT-21-038.pdf | AF52: Compared_All_Platforms_TH_v3.0.xlsx!All_Datasets row 48 (DS-047)
A53: DS-048 | B53: Long-Term Pavement Performance (LTPP) - Non-LTPP Data Access Collection | D53: Labeled-16 | E53: =INDEX(MCDM_Grades!$E$6:$E$238,MATCH(A53,MCDM_Grades!$A$6:$A$238,0)) -> 0 | F53: =INDEX(MCDM_Grades!$F$6:$F$238,MATCH(A53,MCDM_Grades!$A$6:$A$238,0)) -> 100 | G53: =INDEX(MCDM_Grades!$G$6:$G$238,MATCH(A53,MCDM_Grades!$A$6:$A$238,0)) -> 0 | H53: =HYPERLINK("https://infopave.fhwa.dot.gov/?Goto=NON-LTPP","Dataset") -> Dataset | I53: =HYPERLINK("https://infopave.fhwa.dot.gov/?Goto=NON-LTPP","Evidence / paper") -> Evidence / paper | J53: Non-LTPP access collection including C-LTPP; formal version NR | K53: NR | L53: NR | M53: NR | N53: NR | O53: ATOM/XML access point;underlying formats NR | P53: NR | Q53: UNK | R53: NR | S53: Road environment: In-service pavement sections | U53: The Data.gov title contains the spelling 'Non-LTTP' while the description says the access point includes C-LTPP. Dataset boundaries, image-bearing content, label linkage, downloadable file behavior, and license remain unresolved; therefore the record is not scored or ranked. | V53: DS-048 | W53: Retained existing record | Z53: v3 evidence snapshot | AA53: =HYPERLINK("#'Manual_Review'!A"&(MATCH("DS-048",Manual_Review!$A$6:$A$238,0)+5),"Enter review") -> Enter review | AB53: =HYPERLINK("#'MCDM_Checks'!A"&(MATCH("DS-048",MCDM_Checks!$B$6:$B$3733,0)+5),"Check evidence") -> Check evidence | AC53: Other official / repository | AD53: https://infopave.fhwa.dot.gov/?Goto=NON-LTPP | AE53: https://infopave.fhwa.dot.gov/?Goto=NON-LTPP | AF53: Compared_All_Platforms_TH_v3.0.xlsx!All_Datasets row 49 (DS-048)
A54: DS-049 | B54: A Curated RGB Dataset for Real-Time Road Damage Detection using YOLO | D54: Labeled-16 | E54: =INDEX(MCDM_Grades!$E$6:$E$238,MATCH(A54,MCDM_Grades!$A$6:$A$238,0)) -> 55.555556 | F54: =INDEX(MCDM_Grades!$F$6:$F$238,MATCH(A54,MCDM_Grades!$A$6:$A$238,0)) -> 100 | G54: =INDEX(MCDM_Grades!$G$6:$G$238,MATCH(A54,MCDM_Grades!$A$6:$A$238,0)) -> 0.55555556 | H54: =HYPERLINK("https://data.mendeley.com/datasets/s3k75x9zf4/2","Dataset") -> Dataset | I54: =HYPERLINK("https://data.mendeley.com/datasets/s3k75x9zf4/2","Evidence / paper") -> Evidence / paper | J54: 2 | K54: Detection | L54: Images/frames as reported | M54: NR | N54: 3 classes as YOLO bounding boxes | O54: YOLO TXT with normalised coordinates | P54: CC BY 4.0 | Q54: Direct_Download | R54: 1075 (914 train / 161 validation) | S54: NR | U54: No country, region, capture device or collection date is reported; no test split, only train and validation; images resized and padded to 640x640, so original resolution is lost; provenance of the 'curated' images is not stated, so overlap with existing public datasets cannot be ruled out; no peer-reviewed data paper located | V54: DS-049 | W54: Retained existing record | Z54: v3 evidence snapshot | AA54: =HYPERLINK("#'Manual_Review'!A"&(MATCH("DS-049",Manual_Review!$A$6:$A$238,0)+5),"Enter review") -> Enter review | AB54: =HYPERLINK("#'MCDM_Checks'!A"&(MATCH("DS-049",MCDM_Checks!$B$6:$B$3733,0)+5),"Check evidence") -> Check evidence | AC54: Mendeley Data | AD54: https://data.mendeley.com/datasets/s3k75x9zf4/2 | AE54: https://data.mendeley.com/datasets/s3k75x9zf4/2 | AF54: Compared_All_Platforms_TH_v3.0.xlsx!All_Datasets row 50 (DS-049)
A55: DS-050 | B55: A Real-World Road Dataset For Manhole and Speed Breaker Detection in Bangladesh | D55: Labeled-16 | E55: =INDEX(MCDM_Grades!$E$6:$E$238,MATCH(A55,MCDM_Grades!$A$6:$A$238,0)) -> 44.444444 | F55: =INDEX(MCDM_Grades!$F$6:$F$238,MATCH(A55,MCDM_Grades!$A$6:$A$238,0)) -> 100 | G55: =INDEX(MCDM_Grades!$G$6:$G$238,MATCH(A55,MCDM_Grades!$A$6:$A$238,0)) -> 0.44444444 | H55: =HYPERLINK("https://data.mendeley.com/datasets/7zzcmv2wz7/1","Dataset") -> Dataset | I55: =HYPERLINK("https://data.mendeley.com/datasets/7zzcmv2wz7/1","Evidence / paper") -> Evidence / paper | J55: 1 | K55: Classification; Detection | L55: NR | M55: NR | N55: 5 folder classes: Uncovered_Manhole; Square_Manhole; Speed_Breaker; Good_Manhole; Broken_Manhole | O55: Folder-based class labels | P55: CC BY 4.0 | Q55: Direct_Download | R55: NR | S55: Bangladesh; Road environment: Urban road | U55: The subject is road furniture condition (manhole covers and speed breakers) rather than pavement distress, so it does not support pavement-condition modelling; no counts, resolution, device or date reported; only the Broken_Manhole and Uncovered_Manhole classes carry any condition meaning | V55: DS-050 | W55: Retained existing record | Z55: v3 evidence snapshot | AA55: =HYPERLINK("#'Manual_Review'!A"&(MATCH("DS-050",Manual_Review!$A$6:$A$238,0)+5),"Enter review") -> Enter review | AB55: =HYPERLINK("#'MCDM_Checks'!A"&(MATCH("DS-050",MCDM_Checks!$B$6:$B$3733,0)+5),"Check evidence") -> Check evidence | AC55: Mendeley Data | AD55: https://data.mendeley.com/datasets/7zzcmv2wz7/1 | AE55: https://data.mendeley.com/datasets/7zzcmv2wz7/1 | AF55: Compared_All_Platforms_TH_v3.0.xlsx!All_Datasets row 51 (DS-050)
A56: DS-051 | B56: An Annotated Water-Filled, and Dry Potholes Dataset for Deep Learning Applications | D56: Labeled-16 | E56: =INDEX(MCDM_Grades!$E$6:$E$238,MATCH(A56,MCDM_Grades!$A$6:$A$238,0)) -> 30.555556 | F56: =INDEX(MCDM_Grades!$F$6:$F$238,MATCH(A56,MCDM_Grades!$A$6:$A$238,0)) -> 100 | G56: =INDEX(MCDM_Grades!$G$6:$G$238,MATCH(A56,MCDM_Grades!$A$6:$A$238,0)) -> 0.30555556 | H56: =HYPERLINK("https://data.mendeley.com/datasets/tp95cdvgm8/1","Dataset") -> Dataset | I56: =HYPERLINK("https://data.mendeley.com/datasets/tp95cdvgm8/1","Evidence / paper") -> Evidence / paper | J56: 1 | K56: Object detection;Object recognition;Classification | L56: NR | M56: Dashcam/front-rear vehicle videos; still-image acquisition NR | N56: Pothole bounding boxes; water state indicated by dataset scope | O56: Pascal VOC XML;YOLO TXT;images;dashcam MP4 | P56: CC BY 4.0 | Q56: Direct_Download | R56: NR | S56: United Kingdom; Road environment: Outdoor road; water-filled and dry potholes | U56: Image count, resolution, collection geography, annotation procedure, and quality control not reported on landing page | V56: DS-051 | W56: Retained existing record | Z56: v3 evidence snapshot | AA56: =HYPERLINK("#'Manual_Review'!A"&(MATCH("DS-051",Manual_Review!$A$6:$A$238,0)+5),"Enter review") -> Enter review | AB56: =HYPERLINK("#'MCDM_Checks'!A"&(MATCH("DS-051",MCDM_Checks!$B$6:$B$3733,0)+5),"Check evidence") -> Check evidence | AC56: Mendeley Data | AD56: https://data.mendeley.com/datasets/tp95cdvgm8/1 | AE56: https://data.mendeley.com/datasets/tp95cdvgm8/1 | AF56: Compared_All_Platforms_TH_v3.0.xlsx!All_Datasets row 52 (DS-051)
A57: DS-052 | B57: Asphalt Crack Dataset | D57: Labeled-16 | E57: =INDEX(MCDM_Grades!$E$6:$E$238,MATCH(A57,MCDM_Grades!$A$6:$A$238,0)) -> 36.111111 | F57: =INDEX(MCDM_Grades!$F$6:$F$238,MATCH(A57,MCDM_Grades!$A$6:$A$238,0)) -> 100 | G57: =INDEX(MCDM_Grades!$G$6:$G$238,MATCH(A57,MCDM_Grades!$A$6:$A$238,0)) -> 0.36111111 | H57: =HYPERLINK("https://data.mendeley.com/datasets/xnzhj3x8v4/2","Dataset") -> Dataset | I57: =HYPERLINK("https://data.mendeley.com/datasets/xnzhj3x8v4/2","Evidence / paper") -> Evidence / paper | J57: 2 | K57: Classification | L57: Images/frames as reported | M57: Camera (model not stated) | N57: Binary image-level labels: crack; non-crack | O57: NR | P57: CC BY 4.0 | Q57: Direct_Download | R57: 400 | S57: NR | U57: Two-sentence record with no country, device, resolution, date or annotation detail; only 400 images with binary presence labels; oldest record retained in this batch and superseded in every respect by later crack datasets | V57: DS-052 | W57: Retained existing record | Z57: v3 evidence snapshot | AA57: =HYPERLINK("#'Manual_Review'!A"&(MATCH("DS-052",Manual_Review!$A$6:$A$238,0)+5),"Enter review") -> Enter review | AB57: =HYPERLINK("#'MCDM_Checks'!A"&(MATCH("DS-052",MCDM_Checks!$B$6:$B$3733,0)+5),"Check evidence") -> Check evidence | AC57: Mendeley Data | AD57: https://data.mendeley.com/datasets/xnzhj3x8v4/2 | AE57: https://data.mendeley.com/datasets/xnzhj3x8v4/2 | AF57: Compared_All_Platforms_TH_v3.0.xlsx!All_Datasets row 53 (DS-052)
A58: DS-053 | B58: Asphalt Cracked and Uncracked Image Dataset | D58: Labeled-16 | E58: =INDEX(MCDM_Grades!$E$6:$E$238,MATCH(A58,MCDM_Grades!$A$6:$A$238,0)) -> 80.555556 | F58: =INDEX(MCDM_Grades!$F$6:$F$238,MATCH(A58,MCDM_Grades!$A$6:$A$238,0)) -> 100 | G58: =INDEX(MCDM_Grades!$G$6:$G$238,MATCH(A58,MCDM_Grades!$A$6:$A$238,0)) -> 0.80555556 | H58: =HYPERLINK("https://data.mendeley.com/datasets/88kdyyc73h/1","Dataset") -> Dataset | I58: =HYPERLINK("https://data.mendeley.com/datasets/88kdyyc73h/1","Evidence / paper") -> Evidence / paper | J58: 1 | K58: Classification | L58: Images/frames as reported | M58: Vehicle-mounted enclosed camera rig suspended from a towbar-mounted bicycle carrier (fixed height, 30 fps) | N58: Binary image-level labels: cracked; uncracked | O58: Folder-based class labels | P58: CC BY 4.0 | Q58: Direct_Download | R58: 2000 at 1440x1440; more than 8000 at 360x360; more than 3000 at 720x720 | S58: Road environment: Urban road; Rural road | U58: Binary image-level labels only, with no distress typing, localisation or severity; country and route not reported; the 360x360 and 720x720 subsets are crops of the 1440x1440 set, so the three subsets are not independent; the referenced Construction and Building Materials paper is not identified by DOI on the record | V58: DS-053 | W58: Retained existing record | Z58: v3 evidence snapshot | AA58: =HYPERLINK("#'Manual_Review'!A"&(MATCH("DS-053",Manual_Review!$A$6:$A$238,0)+5),"Enter review") -> Enter review | AB58: =HYPERLINK("#'MCDM_Checks'!A"&(MATCH("DS-053",MCDM_Checks!$B$6:$B$3733,0)+5),"Check evidence") -> Check evidence | AC58: Mendeley Data | AD58: https://data.mendeley.com/datasets/88kdyyc73h/1 | AE58: https://data.mendeley.com/datasets/88kdyyc73h/1 | AF58: Compared_All_Platforms_TH_v3.0.xlsx!All_Datasets row 54 (DS-053)
A59: DS-054 | B59: Attain: Inclusive Annotated Pavement Distress Types and Severity Dataset | D59: Labeled-16 | E59: =INDEX(MCDM_Grades!$E$6:$E$238,MATCH(A59,MCDM_Grades!$A$6:$A$238,0)) -> 63.888889 | F59: =INDEX(MCDM_Grades!$F$6:$F$238,MATCH(A59,MCDM_Grades!$A$6:$A$238,0)) -> 100 | G59: =INDEX(MCDM_Grades!$G$6:$G$238,MATCH(A59,MCDM_Grades!$A$6:$A$238,0)) -> 0.63888889 | H59: =HYPERLINK("https://data.mendeley.com/datasets/nykrzdm74f/1","Dataset") -> Dataset | I59: =HYPERLINK("https://data.mendeley.com/datasets/nykrzdm74f/1","Evidence / paper") -> Evidence / paper | J59: 1 | K59: Detection; Classification [Claude] | Object detection;Classification [GPT] | L59: Images/frames as reported | M59: Vehicle-mounted smartphone (front and rear windshield) [Claude] | Vehicle-mounted smartphones on front and rear windshields [GPT] | N59: 10 distress classes with three severity levels (low; medium; high); 19761 annotated distress instances [Claude] | Ten pavement-distress categories reported; 19,761 instances [GPT] | O59: YOLO; Pascal VOC XML; Polygon text | P59: CC BY 4.0 | Q59: Direct_Download | R59: 2293 | S59: Iran; Tehran; Road environment: Urban road; Arterial [Claude] | Road pavement [GPT] | U59: Single-city collection (Tehran) limits geographic transfer; no GPS, IMU or depth channel; per-image acquisition dates not reported; no inter-annotator agreement statistic; class distribution highly imbalanced (Block crack n=61 vs Linear crack n=9019) [Claude] | Image resolution, annotation format, geography details, and quality-control procedure not reported on landing page [GPT] | V59: DS-054 | W59: Retained existing record | Z59: v3 evidence snapshot | AA59: =HYPERLINK("#'Manual_Review'!A"&(MATCH("DS-054",Manual_Review!$A$6:$A$238,0)+5),"Enter review") -> Enter review | AB59: =HYPERLINK("#'MCDM_Checks'!A"&(MATCH("DS-054",MCDM_Checks!$B$6:$B$3733,0)+5),"Check evidence") -> Check evidence | AC59: Mendeley Data | AD59: https://data.mendeley.com/datasets/nykrzdm74f/1 | AE59: https://data.mendeley.com/datasets/nykrzdm74f/1 | AF59: Compared_All_Platforms_TH_v3.0.xlsx!All_Datasets row 55 (DS-054)
A60: DS-055 | B60: Bandung Pothole Image Dataset (BPID) | D60: Labeled-16 | E60: =INDEX(MCDM_Grades!$E$6:$E$238,MATCH(A60,MCDM_Grades!$A$6:$A$238,0)) -> 58.333333 | F60: =INDEX(MCDM_Grades!$F$6:$F$238,MATCH(A60,MCDM_Grades!$A$6:$A$238,0)) -> 100 | G60: =INDEX(MCDM_Grades!$G$6:$G$238,MATCH(A60,MCDM_Grades!$A$6:$A$238,0)) -> 0.58333333 | H60: =HYPERLINK("https://data.mendeley.com/datasets/rgymy6dwdd/1","Dataset") -> Dataset | I60: =HYPERLINK("https://data.mendeley.com/datasets/rgymy6dwdd/1","Evidence / paper") -> Evidence / paper | J60: 1 | K60: Detection | L60: Images/frames as reported | M60: NR | N60: Annotated potholes; high-contrast tree shadows retained as hard negatives | O60: NR | P60: CC BY 4.0 | Q60: Direct_Download | R60: 50 | S60: Indonesia; Bandung City, West Java; Road environment: Urban road | U60: Only 50 images, so it is usable as an out-of-distribution test set and not for training; single distress class; camera, resolution, annotation format and collection dates all unreported; no peer-reviewed data paper located | V60: DS-055 | W60: Retained existing record | Z60: v3 evidence snapshot | AA60: =HYPERLINK("#'Manual_Review'!A"&(MATCH("DS-055",Manual_Review!$A$6:$A$238,0)+5),"Enter review") -> Enter review | AB60: =HYPERLINK("#'MCDM_Checks'!A"&(MATCH("DS-055",MCDM_Checks!$B$6:$B$3733,0)+5),"Check evidence") -> Check evidence | AC60: Mendeley Data | AD60: https://data.mendeley.com/datasets/rgymy6dwdd/1 | AE60: https://data.mendeley.com/datasets/rgymy6dwdd/1 | AF60: Compared_All_Platforms_TH_v3.0.xlsx!All_Datasets row 56 (DS-055)
A61: DS-056 | B61: Bangladesh Road Damage Detection Dataset | D61: Labeled-16 | E61: =INDEX(MCDM_Grades!$E$6:$E$238,MATCH(A61,MCDM_Grades!$A$6:$A$238,0)) -> 61.111111 | F61: =INDEX(MCDM_Grades!$F$6:$F$238,MATCH(A61,MCDM_Grades!$A$6:$A$238,0)) -> 100 | G61: =INDEX(MCDM_Grades!$G$6:$G$238,MATCH(A61,MCDM_Grades!$A$6:$A$238,0)) -> 0.61111111 | H61: =HYPERLINK("https://data.mendeley.com/datasets/ktnx66vtmc/1","Dataset") -> Dataset | I61: =HYPERLINK("https://data.mendeley.com/datasets/ktnx66vtmc/1","Evidence / paper") -> Evidence / paper | J61: 1 | K61: Detection [Claude] | Object detection [GPT] | L61: NR | M61: Three mobile-device cameras | N61: Single class named 'pothole' covering potholes, broken road surfaces and visible cracks; undamaged road images included as negatives [Claude] | Single unified damage class 'pothole'; normal road negatives [GPT] | O61: YOLOv8 [Claude] | YOLOv8;train/validation/test [GPT] | P61: CC BY 4.0 | Q61: Direct_Download | R61: NR | S61: Bangladesh; Multiple roads; exact regions NR; Road environment: Highway;urban road;rural path | U61: Three distinct distress mechanisms are collapsed into a single class labelled 'pothole', which makes the labels semantically inconsistent with every other road-damage taxonomy; no image count, resolution, device or date reported; no peer-reviewed data paper located [Claude] | All damage types collapsed into one class; image count and QC not reported; recent dataset with limited reuse evidence [GPT] | V61: DS-056 | W61: Retained existing record | Z61: v3 evidence snapshot | AA61: =HYPERLINK("#'Manual_Review'!A"&(MATCH("DS-056",Manual_Review!$A$6:$A$238,0)+5),"Enter review") -> Enter review | AB61: =HYPERLINK("#'MCDM_Checks'!A"&(MATCH("DS-056",MCDM_Checks!$B$6:$B$3733,0)+5),"Check evidence") -> Check evidence | AC61: Mendeley Data | AD61: https://data.mendeley.com/datasets/ktnx66vtmc/1 | AE61: https://data.mendeley.com/datasets/ktnx66vtmc/1 | AF61: Compared_All_Platforms_TH_v3.0.xlsx!All_Datasets row 57 (DS-056)
A62: DS-057 | B62: BDRoad-Sense: Benchmark Dataset for Road Surface Detection and Safety Enhancement | D62: Labeled-16 | E62: =INDEX(MCDM_Grades!$E$6:$E$238,MATCH(A62,MCDM_Grades!$A$6:$A$238,0)) -> 88.888889 | F62: =INDEX(MCDM_Grades!$F$6:$F$238,MATCH(A62,MCDM_Grades!$A$6:$A$238,0)) -> 100 | G62: =INDEX(MCDM_Grades!$G$6:$G$238,MATCH(A62,MCDM_Grades!$A$6:$A$238,0)) -> 0.88888889 | H62: =HYPERLINK("https://data.mendeley.com/datasets/z3nx8n396g/3","Dataset") -> Dataset | I62: =HYPERLINK("https://data.mendeley.com/datasets/z3nx8n396g/3","Evidence / paper") -> Evidence / paper | J62: 3 [Claude] | 1 [GPT] | K62: Classification; Detection [Claude] | Multi-class classification;Benchmarking [GPT] | L62: Images/frames as reported | M62: Four different smartphone cameras (handheld field survey) [Claude] | Four smartphone cameras [GPT] | N62: 5 classes: Major Damage; Minor Damage; Normal Road; Manhole; Speed Breaker. Accompanying CSV records image path, class label, location, area type and device [Claude] | Five image-level classes [GPT] | O62: NR (CSV metadata file accompanies the images) [Claude] | JPG;structured class dataset [GPT] | P62: CC BY 4.0 | Q62: Direct_Download | R62: 6350 original; 9107 after augmentation [Claude] | 12687 [GPT] | S62: Bangladesh; Sylhet District (rural and urban) [Claude] | Sylhet District [GPT]; Road environment: Urban road; Rural road [Claude] | Rural;urban roads [GPT] | U62: 2757 of the 9107 released images are augmentations (brightness, contrast and blur simulation) rather than independent captures, so effective sample size is 6350; annotation file format is not stated; damage severity is only two-level; no peer-reviewed data paper located [Claude] | Nearly half the final images are augmented; severity classes are broad; no license visible in retrieved record; limited reuse due to recent release [GPT] | V62: DS-057 | W62: Retained existing record | Z62: v3 evidence snapshot | AA62: =HYPERLINK("#'Manual_Review'!A"&(MATCH("DS-057",Manual_Review!$A$6:$A$238,0)+5),"Enter review") -> Enter review | AB62: =HYPERLINK("#'MCDM_Checks'!A"&(MATCH("DS-057",MCDM_Checks!$B$6:$B$3733,0)+5),"Check evidence") -> Check evidence | AC62: Mendeley Data | AD62: https://data.mendeley.com/datasets/z3nx8n396g/3 | AE62: https://data.mendeley.com/datasets/z3nx8n396g/3 | AF62: Compared_All_Platforms_TH_v3.0.xlsx!All_Datasets row 58 (DS-057)
A63: DS-058 | B63: BDRS2025: Road Surface Image and Video Datasets from Bangladesh | D63: Labeled-16 | E63: =INDEX(MCDM_Grades!$E$6:$E$238,MATCH(A63,MCDM_Grades!$A$6:$A$238,0)) -> 58.333333 | F63: =INDEX(MCDM_Grades!$F$6:$F$238,MATCH(A63,MCDM_Grades!$A$6:$A$238,0)) -> 100 | G63: =INDEX(MCDM_Grades!$G$6:$G$238,MATCH(A63,MCDM_Grades!$A$6:$A$238,0)) -> 0.58333333 | H63: =HYPERLINK("https://data.mendeley.com/datasets/n6cvjnx3b6/1","Dataset") -> Dataset | I63: =HYPERLINK("https://data.mendeley.com/datasets/n6cvjnx3b6/1","Evidence / paper") -> Evidence / paper | J63: 1 | K63: Classification; Detection; Segmentation | L63: Images/frames as reported | M63: Smartphone (natural driving environments) | N63: 5 categories: pothole; crack; speed breaker; zebra crossing; manhole cover. Average of about 500 annotated images per class | O63: NR | P63: CC BY 4.0 | Q63: Direct_Download | R63: 2685 images and 147 videos | S63: Bangladesh; Dhaka; Chandpur; Lakshmipur; Road environment: Urban road; Rural road | U63: Only two of the five classes are pavement distress; annotation format and resolution are unreported; collection dates not stated; the claim of suitability for segmentation is not backed by released masks; no peer-reviewed data paper located | V63: DS-058 | W63: Retained existing record | Z63: v3 evidence snapshot | AA63: =HYPERLINK("#'Manual_Review'!A"&(MATCH("DS-058",Manual_Review!$A$6:$A$238,0)+5),"Enter review") -> Enter review | AB63: =HYPERLINK("#'MCDM_Checks'!A"&(MATCH("DS-058",MCDM_Checks!$B$6:$B$3733,0)+5),"Check evidence") -> Check evidence | AC63: Mendeley Data | AD63: https://data.mendeley.com/datasets/n6cvjnx3b6/1 | AE63: https://data.mendeley.com/datasets/n6cvjnx3b6/1 | AF63: Compared_All_Platforms_TH_v3.0.xlsx!All_Datasets row 59 (DS-058)
A64: DS-059 | B64: CoCG Road Condition - Detection Dataset (CoCGRCDD) | D64: Labeled-16 | E64: =INDEX(MCDM_Grades!$E$6:$E$238,MATCH(A64,MCDM_Grades!$A$6:$A$238,0)) -> 83.333333 | F64: =INDEX(MCDM_Grades!$F$6:$F$238,MATCH(A64,MCDM_Grades!$A$6:$A$238,0)) -> 100 | G64: =INDEX(MCDM_Grades!$G$6:$G$238,MATCH(A64,MCDM_Grades!$A$6:$A$238,0)) -> 0.83333333 | H64: =HYPERLINK("https://data.mendeley.com/datasets/snyyfknw56/1","Dataset") -> Dataset | I64: =HYPERLINK("https://data.mendeley.com/datasets/snyyfknw56/1","Evidence / paper") -> Evidence / paper | J64: 1 | K64: Detection | L64: Images/frames as reported | M64: Vehicle-mounted USB Logitech Brio camera on the car radiator grille | N64: 4 defect classes plus per-frame scene attributes: shadow; painting; outlandish object; path milling; grain or binder defect; manhole | O64: MS COCO (annotations/instances.json) | P64: CC BY 4.0 | Q64: Direct_Download | R64: 2110 video frames (325 defect-free) | S64: Poland; Road environment: Urban road; Rural road | U64: Single camera on a single vehicle in one country; image resolution, collection dates and route not reported; no severity grading; frames are shared with CoCGRCOBB, so the two records must not be pooled as independent samples | V64: DS-059 | W64: Retained existing record | X64: Same frames; new annotations (DS-059, DS-060) | Z64: v3 evidence snapshot | AA64: =HYPERLINK("#'Manual_Review'!A"&(MATCH("DS-059",Manual_Review!$A$6:$A$238,0)+5),"Enter review") -> Enter review | AB64: =HYPERLINK("#'MCDM_Checks'!A"&(MATCH("DS-059",MCDM_Checks!$B$6:$B$3733,0)+5),"Check evidence") -> Check evidence | AC64: Mendeley Data | AD64: https://data.mendeley.com/datasets/snyyfknw56/1 | AE64: https://data.mendeley.com/datasets/snyyfknw56/1 | AF64: Compared_All_Platforms_TH_v3.0.xlsx!All_Datasets row 60 (DS-059)
A65: DS-060 | B65: CoCG Road Condition - Oriented Bounding Boxes (CoCGRCOBB) | D65: Labeled-16 | E65: =INDEX(MCDM_Grades!$E$6:$E$238,MATCH(A65,MCDM_Grades!$A$6:$A$238,0)) -> 88.888889 | F65: =INDEX(MCDM_Grades!$F$6:$F$238,MATCH(A65,MCDM_Grades!$A$6:$A$238,0)) -> 100 | G65: =INDEX(MCDM_Grades!$G$6:$G$238,MATCH(A65,MCDM_Grades!$A$6:$A$238,0)) -> 0.88888889 | H65: =HYPERLINK("https://data.mendeley.com/datasets/2dfyh84pdf/1","Dataset") -> Dataset | I65: =HYPERLINK("https://data.mendeley.com/datasets/2dfyh84pdf/1","Evidence / paper") -> Evidence / paper | J65: 1 | K65: Detection | L65: Images/frames as reported | M65: Vehicle-mounted USB Logitech Brio camera on the car radiator grille | N65: 3 defect classes plus per-frame scene attributes: shadow; painting; outlandish object; path milling; grain or binder defect; manhole | O65: MS COCO oriented bounding boxes (OBB_annotations.json) | P65: CC BY 4.0 | Q65: Direct_Download | R65: 2110 video frames (325 defect-free) | S65: Poland; Road environment: Urban road; Rural road | U65: Re-annotation of the same 2110 frames as CoCGRCDD, so it is not an independent sample; merging longitudinal and transverse cracks into C12 removes orientation-specific labels; resolution, dates and route not reported | V65: DS-060 | W65: Retained existing record | X65: Same frames; new annotations (DS-059, DS-060) | Z65: v3 evidence snapshot | AA65: =HYPERLINK("#'Manual_Review'!A"&(MATCH("DS-060",Manual_Review!$A$6:$A$238,0)+5),"Enter review") -> Enter review | AB65: =HYPERLINK("#'MCDM_Checks'!A"&(MATCH("DS-060",MCDM_Checks!$B$6:$B$3733,0)+5),"Check evidence") -> Check evidence | AC65: Mendeley Data | AD65: https://data.mendeley.com/datasets/2dfyh84pdf/1 | AE65: https://data.mendeley.com/datasets/2dfyh84pdf/1 | AF65: Compared_All_Platforms_TH_v3.0.xlsx!All_Datasets row 61 (DS-060)
A66: DS-061 | B66: Concrete & Pavement Crack Dataset (Omoebamije) | D66: Labeled-16 | E66: =INDEX(MCDM_Grades!$E$6:$E$238,MATCH(A66,MCDM_Grades!$A$6:$A$238,0)) -> 75 | F66: =INDEX(MCDM_Grades!$F$6:$F$238,MATCH(A66,MCDM_Grades!$A$6:$A$238,0)) -> 100 | G66: =INDEX(MCDM_Grades!$G$6:$G$238,MATCH(A66,MCDM_Grades!$A$6:$A$238,0)) -> 0.75 | H66: =HYPERLINK("https://data.mendeley.com/datasets/429vzbgmbx/1","Dataset") -> Dataset | I66: =HYPERLINK("https://data.mendeley.com/datasets/429vzbgmbx/1","Evidence / paper") -> Evidence / paper | J66: 1 [Claude/CodeX] | Version 1 [Claude] | K66: Classification [Claude] | Image classification;Binary crack detection [Claude] | Binary classification;Crack detection [GPT] | Classification; convolutional neural networks (CNNs) for crack detection in concrete [CodeX] | L66: Images/frames as reported | M66: DJI Mavic 2 Enterprise drone (elevated surfaces) and smartphone (surfaces below average window height) [Claude] | UAV (DJI Mavic 2 Enterprise);Smartphone [Claude] | DJI Mavic 2 Enterprise UAV;Samsung smartphone [GPT] | DJI Mavic 2 Enterprise drone; smartphone [CodeX] | N66: Binary folders: positive (crack); negative (non-crack) [Claude] | Binary class: positive (crack);negative (non-crack) [Claude] | Binary positive crack;negative non-crack [GPT] | Crack; non-crack [CodeX] | O66: Folder-based binary class labels [Claude] | Folder-per-class JPEG directories [Claude] | RGB JPEG;positive and negative folders [GPT] | Folder classes [CodeX] | P66: CC BY 4.0 [Claude/GPT/CodeX] | CC BY-SA 4.0 [Claude] | Q66: Direct_Download [Claude/CodeX] | Registration [Claude/GPT] | R66: 30000 | S66: Nigeria; Nigerian Army University Biu, Borno State [Claude] | Biu, Borno State (Nigerian Army University Biu) [Claude] | Biu;Borno State [GPT] | Biu, Borno State [CodeX]; Road environment: Mixed: concrete structure surfaces and pavement surfaces [Claude] | Campus concrete and pavement surfaces [GPT] | University campus; concrete and pavement surfaces [CodeX] | U66: Concrete structure images and pavement images are pooled with no separating label, so a pavement-only subset cannot be extracted from the documentation; licence conflict between the CC BY 4.0 record field and the 'research purposes only' text; downsized to 227x227, too coarse for fine crack measurement; single site [Claude] | Concrete and pavement images are pooled with no field separating them, so the pavement subset cannot be isolated; licence terms conflict between the metadata field and the description; images downsized to 227x227 lose fine crack detail; binary labels only [Claude] | Concrete and pavement imagery are mixed, and the pavement-only subset is not separately quantified; no localization masks or engineering condition labels are provided. [GPT] | Concrete and pavement records are mixed; description inconsistently calls folders concrete-only; provenance and QA detail limited [CodeX] | V66: DS-061 | W66: Retained existing record | Z66: v3 evidence snapshot | AA66: =HYPERLINK("#'Manual_Review'!A"&(MATCH("DS-061",Manual_Review!$A$6:$A$238,0)+5),"Enter review") -> Enter review | AB66: =HYPERLINK("#'MCDM_Checks'!A"&(MATCH("DS-061",MCDM_Checks!$B$6:$B$3733,0)+5),"Check evidence") -> Check evidence | AC66: Mendeley Data; Kaggle | AD66: https://data.mendeley.com/datasets/429vzbgmbx/1 | AE66: https://data.mendeley.com/datasets/429vzbgmbx/1 | AF66: Compared_All_Platforms_TH_v3.0.xlsx!All_Datasets row 62 (DS-061)
A67: DS-062 | B67: CRACK500 with Noisy Annotation Masks | D67: Labeled-16 | E67: =INDEX(MCDM_Grades!$E$6:$E$238,MATCH(A67,MCDM_Grades!$A$6:$A$238,0)) -> 58.333333 | F67: =INDEX(MCDM_Grades!$F$6:$F$238,MATCH(A67,MCDM_Grades!$A$6:$A$238,0)) -> 100 | G67: =INDEX(MCDM_Grades!$G$6:$G$238,MATCH(A67,MCDM_Grades!$A$6:$A$238,0)) -> 0.58333333 | H67: =HYPERLINK("https://data.mendeley.com/datasets/wddt4gbttd/1","Dataset") -> Dataset | I67: =HYPERLINK("https://data.mendeley.com/datasets/wddt4gbttd/1","Evidence / paper") -> Evidence / paper | J67: 1 | K67: Segmentation | L67: NR | M67: NR (inherited from CRACK500) | N67: Training crack masks deliberately corrupted at four noise levels: 10, 20, 50 and 100 percent of masks replaced by their noisy version | O67: Mask image folders named train_crop_mask_(10,20,50,100)pct | P67: CC BY 4.0 | Q67: Direct_Download | R67: NR | S67: NR (derived from CRACK500); Road environment: Pavement surface | U67: This record contains only corrupted training masks; the training images and the validation and test sets must be obtained separately from https://github.com/fyangneil/pavement-crack-detection, so the Mendeley record is not a standalone dataset; no counts or resolution reported; the referenced SelectSeg article was listed as upcoming at deposit time and no DOI is given | V67: DS-062 | W67: Retained existing record | X67: Parent and noisy-mask derivative (DS-007, DS-062) | Z67: v3 evidence snapshot | AA67: =HYPERLINK("#'Manual_Review'!A"&(MATCH("DS-062",Manual_Review!$A$6:$A$238,0)+5),"Enter review") -> Enter review | AB67: =HYPERLINK("#'MCDM_Checks'!A"&(MATCH("DS-062",MCDM_Checks!$B$6:$B$3733,0)+5),"Check evidence") -> Check evidence | AC67: Mendeley Data | AD67: https://data.mendeley.com/datasets/wddt4gbttd/1 | AE67: https://data.mendeley.com/datasets/wddt4gbttd/1 | AF67: Compared_All_Platforms_TH_v3.0.xlsx!All_Datasets row 63 (DS-062)
A68: DS-063 | B68: CrackAirport: A Dataset for Segmentation of Cracks in Airport Pavements | D68: Labeled-16 | E68: =INDEX(MCDM_Grades!$E$6:$E$238,MATCH(A68,MCDM_Grades!$A$6:$A$238,0)) -> 75 | F68: =INDEX(MCDM_Grades!$F$6:$F$238,MATCH(A68,MCDM_Grades!$A$6:$A$238,0)) -> 100 | G68: =INDEX(MCDM_Grades!$G$6:$G$238,MATCH(A68,MCDM_Grades!$A$6:$A$238,0)) -> 0.75 | H68: =HYPERLINK("https://data.mendeley.com/datasets/3v5r2fxf89/1","Dataset") -> Dataset | I68: =HYPERLINK("https://data.mendeley.com/datasets/3v5r2fxf89/1","Evidence / paper") -> Evidence / paper | J68: 1 | K68: Segmentation | L68: Images/frames as reported | M68: UAV-mounted Sony ILCE-7RM4A camera at 100 feet altitude | N68: Crack segmentation annotations; scenes include aircraft, T-hangars, vegetation, airport markings and signs, and traces of previous maintenance | O68: NR | P68: CC BY 4.0 | Q68: Direct_Download | R68: 2226 | S68: United States; Local airports in Tennessee; Road environment: Airport pavement (runway, taxiway and apron environment) | U68: Airport pavement rather than roadway, so distress mix and traffic loading differ from highway pavement and CAV transfer is limited; single class; images with very few crack pixels were deliberately removed, which biases the crack-pixel prior away from real operational distributions; collection dates not reported; annotation format not stated | V68: DS-063 | W68: Retained existing record | Z68: v3 evidence snapshot | AA68: =HYPERLINK("#'Manual_Review'!A"&(MATCH("DS-063",Manual_Review!$A$6:$A$238,0)+5),"Enter review") -> Enter review | AB68: =HYPERLINK("#'MCDM_Checks'!A"&(MATCH("DS-063",MCDM_Checks!$B$6:$B$3733,0)+5),"Check evidence") -> Check evidence | AC68: Mendeley Data | AD68: https://data.mendeley.com/datasets/3v5r2fxf89/1 | AE68: https://data.mendeley.com/datasets/3v5r2fxf89/1 | AF68: Compared_All_Platforms_TH_v3.0.xlsx!All_Datasets row 64 (DS-063)
A69: DS-064 | B69: Dataset for Drone-based Inspection of Road Pavement Structures for Cracks | D69: Labeled-16 | E69: =INDEX(MCDM_Grades!$E$6:$E$238,MATCH(A69,MCDM_Grades!$A$6:$A$238,0)) -> 52.777778 | F69: =INDEX(MCDM_Grades!$F$6:$F$238,MATCH(A69,MCDM_Grades!$A$6:$A$238,0)) -> 100 | G69: =INDEX(MCDM_Grades!$G$6:$G$238,MATCH(A69,MCDM_Grades!$A$6:$A$238,0)) -> 0.52777778 | H69: =HYPERLINK("https://data.mendeley.com/datasets/csd32bm8zx/1","Dataset") -> Dataset | I69: =HYPERLINK("https://data.mendeley.com/datasets/csd32bm8zx/1","Evidence / paper") -> Evidence / paper | J69: Version 1 [Claude] | 1 [Claude] | K69: Semantic segmentation;Crack characterisation [Claude] | Detection; Segmentation [Claude] | L69: NR | M69: UAV (DJI MINI 2, 12 MP camera, 83-degree field of view, six passes at varying altitude and horizontal speed) [Claude] | UAV (DJI MINI 2, 12 MP camera, 83 degree field of view, continuous recording, six passes at different altitudes and horizontal speeds) [Claude] | N69: Crack regions, with physical length and width measurements taken for some cracks and road landmarks to support crack characterisation [Claude] | UNK - physical length and width measurements were taken for some cracks and road landmarks for crack characterisation evaluation, but it is not documented whether image-level annotations, boxes or masks are included [Claude] | O69: NR | P69: CC BY-SA 4.0 [Claude] | CC BY 4.0 [Claude] | Q69: Metadata_Only [Claude] | Direct_Download [Claude] | R69: NR | S69: Canada; Montmorency Forest laboratory, Universite Laval, north of Quebec City [Claude] | Montmorency Forest laboratory experimental road, north of Quebec City [Claude]; Road environment: Experimental road, 386 m [Claude] | Experimental road (386 m), used for testing pavement paints and laying techniques [Claude] | U69: The Kaggle record is only about 100 kB and functions as a pointer: the imagery itself must be obtained from the Mendeley Data record, so Kaggle access is metadata only; single 386 m experimental road painted for test purposes, which limits representativeness; image counts and annotation format not stated [Claude] | Pending: it is unresolved whether AI-usable image annotations are included or only post-hoc physical crack measurements; frame and video counts are not reported; the associated paper is referenced but not identified by DOI on the record [Claude] | V69: DS-064 | W69: Retained existing record | Z69: v3 evidence snapshot | AA69: =HYPERLINK("#'Manual_Review'!A"&(MATCH("DS-064",Manual_Review!$A$6:$A$238,0)+5),"Enter review") -> Enter review | AB69: =HYPERLINK("#'MCDM_Checks'!A"&(MATCH("DS-064",MCDM_Checks!$B$6:$B$3733,0)+5),"Check evidence") -> Check evidence | AC69: Mendeley Data; Kaggle | AD69: https://data.mendeley.com/datasets/csd32bm8zx/1 | AE69: https://data.mendeley.com/datasets/csd32bm8zx/1 | AF69: Compared_All_Platforms_TH_v3.0.xlsx!All_Datasets row 65 (DS-064)
A70: DS-065 | B70: Dataset of Unpaved and Paved Road Surface with Seasons | D70: Labeled-16 | E70: =INDEX(MCDM_Grades!$E$6:$E$238,MATCH(A70,MCDM_Grades!$A$6:$A$238,0)) -> 69.444444 | F70: =INDEX(MCDM_Grades!$F$6:$F$238,MATCH(A70,MCDM_Grades!$A$6:$A$238,0)) -> 100 | G70: =INDEX(MCDM_Grades!$G$6:$G$238,MATCH(A70,MCDM_Grades!$A$6:$A$238,0)) -> 0.69444444 | H70: =HYPERLINK("https://data.mendeley.com/datasets/tj2m7zz4rg/2","Dataset") -> Dataset | I70: =HYPERLINK("https://data.mendeley.com/datasets/tj2m7zz4rg/2","Evidence / paper") -> Evidence / paper | J70: 2022 (v2); Unpaved and Paved Road Surface with Seasons | K70: Distress / roughness | L70: Images + videos | M70: Other / mixed capture | N70: Paved/unpaved and seasonal/road-condition folders including potholes, uneven road, speed breakers and water presence. | O70: Folder/category labels; object boxes/masks not verified | P70: CC BY 4.0 | Q70: Public links | R70: 8,484 images; repository states 13 videos, associated paper states 10 | S70: Nashik and Mumbai, India | T70: Sonali Bhutad and Kailas Patil | U70: Includes rotated augmentation (4,242 original + 4,242 rotated per paper). Video-count discrepancy preserved. Auxiliary imagery rather than strict AV-footage match. | V70: DS-065; D034 | W70: Same release | Z70: AV inventory evidence snapshot | AA70: =HYPERLINK("#'Manual_Review'!A"&(MATCH("DS-065",Manual_Review!$A$6:$A$238,0)+5),"Enter review") -> Enter review | AB70: =HYPERLINK("#'MCDM_Checks'!A"&(MATCH("DS-065",MCDM_Checks!$B$6:$B$3733,0)+5),"Check evidence") -> Check evidence | AC70: Mendeley Data | AD70: https://data.mendeley.com/datasets/tj2m7zz4rg/2 | AE70: https://data.mendeley.com/datasets/tj2m7zz4rg/2 | AF70: Compared_All_Platforms_TH_v3.0.xlsx!All_Datasets row 66 (DS-065); AV_Pavement_Dataset_Inventory.xlsx!Datasets row 40 (D034)
A71: DS-066 | B71: FCDD: A High-Resolution Unstructured Environment Dataset with Multiple Sand Roads | D71: Labeled-16 | E71: =INDEX(MCDM_Grades!$E$6:$E$238,MATCH(A71,MCDM_Grades!$A$6:$A$238,0)) -> 77.777778 | F71: =INDEX(MCDM_Grades!$F$6:$F$238,MATCH(A71,MCDM_Grades!$A$6:$A$238,0)) -> 100 | G71: =INDEX(MCDM_Grades!$G$6:$G$238,MATCH(A71,MCDM_Grades!$A$6:$A$238,0)) -> 0.77777778 | H71: =HYPERLINK("https://data.mendeley.com/datasets/7wr6hxk54h/1","Dataset") -> Dataset | I71: =HYPERLINK("https://data.mendeley.com/datasets/7wr6hxk54h/1","Evidence / paper") -> Evidence / paper | J71: 1 | K71: Segmentation | L71: Images/frames as reported | M71: Vehicle-mounted 4K camera | N71: 17 semantic classes including road surfaces, markings, cat's eyes, cracks, potholes, vehicles, people, animals and obstacles | O71: Pixel-level semantic masks | P71: CC BY 4.0 | Q71: Direct_Download | R71: 500 pixel-level annotated images (400 train / 100 validation) | S71: Brazil; Florianopolis coastal route (12.2 km), Santa Catarina; Road environment: Coastal route: asphalt road; dirt road; soft sand; hard sand; wet sand | U71: Pavement distress is a minor part of the label space (2 of 17 classes) inside a driving-scene segmentation dataset, so distress-instance counts are not reported; only 500 annotated images; single coastal route; collection dates not reported | V71: DS-066 | W71: Retained existing record | Z71: v3 evidence snapshot | AA71: =HYPERLINK("#'Manual_Review'!A"&(MATCH("DS-066",Manual_Review!$A$6:$A$238,0)+5),"Enter review") -> Enter review | AB71: =HYPERLINK("#'MCDM_Checks'!A"&(MATCH("DS-066",MCDM_Checks!$B$6:$B$3733,0)+5),"Check evidence") -> Check evidence | AC71: Mendeley Data | AD71: https://data.mendeley.com/datasets/7wr6hxk54h/1 | AE71: https://data.mendeley.com/datasets/7wr6hxk54h/1 | AF71: Compared_All_Platforms_TH_v3.0.xlsx!All_Datasets row 67 (DS-066)
A72: DS-067 | B72: HighRPD: High-Altitude Drone Dataset of Road Pavement Distress | D72: Labeled-16 | E72: =INDEX(MCDM_Grades!$E$6:$E$238,MATCH(A72,MCDM_Grades!$A$6:$A$238,0)) -> 100 | F72: =INDEX(MCDM_Grades!$F$6:$F$238,MATCH(A72,MCDM_Grades!$A$6:$A$238,0)) -> 100 | G72: =INDEX(MCDM_Grades!$G$6:$G$238,MATCH(A72,MCDM_Grades!$A$6:$A$238,0)) -> 1 | H72: =HYPERLINK("https://data.mendeley.com/datasets/sywswj7djj/1","Dataset") -> Dataset | I72: =HYPERLINK("https://data.mendeley.com/datasets/sywswj7djj/1","Evidence / paper") -> Evidence / paper | J72: 1 | K72: Detection [Claude] | Object detection;YOLO benchmarking [GPT] | object detection; classification [Test_Batch] | L72: Images/frames as reported | M72: UAV (DJI M300 RTK with Zenmuse P1, 35 mm lens, 50 m flight height) [Claude] | UAV at 50 m altitude [GPT] | UAV or drone [Test_Batch] | N72: 3 classes; 12365 line annotations; 8239 block annotations; 1412 pit annotations [Claude] | Class 0 line;class 1 block;class 2 pit [GPT] | line; block; pit [Test_Batch] | O72: YOLO TXT (class, normalised centre x, centre y, width, height) [Claude] | YOLO TXT bounding boxes;JPG [GPT] | P72: CC BY 4.0 | Q72: Direct_Download | R72: 11696 | S72: China; Shanxi Province (37.768N 112.772E to 37.771N 112.762E) [Claude] | Shanxi [Test_Batch]; Road environment: Highway [Claude/Test_Batch] | Road pavement; aerial perspective [GPT] | U72: Single highway corridor of roughly 1 km, so scene diversity is narrow; nadir UAV viewpoint at 50 m does not match a vehicle-mounted camera geometry; collection dates, weather and lighting not reported; per-tile geo-referencing not released despite RTK platform [Claude] | Aerial viewpoint differs from typical CAV forward-facing imagery; broad distress taxonomy; no engineering condition indices [GPT] | Limited taxonomy and geography; license, navigation metadata, and engineering condition indicators were not found. [Test_Batch] | V72: DS-067 | W72: Retained existing record | Z72: v3 evidence snapshot | AA72: =HYPERLINK("#'Manual_Review'!A"&(MATCH("DS-067",Manual_Review!$A$6:$A$238,0)+5),"Enter review") -> Enter review | AB72: =HYPERLINK("#'MCDM_Checks'!A"&(MATCH("DS-067",MCDM_Checks!$B$6:$B$3733,0)+5),"Check evidence") -> Check evidence | AC72: Mendeley Data | AD72: https://data.mendeley.com/datasets/sywswj7djj/1 | AE72: https://data.mendeley.com/datasets/sywswj7djj/1 | AF72: Compared_All_Platforms_TH_v3.0.xlsx!All_Datasets row 68 (DS-067)
A73: DS-068 | B73: IROSCD: Indonesia Road Surface Classification Dataset | D73: Labeled-16 | E73: =INDEX(MCDM_Grades!$E$6:$E$238,MATCH(A73,MCDM_Grades!$A$6:$A$238,0)) -> 55.555556 | F73: =INDEX(MCDM_Grades!$F$6:$F$238,MATCH(A73,MCDM_Grades!$A$6:$A$238,0)) -> 100 | G73: =INDEX(MCDM_Grades!$G$6:$G$238,MATCH(A73,MCDM_Grades!$A$6:$A$238,0)) -> 0.55555556 | H73: =HYPERLINK("https://data.mendeley.com/datasets/ftcrvjz92c/1","Dataset") -> Dataset | I73: =HYPERLINK("https://data.mendeley.com/datasets/ftcrvjz92c/1","Evidence / paper") -> Evidence / paper | J73: 1 | K73: Classification | L73: NR | M73: Smartphone | N73: 4 image-level classes: Normal Road; Damaged Road; Bumpy Road; Wet Road | O73: NR | P73: CC BY 4.0 | Q73: Direct_Download | R73: NR | S73: Indonesia; Various urban and rural regions across Indonesia; Road environment: Urban road; Rural road | U73: No image count, per-class count, resolution or capture date is reported; the four classes conflate distinct distress mechanisms (cracks, potholes, bumps) into a single 'Damaged Road' label, so it cannot support distress-type modelling; deposited 2026-07-27, very recent and unvalidated | V73: DS-068 | W73: Retained existing record | Z73: v3 evidence snapshot | AA73: =HYPERLINK("#'Manual_Review'!A"&(MATCH("DS-068",Manual_Review!$A$6:$A$238,0)+5),"Enter review") -> Enter review | AB73: =HYPERLINK("#'MCDM_Checks'!A"&(MATCH("DS-068",MCDM_Checks!$B$6:$B$3733,0)+5),"Check evidence") -> Check evidence | AC73: Mendeley Data | AD73: https://data.mendeley.com/datasets/ftcrvjz92c/1 | AE73: https://data.mendeley.com/datasets/ftcrvjz92c/1 | AF73: Compared_All_Platforms_TH_v3.0.xlsx!All_Datasets row 69 (DS-068)
A74: DS-069 | B74: Multi-Weather Pothole Detection (MWPD) | D74: Labeled-16 | E74: =INDEX(MCDM_Grades!$E$6:$E$238,MATCH(A74,MCDM_Grades!$A$6:$A$238,0)) -> 30.555556 | F74: =INDEX(MCDM_Grades!$F$6:$F$238,MATCH(A74,MCDM_Grades!$A$6:$A$238,0)) -> 100 | G74: =INDEX(MCDM_Grades!$G$6:$G$238,MATCH(A74,MCDM_Grades!$A$6:$A$238,0)) -> 0.30555556 | H74: =HYPERLINK("https://data.mendeley.com/datasets/s5hx9n2jc3/2","Dataset") -> Dataset | I74: =HYPERLINK("https://data.mendeley.com/datasets/s5hx9n2jc3/2","Evidence / paper") -> Evidence / paper | J74: 2 [Claude] | 1 [Claude] | Version 1 [Claude] | K74: Detection [Claude] | Object detection [Claude] | L74: NR | M74: NR | N74: Pothole bounding boxes [Claude] | Pothole bounding boxes; augmentation applied via Roboflow (scaling, shifting, shearing, cropping, rotation, colour perturbation, contrast adjustment, noise addition, brightness adjustment) [Claude] | Single class: pothole, with bounding-box annotations [Claude] | O74: NR | P74: CC BY 4.0 [Claude] | CC0: Public Domain [Claude] | Q74: Direct_Download [Claude] | Registration [Claude] | R74: NR | S74: NR (depositor affiliation: American International University Bangladesh) | U74: No image count, resolution, capture device, country or date is reported; single distress class; a near-identical record by the same authors exists at 10.17632/d4n32gbmk4.1 (logged as MDL-038, Pending) and the relationship between the two is undocumented [Claude] | Pending: same title, same three authors and same institution as MDL-031 (10.17632/s5hx9n2jc3.2, deposited three months earlier), with a description that is identical except for an added sentence on Roboflow augmentation. Neither record references the other. Mendeley Data does not expose a file manifest to non-interactive retrieval, so it could not be confirmed whether this is a duplicate deposit, an augmented derivative, or a distinct collection [Claude] | Lighting and weather strata are stated but no per-stratum counts, image count, resolution, country or capture device are given; annotation format not specified; no provenance for the source imagery [Claude] | V74: DS-069 | W74: Retained existing record | Z74: v3 evidence snapshot | AA74: =HYPERLINK("#'Manual_Review'!A"&(MATCH("DS-069",Manual_Review!$A$6:$A$238,0)+5),"Enter review") -> Enter review | AB74: =HYPERLINK("#'MCDM_Checks'!A"&(MATCH("DS-069",MCDM_Checks!$B$6:$B$3733,0)+5),"Check evidence") -> Check evidence | AC74: Mendeley Data; Kaggle | AD74: https://data.mendeley.com/datasets/s5hx9n2jc3/2 | AE74: https://data.mendeley.com/datasets/s5hx9n2jc3/2 | AF74: Compared_All_Platforms_TH_v3.0.xlsx!All_Datasets row 70 (DS-069)
A75: DS-070 | B75: Multiclass Road Surface Damage Classification Dataset: Computer Vision | D75: Labeled-16 | E75: =INDEX(MCDM_Grades!$E$6:$E$238,MATCH(A75,MCDM_Grades!$A$6:$A$238,0)) -> 55.555556 | F75: =INDEX(MCDM_Grades!$F$6:$F$238,MATCH(A75,MCDM_Grades!$A$6:$A$238,0)) -> 100 | G75: =INDEX(MCDM_Grades!$G$6:$G$238,MATCH(A75,MCDM_Grades!$A$6:$A$238,0)) -> 0.55555556 | H75: =HYPERLINK("https://data.mendeley.com/datasets/697w4jkr2x/2","Dataset") -> Dataset | I75: =HYPERLINK("https://data.mendeley.com/datasets/697w4jkr2x/2","Evidence / paper") -> Evidence / paper | J75: 2 | K75: Classification | L75: Images/frames as reported | M75: NR | N75: 3 image-level classes with per-class counts | O75: Folder-based class labels | P75: CC BY 4.0 | Q75: Direct_Download | R75: 1530 (Surface erosion 651; Crack 478; Pothole 401) | S75: NR | U75: No country, region, capture device or collection date is reported; image-level labels only, with no localisation or severity; the 80/10/10 split is described as the intended workflow rather than as a shipped split; shares depositors with MDL-024 and provenance overlap cannot be ruled out | V75: DS-070 | W75: Retained existing record | Z75: v3 evidence snapshot | AA75: =HYPERLINK("#'Manual_Review'!A"&(MATCH("DS-070",Manual_Review!$A$6:$A$238,0)+5),"Enter review") -> Enter review | AB75: =HYPERLINK("#'MCDM_Checks'!A"&(MATCH("DS-070",MCDM_Checks!$B$6:$B$3733,0)+5),"Check evidence") -> Check evidence | AC75: Mendeley Data | AD75: https://data.mendeley.com/datasets/697w4jkr2x/2 | AE75: https://data.mendeley.com/datasets/697w4jkr2x/2 | AF75: Compared_All_Platforms_TH_v3.0.xlsx!All_Datasets row 71 (DS-070)
A76: DS-071 | B76: Multimodal (Image + Point Cloud) Crack Segmentation Dataset | D76: Labeled-16 | E76: =INDEX(MCDM_Grades!$E$6:$E$238,MATCH(A76,MCDM_Grades!$A$6:$A$238,0)) -> 36.111111 | F76: =INDEX(MCDM_Grades!$F$6:$F$238,MATCH(A76,MCDM_Grades!$A$6:$A$238,0)) -> 100 | G76: =INDEX(MCDM_Grades!$G$6:$G$238,MATCH(A76,MCDM_Grades!$A$6:$A$238,0)) -> 0.36111111 | H76: =HYPERLINK("https://data.mendeley.com/datasets/zs3t38sxds/1","Dataset") -> Dataset | I76: =HYPERLINK("https://data.mendeley.com/datasets/zs3t38sxds/1","Evidence / paper") -> Evidence / paper | J76: 1 [Claude] | Version 1 [Claude] | K76: Segmentation [Claude] | Semantic segmentation;Multimodal fusion [Claude] | L76: NR | M76: Intel RealSense L515 LiDAR camera (synchronous image and point cloud capture) [Claude] | LiDAR camera (Intel RealSense L515), synchronous image and point-cloud capture [Claude] | N76: Crack segmentation across varied material, illumination, surface contamination and occlusion conditions (label format not documented) [Claude] | Crack segmentation over paired image and point-cloud data;class list not enumerated on the record [Claude] | O76: NR | P76: CC BY 4.0 [Claude] | CC BY-NC-SA 4.0 [Claude] | Q76: Direct_Download [Claude] | Registration [Claude] | R76: NR | S76: Road environment: Mixed: building surfaces; underground coal mine roadway surrounding rock; pavement [Claude] | Building surfaces;Underground coal mine roadways;Pavement [Claude] | U76: Pavement is only one of three scene types alongside building surfaces and mine roadway rock, and the pavement subset is not separately identified or counted; no image, frame or point-cloud counts; no annotation format; no country or date; no peer-reviewed data paper located [Claude] | This is the only Kaggle record found that pairs imagery with LiDAR point clouds for crack analysis, but pavement is one of three scene types (alongside building surfaces and coal mine roadways) and the record gives no counts, so the pavement fraction of the 38.7 GB is unknown. Annotation format and per-scene splits are also unstated, leaving eligibility unresolved [Claude] | V76: DS-071 | W76: Retained existing record | Z76: v3 evidence snapshot | AA76: =HYPERLINK("#'Manual_Review'!A"&(MATCH("DS-071",Manual_Review!$A$6:$A$238,0)+5),"Enter review") -> Enter review | AB76: =HYPERLINK("#'MCDM_Checks'!A"&(MATCH("DS-071",MCDM_Checks!$B$6:$B$3733,0)+5),"Check evidence") -> Check evidence | AC76: Mendeley Data; Kaggle | AD76: https://data.mendeley.com/datasets/zs3t38sxds/1 | AE76: https://data.mendeley.com/datasets/zs3t38sxds/1 | AF76: Compared_All_Platforms_TH_v3.0.xlsx!All_Datasets row 72 (DS-071)
A77: DS-072 | B77: N-RDD2024: Road Damage and Defects — v5 | D77: Labeled-16 | E77: =INDEX(MCDM_Grades!$E$6:$E$238,MATCH(A77,MCDM_Grades!$A$6:$A$238,0)) -> 47.222222 | F77: =INDEX(MCDM_Grades!$F$6:$F$238,MATCH(A77,MCDM_Grades!$A$6:$A$238,0)) -> 100 | G77: =INDEX(MCDM_Grades!$G$6:$G$238,MATCH(A77,MCDM_Grades!$A$6:$A$238,0)) -> 0.47222222 | H77: =HYPERLINK("https://data.mendeley.com/datasets/27c8pwsd6v/5","Dataset") -> Dataset | I77: =HYPERLINK("https://data.mendeley.com/datasets/27c8pwsd6v/5","Evidence / paper") -> Evidence / paper | J77: 2024 (v5); N-RDD2024 — Road damage and defects | K77: Distress / roughness | L77: Images / patches | M77: Human-driven survey | N77: D00 longitudinal crack; D10 transverse crack; D20 alligator crack; D30 repaired crack; D40 pothole; D50 pedestrian-crossing blur; D60 lane-line blur; D70 manhole cover; D80 patch; D90 rutting | O77: Object-detection labels; verify archive format before training | P77: CC BY 4.0 | Q77: Public links | R77: Image count not independently confirmed from v5 landing page. | S77: Includes RDD2022's six-country imagery; exact v5 geographic totals unverified. | T77: Ömer Kaya and Muhammed Yasin Çodur / Erzurum Technical University | U77: Derivative overlap with RDD2022; not all classes indicate defects (e.g., manhole cover). Expanded distress vocabulary useful. | V77: DS-072; D018 | W77: Same version represented in legacy family row | X77: Derived/compiled RDD family (DS-035, DS-072, DS-095, DS-099, DS-132, DS-162, DS-104, DS-105) | Y77: Legacy DS-072 preferred URL was /3 although Dataset_Version and DOI fields also included /5. Current canonical review is v5; legacy checks must not be silently treated as v5 payload verification. | Z77: AV inventory evidence snapshot | AA77: =HYPERLINK("#'Manual_Review'!A"&(MATCH("DS-072",Manual_Review!$A$6:$A$238,0)+5),"Enter review") -> Enter review | AB77: =HYPERLINK("#'MCDM_Checks'!A"&(MATCH("DS-072",MCDM_Checks!$B$6:$B$3733,0)+5),"Check evidence") -> Check evidence | AC77: Mendeley Data | AD77: https://data.mendeley.com/datasets/27c8pwsd6v/5 | AE77: https://data.mendeley.com/datasets/27c8pwsd6v/5 | AF77: Compared_All_Platforms_TH_v3.0.xlsx!All_Datasets row 73 (DS-072); AV_Pavement_Dataset_Inventory.xlsx!Datasets row 24 (D018)
A78: DS-073 | B78: PathCare: A Dataset for Road Fault Diagnosis | D78: Labeled-16 | E78: =INDEX(MCDM_Grades!$E$6:$E$238,MATCH(A78,MCDM_Grades!$A$6:$A$238,0)) -> 63.888889 | F78: =INDEX(MCDM_Grades!$F$6:$F$238,MATCH(A78,MCDM_Grades!$A$6:$A$238,0)) -> 100 | G78: =INDEX(MCDM_Grades!$G$6:$G$238,MATCH(A78,MCDM_Grades!$A$6:$A$238,0)) -> 0.63888889 | H78: =HYPERLINK("https://data.mendeley.com/datasets/6p52w7d5xd/2","Dataset") -> Dataset | I78: =HYPERLINK("https://data.mendeley.com/datasets/6p52w7d5xd/2","Evidence / paper") -> Evidence / paper | J78: 2 | K78: Instance segmentation;Classification | L78: Images/frames as reported | M78: Vehicle-mounted GoPro Hero 9 | N78: Three classes: crack;pothole;uneven surface | O78: Roboflow annotations; exact export format NR | P78: NR | Q78: Direct_Download | R78: 386 | S78: Pakistan; Road environment: Various road types; 28-km route | U78: Small image set; performance claim lacks independent validation in landing-page evidence; license not visible in retrieved record | V78: DS-073 | W78: Retained existing record | Z78: v3 evidence snapshot | AA78: =HYPERLINK("#'Manual_Review'!A"&(MATCH("DS-073",Manual_Review!$A$6:$A$238,0)+5),"Enter review") -> Enter review | AB78: =HYPERLINK("#'MCDM_Checks'!A"&(MATCH("DS-073",MCDM_Checks!$B$6:$B$3733,0)+5),"Check evidence") -> Check evidence | AC78: Mendeley Data | AD78: https://data.mendeley.com/datasets/6p52w7d5xd/2 | AE78: https://data.mendeley.com/datasets/6p52w7d5xd/2 | AF78: Compared_All_Platforms_TH_v3.0.xlsx!All_Datasets row 74 (DS-073)
A79: DS-074 | B79: PaveCrack1300: UAV-Acquired Pavement Crack Segmentation Dataset | D79: Labeled-16 | E79: =INDEX(MCDM_Grades!$E$6:$E$238,MATCH(A79,MCDM_Grades!$A$6:$A$238,0)) -> 94.444444 | F79: =INDEX(MCDM_Grades!$F$6:$F$238,MATCH(A79,MCDM_Grades!$A$6:$A$238,0)) -> 100 | G79: =INDEX(MCDM_Grades!$G$6:$G$238,MATCH(A79,MCDM_Grades!$A$6:$A$238,0)) -> 0.94444444 | H79: =HYPERLINK("https://data.mendeley.com/datasets/8b27pdcxv7/1","Dataset") -> Dataset | I79: =HYPERLINK("https://data.mendeley.com/datasets/8b27pdcxv7/1","Evidence / paper") -> Evidence / paper | J79: 1 | K79: Segmentation | L79: Images/frames as reported | M79: UAV (DJI Mini 4 Pro) [Claude] | DJI Mini 4 Pro UAV [CodeX] | N79: Binary pixel masks (crack = 255, background = 0); mean crack pixel occupancy 10.80 percent, median 8.61 percent, range 4.03 to 56.14 percent [Claude] | Crack pixels; background [CodeX] | O79: JPEG RGB images with paired binary PNG masks [Claude] | Binary PNG mask [CodeX] | P79: CC BY 4.0 | Q79: Direct_Download | R79: 1300 image-mask pairs [Claude] | 1300 [CodeX] | S79: China; Shenyang (Shenyang Jianzhu University campus and surrounding road network) [Claude] | Shenyang [CodeX]; Road environment: Campus road; Urban road [Claude] | University campus roads; surrounding road network [CodeX] | U79: Single class (crack) with no distress typing or severity; one campus and its immediate road network; 1300 pairs is small for segmentation pretraining; collection dates, weather and flight altitude not reported; no peer-reviewed data paper located [Claude] | Single-city collection; binary crack-only labels; road segment count and collection conditions NR [CodeX] | V79: DS-074 | W79: Retained existing record | Z79: v3 evidence snapshot | AA79: =HYPERLINK("#'Manual_Review'!A"&(MATCH("DS-074",Manual_Review!$A$6:$A$238,0)+5),"Enter review") -> Enter review | AB79: =HYPERLINK("#'MCDM_Checks'!A"&(MATCH("DS-074",MCDM_Checks!$B$6:$B$3733,0)+5),"Check evidence") -> Check evidence | AC79: Mendeley Data | AD79: https://data.mendeley.com/datasets/8b27pdcxv7/1 | AE79: https://data.mendeley.com/datasets/8b27pdcxv7/1 | AF79: Compared_All_Platforms_TH_v3.0.xlsx!All_Datasets row 75 (DS-074)
A80: DS-075 | B80: PaveDistress: Comprehensive Dataset of Pavement Distresses | D80: Labeled-16 | E80: =INDEX(MCDM_Grades!$E$6:$E$238,MATCH(A80,MCDM_Grades!$A$6:$A$238,0)) -> 61.111111 | F80: =INDEX(MCDM_Grades!$F$6:$F$238,MATCH(A80,MCDM_Grades!$A$6:$A$238,0)) -> 100 | G80: =INDEX(MCDM_Grades!$G$6:$G$238,MATCH(A80,MCDM_Grades!$A$6:$A$238,0)) -> 0.61111111 | H80: =HYPERLINK("https://data.mendeley.com/datasets/f46zt2g83x/1","Dataset") -> Dataset | I80: =HYPERLINK("https://data.mendeley.com/datasets/f46zt2g83x/1","Evidence / paper") -> Evidence / paper | J80: 1 | K80: Detection; Classification; Segmentation [Claude] | classification; object detection; segmentation; distress measurement [GPT] | L80: NR | M80: Specialised pavement inspection vehicle [Claude] | Specialized pavement inspection vehicle; Basler raL2048-80km line-scan camera; infrared laser-assisted lighting [GPT] | N80: Category folders for transverse, longitudinal and map cracks, patches, potholes and defect-free background images [Claude] | background; crack; patch; pothole; other; crack subtypes [GPT] | O80: folder-level classes; fine-grained annotation format NR | P80: CC BY 4.0 | Q80: Direct_Download | R80: NR | S80: China; S315 highway [Claude] | S315 highway, Bayanhaote-Erkehashiha segment [GPT]; Road environment: Highway [Claude] | Highway asphalt pavement [GPT] | U80: No image count is stated on the canonical record or recoverable without downloading; annotation format and annotation method are not documented; collection dates not reported; single highway corridor [Claude] | Total image count and exact annotation schema not found; potholes are reported as limited; single highway segment [GPT] | V80: DS-075 | W80: Retained existing record | Z80: v3 evidence snapshot | AA80: =HYPERLINK("#'Manual_Review'!A"&(MATCH("DS-075",Manual_Review!$A$6:$A$238,0)+5),"Enter review") -> Enter review | AB80: =HYPERLINK("#'MCDM_Checks'!A"&(MATCH("DS-075",MCDM_Checks!$B$6:$B$3733,0)+5),"Check evidence") -> Check evidence | AC80: Mendeley Data | AD80: https://data.mendeley.com/datasets/f46zt2g83x/1 | AE80: https://data.mendeley.com/datasets/f46zt2g83x/1 | AF80: Compared_All_Platforms_TH_v3.0.xlsx!All_Datasets row 76 (DS-075)
A81: DS-076 | B81: Pavement Distress Dataset (Liu) | D81: Labeled-16 | E81: =INDEX(MCDM_Grades!$E$6:$E$238,MATCH(A81,MCDM_Grades!$A$6:$A$238,0)) -> 33.333333 | F81: =INDEX(MCDM_Grades!$F$6:$F$238,MATCH(A81,MCDM_Grades!$A$6:$A$238,0)) -> 100 | G81: =INDEX(MCDM_Grades!$G$6:$G$238,MATCH(A81,MCDM_Grades!$A$6:$A$238,0)) -> 0.33333333 | H81: =HYPERLINK("https://data.mendeley.com/datasets/cbm6dkvggn/1","Dataset") -> Dataset | I81: =HYPERLINK("https://data.mendeley.com/datasets/cbm6dkvggn/1","Evidence / paper") -> Evidence / paper | J81: 1 | K81: NR | L81: Images/frames as reported | M81: NR | N81: NR | O81: NR | P81: CC BY 4.0 | Q81: Direct_Download | R81: 10544 total: 6200 asphalt pavement; 4344 concrete pavement; plus a 212-image complex background subset drawn from the asphalt test set | S81: NR (depositor affiliation: Wuhan University of Science and Technology) | U81: The record documents nothing beyond three image counts: no distress taxonomy, no annotation format, no evidence that labels exist at all, no resolution, no country, no capture device and no associated publication. Cannot be treated as an annotated dataset without downloading and inspecting the archive | V81: DS-076 | W81: Retained existing record | Z81: v3 evidence snapshot | AA81: =HYPERLINK("#'Manual_Review'!A"&(MATCH("DS-076",Manual_Review!$A$6:$A$238,0)+5),"Enter review") -> Enter review | AB81: =HYPERLINK("#'MCDM_Checks'!A"&(MATCH("DS-076",MCDM_Checks!$B$6:$B$3733,0)+5),"Check evidence") -> Check evidence | AC81: Mendeley Data | AD81: https://data.mendeley.com/datasets/cbm6dkvggn/1 | AE81: https://data.mendeley.com/datasets/cbm6dkvggn/1 | AF81: Compared_All_Platforms_TH_v3.0.xlsx!All_Datasets row 77 (DS-076)
A82: DS-077 | B82: PavementDamagesG-7 | D82: Labeled-16 | E82: =INDEX(MCDM_Grades!$E$6:$E$238,MATCH(A82,MCDM_Grades!$A$6:$A$238,0)) -> 66.666667 | F82: =INDEX(MCDM_Grades!$F$6:$F$238,MATCH(A82,MCDM_Grades!$A$6:$A$238,0)) -> 100 | G82: =INDEX(MCDM_Grades!$G$6:$G$238,MATCH(A82,MCDM_Grades!$A$6:$A$238,0)) -> 0.66666667 | H82: =HYPERLINK("https://data.mendeley.com/datasets/yb65trwbd8/3","Dataset") -> Dataset | I82: =HYPERLINK("https://data.mendeley.com/datasets/yb65trwbd8/3","Evidence / paper") -> Evidence / paper | J82: 3 | K82: Segmentation; Classification | L82: NR | M82: StereoLabs ZED 2i stereo camera | N82: 7 pixel-wise mask classes: longitudinal/transverse crack; alligator cracking; pothole; pavement marking; drains; patching; background or no damage | O82: RGB JPG images with pixel-wise PNG masks, one RGB colour code per damage class | P82: CC BY 4.0 | Q82: Direct_Download | R82: NR | S82: Colombia; Cali; Road environment: Urban road (flexible pavement) | U82: No image count is reported anywhere on the record, so dataset scale is unknown; although a ZED 2i stereo camera was used it is not stated whether depth or disparity data are included; three versions with no changelog; no peer-reviewed data paper located | V82: DS-077 | W82: Retained existing record | Z82: v3 evidence snapshot | AA82: =HYPERLINK("#'Manual_Review'!A"&(MATCH("DS-077",Manual_Review!$A$6:$A$238,0)+5),"Enter review") -> Enter review | AB82: =HYPERLINK("#'MCDM_Checks'!A"&(MATCH("DS-077",MCDM_Checks!$B$6:$B$3733,0)+5),"Check evidence") -> Check evidence | AC82: Mendeley Data | AD82: https://data.mendeley.com/datasets/yb65trwbd8/3 | AE82: https://data.mendeley.com/datasets/yb65trwbd8/3 | AF82: Compared_All_Platforms_TH_v3.0.xlsx!All_Datasets row 78 (DS-077)
A83: DS-078 | B83: PDD: A Pixel-Level Road Pavement Deformation Dataset for Semantic Segmentation of Road Surface Distresses | D83: Labeled-16 | E83: =INDEX(MCDM_Grades!$E$6:$E$238,MATCH(A83,MCDM_Grades!$A$6:$A$238,0)) -> 88.888889 | F83: =INDEX(MCDM_Grades!$F$6:$F$238,MATCH(A83,MCDM_Grades!$A$6:$A$238,0)) -> 100 | G83: =INDEX(MCDM_Grades!$G$6:$G$238,MATCH(A83,MCDM_Grades!$A$6:$A$238,0)) -> 0.88888889 | H83: =HYPERLINK("https://data.mendeley.com/datasets/fgtjn9kjkd/1","Dataset") -> Dataset | I83: =HYPERLINK("https://data.mendeley.com/datasets/fgtjn9kjkd/1","Evidence / paper") -> Evidence / paper | J83: 1 | K83: Segmentation | L83: Images/frames as reported | M83: Vehicle-mounted Logitech C925e webcam; Intel RealSense D455 RGB-D camera; GoPro HERO10; handheld Samsung Galaxy A55 smartphone | N83: 5 deformation classes with polygon boundaries | O83: YOLO segmentation (polygon) | P83: CC BY-NC 3.0 | Q83: Direct_Download | R83: 6332 | S83: Indonesia; Lampung Province (Bandar Lampung City; South Lampung; East Lampung; Central Lampung; Metro City; Pesawaran Regency); Road environment: Urban road; Rural road | U83: CC BY-NC 3.0 blocks commercial reuse; no associated peer-reviewed data paper located, so counts rest on the depositor description alone; although an Intel RealSense D455 RGB-D camera was used, it is not stated whether depth frames are included in the release; cracking classes are absent (deformation distresses only) | V83: DS-078 | W83: Retained existing record | Z83: v3 evidence snapshot | AA83: =HYPERLINK("#'Manual_Review'!A"&(MATCH("DS-078",Manual_Review!$A$6:$A$238,0)+5),"Enter review") -> Enter review | AB83: =HYPERLINK("#'MCDM_Checks'!A"&(MATCH("DS-078",MCDM_Checks!$B$6:$B$3733,0)+5),"Check evidence") -> Check evidence | AC83: Mendeley Data | AD83: https://data.mendeley.com/datasets/fgtjn9kjkd/1 | AE83: https://data.mendeley.com/datasets/fgtjn9kjkd/1 | AF83: Compared_All_Platforms_TH_v3.0.xlsx!All_Datasets row 79 (DS-078)
A84: DS-079 | B84: Pothole Mix | D84: Labeled-16 | E84: =INDEX(MCDM_Grades!$E$6:$E$238,MATCH(A84,MCDM_Grades!$A$6:$A$238,0)) -> 75 | F84: =INDEX(MCDM_Grades!$F$6:$F$238,MATCH(A84,MCDM_Grades!$A$6:$A$238,0)) -> 100 | G84: =INDEX(MCDM_Grades!$G$6:$G$238,MATCH(A84,MCDM_Grades!$A$6:$A$238,0)) -> 0.75 | H84: =HYPERLINK("https://data.mendeley.com/datasets/kfth5g2xk3/2","Dataset") -> Dataset | I84: =HYPERLINK("https://data.mendeley.com/datasets/kfth5g2xk3/2","Evidence / paper") -> Evidence / paper | J84: 2022 (v2); Pothole Mix / SHREC 2022 | K84: Distress / roughness | L84: Images + videos | M84: Other / mixed capture | N84: Crack and pothole image masks; 359 video-mask clips generated from disparity by CV processing. | O84: Semantic image masks; RGB-D videos; imperfect algorithmic video masks | P84: CC BY-NC 3.0 (v2); underlying component licenses also matter. | Q84: Public links | R84: 4,340 image-mask pairs; 797 RGB/disparity clip pairs; 359 mask clips | S84: Mixed source datasets; RGB-D near-ground road capture. | T84: CNR IMATI / Andrea Ranieri, Elia Moscoso Thompson, Silvia Biasotti | U84: Compilation overlaps Crack500, GAPs384, EdmCrack600, Pothole-600 and other data. Video masks are not fully manual ground truth; avoid leakage when combining sources. | V84: DS-079; D030 | W84: Same dataset | X84: Stereo pothole / compiled ancestry (DS-043, DS-157, DS-079, DS-040) | Z84: AV inventory evidence snapshot | AA84: =HYPERLINK("#'Manual_Review'!A"&(MATCH("DS-079",Manual_Review!$A$6:$A$238,0)+5),"Enter review") -> Enter review | AB84: =HYPERLINK("#'MCDM_Checks'!A"&(MATCH("DS-079",MCDM_Checks!$B$6:$B$3733,0)+5),"Check evidence") -> Check evidence | AC84: Mendeley Data | AD84: https://data.mendeley.com/datasets/kfth5g2xk3/2 | AE84: https://data.mendeley.com/datasets/kfth5g2xk3/2 | AF84: Compared_All_Platforms_TH_v3.0.xlsx!All_Datasets row 80 (DS-079); AV_Pavement_Dataset_Inventory.xlsx!Datasets row 36 (D030)
A85: DS-080 | B85: Pothole Videos | D85: Labeled-16 | E85: =INDEX(MCDM_Grades!$E$6:$E$238,MATCH(A85,MCDM_Grades!$A$6:$A$238,0)) -> 94.444444 | F85: =INDEX(MCDM_Grades!$F$6:$F$238,MATCH(A85,MCDM_Grades!$A$6:$A$238,0)) -> 100 | G85: =INDEX(MCDM_Grades!$G$6:$G$238,MATCH(A85,MCDM_Grades!$A$6:$A$238,0)) -> 0.94444444 | H85: =HYPERLINK("https://data.mendeley.com/datasets/5bwfg4v4cd/3","Dataset") -> Dataset | I85: =HYPERLINK("https://data.mendeley.com/datasets/5bwfg4v4cd/3","Evidence / paper") -> Evidence / paper | J85: 2024 (v3); Pothole Videos | K85: Distress / roughness | L85: Video / sequences | M85: Other / mixed capture | N85: Pothole segmentation. | O85: Paired RGB/mask videos; manual first-frame mask propagated with tracking | P85: CC BY 4.0 | Q85: Public links | R85: 619 clips, 48 frames each | S85: Hulu Sungai Tengah, Indonesia | T85: Muhammad Ihsan, Agus Harjoko, Muhammad Alfian Amrizal / Universitas Gadjah Mada | U85: Camera about 130 cm above road; very different perspective from AV dashcams. Masks partly propagated automatically; not all independently hand-drawn. | V85: DS-080; D031 | W85: Same release | Z85: AV inventory evidence snapshot | AA85: =HYPERLINK("#'Manual_Review'!A"&(MATCH("DS-080",Manual_Review!$A$6:$A$238,0)+5),"Enter review") -> Enter review | AB85: =HYPERLINK("#'MCDM_Checks'!A"&(MATCH("DS-080",MCDM_Checks!$B$6:$B$3733,0)+5),"Check evidence") -> Check evidence | AC85: Mendeley Data | AD85: https://data.mendeley.com/datasets/5bwfg4v4cd/3 | AE85: https://data.mendeley.com/datasets/5bwfg4v4cd/3 | AF85: Compared_All_Platforms_TH_v3.0.xlsx!All_Datasets row 81 (DS-080); AV_Pavement_Dataset_Inventory.xlsx!Datasets row 37 (D031)
A86: DS-081 | B86: Road crack detection based on YOLO - SW algorithm | D86: Labeled-16 | E86: =INDEX(MCDM_Grades!$E$6:$E$238,MATCH(A86,MCDM_Grades!$A$6:$A$238,0)) -> 5.5555556 | F86: =INDEX(MCDM_Grades!$F$6:$F$238,MATCH(A86,MCDM_Grades!$A$6:$A$238,0)) -> 100 | G86: =INDEX(MCDM_Grades!$G$6:$G$238,MATCH(A86,MCDM_Grades!$A$6:$A$238,0)) -> 0.055555556 | H86: =HYPERLINK("https://data.mendeley.com/datasets/8wpk4c4n2m/2","Dataset") -> Dataset | I86: =HYPERLINK("https://data.mendeley.com/datasets/8wpk4c4n2m/2","Evidence / paper") -> Evidence / paper | J86: 2 | K86: Detection | L86: NR | M86: NR | N86: NR | O86: NR | P86: CC BY 4.0 | Q86: Direct_Download | R86: NR | S86: NR | U86: Pending: the entire description is the two words 'Algorithm research'. It could not be determined whether the deposit contains road imagery, annotations, model code or results, so dataset-versus-code status is unresolved | V86: DS-081 | W86: Retained existing record | Z86: v3 evidence snapshot | AA86: =HYPERLINK("#'Manual_Review'!A"&(MATCH("DS-081",Manual_Review!$A$6:$A$238,0)+5),"Enter review") -> Enter review | AB86: =HYPERLINK("#'MCDM_Checks'!A"&(MATCH("DS-081",MCDM_Checks!$B$6:$B$3733,0)+5),"Check evidence") -> Check evidence | AC86: Mendeley Data | AD86: https://data.mendeley.com/datasets/8wpk4c4n2m/2 | AE86: https://data.mendeley.com/datasets/8wpk4c4n2m/2 | AF86: Compared_All_Platforms_TH_v3.0.xlsx!All_Datasets row 82 (DS-081)
A87: DS-082 | B87: RoadDamageVision: Annotated Dataset of Road Damage Images | D87: Labeled-16 | E87: =INDEX(MCDM_Grades!$E$6:$E$238,MATCH(A87,MCDM_Grades!$A$6:$A$238,0)) -> 63.888889 | F87: =INDEX(MCDM_Grades!$F$6:$F$238,MATCH(A87,MCDM_Grades!$A$6:$A$238,0)) -> 100 | G87: =INDEX(MCDM_Grades!$G$6:$G$238,MATCH(A87,MCDM_Grades!$A$6:$A$238,0)) -> 0.63888889 | H87: =HYPERLINK("https://data.mendeley.com/datasets/ypm4h4z25c/3","Dataset") -> Dataset | I87: =HYPERLINK("https://data.mendeley.com/datasets/ypm4h4z25c/3","Evidence / paper") -> Evidence / paper | J87: 3 | K87: Detection | L87: NR | M87: UAV (drone), model not stated | N87: 6 classes; 7647 labelled road damage instances; D40 is the most common at 3566 instances and occurs mainly in the Spanish imagery, while D10 and D20 appear only in the Chinese imagery | O87: Bounding boxes with class labels (format standardised, file format not stated) | P87: CC BY 4.0 | Q87: Direct_Download | R87: NR | S87: China; Spain; Urban, suburban and rural settings; Road environment: Urban road; Suburban road; Rural road | U87: Image count is not reported, only the 7647 instance count; severe class-by-country confounding (D10 and D20 exist only in the Chinese subset, D40 mainly in the Spanish subset) means naive training will learn country rather than distress; drone model, altitude, resolution and dates unreported; three versions with no changelog | V87: DS-082 | W87: Retained existing record | Z87: v3 evidence snapshot | AA87: =HYPERLINK("#'Manual_Review'!A"&(MATCH("DS-082",Manual_Review!$A$6:$A$238,0)+5),"Enter review") -> Enter review | AB87: =HYPERLINK("#'MCDM_Checks'!A"&(MATCH("DS-082",MCDM_Checks!$B$6:$B$3733,0)+5),"Check evidence") -> Check evidence | AC87: Mendeley Data | AD87: https://data.mendeley.com/datasets/ypm4h4z25c/3 | AE87: https://data.mendeley.com/datasets/ypm4h4z25c/3 | AF87: Compared_All_Platforms_TH_v3.0.xlsx!All_Datasets row 83 (DS-082)
A88: DS-083 | B88: RSD-BD: Road Surface Damage Image Dataset from Major Cities of Bangladesh | D88: Labeled-16 | E88: =INDEX(MCDM_Grades!$E$6:$E$238,MATCH(A88,MCDM_Grades!$A$6:$A$238,0)) -> 61.111111 | F88: =INDEX(MCDM_Grades!$F$6:$F$238,MATCH(A88,MCDM_Grades!$A$6:$A$238,0)) -> 100 | G88: =INDEX(MCDM_Grades!$G$6:$G$238,MATCH(A88,MCDM_Grades!$A$6:$A$238,0)) -> 0.61111111 | H88: =HYPERLINK("https://data.mendeley.com/datasets/745n5wnt7v/1","Dataset") -> Dataset | I88: =HYPERLINK("https://data.mendeley.com/datasets/745n5wnt7v/1","Evidence / paper") -> Evidence / paper | J88: 1 | K88: Classification [Claude] | Classification;Benchmarking;Severity assessment (potential use) [GPT] | L88: Images/frames as reported | M88: Camera platform NR | N88: 3 balanced image-level classes of 500 images each [Claude] | 500 asphalt-damage;500 crack;500 pothole images [GPT] | O88: JPG images in class folders [Claude] | JPG;class folders or structure NR [GPT] | P88: CC BY 4.0 | Q88: Direct_Download | R88: 1500 (500 per class) [Claude] | 1500 [GPT] | S88: Bangladesh; Dhaka; Mymensingh; Chattogram; Road environment: Urban road; Semi-urban road [Claude] | Urban;semi-urban roads [GPT] | U88: Image-level classification labels only, with no localisation, severity or annotation files; capture device and collection dates unreported; exact resolutions not enumerated; the 'Asphalt Damage' class is not defined against a standard distress taxonomy [Claude] | Annotation method, exact image resolution, license, and collection platform not reported in retrieved authoritative evidence [GPT] | V88: DS-083 | W88: Retained existing record | Z88: v3 evidence snapshot | AA88: =HYPERLINK("#'Manual_Review'!A"&(MATCH("DS-083",Manual_Review!$A$6:$A$238,0)+5),"Enter review") -> Enter review | AB88: =HYPERLINK("#'MCDM_Checks'!A"&(MATCH("DS-083",MCDM_Checks!$B$6:$B$3733,0)+5),"Check evidence") -> Check evidence | AC88: Mendeley Data | AD88: https://data.mendeley.com/datasets/745n5wnt7v/1 | AE88: https://data.mendeley.com/datasets/745n5wnt7v/1 | AF88: Compared_All_Platforms_TH_v3.0.xlsx!All_Datasets row 84 (DS-083)
A89: DS-084 | B89: SDNET2018 (Structural Defects Network 2018) | C89: 1 | D89: Labeled-16 | E89: =INDEX(MCDM_Grades!$E$6:$E$238,MATCH(A89,MCDM_Grades!$A$6:$A$238,0)) -> 88.888889 | F89: =INDEX(MCDM_Grades!$F$6:$F$238,MATCH(A89,MCDM_Grades!$A$6:$A$238,0)) -> 100 | G89: =INDEX(MCDM_Grades!$G$6:$G$238,MATCH(A89,MCDM_Grades!$A$6:$A$238,0)) -> 0.88888889 | H89: =HYPERLINK("https://digitalcommons.usu.edu/all_datasets/48/","Dataset") -> Dataset | I89: =HYPERLINK("https://doi.org/10.1016/j.dib.2018.11.015","Evidence / paper") -> Evidence / paper | J89: USU SDNET2018 deposit, 2018; pavement subset within full release | K89: Image classification;Crack detection benchmarking [Claude] | Binary classification;Crack detection [GPT] | classification [Test_Batch] | L89: Images/frames as reported | M89: Handheld digital camera (16 MP Nikon) [Claude] | 16 MP Nikon digital camera [GPT] | Digital camera [Test_Batch] | N89: Binary sub-image label: Cracked;Non-cracked [Claude] | Pavement subset: 2,608 cracked and 21,726 uncracked subimages [GPT] | cracked; non-cracked; pavement; bridge deck; wall [Test_Batch] | O89: Folder-per-class image directories [Claude] | JPEG subimages;C or U binary labels [GPT] | Folder labels [Test_Batch] | P89: Other (specified in description) [Claude] | CC BY 4.0 [GPT] | Q89: Registration [Claude/GPT] | Direct_Download [Test_Batch] | R89: 56092 [Claude/Test_Batch] | 24334 [GPT] | S89: United States; Logan, Utah (Utah State University campus) [Claude] | Utah State University campus;Logan;Utah [GPT]; Road environment: Campus roads and sidewalks (pavement subset);bridge decks;building walls [Claude] | Roads and sidewalks;concrete pavement [GPT] | Pavement; bridge deck; wall [Test_Batch] | U89: Only 104 of the 230 source photographs are pavement (the remainder are bridge decks and walls), so the pavement subset must be separated before use; labels are binary crack/non-crack with no distress typing; sub-image labels are known to be noisy near crack boundaries; close-range handheld geometry is unlike vehicle-mounted survey imagery; licence terms are not restated on the Kaggle record [Claude] | Kaggle is a mirror of a broader concrete dataset containing bridge-deck, wall, and pavement images; this record describes only the separable pavement subset and provides no distress type or severity labels beyond crack presence. [GPT] | Concrete-focused mixed-structure dataset; pavement subset is not the entire corpus and labels are binary rather than pavement-engineering distress classes. [Test_Batch] | V89: DS-084 | W89: Retained existing record | Y89: Whole-deposit count is not pavement-only count; related crops are not independent images. No payload inspection. | Z89: Primary documentation checked | AA89: =HYPERLINK("#'Manual_Review'!A"&(MATCH("DS-084",Manual_Review!$A$6:$A$238,0)+5),"Enter review") -> Enter review | AB89: =HYPERLINK("#'MCDM_Checks'!A"&(MATCH("DS-084",MCDM_Checks!$B$6:$B$3733,0)+5),"Check evidence") -> Check evidence | AC89: Other official / repository | AD89: https://digitalcommons.usu.edu/all_datasets/48/ | AE89: https://doi.org/10.1016/j.dib.2018.11.015 | AF89: Compared_All_Platforms_TH_v3.0.xlsx!All_Datasets row 85 (DS-084)
A90: DS-085 | B90: TRIB Crack Dataset | D90: Labeled-16 | E90: =INDEX(MCDM_Grades!$E$6:$E$238,MATCH(A90,MCDM_Grades!$A$6:$A$238,0)) -> 69.444444 | F90: =INDEX(MCDM_Grades!$F$6:$F$238,MATCH(A90,MCDM_Grades!$A$6:$A$238,0)) -> 100 | G90: =INDEX(MCDM_Grades!$G$6:$G$238,MATCH(A90,MCDM_Grades!$A$6:$A$238,0)) -> 0.69444444 | H90: =HYPERLINK("https://data.mendeley.com/datasets/gd5t95rv5t/1","Dataset") -> Dataset | I90: =HYPERLINK("https://data.mendeley.com/datasets/gd5t95rv5t/1","Evidence / paper") -> Evidence / paper | J90: 1 | K90: Detection; Classification | L90: Images/frames as reported | M90: Professional digital camera held 100 cm above the road surface | N90: UNK - crack types and artefacts (oil stains, road markings, leaves) are described in prose, but no annotation files, masks or label format are documented | O90: NR | P90: CC BY 4.0 | Q90: Direct_Download | R90: 137 original RGB images, tiled to 256x256 patches with augmentation | S90: Romania; Bucharest (7 streets); Road environment: Urban road | U90: It is not documented whether any annotation files are included, so AI usability is unresolved; only 137 original images; original capture resolution not stated; the released tiles are augmented, so tiles are not independent samples | V90: DS-085 | W90: Retained existing record | Z90: v3 evidence snapshot | AA90: =HYPERLINK("#'Manual_Review'!A"&(MATCH("DS-085",Manual_Review!$A$6:$A$238,0)+5),"Enter review") -> Enter review | AB90: =HYPERLINK("#'MCDM_Checks'!A"&(MATCH("DS-085",MCDM_Checks!$B$6:$B$3733,0)+5),"Check evidence") -> Check evidence | AC90: Mendeley Data | AD90: https://data.mendeley.com/datasets/gd5t95rv5t/1 | AE90: https://data.mendeley.com/datasets/gd5t95rv5t/1 | AF90: Compared_All_Platforms_TH_v3.0.xlsx!All_Datasets row 86 (DS-085)
A91: DS-086 | B91: UAV Dataset for Automated Road Surface Degradation Detection in Real-World Conditions | D91: Labeled-16 | E91: =INDEX(MCDM_Grades!$E$6:$E$238,MATCH(A91,MCDM_Grades!$A$6:$A$238,0)) -> 69.444444 | F91: =INDEX(MCDM_Grades!$F$6:$F$238,MATCH(A91,MCDM_Grades!$A$6:$A$238,0)) -> 100 | G91: =INDEX(MCDM_Grades!$G$6:$G$238,MATCH(A91,MCDM_Grades!$A$6:$A$238,0)) -> 0.69444444 | H91: =HYPERLINK("https://data.mendeley.com/datasets/c6f2b7mx9t/1","Dataset") -> Dataset | I91: =HYPERLINK("https://data.mendeley.com/datasets/c6f2b7mx9t/1","Evidence / paper") -> Evidence / paper | J91: 1 | K91: Detection | L91: Images/frames as reported | M91: UAV (drone) and ground-based cameras [Claude] | UAV; ground-based camera [CodeX] | N91: 8 pavement distress classes as bounding boxes [Claude] | Eight road-anomaly classes [CodeX] | O91: YOLO TXT (class_id, x_center, y_center, width, height) [Claude] | YOLO TXT bounding boxes (class_id x_center y_center width height)) [CodeX] | P91: CC BY 4.0 | Q91: Direct_Download | R91: 11024 (8306 train / 2012 validation / 706 test) [Claude] | 11024 [CodeX] | S91: Road environment: Urban road; Rural road [Claude] | Urban; rural [CodeX] | U91: No country, region or collection date is reported anywhere on the record, which blocks any geographic transfer assessment; the record title and the internal dataset name (RoadAnomaly-YOLO) disagree; images are uniformly resized to 640x640 so original capture resolution is lost; per-class instance counts not reported; no peer-reviewed data paper located [Claude] | Country, exact locations, road segment count, QA protocol, and evaluation metrics NR [CodeX] | V91: DS-086 | W91: Retained existing record | Z91: v3 evidence snapshot | AA91: =HYPERLINK("#'Manual_Review'!A"&(MATCH("DS-086",Manual_Review!$A$6:$A$238,0)+5),"Enter review") -> Enter review | AB91: =HYPERLINK("#'MCDM_Checks'!A"&(MATCH("DS-086",MCDM_Checks!$B$6:$B$3733,0)+5),"Check evidence") -> Check evidence | AC91: Mendeley Data | AD91: https://data.mendeley.com/datasets/c6f2b7mx9t/1 | AE91: https://data.mendeley.com/datasets/c6f2b7mx9t/1 | AF91: Compared_All_Platforms_TH_v3.0.xlsx!All_Datasets row 87 (DS-086)
A92: DS-087 | B92: BLACrack | D92: Labeled-16 | E92: =INDEX(MCDM_Grades!$E$6:$E$238,MATCH(A92,MCDM_Grades!$A$6:$A$238,0)) -> 77.777778 | F92: =INDEX(MCDM_Grades!$F$6:$F$238,MATCH(A92,MCDM_Grades!$A$6:$A$238,0)) -> 94.444444 | G92: =INDEX(MCDM_Grades!$G$6:$G$238,MATCH(A92,MCDM_Grades!$A$6:$A$238,0)) -> 0.83333333 | H92: =HYPERLINK("https://huggingface.co/datasets/lambert1862/BLACrack","Dataset") -> Dataset | I92: =HYPERLINK("https://huggingface.co/datasets/lambert1862/BLACrack","Evidence / paper") -> Evidence / paper | J92: pre-release / request-access version | K92: Semantic_Segmentation | L92: Images/frames as reported | M92: High-speed pavement inspection vehicle; line-scan camera | N92: Pixel-level crack masks; bright-light, low-light, and alligator-crack subsets | O92: Image files; binary masks | P92: CC BY-NC-SA 4.0 | Q92: Request_Required | R92: 730 | S92: China; Liaoning Province; Road environment: Highway | U92: The HF repository contains metadata rather than the full image corpus; the data card states public release is contingent on paper acceptance and early access is request-based. | V92: DS-087 | W92: Retained existing record | Z92: v3 evidence snapshot | AA92: =HYPERLINK("#'Manual_Review'!A"&(MATCH("DS-087",Manual_Review!$A$6:$A$238,0)+5),"Enter review") -> Enter review | AB92: =HYPERLINK("#'MCDM_Checks'!A"&(MATCH("DS-087",MCDM_Checks!$B$6:$B$3733,0)+5),"Check evidence") -> Check evidence | AC92: Hugging Face | AD92: https://huggingface.co/datasets/lambert1862/BLACrack | AE92: https://huggingface.co/datasets/lambert1862/BLACrack | AF92: Compared_All_Platforms_TH_v3.0.xlsx!All_Datasets row 88 (DS-087)
A93: DS-088 | B93: Chrisathy/LCSD (Low-light Crack Segmentation Dataset) | D93: Labeled-16 | E93: =INDEX(MCDM_Grades!$E$6:$E$238,MATCH(A93,MCDM_Grades!$A$6:$A$238,0)) -> 58.333333 | F93: =INDEX(MCDM_Grades!$F$6:$F$238,MATCH(A93,MCDM_Grades!$A$6:$A$238,0)) -> 100 | G93: =INDEX(MCDM_Grades!$G$6:$G$238,MATCH(A93,MCDM_Grades!$A$6:$A$238,0)) -> 0.58333333 | H93: =HYPERLINK("https://huggingface.co/datasets/Chrisathy/LCSD","Dataset") -> Dataset | I93: =HYPERLINK("https://huggingface.co/datasets/Chrisathy/LCSD","Evidence / paper") -> Evidence / paper | J93: main | K93: Semantic segmentation; few-shot segmentation | L93: Images/frames as reported | M93: UAV (per CrackNex paper context) | N93: Binary crack segmentation masks; 102 well-lit train / 41 low-light test | O93: Image masks | P93: Apache-2.0 | Q93: Direct_Download | R93: 143 | S93: Road environment: UNK (UAV inspection surfaces; pavement share unresolved) | U93: Pending: whether imagery is pavement/road surface versus general concrete structures is unresolved from the card; very small; no collection context | V93: DS-088 | W93: Retained existing record | Z93: v3 evidence snapshot | AA93: =HYPERLINK("#'Manual_Review'!A"&(MATCH("DS-088",Manual_Review!$A$6:$A$238,0)+5),"Enter review") -> Enter review | AB93: =HYPERLINK("#'MCDM_Checks'!A"&(MATCH("DS-088",MCDM_Checks!$B$6:$B$3733,0)+5),"Check evidence") -> Check evidence | AC93: Hugging Face | AD93: https://huggingface.co/datasets/Chrisathy/LCSD | AE93: https://huggingface.co/datasets/Chrisathy/LCSD | AF93: Compared_All_Platforms_TH_v3.0.xlsx!All_Datasets row 89 (DS-088)
A94: DS-089 | B94: crack | D94: Labeled-16 | E94: =INDEX(MCDM_Grades!$E$6:$E$238,MATCH(A94,MCDM_Grades!$A$6:$A$238,0)) -> 38.888889 | F94: =INDEX(MCDM_Grades!$F$6:$F$238,MATCH(A94,MCDM_Grades!$A$6:$A$238,0)) -> 100 | G94: =INDEX(MCDM_Grades!$G$6:$G$238,MATCH(A94,MCDM_Grades!$A$6:$A$238,0)) -> 0.38888889 | H94: =HYPERLINK("https://huggingface.co/datasets/Mr-Perfectuz/crack","Dataset") -> Dataset | I94: =HYPERLINK("https://huggingface.co/datasets/Mr-Perfectuz/crack","Evidence / paper") -> Evidence / paper | J94: Hugging Face main | K94: Semantic_Segmentation | L94: Images/frames as reported | M94: NR | N94: Crack segmentation labels indicated by Hub task metadata; exact taxonomy NR | O94: Image files; mask/label structure NR | P94: NR | Q94: Direct_Download | R94: 3380 | S94: NR | U94: Dataset page content could not be fully verified; pavement specificity, provenance, collection date, license, annotation format, and quality control remain unresolved. | V94: DS-089 | W94: Retained existing record | Z94: v3 evidence snapshot | AA94: =HYPERLINK("#'Manual_Review'!A"&(MATCH("DS-089",Manual_Review!$A$6:$A$238,0)+5),"Enter review") -> Enter review | AB94: =HYPERLINK("#'MCDM_Checks'!A"&(MATCH("DS-089",MCDM_Checks!$B$6:$B$3733,0)+5),"Check evidence") -> Check evidence | AC94: Hugging Face | AD94: https://huggingface.co/datasets/Mr-Perfectuz/crack | AE94: https://huggingface.co/datasets/Mr-Perfectuz/crack | AF94: Compared_All_Platforms_TH_v3.0.xlsx!All_Datasets row 90 (DS-089)
A95: DS-090 | B95: CrackBlock600k | D95: Labeled-16 | E95: =INDEX(MCDM_Grades!$E$6:$E$238,MATCH(A95,MCDM_Grades!$A$6:$A$238,0)) -> 91.666667 | F95: =INDEX(MCDM_Grades!$F$6:$F$238,MATCH(A95,MCDM_Grades!$A$6:$A$238,0)) -> 100 | G95: =INDEX(MCDM_Grades!$G$6:$G$238,MATCH(A95,MCDM_Grades!$A$6:$A$238,0)) -> 0.91666667 | H95: =HYPERLINK("https://zenodo.org/records/17636238","Dataset") -> Dataset | I95: =HYPERLINK("https://zenodo.org/records/17636238","Evidence / paper") -> Evidence / paper | J95: November 2025 release | K95: Semantic_Segmentation;Image_Classification;Label_Noise_Mitigation [Claude] | Image_Classification; Semantic_Segmentation [GPT] | L95: Images/frames as reported | M95: Survey_Vehicle [Claude] | CiCS I inspection vehicle; fixed line-scan camera; approximately 30 km/h [GPT] | N95: Block-level binary label: 1 = crack present, 0 = no crack (600,000 1000x1000 patches) [Claude] | Crack/non-crack patch labels; pixel-level crack masks reported for supported tasks [GPT] | O95: PNG_Mask;Block_Label_Map [Claude] | Image patches; segmentation masks; metadata files [GPT] | P95: CC-BY-4.0 | Q95: Direct_Download | R95: 50000 [Claude] | 600000 [GPT] | S95: China; Zhejiang Province; Road environment: Highway | U95: Grayscale only and single distress class (crack); block-level binary labels are coarse relative to pixel masks; ~51 GB across six RAR parts requires non-standard extraction tooling; description states source images are 2000x3000 standardized to 2200x3400 while the structure section states 3400x2200, an unresolved internal inconsistency [Claude] | Geographically concentrated; overlapping patches may inflate nominal sample count; license metadata conflict; no engineering-condition indicators or auxiliary sensors reported. [GPT] | V95: DS-090 | W95: Retained existing record | X95: Same acquisition lineage; different archives/releases (DS-003, DS-025, DS-090) | Z95: v3 snapshot with fresh D4 evidence | AA95: =HYPERLINK("#'Manual_Review'!A"&(MATCH("DS-090",Manual_Review!$A$6:$A$238,0)+5),"Enter review") -> Enter review | AB95: =HYPERLINK("#'MCDM_Checks'!A"&(MATCH("DS-090",MCDM_Checks!$B$6:$B$3733,0)+5),"Check evidence") -> Check evidence | AC95: Zenodo; Hugging Face | AD95: https://zenodo.org/records/17636238 | AE95: https://zenodo.org/records/17636238 | AF95: Compared_All_Platforms_TH_v3.0.xlsx!All_Datasets row 91 (DS-090)
A96: DS-091 | B96: fcakyon/crack-instance-segmentation | D96: Labeled-16 | E96: =INDEX(MCDM_Grades!$E$6:$E$238,MATCH(A96,MCDM_Grades!$A$6:$A$238,0)) -> 50 | F96: =INDEX(MCDM_Grades!$F$6:$F$238,MATCH(A96,MCDM_Grades!$A$6:$A$238,0)) -> 100 | G96: =INDEX(MCDM_Grades!$G$6:$G$238,MATCH(A96,MCDM_Grades!$A$6:$A$238,0)) -> 0.5 | H96: =HYPERLINK("https://huggingface.co/datasets/fcakyon/crack-instance-segmentation","Dataset") -> Dataset | I96: =HYPERLINK("https://huggingface.co/datasets/fcakyon/crack-instance-segmentation","Evidence / paper") -> Evidence / paper | J96: main (parquet updated 2023-08) | K96: Image segmentation | L96: NR | M96: NR | N96: Crack instances (Roboflow export; full and mini subsets) | O96: COCO JSON (roboflow2huggingface) | P96: NR | Q96: Direct_Download | R96: NR | S96: NR | U96: Pending: label taxonomy, image count, license, and pavement-vs-wall surface domain unresolved; <1K images; auto-generated card only | V96: DS-091 | W96: Retained existing record | Z96: v3 evidence snapshot | AA96: =HYPERLINK("#'Manual_Review'!A"&(MATCH("DS-091",Manual_Review!$A$6:$A$238,0)+5),"Enter review") -> Enter review | AB96: =HYPERLINK("#'MCDM_Checks'!A"&(MATCH("DS-091",MCDM_Checks!$B$6:$B$3733,0)+5),"Check evidence") -> Check evidence | AC96: Hugging Face | AD96: https://huggingface.co/datasets/fcakyon/crack-instance-segmentation | AE96: https://huggingface.co/datasets/fcakyon/crack-instance-segmentation | AF96: Compared_All_Platforms_TH_v3.0.xlsx!All_Datasets row 92 (DS-091)
A97: DS-092 | B97: global-potholes-dataset | D97: Labeled-16 | E97: =INDEX(MCDM_Grades!$E$6:$E$238,MATCH(A97,MCDM_Grades!$A$6:$A$238,0)) -> 50 | F97: =INDEX(MCDM_Grades!$F$6:$F$238,MATCH(A97,MCDM_Grades!$A$6:$A$238,0)) -> 100 | G97: =INDEX(MCDM_Grades!$G$6:$G$238,MATCH(A97,MCDM_Grades!$A$6:$A$238,0)) -> 0.5 | H97: =HYPERLINK("https://huggingface.co/datasets/Outerview/global-potholes-dataset","Dataset") -> Dataset | I97: =HYPERLINK("https://huggingface.co/datasets/Outerview/global-potholes-dataset","Evidence / paper") -> Evidence / paper | J97: Hugging Face sample / actively updated release | K97: Object_Detection; Geospatial_Condition_Mapping | L97: Images/frames as reported | M97: Mapillary street-level imagery | N97: Geolocated pothole detections generated by Outerview AI; latitude/longitude and related record metadata | O97: Parquet; CSV; GeoJSON; image ZIP | P97: CC BY 4.0 | Q97: Direct_Download | R97: 29000 | S97: Multiple; Global; Road environment: Mixed | U97: The Hub release is a sample relative to the claimed multi-million-record collection; labels are AI-generated; independent annotation validation and image-level provenance are incomplete. | V97: DS-092 | W97: Retained existing record | X97: Mapillary image source family (DS-195, DS-196, DS-092) | Z97: v3 evidence snapshot | AA97: =HYPERLINK("#'Manual_Review'!A"&(MATCH("DS-092",Manual_Review!$A$6:$A$238,0)+5),"Enter review") -> Enter review | AB97: =HYPERLINK("#'MCDM_Checks'!A"&(MATCH("DS-092",MCDM_Checks!$B$6:$B$3733,0)+5),"Check evidence") -> Check evidence | AC97: Hugging Face | AD97: https://huggingface.co/datasets/Outerview/global-potholes-dataset | AE97: https://huggingface.co/datasets/Outerview/global-potholes-dataset | AF97: Compared_All_Platforms_TH_v3.0.xlsx!All_Datasets row 93 (DS-092)
A98: DS-093 | B98: keremberke/pothole-segmentation (Roboflow export) | D98: Labeled-16 | E98: =INDEX(MCDM_Grades!$E$6:$E$238,MATCH(A98,MCDM_Grades!$A$6:$A$238,0)) -> 61.111111 | F98: =INDEX(MCDM_Grades!$F$6:$F$238,MATCH(A98,MCDM_Grades!$A$6:$A$238,0)) -> 100 | G98: =INDEX(MCDM_Grades!$G$6:$G$238,MATCH(A98,MCDM_Grades!$A$6:$A$238,0)) -> 0.61111111 | H98: =HYPERLINK("https://huggingface.co/datasets/keremberke/pothole-segmentation","Dataset") -> Dataset | I98: =HYPERLINK("https://huggingface.co/datasets/keremberke/pothole-segmentation","Evidence / paper") -> Evidence / paper | J98: HF export of Roboflow IMACS Pothole Detection v4 [Claude] | Roboflow export dated 2023-01-15 [GPT] | K98: Image segmentation; object detection [Claude] | Instance_Segmentation [GPT] | L98: Images/frames as reported | M98: NR | N98: Single class: pothole [Claude] | Single pothole class with pixel/instance segmentation annotations [GPT] | O98: COCO JSON (polygon) [Claude] | COCO JSON; image files [GPT] | P98: CC BY 4.0 | Q98: Direct_Download | R98: 90 | S98: Road environment: Mixed urban/rural street-view scenes (per sample images) [Claude] | Mixed [GPT] | U98: Very small (90 images); single distress class; no collection context, geography, or sensor metadata; Roboflow re-export rather than original release [Claude] | Very small dataset; acquisition location, camera platform, image resolution, and labeling quality controls are not adequately documented. [GPT] | V98: DS-093 | W98: Retained existing record | X98: Similar labels; different upstream projects (DS-093, DS-094, DS-153) | Z98: v3 evidence snapshot | AA98: =HYPERLINK("#'Manual_Review'!A"&(MATCH("DS-093",Manual_Review!$A$6:$A$238,0)+5),"Enter review") -> Enter review | AB98: =HYPERLINK("#'MCDM_Checks'!A"&(MATCH("DS-093",MCDM_Checks!$B$6:$B$3733,0)+5),"Check evidence") -> Check evidence | AC98: Hugging Face | AD98: https://huggingface.co/datasets/keremberke/pothole-segmentation | AE98: https://huggingface.co/datasets/keremberke/pothole-segmentation | AF98: Compared_All_Platforms_TH_v3.0.xlsx!All_Datasets row 94 (DS-093)
A99: DS-094 | B99: manot/pothole-segmentation2 | D99: Labeled-16 | E99: =INDEX(MCDM_Grades!$E$6:$E$238,MATCH(A99,MCDM_Grades!$A$6:$A$238,0)) -> 55.555556 | F99: =INDEX(MCDM_Grades!$F$6:$F$238,MATCH(A99,MCDM_Grades!$A$6:$A$238,0)) -> 100 | G99: =INDEX(MCDM_Grades!$G$6:$G$238,MATCH(A99,MCDM_Grades!$A$6:$A$238,0)) -> 0.55555556 | H99: =HYPERLINK("https://huggingface.co/datasets/manot/pothole-segmentation2","Dataset") -> Dataset | I99: =HYPERLINK("https://huggingface.co/datasets/manot/pothole-segmentation2","Evidence / paper") -> Evidence / paper | J99: main | K99: Object detection | L99: NR | M99: NR | N99: Pothole annotations (Roboflow export) | O99: COCO JSON with bounding boxes in exposed loader; do not infer masks from repository name | P99: CC BY 4.0 (loader declaration; upstream rights not separately audited) | Q99: Direct_Download | R99: NR | S99: NR | U99: Auto-generated loading script only; <1K images; license and image count not reported; another Roboflow pothole export overlapping in scope with DSHF-001 family but different source project | V99: DS-094 | W99: Retained existing record | X99: Similar labels; different upstream projects (DS-093, DS-094, DS-153) | Z99: v3 evidence snapshot | AA99: =HYPERLINK("#'Manual_Review'!A"&(MATCH("DS-094",Manual_Review!$A$6:$A$238,0)+5),"Enter review") -> Enter review | AB99: =HYPERLINK("#'MCDM_Checks'!A"&(MATCH("DS-094",MCDM_Checks!$B$6:$B$3733,0)+5),"Check evidence") -> Check evidence | AC99: Hugging Face | AD99: https://huggingface.co/datasets/manot/pothole-segmentation2 | AE99: https://huggingface.co/datasets/manot/pothole-segmentation2 | AF99: Compared_All_Platforms_TH_v3.0.xlsx!All_Datasets row 95 (DS-094)
A100: DS-095 | B100: n-rdd2024-distilled-frdc | D100: Labeled-16 | E100: =INDEX(MCDM_Grades!$E$6:$E$238,MATCH(A100,MCDM_Grades!$A$6:$A$238,0)) -> 58.333333 | F100: =INDEX(MCDM_Grades!$F$6:$F$238,MATCH(A100,MCDM_Grades!$A$6:$A$238,0)) -> 100 | G100: =INDEX(MCDM_Grades!$G$6:$G$238,MATCH(A100,MCDM_Grades!$A$6:$A$238,0)) -> 0.58333333 | H100: =HYPERLINK("https://huggingface.co/datasets/TamAko783/n-rdd2024-distilled-frdc","Dataset") -> Dataset | I100: =HYPERLINK("https://huggingface.co/datasets/TamAko783/n-rdd2024-distilled-frdc","Evidence / paper") -> Evidence / paper | J100: distilled FRDC pseudo-label release | K100: Object_Detection; Knowledge_Distillation | L100: NR | M100: Source-dependent road imagery | N100: Ten-class pseudo-label taxonomy documented in the repository configuration | O100: YOLO text annotations; image files | P100: NR | Q100: Direct_Download | R100: NR | S100: Multiple; Source-dependent; Road environment: Mixed | U100: Pseudo-labeled derivative; exact source-image provenance, license, label error rate, and manual validation are incompletely documented. | V100: DS-095 | W100: Retained existing record | X100: Derived/compiled RDD family (DS-035, DS-072, DS-095, DS-099, DS-132, DS-162, DS-104, DS-105) | Z100: v3 evidence snapshot | AA100: =HYPERLINK("#'Manual_Review'!A"&(MATCH("DS-095",Manual_Review!$A$6:$A$238,0)+5),"Enter review") -> Enter review | AB100: =HYPERLINK("#'MCDM_Checks'!A"&(MATCH("DS-095",MCDM_Checks!$B$6:$B$3733,0)+5),"Check evidence") -> Check evidence | AC100: Hugging Face | AD100: https://huggingface.co/datasets/TamAko783/n-rdd2024-distilled-frdc | AE100: https://huggingface.co/datasets/TamAko783/n-rdd2024-distilled-frdc | AF100: Compared_All_Platforms_TH_v3.0.xlsx!All_Datasets row 96 (DS-095)
A101: DS-096 | B101: PaveBench | C101: 4 | D101: Labeled-16 | E101: =INDEX(MCDM_Grades!$E$6:$E$238,MATCH(A101,MCDM_Grades!$A$6:$A$238,0)) -> 100 | F101: =INDEX(MCDM_Grades!$F$6:$F$238,MATCH(A101,MCDM_Grades!$A$6:$A$238,0)) -> 100 | G101: =INDEX(MCDM_Grades!$G$6:$G$238,MATCH(A101,MCDM_Grades!$A$6:$A$238,0)) -> 1 | H101: =HYPERLINK("https://huggingface.co/datasets/MML-Group/PaveBench","Dataset") -> Dataset | I101: =HYPERLINK("https://arxiv.org/abs/2604.02804","Evidence / paper") -> Evidence / paper | J101: Hugging Face MML-Group/PaveBench, current card snapshot 2026-10-11 | K101: Distress / roughness | L101: Images / patches | M101: Human-driven survey | N101: Longitudinal/transverse/alligator cracks, patch, pothole, negative; VQA also covers severity and maintenance. | O101: Class labels, COCO-style boxes, masks, JSONL question-answer dialogues | P101: CC BY-NC-SA 4.0 | Q101: Public links | R101: 20,124 visual images; 32,160 QA pairs | S101: Liaoning Province, China | T101: Multi-Modal Learning Group / Dexiang Li and collaborators | U101: Distinct from driver-view camera imagery. Detection/segmentation merge longitudinal and transverse into linear crack. Very useful distress annotations but not strict AV footage. Paper posted 2026-04-03 (before review cutoff). | V101: DS-096; D028 | W101: Same dataset | Y101: Documentation-only pass does not validate mask accuracy, physical metrology, benchmark independence or maintenance outcomes. | Z101: Primary documentation checked | AA101: =HYPERLINK("#'Manual_Review'!A"&(MATCH("DS-096",Manual_Review!$A$6:$A$238,0)+5),"Enter review") -> Enter review | AB101: =HYPERLINK("#'MCDM_Checks'!A"&(MATCH("DS-096",MCDM_Checks!$B$6:$B$3733,0)+5),"Check evidence") -> Check evidence | AC101: Hugging Face | AD101: https://huggingface.co/datasets/MML-Group/PaveBench | AE101: https://arxiv.org/abs/2604.02804 | AF101: Compared_All_Platforms_TH_v3.0.xlsx!All_Datasets row 97 (DS-096); AV_Pavement_Dataset_Inventory.xlsx!Datasets row 34 (D028)
